{
  "type": "Feature",
  "properties": {
    "gn:admin1_code":"3.0",
    "gn:admin2_code":"407.0",
    "gn:admin3_code":"40702.0",
    "gn:admin4_code":"4070204.0",
    "gn:asciiname":"Membrillo",
    "gn:country_code":"DO",
    "gn:dem":340,
    "gn:feature_class":"P",
    "gn:feature_code":"PPL",
    "gn:name":"Membrillo",
    "gn:population":0,
    "gn:timezone":"America/Santo_Domingo",
    "iso:country":"DO",
    "wof:name":"Membrillo",
    "wof:placetype":"locality"
},
  "geometry": {"coordinates":[-71.11667,18.08333],"type":"Point"}
}