{
  "type": "Feature",
  "properties": {
    "gn:admin1_code":"35.0",
    "gn:admin2_code":"1701.0",
    "gn:admin3_code":"170101.0",
    "gn:admin4_code":"17010108.0",
    "gn:asciiname":"Agua de Limon",
    "gn:country_code":"DO",
    "gn:dem":184,
    "gn:feature_class":"P",
    "gn:feature_code":"PPL",
    "gn:name":"Agua de Lim\u00f3n",
    "gn:population":0,
    "gn:timezone":"America/Santo_Domingo",
    "iso:country":"DO",
    "wof:name":"Agua de Limon",
    "wof:placetype":"locality"
},
  "geometry": {"coordinates":[-70.33333,18.35],"type":"Point"}
}