{
  "type": "Feature",
  "properties": {
    "gn:admin1_code":"28.0",
    "gn:admin2_code":"801.0",
    "gn:admin3_code":"80104.0",
    "gn:admin4_code":"8010404.0",
    "gn:asciiname":"Sabaneta",
    "gn:country_code":"DO",
    "gn:dem":86,
    "gn:feature_class":"P",
    "gn:feature_code":"PPL",
    "gn:name":"Sabaneta",
    "gn:population":0,
    "gn:timezone":"America/Santo_Domingo",
    "iso:country":"DO",
    "wof:name":"Sabaneta",
    "wof:placetype":"locality"
},
  "geometry": {"coordinates":[-69.04308,18.72147],"type":"Point"}
}