{
  "type": "Feature",
  "properties": {
    "gn:admin1_code":"8.0",
    "gn:admin2_code":"903.0",
    "gn:admin3_code":"90303.0",
    "gn:admin4_code":"9030302.0",
    "gn:asciiname":"Los Penones",
    "gn:country_code":"DO",
    "gn:dem":202,
    "gn:feature_class":"P",
    "gn:feature_code":"PPL",
    "gn:name":"Los Pe\u00f1ones",
    "gn:population":0,
    "gn:timezone":"America/Santo_Domingo",
    "iso:country":"DO",
    "name:und_x_variant":[
        "El Pe\u00f1\u00f3n",
        "Los Pe\u00f1ones"
    ],
    "wof:name":"Los Penones",
    "wof:placetype":"locality"
},
  "geometry": {"coordinates":[-70.40719,19.62125],"type":"Point"}
}