{
  "type": "Feature",
  "properties": {
    "gn:admin1_code":"33.0",
    "gn:admin2_code":"2101.0",
    "gn:admin3_code":"210102.0",
    "gn:admin4_code":"21010204.0",
    "gn:asciiname":"Los Corozos",
    "gn:country_code":"DO",
    "gn:dem":72,
    "gn:feature_class":"P",
    "gn:feature_code":"PPL",
    "gn:name":"Los Corozos",
    "gn:population":0,
    "gn:timezone":"America/Santo_Domingo",
    "iso:country":"DO",
    "wof:name":"Los Corozos",
    "wof:placetype":"locality"
},
  "geometry": {"coordinates":[-70.12255999999999,18.46524],"type":"Point"}
}