{
  "type": "Feature",
  "properties": {
    "gn:admin1_code":"37.0",
    "gn:admin2_code":"3202.0",
    "gn:admin3_code":"320201.0",
    "gn:admin4_code":"32020101.0",
    "gn:asciiname":"Bayona",
    "gn:country_code":"DO",
    "gn:dem":31,
    "gn:feature_class":"P",
    "gn:feature_code":"PPL",
    "gn:name":"Bayona",
    "gn:population":0,
    "gn:timezone":"America/Santo_Domingo",
    "iso:country":"DO",
    "name:und_x_variant":[
        "Cabayona",
        "Bayona"
    ],
    "wof:name":"Bayona",
    "wof:placetype":"locality"
},
  "geometry": {"coordinates":[-70.00386999999999,18.47226],"type":"Point"}
}