{
  "type": "Feature",
  "properties": {
    "gn:admin1_code":"21.0",
    "gn:admin2_code":"2404.0",
    "gn:admin3_code":"240404.0",
    "gn:admin4_code":"24040404.0",
    "gn:asciiname":"El Hundidero",
    "gn:country_code":"DO",
    "gn:dem":114,
    "gn:feature_class":"P",
    "gn:feature_code":"PPL",
    "gn:name":"El Hundidero",
    "gn:population":0,
    "gn:timezone":"America/Santo_Domingo",
    "iso:country":"DO",
    "wof:name":"El Hundidero",
    "wof:placetype":"locality"
},
  "geometry": {"coordinates":[-70.24528000000001,19.04029],"type":"Point"}
}