{
  "type": "Feature",
  "properties": {
    "gn:admin1_code":"3.0",
    "gn:admin2_code":"404.0",
    "gn:admin3_code":"40402.0",
    "gn:admin4_code":"4040202.0",
    "gn:asciiname":"El Maniel",
    "gn:country_code":"DO",
    "gn:dem":821,
    "gn:feature_class":"P",
    "gn:feature_code":"PPL",
    "gn:name":"El Maniel",
    "gn:population":0,
    "gn:timezone":"America/Santo_Domingo",
    "iso:country":"DO",
    "wof:name":"El Maniel",
    "wof:placetype":"locality"
},
  "geometry": {"coordinates":[-71.23333000000002,17.98333],"type":"Point"}
}