{
  "type": "Feature",
  "properties": {
    "gn:admin1_code":"32.0",
    "gn:admin2_code":"2901.0",
    "gn:admin3_code":"290102.0",
    "gn:admin4_code":"29010204.0",
    "gn:asciiname":"Cruce del Bosque",
    "gn:country_code":"DO",
    "gn:dem":67,
    "gn:feature_class":"P",
    "gn:feature_code":"PPL",
    "gn:name":"Cruce del Bosque",
    "gn:population":0,
    "gn:timezone":"America/Santo_Domingo",
    "iso:country":"DO",
    "wof:name":"Cruce del Bosque",
    "wof:placetype":"locality"
},
  "geometry": {"coordinates":[-69.90406999999999,18.81816],"type":"Point"}
}