{
  "type": "Feature",
  "properties": {
    "gn:admin1_code":"25.0",
    "gn:admin2_code":"2505.0",
    "gn:admin3_code":"250504.0",
    "gn:admin4_code":"25050402.0",
    "gn:asciiname":"Manaclar",
    "gn:country_code":"DO",
    "gn:dem":918,
    "gn:feature_class":"P",
    "gn:feature_code":"PPL",
    "gn:name":"Manaclar",
    "gn:population":0,
    "gn:timezone":"America/Santo_Domingo",
    "iso:country":"DO",
    "wof:name":"Manaclar",
    "wof:placetype":"locality"
},
  "geometry": {"coordinates":[-70.87078000000002,19.23706],"type":"Point"}
}