{
  "type": "Feature",
  "properties": {
    "gn:country":"DO",
    "gn:fcode":"PPL",
    "gn:population":11642,
    "iso:country":"DO",
    "name:ast_x_preferred":[
        "Villa V\u00e1squez"
    ],
    "name:cat_x_preferred":[
        "Villa V\u00e1squez"
    ],
    "name:ceb_x_preferred":[
        "Villa V\u00e1squez"
    ],
    "name:deu_x_preferred":[
        "Villa V\u00e1squez"
    ],
    "name:eng_x_preferred":[
        "Villa V\u00e1squez"
    ],
    "name:fra_x_preferred":[
        "villa V\u00e1squez"
    ],
    "name:ita_x_preferred":[
        "Villa V\u00e1squez"
    ],
    "name:jpn_x_preferred":[
        "\u30d3\u30fc\u30b8\u30e3\u30fb\u30d0\u30b9\u30b1\u30b9"
    ],
    "name:nan_x_preferred":[
        "Villa V\u00e1squez"
    ],
    "name:nld_x_preferred":[
        "Villa V\u00e1squez"
    ],
    "name:pol_x_preferred":[
        "Villa V\u00e1squez"
    ],
    "name:por_x_preferred":[
        "Villa V\u00e1squez"
    ],
    "name:slv_x_preferred":[
        "Villa V\u00e1squez"
    ],
    "name:spa_x_preferred":[
        "Villa V\u00e1squez"
    ],
    "name:swe_x_preferred":[
        "Villa V\u00e1squez"
    ],
    "name:und_x_variant":[
        "Villa Isabel"
    ],
    "name:zho_x_preferred":[
        "\u5df4\u65af\u514b\u65af\u93ae"
    ],
    "qs:name":"Villa V\u00e1squez",
    "qs:photos_9r":0,
    "qs:photos_sr":0,
    "qs:pop_sr":"6",
    "wd:wordcount":478,
    "wof:name":"Villa V\u00e1squez",
    "wof:placetype":"locality",
    "wof:population":11642
},
  "geometry": {"coordinates":[-71.4464,19.7411],"type":"Point"}
}