{
  "type": "Feature",
  "properties": {
    "gn:country":"DO",
    "gn:fcode":"PPL",
    "gn:pop":11642,
    "iso:country":"DO",
    "name:unk_x_variant":[
        "Villa Isabel"
    ],
    "qs:name":"Villa V\u00e1squez",
    "qs:photos_9r":0,
    "qs:photos_sr":0,
    "qs:pop_sr":"6",
    "wd:wordcount":478,
    "wof:name":"Villa V\u00e1squez",
    "wof:placetype":"locality",
    "wof:population":11642
},
  "geometry": {"coordinates":[-71.4464,19.7411],"type":"Point"}
}