{
  "type": "Feature",
  "properties": {
    "gn:admin1_code":"11.0",
    "gn:admin2_code":"705.0",
    "gn:admin3_code":"70502.0",
    "gn:admin4_code":"7050202.0",
    "gn:asciiname":"Piedra Blanca",
    "gn:country_code":"DO",
    "gn:dem":784,
    "gn:feature_class":"P",
    "gn:feature_code":"PPL",
    "gn:name":"Piedra Blanca",
    "gn:population":0,
    "gn:timezone":"America/Santo_Domingo",
    "iso:country":"DO",
    "wof:name":"Piedra Blanca",
    "wof:placetype":"locality"
},
  "geometry": {"coordinates":[-71.52597,19.22781],"type":"Point"}
}