{
  "type": "Feature",
  "properties": {
    "gn:admin1_code":"20.0",
    "gn:asciiname":"La Herradura",
    "gn:country_code":"DO",
    "gn:dem":-9999,
    "gn:feature_class":"P",
    "gn:feature_code":"PPL",
    "gn:name":"La Herradura",
    "gn:population":0,
    "gn:timezone":"America/Santo_Domingo",
    "iso:country":"DO",
    "wof:name":"La Herradura",
    "wof:placetype":"locality"
},
  "geometry": {"coordinates":[-69.21666999999999,19.33333],"type":"Point"}
}