{
  "type": "Feature",
  "properties": {
    "gn:admin1_code":"11.0",
    "gn:admin2_code":"702.0",
    "gn:admin3_code":"70202.0",
    "gn:admin4_code":"7020202.0",
    "gn:asciiname":"El Mamoncito",
    "gn:country_code":"DO",
    "gn:dem":313,
    "gn:feature_class":"P",
    "gn:feature_code":"PPL",
    "gn:name":"El Mamoncito",
    "gn:population":0,
    "gn:timezone":"America/Santo_Domingo",
    "iso:country":"DO",
    "wof:name":"El Mamoncito",
    "wof:placetype":"locality"
},
  "geometry": {"coordinates":[-71.70248000000002,19.03427000000001],"type":"Point"}
}