{
  "type": "Feature",
  "properties": {
    "gn:admin1_code":"1.0",
    "gn:admin2_code":"205.0",
    "gn:admin3_code":"20501.0",
    "gn:admin4_code":"2050104.0",
    "gn:asciiname":"Banadero",
    "gn:country_code":"DO",
    "gn:dem":1309,
    "gn:feature_class":"P",
    "gn:feature_code":"PPL",
    "gn:name":"Ba\u00f1adero",
    "gn:population":0,
    "gn:timezone":"America/Santo_Domingo",
    "iso:country":"DO",
    "wof:name":"Banadero",
    "wof:placetype":"locality"
},
  "geometry": {"coordinates":[-70.71819000000001,18.59296],"type":"Point"}
}