{
  "type": "Feature",
  "properties": {
    "gn:admin1_code":"1.0",
    "gn:admin2_code":"210.0",
    "gn:admin3_code":"21001.0",
    "gn:admin4_code":"2100108.0",
    "gn:asciiname":"La Finca",
    "gn:country_code":"DO",
    "gn:dem":1439,
    "gn:feature_class":"P",
    "gn:feature_code":"PPL",
    "gn:name":"La Finca",
    "gn:population":0,
    "gn:timezone":"America/Santo_Domingo",
    "iso:country":"DO",
    "wof:name":"La Finca",
    "wof:placetype":"locality"
},
  "geometry": {"coordinates":[-70.73333000000002,18.66667],"type":"Point"}
}