{
  "type": "Feature",
  "properties": {
    "gn:admin1_code":"32.0",
    "gn:admin2_code":"2903.0",
    "gn:admin3_code":"290302.0",
    "gn:admin4_code":"29030202.0",
    "gn:asciiname":"El Yayal",
    "gn:country_code":"DO",
    "gn:dem":261,
    "gn:feature_class":"P",
    "gn:feature_code":"PPL",
    "gn:name":"El Yayal",
    "gn:population":0,
    "gn:timezone":"America/Santo_Domingo",
    "iso:country":"DO",
    "wof:name":"El Yayal",
    "wof:placetype":"locality"
},
  "geometry": {"coordinates":[-69.71228000000001,18.98256],"type":"Point"}
}