{
  "type": "Feature",
  "properties": {
    "gn:admin1_code":"33.0",
    "gn:admin2_code":"2105.0",
    "gn:admin3_code":"210504.0",
    "gn:admin4_code":"21050404.0",
    "gn:asciiname":"Los Anones",
    "gn:country_code":"DO",
    "gn:dem":146,
    "gn:feature_class":"P",
    "gn:feature_code":"PPL",
    "gn:name":"Los Anones",
    "gn:population":0,
    "gn:timezone":"America/Santo_Domingo",
    "iso:country":"DO",
    "name:und_x_variant":[
        "Los Aones",
        "Los Anones"
    ],
    "wof:name":"Los Anones",
    "wof:placetype":"locality"
},
  "geometry": {"coordinates":[-70.15274000000001,18.58137],"type":"Point"}
}