{
  "type": "Feature",
  "properties": {
    "gn:admin1_code":"15.0",
    "gn:admin2_code":"1502.0",
    "gn:admin3_code":"150201.0",
    "gn:admin4_code":"15020103.0",
    "gn:asciiname":"Jobo Corcobado",
    "gn:country_code":"DO",
    "gn:dem":28,
    "gn:feature_class":"P",
    "gn:feature_code":"PPL",
    "gn:name":"Jobo Corcobado",
    "gn:population":0,
    "gn:timezone":"America/Santo_Domingo",
    "iso:country":"DO",
    "wof:name":"Jobo Corcobado",
    "wof:placetype":"locality"
},
  "geometry": {"coordinates":[-71.46706,19.70078],"type":"Point"}
}