{
  "type": "Feature",
  "properties": {
    "gn:admin1_code":"18.0",
    "gn:admin2_code":"1808.0",
    "gn:admin3_code":"180802.0",
    "gn:admin4_code":"18080203.0",
    "gn:asciiname":"Punta Rucia",
    "gn:country_code":"DO",
    "gn:dem":6,
    "gn:feature_class":"P",
    "gn:feature_code":"PPL",
    "gn:name":"Punta Rucia",
    "gn:population":0,
    "gn:timezone":"America/Santo_Domingo",
    "iso:country":"DO",
    "wof:name":"Punta Rucia",
    "wof:placetype":"locality"
},
  "geometry": {"coordinates":[-71.21324,19.84027],"type":"Point"}
}