{
  "type": "Feature",
  "properties": {
    "gn:admin1_code":"18.0",
    "gn:admin2_code":"1806.0",
    "gn:admin3_code":"180603.0",
    "gn:admin4_code":"18060302.0",
    "gn:asciiname":"Los Arquies",
    "gn:country_code":"DO",
    "gn:dem":32,
    "gn:feature_class":"P",
    "gn:feature_code":"PPL",
    "gn:name":"Los Arqu\u00edes",
    "gn:population":0,
    "gn:timezone":"America/Santo_Domingo",
    "iso:country":"DO",
    "wof:name":"Los Arquies",
    "wof:placetype":"locality"
},
  "geometry": {"coordinates":[-71.00903000000002,19.81544],"type":"Point"}
}