{
  "type": "Feature",
  "properties": {
    "gn:admin1_code":"12.0",
    "gn:admin2_code":"1202.0",
    "gn:admin3_code":"120201.0",
    "gn:admin4_code":"12020102.0",
    "gn:asciiname":"Higo Prieto",
    "gn:country_code":"DO",
    "gn:dem":75,
    "gn:feature_class":"P",
    "gn:feature_code":"PPL",
    "gn:name":"Higo Prieto",
    "gn:population":0,
    "gn:timezone":"America/Santo_Domingo",
    "iso:country":"DO",
    "name:und_x_variant":[
        "Batey Higo Prieto",
        "Higo Prieto"
    ],
    "wof:name":"Higo Prieto",
    "wof:placetype":"locality"
},
  "geometry": {"coordinates":[-69.00253000000001,18.5541],"type":"Point"}
}