{
  "type": "Feature",
  "properties": {
    "gn:admin1_code":"28.0",
    "gn:admin2_code":"801.0",
    "gn:admin3_code":"80101.0",
    "gn:admin4_code":"8010107.0",
    "gn:asciiname":"Sabana Quemada",
    "gn:country_code":"DO",
    "gn:dem":105,
    "gn:feature_class":"P",
    "gn:feature_code":"PPL",
    "gn:name":"Sabana Quemada",
    "gn:population":0,
    "gn:timezone":"America/Santo_Domingo",
    "iso:country":"DO",
    "wof:name":"Sabana Quemada",
    "wof:placetype":"locality"
},
  "geometry": {"coordinates":[-69.13479,18.79657000000001],"type":"Point"}
}