{
  "type": "Feature",
  "properties": {
    "gn:admin1_code":"1.0",
    "gn:asciiname":"Hondo Valle",
    "gn:country_code":"DO",
    "gn:dem":1441,
    "gn:feature_class":"P",
    "gn:feature_code":"PPL",
    "gn:name":"Hondo Valle",
    "gn:population":0,
    "gn:timezone":"America/Santo_Domingo",
    "iso:country":"DO",
    "wof:name":"Hondo Valle",
    "wof:placetype":"locality"
},
  "geometry": {"coordinates":[-70.83333,18.88333],"type":"Point"}
}