{
  "type": "Feature",
  "properties": {
    "gn:admin1_code":"1.0",
    "gn:asciiname":"Hondo Valle",
    "gn:country_code":"DO",
    "gn:dem":1441,
    "gn:feature_class":"P",
    "gn:feature_code":"PPL",
    "gn:name":"Hondo Valle",
    "gn:population":0,
    "gn:timezone":"America/Santo_Domingo",
    "iso:country":"DO",
    "name:ceb_x_preferred":[
        "Hondo Valle"
    ],
    "name:ita_x_preferred":[
        "Hondo Valle"
    ],
    "name:por_x_preferred":[
        "Hondo Valle"
    ],
    "name:slv_x_preferred":[
        "Hondo Valle"
    ],
    "name:spa_x_preferred":[
        "Hondo Valle"
    ],
    "name:swe_x_preferred":[
        "Hondo Valle"
    ],
    "name:zho_x_preferred":[
        "\u7fc1\u591a\u93ae"
    ],
    "wof:name":"Hondo Valle",
    "wof:placetype":"locality"
},
  "geometry": {"coordinates":[-70.83333,18.88333],"type":"Point"}
}