{
  "type": "Feature",
  "properties": {
    "gn:admin1_code":"31.0",
    "gn:admin2_code":"2801.0",
    "gn:admin3_code":"280104.0",
    "gn:admin4_code":"28010402.0",
    "gn:asciiname":"Rio Piedra",
    "gn:country_code":"DO",
    "gn:dem":339,
    "gn:feature_class":"P",
    "gn:feature_code":"PPL",
    "gn:name":"R\u00edo Piedra",
    "gn:population":0,
    "gn:timezone":"America/Santo_Domingo",
    "iso:country":"DO",
    "wof:name":"Rio Piedra",
    "wof:placetype":"locality"
},
  "geometry": {"coordinates":[-70.45806999999998,18.90553],"type":"Point"}
}