{
  "type": "Feature",
  "properties": {
    "gn:admin1_code":"29.0",
    "gn:admin2_code":"3001.0",
    "gn:admin3_code":"300101.0",
    "gn:admin4_code":"30010102.0",
    "gn:asciiname":"Batey Hoyon",
    "gn:country_code":"DO",
    "gn:dem":57,
    "gn:feature_class":"P",
    "gn:feature_code":"PPL",
    "gn:name":"Batey Hoy\u00f3n",
    "gn:population":0,
    "gn:timezone":"America/Santo_Domingo",
    "iso:country":"DO",
    "name:und_x_variant":[
        "Hoy\u00f3n",
        "Batey Hoy\u00f3n"
    ],
    "wof:name":"Batey Hoyon",
    "wof:placetype":"locality"
},
  "geometry": {"coordinates":[-69.41812,18.72124],"type":"Point"}
}