{
  "type": "Feature",
  "properties": {
    "gn:admin1_code":"12.0",
    "gn:admin2_code":"1203.0",
    "gn:admin3_code":"120301.0",
    "gn:admin4_code":"12030101.0",
    "gn:asciiname":"Cumayasa Kilometros Cuarto y Medio",
    "gn:country_code":"DO",
    "gn:dem":61,
    "gn:feature_class":"P",
    "gn:feature_code":"PPL",
    "gn:name":"Cumayasa Kil\u00f3metros Cuarto y Medio",
    "gn:population":0,
    "gn:timezone":"America/Santo_Domingo",
    "iso:country":"DO",
    "name:und_x_variant":[
        "Cumayasa Kil\u00f3metros 4 1/2",
        "Cumayasa Kil\u00f3metros Cuarto y Medio"
    ],
    "wof:name":"Cumayasa Kilometros Cuarto y Medio",
    "wof:placetype":"locality"
},
  "geometry": {"coordinates":[-69.00856999999999,18.44614],"type":"Point"}
}