{
  "type": "Feature",
  "properties": {
    "gn:admin1_code":"21.0",
    "gn:admin2_code":"2404.0",
    "gn:admin3_code":"240404.0",
    "gn:admin4_code":"24040404.0",
    "gn:asciiname":"Los Cerros",
    "gn:country_code":"DO",
    "gn:dem":139,
    "gn:feature_class":"P",
    "gn:feature_code":"PPL",
    "gn:name":"Los Cerros",
    "gn:population":0,
    "gn:timezone":"America/Santo_Domingo",
    "iso:country":"DO",
    "wof:name":"Los Cerros",
    "wof:placetype":"locality"
},
  "geometry": {"coordinates":[-70.22943000000001,19.03962000000001],"type":"Point"}
}