{
  "type": "Feature",
  "properties": {
    "gn:admin1_code":"25.0",
    "gn:admin2_code":"2501.0",
    "gn:admin3_code":"250101.0",
    "gn:admin4_code":"25010108.0",
    "gn:asciiname":"La Guama",
    "gn:country_code":"DO",
    "gn:dem":822,
    "gn:feature_class":"P",
    "gn:feature_code":"PPL",
    "gn:name":"La Guama",
    "gn:population":0,
    "gn:timezone":"America/Santo_Domingo",
    "iso:country":"DO",
    "wof:name":"La Guama",
    "wof:placetype":"locality"
},
  "geometry": {"coordinates":[-70.64830000000001,19.56236],"type":"Point"}
}