{
  "type": "Feature",
  "properties": {
    "gn:admin1_code":"3.0",
    "gn:admin2_code":"401.0",
    "gn:admin3_code":"40101.0",
    "gn:admin4_code":"4010102.0",
    "gn:asciiname":"Payaso",
    "gn:country_code":"DO",
    "gn:dem":661,
    "gn:feature_class":"P",
    "gn:feature_code":"PPL",
    "gn:name":"Payaso",
    "gn:population":0,
    "gn:timezone":"America/Santo_Domingo",
    "iso:country":"DO",
    "name:und_x_variant":[
        "El Payaso",
        "Payaso"
    ],
    "wof:name":"Payaso",
    "wof:placetype":"locality"
},
  "geometry": {"coordinates":[-71.11620000000001,18.15186],"type":"Point"}
}