{
  "type": "Feature",
  "properties": {
    "gn:admin1_code":"29.0",
    "gn:admin2_code":"3002.0",
    "gn:admin3_code":"300201.0",
    "gn:admin4_code":"30020102.0",
    "gn:asciiname":"El Centro",
    "gn:country_code":"DO",
    "gn:dem":90,
    "gn:feature_class":"P",
    "gn:feature_code":"PPL",
    "gn:name":"El Centro",
    "gn:population":0,
    "gn:timezone":"America/Santo_Domingo",
    "iso:country":"DO",
    "wof:name":"El Centro",
    "wof:placetype":"locality"
},
  "geometry": {"coordinates":[-69.40568,19.0181],"type":"Point"}
}