{
  "type": "Feature",
  "properties": {
    "gn:admin1_code":"30.0",
    "gn:admin2_code":"1303.0",
    "gn:admin3_code":"130301.0",
    "gn:admin4_code":"13030108.0",
    "gn:asciiname":"La Jagua",
    "gn:country_code":"DO",
    "gn:dem":1013,
    "gn:feature_class":"P",
    "gn:feature_code":"PPL",
    "gn:name":"La Jagua",
    "gn:population":0,
    "gn:timezone":"America/Santo_Domingo",
    "iso:country":"DO",
    "wof:name":"La Jagua",
    "wof:placetype":"locality"
},
  "geometry": {"coordinates":[-70.62104000000002,19.06122],"type":"Point"}
}