{
  "type": "Feature",
  "properties": {
    "gn:country":"DO",
    "gn:fcode":"PPL",
    "gn:population":3816,
    "iso:country":"DO",
    "qs:name":"Tireo Arriba",
    "qs:photos_9r":0,
    "qs:photos_sr":0,
    "qs:pop_sr":"4",
    "wof:name":"Tireo Arriba",
    "wof:placetype":"locality",
    "wof:population":3816
},
  "geometry": {"coordinates":[-70.6885,18.93537],"type":"Point"}
}