{
  "type": "Feature",
  "properties": {
    "gn:admin1_code":"33.0",
    "gn:asciiname":"Los Manantiales",
    "gn:country_code":"DO",
    "gn:dem":440,
    "gn:feature_class":"P",
    "gn:feature_code":"PPL",
    "gn:name":"Los Manantiales",
    "gn:population":0,
    "gn:timezone":"America/Santo_Domingo",
    "iso:country":"DO",
    "name:und_x_variant":[
        "Manantiales",
        "Los Manantiales"
    ],
    "wof:name":"Los Manantiales",
    "wof:placetype":"locality"
},
  "geometry": {"coordinates":[-70.30065,18.47613],"type":"Point"}
}