{
  "type": "Feature",
  "properties": {
    "gn:admin1_code":"1.0",
    "gn:admin2_code":"201.0",
    "gn:admin3_code":"20109.0",
    "gn:admin4_code":"2010902.0",
    "gn:asciiname":"Las Yayitas",
    "gn:country_code":"DO",
    "gn:dem":224,
    "gn:feature_class":"P",
    "gn:feature_code":"PPL",
    "gn:name":"Las Yayitas",
    "gn:population":0,
    "gn:timezone":"America/Santo_Domingo",
    "iso:country":"DO",
    "name:und_x_variant":[
        "La Yayitas",
        "Las Yayistas",
        "Las Yayitas"
    ],
    "wof:name":"Las Yayitas",
    "wof:placetype":"locality"
},
  "geometry": {"coordinates":[-70.73727,18.49853],"type":"Point"}
}