{
  "type": "Feature",
  "properties": {
    "gn:admin1_code":"33.0",
    "gn:admin2_code":"2105.0",
    "gn:admin3_code":"210501.0",
    "gn:admin4_code":"21050103.0",
    "gn:asciiname":"Batey Los Guineos",
    "gn:country_code":"DO",
    "gn:dem":156,
    "gn:feature_class":"P",
    "gn:feature_code":"PPL",
    "gn:name":"Batey Los Guineos",
    "gn:population":0,
    "gn:timezone":"America/Santo_Domingo",
    "iso:country":"DO",
    "wof:name":"Batey Los Guineos",
    "wof:placetype":"locality"
},
  "geometry": {"coordinates":[-70.18875,18.6697],"type":"Point"}
}