{
  "type": "Feature",
  "properties": {
    "gn:admin1_code":"6.0",
    "gn:admin2_code":"601.0",
    "gn:admin3_code":"60101.0",
    "gn:admin4_code":"6010105.0",
    "gn:asciiname":"La Yagueiza",
    "gn:country_code":"DO",
    "gn:dem":184,
    "gn:feature_class":"P",
    "gn:feature_code":"PPL",
    "gn:name":"La Yag\u00fciza",
    "gn:population":0,
    "gn:timezone":"America/Santo_Domingo",
    "iso:country":"DO",
    "name:und_x_variant":[
        "Yaguiza",
        "La Yaq\u00fciza",
        "La Yag\u00fciza"
    ],
    "wof:name":"La Yagueiza",
    "wof:placetype":"locality"
},
  "geometry": {"coordinates":[-70.30685,19.36397],"type":"Point"}
}