{
  "type": "Feature",
  "properties": {
    "gn:admin1_code":"9.0",
    "gn:admin2_code":"1001.0",
    "gn:admin3_code":"100103.0",
    "gn:admin4_code":"10010302.0",
    "gn:asciiname":"Las Lajas",
    "gn:country_code":"DO",
    "gn:dem":38,
    "gn:feature_class":"P",
    "gn:feature_code":"PPL",
    "gn:name":"Las Lajas",
    "gn:population":0,
    "gn:timezone":"America/Santo_Domingo",
    "iso:country":"DO",
    "name:bre_x_preferred":[
        "Las Lajas"
    ],
    "name:ceb_x_preferred":[
        "Las Lajas"
    ],
    "name:deu_x_preferred":[
        "Las Lajas"
    ],
    "name:fra_x_preferred":[
        "Las Lajas"
    ],
    "name:ita_x_preferred":[
        "Las Lajas"
    ],
    "name:lit_x_preferred":[
        "Las Lachasas"
    ],
    "name:nld_x_preferred":[
        "Las Lajas"
    ],
    "name:pol_x_preferred":[
        "Las Lajas"
    ],
    "name:spa_x_preferred":[
        "Las Lajas"
    ],
    "name:swe_x_preferred":[
        "Las Lajas"
    ],
    "wof:name":"Las Lajas",
    "wof:placetype":"locality"
},
  "geometry": {"coordinates":[-71.97899,18.61066],"type":"Point"}
}