{
  "type": "Feature",
  "properties": {
    "iso:country":"DO",
    "name:ceb_x_preferred":[
        "Los Llanos"
    ],
    "name:chi_x_preferred":[
        "\u8056\u4f55\u585e\u5fb7\u6d1b\u65af\u5229\u4e9e\u8afe\u65af"
    ],
    "name:dut_x_preferred":[
        "San Jos\u00e9 de los Llanos"
    ],
    "name:eng_x_preferred":[
        "San Jos\u00e9 de los Llanos"
    ],
    "name:fre_x_preferred":[
        "San Jos\u00e9 de los Llanos"
    ],
    "name:ita_x_preferred":[
        "San Jos\u00e9 de los Llanos"
    ],
    "name:jpn_x_preferred":[
        "\u30ed\u30b9\u30fb\u30b8\u30e3\u30ce\u30b9"
    ],
    "name:nan_x_preferred":[
        "San Jos\u00e9 de los Llanos"
    ],
    "name:pol_x_preferred":[
        "San Jos\u00e9 de Los Llanos"
    ],
    "name:por_x_preferred":[
        "San Jos\u00e9 de los Llanos"
    ],
    "name:spa_x_preferred":[
        "San Jos\u00e9 de Los Llanos"
    ],
    "name:swe_x_preferred":[
        "Los Llanos"
    ],
    "name:unk_x_variant":[
        "San Jos\u00e9 de Los Llanos"
    ],
    "name:zho_min_nan_x_preferred":[
        "San Jos\u00e9 de los Llanos"
    ],
    "name:zho_x_preferred":[
        "\u8056\u4f55\u585e\u5fb7\u6d1b\u65af\u5229\u4e9e\u8afe\u65af"
    ],
    "qs:gn_country":"DO",
    "qs:gn_fcode":"PPL",
    "qs:gn_pop":5529,
    "qs:name":"Los Llanos",
    "qs:name_adm0":"Rep\u00fablica Dominicana",
    "qs:name_adm1":"San Pedro de Marcoris",
    "qs:photos":0,
    "qs:photos_1k":0,
    "qs:photos_9k":0,
    "qs:photos_9r":0,
    "qs:photos_all":0,
    "qs:photos_sr":0,
    "qs:placetype":"Town",
    "qs:pop_sr":"5",
    "qs:woe_adm0":23424800,
    "wof:name":"Los Llanos",
    "wof:placetype":"locality",
    "wof:population":5529
},
  "geometry": {"coordinates":[-69.49581000000001,18.62035],"type":"Point"}
}