{
  "type": "Feature",
  "properties": {
    "gn:admin1_code":"31.0",
    "gn:admin2_code":"2801.0",
    "gn:admin3_code":"280105.0",
    "gn:admin4_code":"28010502.0",
    "gn:asciiname":"El Cruce",
    "gn:country_code":"DO",
    "gn:dem":194,
    "gn:feature_class":"P",
    "gn:feature_code":"PPL",
    "gn:name":"El Cruce",
    "gn:population":0,
    "gn:timezone":"America/Santo_Domingo",
    "iso:country":"DO",
    "wof:name":"El Cruce",
    "wof:placetype":"locality"
},
  "geometry": {"coordinates":[-70.4389,18.98612],"type":"Point"}
}