{
  "type": "Feature",
  "properties": {
    "gn:admin1_code":"24.0",
    "gn:admin2_code":"2302.0",
    "gn:admin3_code":"230201.0",
    "gn:admin4_code":"23020104.0",
    "gn:asciiname":"Batey Casui",
    "gn:cc2":"DO",
    "gn:country_code":"DO",
    "gn:dem":20,
    "gn:feature_class":"P",
    "gn:feature_code":"PPL",
    "gn:name":"Batey Casu\u00ed",
    "gn:population":0,
    "gn:timezone":"America/Santo_Domingo",
    "iso:country":"DO",
    "name:und_x_variant":[
        "Cas\u00fa",
        "Cas\u00fa\u00ed",
        "Batey Casu\u00ed"
    ],
    "wof:name":"Batey Casui",
    "wof:placetype":"locality"
},
  "geometry": {"coordinates":[-69.41667,18.63333],"type":"Point"}
}