{
  "type": "Feature",
  "properties": {
    "gn:admin1_code":"26.0",
    "gn:admin2_code":"2601.0",
    "gn:admin3_code":"260101.0",
    "gn:admin4_code":"26010109.0",
    "gn:asciiname":"Canada de la Palma",
    "gn:country_code":"DO",
    "gn:dem":342,
    "gn:feature_class":"P",
    "gn:feature_code":"PPL",
    "gn:name":"Ca\u00f1ada de la Palma",
    "gn:population":0,
    "gn:timezone":"America/Santo_Domingo",
    "iso:country":"DO",
    "wof:name":"Canada de la Palma",
    "wof:placetype":"locality"
},
  "geometry": {"coordinates":[-71.32289,19.40052],"type":"Point"}
}