{
  "type": "Feature",
  "properties": {
    "gn:admin1_code":"10.0",
    "gn:admin2_code":"1101.0",
    "gn:admin3_code":"110104.0",
    "gn:admin4_code":"11010403.0",
    "gn:asciiname":"La Tierra",
    "gn:country_code":"DO",
    "gn:dem":14,
    "gn:feature_class":"P",
    "gn:feature_code":"PPL",
    "gn:name":"La Tierra",
    "gn:population":0,
    "gn:timezone":"America/Santo_Domingo",
    "iso:country":"DO",
    "wof:name":"La Tierra",
    "wof:placetype":"locality"
},
  "geometry": {"coordinates":[-68.59999999999999,18.78333],"type":"Point"}
}