{
  "type": "Feature",
  "properties": {
    "gn:admin1_code":"8.0",
    "gn:admin2_code":"901.0",
    "gn:admin3_code":"90103.0",
    "gn:admin4_code":"9010302.0",
    "gn:asciiname":"Guayabillo",
    "gn:country_code":"DO",
    "gn:dem":579,
    "gn:feature_class":"P",
    "gn:feature_code":"PPL",
    "gn:name":"Guayabillo",
    "gn:population":0,
    "gn:timezone":"America/Santo_Domingo",
    "iso:country":"DO",
    "wof:name":"Guayabillo",
    "wof:placetype":"locality"
},
  "geometry": {"coordinates":[-70.54619,19.4847],"type":"Point"}
}