{
  "type": "Feature",
  "properties": {
    "gn:admin1_code":"3.0",
    "gn:admin2_code":"403.0",
    "gn:admin3_code":"40301.0",
    "gn:admin4_code":"4030102.0",
    "gn:asciiname":"Penalva",
    "gn:country_code":"DO",
    "gn:dem":236,
    "gn:feature_class":"P",
    "gn:feature_code":"PPL",
    "gn:name":"Pe\u00f1alva",
    "gn:population":0,
    "gn:timezone":"America/Santo_Domingo",
    "iso:country":"DO",
    "name:bpy_x_preferred":[
        "\u09aa\u09c7\u09a8\u09be\u09b2\u09ad\u09be"
    ],
    "name:eus_x_preferred":[
        "Penalva"
    ],
    "name:fra_x_preferred":[
        "Penalva"
    ],
    "name:hye_x_preferred":[
        "\u054a\u0565\u0576\u0561\u056c\u057e\u0561"
    ],
    "name:ita_x_preferred":[
        "Penalva"
    ],
    "name:kat_x_preferred":[
        "\u10de\u10d4\u10dc\u10d0\u10da\u10d5\u10d0"
    ],
    "name:kaz_x_preferred":[
        "\u041f\u0435\u043d\u0430\u043b\u0432\u0430"
    ],
    "name:nld_x_preferred":[
        "Penalva"
    ],
    "name:nor_x_preferred":[
        "Penalva"
    ],
    "name:pol_x_preferred":[
        "Penalva"
    ],
    "name:por_x_preferred":[
        "Penalva"
    ],
    "name:ron_x_preferred":[
        "Penalva"
    ],
    "name:rus_x_preferred":[
        "\u041f\u0435\u043d\u0430\u043b\u0432\u0430"
    ],
    "name:spa_x_preferred":[
        "Penalva"
    ],
    "name:und_x_variant":[
        "Pe\u00f1alba",
        "Pe\u00f1alva"
    ],
    "name:vie_x_preferred":[
        "Penalva"
    ],
    "name:vol_x_preferred":[
        "Penalva"
    ],
    "name:war_x_preferred":[
        "Penalva"
    ],
    "name:zho_x_preferred":[
        "\u4f69\u7eb3\u5c14\u74e6"
    ],
    "wof:name":"Penalva",
    "wof:placetype":"locality"
},
  "geometry": {"coordinates":[-71.23860000000001,17.92987],"type":"Point"}
}