{
  "type": "Feature",
  "properties": {
    "gn:admin1_code":"3.0",
    "gn:admin2_code":"403.0",
    "gn:admin3_code":"40301.0",
    "gn:admin4_code":"4030102.0",
    "gn:asciiname":"Penalva",
    "gn:country_code":"DO",
    "gn:dem":236,
    "gn:feature_class":"P",
    "gn:feature_code":"PPL",
    "gn:name":"Pe\u00f1alva",
    "gn:population":0,
    "gn:timezone":"America/Santo_Domingo",
    "iso:country":"DO",
    "name:und_x_variant":[
        "Pe\u00f1alba",
        "Pe\u00f1alva"
    ],
    "wof:name":"Penalva",
    "wof:placetype":"locality"
},
  "geometry": {"coordinates":[-71.23860000000001,17.92987],"type":"Point"}
}