{
  "type": "Feature",
  "properties": {
    "gn:admin1_code":"37.0",
    "gn:admin2_code":"3203.0",
    "gn:admin3_code":"320301.0",
    "gn:admin4_code":"32030101.0",
    "gn:asciiname":"San Felipe",
    "gn:country_code":"DO",
    "gn:dem":49,
    "gn:feature_class":"P",
    "gn:feature_code":"PPL",
    "gn:name":"San Felipe",
    "gn:population":0,
    "gn:timezone":"America/Santo_Domingo",
    "iso:country":"DO",
    "wof:name":"San Felipe",
    "wof:placetype":"locality"
},
  "geometry": {"coordinates":[-69.91582,18.5726],"type":"Point"}
}