{
  "type": "Feature",
  "properties": {
    "gn:admin1_code":"21.0",
    "gn:admin2_code":"2401.0",
    "gn:admin3_code":"240101.0",
    "gn:admin4_code":"24010106.0",
    "gn:asciiname":"Sabana Grande Abajo",
    "gn:country_code":"DO",
    "gn:dem":60,
    "gn:feature_class":"P",
    "gn:feature_code":"PPL",
    "gn:name":"Sabana Grande Abajo",
    "gn:population":0,
    "gn:timezone":"America/Santo_Domingo",
    "iso:country":"DO",
    "name:spa_x_preferred":[
        "Sabana Grande Abajo"
    ],
    "name:und_x_variant":[
        "Sabana Grande",
        "Sabana Grande Abajo"
    ],
    "wof:name":"Sabana Grande Abajo",
    "wof:placetype":"locality"
},
  "geometry": {"coordinates":[-70.0921,19.04282000000001],"type":"Point"}
}