{
  "type": "Feature",
  "properties": {
    "gn:admin1_code":"15.0",
    "gn:admin2_code":"1503.0",
    "gn:admin3_code":"150304.0",
    "gn:admin4_code":"15030403.0",
    "gn:asciiname":"El Hospital",
    "gn:country_code":"DO",
    "gn:dem":95,
    "gn:feature_class":"P",
    "gn:feature_code":"PPL",
    "gn:name":"El Hospital",
    "gn:population":0,
    "gn:timezone":"America/Santo_Domingo",
    "iso:country":"DO",
    "wof:name":"El Hospital",
    "wof:placetype":"locality"
},
  "geometry": {"coordinates":[-71.28064999999999,19.59709],"type":"Point"}
}