{
  "type": "Feature",
  "properties": {
    "gn:admin1_code":"8.0",
    "gn:admin2_code":"903.0",
    "gn:admin3_code":"90304.0",
    "gn:admin4_code":"9030404.0",
    "gn:asciiname":"Magante",
    "gn:country_code":"DO",
    "gn:dem":60,
    "gn:feature_class":"P",
    "gn:feature_code":"PPL",
    "gn:name":"Magante",
    "gn:population":0,
    "gn:timezone":"America/Santo_Domingo",
    "iso:country":"DO",
    "wof:name":"Magante",
    "wof:placetype":"locality"
},
  "geometry": {"coordinates":[-70.13302,19.58234],"type":"Point"}
}