{
  "type": "Feature",
  "properties": {
    "gn:admin1_code":"27.0",
    "gn:asciiname":"Arroyo de Agua",
    "gn:country_code":"DO",
    "gn:dem":112,
    "gn:feature_class":"P",
    "gn:feature_code":"PPL",
    "gn:name":"Arroyo de Agua",
    "gn:population":0,
    "gn:timezone":"America/Santo_Domingo",
    "iso:country":"DO",
    "wof:name":"Arroyo de Agua",
    "wof:placetype":"locality"
},
  "geometry": {"coordinates":[-71.18333,19.55],"type":"Point"}
}