{
  "type": "Feature",
  "properties": {
    "gn:admin1_code":"11.0",
    "gn:admin2_code":"701.0",
    "gn:admin3_code":"70101.0",
    "gn:admin4_code":"7010108.0",
    "gn:asciiname":"El Pino",
    "gn:country_code":"DO",
    "gn:dem":396,
    "gn:feature_class":"P",
    "gn:feature_code":"PPL",
    "gn:name":"El Pino",
    "gn:population":0,
    "gn:timezone":"America/Santo_Domingo",
    "iso:country":"DO",
    "name:ast_x_preferred":[
        "El Pino"
    ],
    "name:ceb_x_preferred":[
        "El Pino"
    ],
    "name:deu_x_preferred":[
        "El Pino"
    ],
    "name:glg_x_preferred":[
        "O Pino"
    ],
    "name:spa_x_preferred":[
        "El Pino"
    ],
    "name:srp_x_preferred":[
        "\u0415\u043b \u041f\u0438\u043d\u043e"
    ],
    "name:swe_x_preferred":[
        "El Pino"
    ],
    "wof:name":"El Pino",
    "wof:placetype":"locality"
},
  "geometry": {"coordinates":[-71.66667,18.88333],"type":"Point"}
}