{
  "type": "Feature",
  "properties": {
    "gn:admin1_code":"11.0",
    "gn:admin2_code":"701.0",
    "gn:admin3_code":"70101.0",
    "gn:admin4_code":"7010108.0",
    "gn:asciiname":"El Pino",
    "gn:country_code":"DO",
    "gn:dem":396,
    "gn:feature_class":"P",
    "gn:feature_code":"PPL",
    "gn:name":"El Pino",
    "gn:population":0,
    "gn:timezone":"America/Santo_Domingo",
    "iso:country":"DO",
    "wof:name":"El Pino",
    "wof:placetype":"locality"
},
  "geometry": {"coordinates":[-71.66667,18.88333],"type":"Point"}
}