{
  "type": "Feature",
  "properties": {
    "gn:admin1_code":"15.0",
    "gn:admin2_code":"1503.0",
    "gn:admin3_code":"150304.0",
    "gn:admin4_code":"15030405.0",
    "gn:asciiname":"La Caida",
    "gn:country_code":"DO",
    "gn:dem":77,
    "gn:feature_class":"P",
    "gn:feature_code":"PPL",
    "gn:name":"La Ca\u00edda",
    "gn:population":0,
    "gn:timezone":"America/Santo_Domingo",
    "iso:country":"DO",
    "wof:name":"La Caida",
    "wof:placetype":"locality"
},
  "geometry": {"coordinates":[-71.17870000000001,19.58904],"type":"Point"}
}