{
  "type": "Feature",
  "properties": {
    "gn:admin1_code":"30.0",
    "gn:admin2_code":"1301.0",
    "gn:admin3_code":"130101.0",
    "gn:admin4_code":"13010117.0",
    "gn:asciiname":"El Mamey Abajo",
    "gn:country_code":"DO",
    "gn:dem":234,
    "gn:feature_class":"P",
    "gn:feature_code":"PPL",
    "gn:name":"El Mamey Abajo",
    "gn:population":0,
    "gn:timezone":"America/Santo_Domingo",
    "iso:country":"DO",
    "wof:name":"El Mamey Abajo",
    "wof:placetype":"locality"
},
  "geometry": {"coordinates":[-70.63415000000001,19.3288],"type":"Point"}
}