{
  "type": "Feature",
  "properties": {
    "gn:admin1_code":"25.0",
    "gn:admin2_code":"2505.0",
    "gn:admin3_code":"250502.0",
    "gn:admin4_code":"25050206.0",
    "gn:asciiname":"El Guayabo",
    "gn:country_code":"DO",
    "gn:dem":493,
    "gn:feature_class":"P",
    "gn:feature_code":"PPL",
    "gn:name":"El Guayabo",
    "gn:population":0,
    "gn:timezone":"America/Santo_Domingo",
    "iso:country":"DO",
    "wof:name":"El Guayabo",
    "wof:placetype":"locality"
},
  "geometry": {"coordinates":[-71.17381,19.35489],"type":"Point"}
}