{
  "type": "Feature",
  "properties": {
    "gn:admin1_code":"20.0",
    "gn:admin2_code":"2001.0",
    "gn:admin3_code":"200104.0",
    "gn:admin4_code":"20010402.0",
    "gn:asciiname":"La Llanada de Dionisio",
    "gn:country_code":"DO",
    "gn:dem":100,
    "gn:feature_class":"P",
    "gn:feature_code":"PPL",
    "gn:name":"La Llanada de Dionisio",
    "gn:population":0,
    "gn:timezone":"America/Santo_Domingo",
    "iso:country":"DO",
    "name:und_x_variant":[
        "Llanada de Dionisio",
        "La Llanada",
        "La Llanada de Dionisio"
    ],
    "wof:name":"La Llanada de Dionisio",
    "wof:placetype":"locality"
},
  "geometry": {"coordinates":[-69.22878,19.24727],"type":"Point"}
}