{
  "type": "Feature",
  "properties": {
    "gn:admin1_code":"36.0",
    "gn:admin2_code":"3102.0",
    "gn:admin3_code":"310201.0",
    "gn:admin4_code":"31020102.0",
    "gn:asciiname":"El Cacheo",
    "gn:country_code":"DO",
    "gn:dem":1147,
    "gn:feature_class":"P",
    "gn:feature_code":"PPL",
    "gn:name":"El Cacheo",
    "gn:population":0,
    "gn:timezone":"America/Santo_Domingo",
    "iso:country":"DO",
    "name:und_x_variant":[
        "El Caceo",
        "El Cacheo"
    ],
    "wof:name":"El Cacheo",
    "wof:placetype":"locality"
},
  "geometry": {"coordinates":[-70.55249999999999,18.64994],"type":"Point"}
}