{
  "type": "Feature",
  "properties": {
    "gn:admin1_code":"30.0",
    "gn:admin2_code":"1301.0",
    "gn:admin3_code":"130101.0",
    "gn:admin4_code":"13010111.0",
    "gn:asciiname":"La Torre",
    "gn:country_code":"DO",
    "gn:dem":222,
    "gn:feature_class":"P",
    "gn:feature_code":"PPL",
    "gn:name":"La Torre",
    "gn:population":0,
    "gn:timezone":"America/Santo_Domingo",
    "iso:country":"DO",
    "name:ara_x_preferred":[
        "\u0644\u0627 \u062a\u0648\u0631\u064a"
    ],
    "name:ast_x_preferred":[
        "La Torre"
    ],
    "name:azb_x_preferred":[
        "\u0644\u0627 \u062a\u0631\u0647"
    ],
    "name:cat_x_preferred":[
        "La Torre"
    ],
    "name:deu_x_preferred":[
        "La Torre"
    ],
    "name:eus_x_preferred":[
        "La Torre"
    ],
    "name:fas_x_preferred":[
        "\u0644\u0627 \u062a\u0631\u0647"
    ],
    "name:fra_x_preferred":[
        "La Torre"
    ],
    "name:hun_x_preferred":[
        "La Torre"
    ],
    "name:hye_x_preferred":[
        "\u053c\u0561 \u054f\u0578\u057c\u0565"
    ],
    "name:ina_x_preferred":[
        "La Torre"
    ],
    "name:ita_x_preferred":[
        "La Torre"
    ],
    "name:mkd_x_preferred":[
        "\u041b\u0430 \u0422\u0443\u0440\u0435"
    ],
    "name:msa_x_preferred":[
        "La Torre"
    ],
    "name:nld_x_preferred":[
        "La Torre"
    ],
    "name:oci_x_preferred":[
        "La Torre"
    ],
    "name:pol_x_preferred":[
        "La Torre"
    ],
    "name:por_x_preferred":[
        "La Torre"
    ],
    "name:rus_x_preferred":[
        "\u041b\u0430-\u0422\u043e\u0440\u0440\u0435"
    ],
    "name:spa_x_preferred":[
        "La Torre"
    ],
    "name:ukr_x_preferred":[
        "\u041b\u0430-\u0422\u043e\u0440\u0440\u0435"
    ],
    "name:und_x_variant":[
        "La Torre y Caimito"
    ],
    "name:uzb_x_preferred":[
        "La Torre"
    ],
    "name:vie_x_preferred":[
        "La Torre"
    ],
    "name:war_x_preferred":[
        "La Torre"
    ],
    "name:zho_x_preferred":[
        "\u62c9\u6258\u96f7"
    ],
    "wof:name":"La Torre",
    "wof:placetype":"locality"
},
  "geometry": {"coordinates":[-70.61881,19.34316],"type":"Point"}
}