{
  "type": "Feature",
  "properties": {
    "gn:admin1_code":"30.0",
    "gn:admin2_code":"1301.0",
    "gn:admin3_code":"130101.0",
    "gn:admin4_code":"13010111.0",
    "gn:asciiname":"La Torre",
    "gn:country_code":"DO",
    "gn:dem":222,
    "gn:feature_class":"P",
    "gn:feature_code":"PPL",
    "gn:name":"La Torre",
    "gn:population":0,
    "gn:timezone":"America/Santo_Domingo",
    "iso:country":"DO",
    "name:und_x_variant":[
        "La Torre y Caimito",
        "La Torre"
    ],
    "wof:name":"La Torre",
    "wof:placetype":"locality"
},
  "geometry": {"coordinates":[-70.61881,19.34316],"type":"Point"}
}