{
  "type": "Feature",
  "properties": {
    "gn:admin1_code":"18.0",
    "gn:admin2_code":"1802.0",
    "gn:admin3_code":"180201.0",
    "gn:admin4_code":"18020102.0",
    "gn:asciiname":"El Jamo",
    "gn:country_code":"DO",
    "gn:dem":377,
    "gn:feature_class":"P",
    "gn:feature_code":"PPL",
    "gn:name":"El Jamo",
    "gn:population":0,
    "gn:timezone":"America/Santo_Domingo",
    "iso:country":"DO",
    "wof:name":"El Jamo",
    "wof:placetype":"locality"
},
  "geometry": {"coordinates":[-70.83109,19.66277],"type":"Point"}
}