{
  "type": "Feature",
  "properties": {
    "gn:admin1_code":"36.0",
    "gn:admin2_code":"3101.0",
    "gn:admin3_code":"310103.0",
    "gn:admin4_code":"31010302.0",
    "gn:asciiname":"La Majagua",
    "gn:country_code":"DO",
    "gn:dem":836,
    "gn:feature_class":"P",
    "gn:feature_code":"PPL",
    "gn:name":"La Majagua",
    "gn:population":0,
    "gn:timezone":"America/Santo_Domingo",
    "iso:country":"DO",
    "wof:name":"La Majagua",
    "wof:placetype":"locality"
},
  "geometry": {"coordinates":[-70.41107,18.62214],"type":"Point"}
}