{
  "type": "Feature",
  "properties": {
    "gn:admin1_code":"25.0",
    "gn:admin2_code":"2505.0",
    "gn:admin3_code":"250502.0",
    "gn:admin4_code":"25050212.0",
    "gn:asciiname":"Cabreja",
    "gn:country_code":"DO",
    "gn:dem":471,
    "gn:feature_class":"P",
    "gn:feature_code":"PPL",
    "gn:name":"Cabreja",
    "gn:population":0,
    "gn:timezone":"America/Santo_Domingo",
    "iso:country":"DO",
    "wof:name":"Cabreja",
    "wof:placetype":"locality"
},
  "geometry": {"coordinates":[-71.10847,19.33848],"type":"Point"}
}