{
  "type": "Feature",
  "properties": {
    "gn:admin1_code":"1.0",
    "gn:admin2_code":"201.0",
    "gn:admin3_code":"20104.0",
    "gn:admin4_code":"2010401.0",
    "gn:asciiname":"Jura",
    "gn:country_code":"DO",
    "gn:dem":53,
    "gn:feature_class":"P",
    "gn:feature_code":"PPL",
    "gn:name":"Jura",
    "gn:population":0,
    "gn:timezone":"America/Santo_Domingo",
    "iso:country":"DO",
    "name:und_x_variant":[
        "Botado",
        "El Jura",
        "Jura"
    ],
    "wof:name":"Jura",
    "wof:placetype":"locality"
},
  "geometry": {"coordinates":[-70.77074,18.43857],"type":"Point"}
}