{
  "type": "Feature",
  "properties": {
    "gn:admin1_code":"10.0",
    "gn:admin2_code":"1101.0",
    "gn:admin3_code":"110101.0",
    "gn:admin4_code":"11010105.0",
    "gn:asciiname":"La Llanada",
    "gn:country_code":"DO",
    "gn:dem":142,
    "gn:feature_class":"P",
    "gn:feature_code":"PPL",
    "gn:name":"La Llanada",
    "gn:population":0,
    "gn:timezone":"America/Santo_Domingo",
    "iso:country":"DO",
    "name:und_x_variant":[
        "Las Llanadas",
        "La Llanada"
    ],
    "wof:name":"La Llanada",
    "wof:placetype":"locality"
},
  "geometry": {"coordinates":[-68.73295,18.66527],"type":"Point"}
}