{
  "type": "Feature",
  "properties": {
    "gn:admin1_code":"18.0",
    "gn:admin2_code":"1807.0",
    "gn:admin3_code":"180701.0",
    "gn:admin4_code":"18070103.0",
    "gn:asciiname":"Los Altos de Jalisco",
    "gn:country_code":"DO",
    "gn:dem":37,
    "gn:feature_class":"P",
    "gn:feature_code":"PPL",
    "gn:name":"Los Altos de Jalisco",
    "gn:population":0,
    "gn:timezone":"America/Santo_Domingo",
    "iso:country":"DO",
    "name:und_x_variant":[
        "Alto de los Peregrines",
        "Alto de Los Peregrinos",
        "Los Altos de Jalisco"
    ],
    "wof:name":"Los Altos de Jalisco",
    "wof:placetype":"locality"
},
  "geometry": {"coordinates":[-70.52863000000001,19.7457],"type":"Point"}
}