{
  "type": "Feature",
  "properties": {
    "gn:admin1_code":"28.0",
    "gn:admin2_code":"801.0",
    "gn:admin3_code":"80103.0",
    "gn:admin4_code":"8010303.0",
    "gn:asciiname":"Las Culebras",
    "gn:country_code":"DO",
    "gn:dem":300,
    "gn:feature_class":"P",
    "gn:feature_code":"PPL",
    "gn:name":"Las Culebras",
    "gn:population":0,
    "gn:timezone":"America/Santo_Domingo",
    "iso:country":"DO",
    "name:und_x_variant":[
        "La Culebra",
        "Las Culebras"
    ],
    "wof:name":"Las Culebras",
    "wof:placetype":"locality"
},
  "geometry": {"coordinates":[-69.25190000000001,18.84614],"type":"Point"}
}