{
  "type": "Feature",
  "properties": {
    "gn:admin1_code":"2.0",
    "gn:admin2_code":"303.0",
    "gn:admin3_code":"30303.0",
    "gn:admin4_code":"3030302.0",
    "gn:asciiname":"La Higueera",
    "gn:country_code":"DO",
    "gn:dem":61,
    "gn:feature_class":"P",
    "gn:feature_code":"PPL",
    "gn:name":"La Hig\u00fcera",
    "gn:population":0,
    "gn:timezone":"America/Santo_Domingo",
    "iso:country":"DO",
    "wof:name":"La Higueera",
    "wof:placetype":"locality"
},
  "geometry": {"coordinates":[-71.1382,18.42742],"type":"Point"}
}