{
  "type": "Feature",
  "properties": {
    "gn:admin1_code":"1.0",
    "gn:asciiname":"Carmono",
    "gn:cc2":"DO",
    "gn:country_code":"DO",
    "gn:dem":62,
    "gn:feature_class":"P",
    "gn:feature_code":"PPL",
    "gn:name":"Carmono",
    "gn:population":0,
    "gn:timezone":"America/Santo_Domingo",
    "iso:country":"DO",
    "name:und_x_variant":[
        "Carmona",
        "Carmono"
    ],
    "wof:name":"Carmono",
    "wof:placetype":"locality"
},
  "geometry": {"coordinates":[-70.51666999999998,18.28333],"type":"Point"}
}