{
  "type": "Feature",
  "properties": {
    "gn:admin1_code":"4.0",
    "gn:admin2_code":"503.0",
    "gn:admin3_code":"50301.0",
    "gn:admin4_code":"5030103.0",
    "gn:asciiname":"La Estancia",
    "gn:country_code":"DO",
    "gn:dem":265,
    "gn:feature_class":"P",
    "gn:feature_code":"PPL",
    "gn:name":"La Estancia",
    "gn:population":0,
    "gn:timezone":"America/Santo_Domingo",
    "iso:country":"DO",
    "wof:name":"La Estancia",
    "wof:placetype":"locality"
},
  "geometry": {"coordinates":[-71.51711999999998,19.44398],"type":"Point"}
}