{
  "type": "Feature",
  "properties": {
    "gn:admin1_code":"4.0",
    "gn:admin2_code":"501.0",
    "gn:admin3_code":"50101.0",
    "gn:admin4_code":"5010103.0",
    "gn:asciiname":"Lajas Arribas",
    "gn:country_code":"DO",
    "gn:dem":127,
    "gn:feature_class":"P",
    "gn:feature_code":"PPL",
    "gn:name":"Lajas Arribas",
    "gn:population":0,
    "gn:timezone":"America/Santo_Domingo",
    "iso:country":"DO",
    "wof:name":"Lajas Arribas",
    "wof:placetype":"locality"
},
  "geometry": {"coordinates":[-71.60666999999999,19.52791],"type":"Point"}
}