{
  "type": "Feature",
  "properties": {
    "gn:admin1_code":"30.0",
    "gn:admin2_code":"1304.0",
    "gn:admin3_code":"130401.0",
    "gn:admin4_code":"13040103.0",
    "gn:asciiname":"La Pina Vieja",
    "gn:country_code":"DO",
    "gn:dem":60,
    "gn:feature_class":"P",
    "gn:feature_code":"PPL",
    "gn:name":"La Pi\u00f1a Vieja",
    "gn:population":0,
    "gn:timezone":"America/Santo_Domingo",
    "iso:country":"DO",
    "wof:name":"La Pina Vieja",
    "wof:placetype":"locality"
},
  "geometry": {"coordinates":[-70.33333,19.13333],"type":"Point"}
}