{
  "type": "Feature",
  "properties": {
    "gn:admin1_code":"28.0",
    "gn:asciiname":"Sabana El Barrero",
    "gn:country_code":"DO",
    "gn:dem":98,
    "gn:feature_class":"P",
    "gn:feature_code":"PPL",
    "gn:name":"Sabana El Barrero",
    "gn:population":0,
    "gn:timezone":"America/Santo_Domingo",
    "iso:country":"DO",
    "wof:name":"Sabana El Barrero",
    "wof:placetype":"locality"
},
  "geometry": {"coordinates":[-68.77266,18.91163],"type":"Point"}
}