{
  "type": "Feature",
  "properties": {
    "gn:admin1_code":"18.0",
    "gn:admin2_code":"1805.0",
    "gn:admin3_code":"180502.0",
    "gn:admin4_code":"18050202.0",
    "gn:asciiname":"Verraco",
    "gn:country_code":"DO",
    "gn:dem":160,
    "gn:feature_class":"P",
    "gn:feature_code":"PPL",
    "gn:name":"Verraco",
    "gn:population":0,
    "gn:timezone":"America/Santo_Domingo",
    "iso:country":"DO",
    "name:und_x_variant":[
        "Los Verracos",
        "Los Berracos",
        "Verraco"
    ],
    "wof:name":"Verraco",
    "wof:placetype":"locality"
},
  "geometry": {"coordinates":[-70.99606999999997,19.75296],"type":"Point"}
}