{
  "type": "Feature",
  "properties": {
    "gn:admin1_code":"31.0",
    "gn:admin2_code":"2801.0",
    "gn:admin3_code":"280106.0",
    "gn:admin4_code":"28010603.0",
    "gn:asciiname":"Los Cascarones",
    "gn:country_code":"DO",
    "gn:dem":1149,
    "gn:feature_class":"P",
    "gn:feature_code":"PPL",
    "gn:name":"Los Cascarones",
    "gn:population":0,
    "gn:timezone":"America/Santo_Domingo",
    "iso:country":"DO",
    "wof:name":"Los Cascarones",
    "wof:placetype":"locality"
},
  "geometry": {"coordinates":[-70.54655,18.86822],"type":"Point"}
}