{
  "type": "Feature",
  "properties": {
    "gn:admin1_code":"6.0",
    "gn:admin2_code":"605.0",
    "gn:admin3_code":"60504.0",
    "gn:admin4_code":"6050402.0",
    "gn:asciiname":"Bombillo",
    "gn:country_code":"DO",
    "gn:dem":47,
    "gn:feature_class":"P",
    "gn:feature_code":"PPL",
    "gn:name":"Bombillo",
    "gn:population":0,
    "gn:timezone":"America/Santo_Domingo",
    "iso:country":"DO",
    "name:und_x_variant":[
        "El Bombillo",
        "Bombillo"
    ],
    "wof:name":"Bombillo",
    "wof:placetype":"locality"
},
  "geometry": {"coordinates":[-69.95841,19.19439],"type":"Point"}
}