{
  "type": "Feature",
  "properties": {
    "gn:admin1_code":"37.0",
    "gn:admin2_code":"3205.0",
    "gn:admin3_code":"320502.0",
    "gn:admin4_code":"32050201.0",
    "gn:asciiname":"Estorga",
    "gn:country_code":"DO",
    "gn:dem":32,
    "gn:feature_class":"P",
    "gn:feature_code":"PPL",
    "gn:name":"Estorga",
    "gn:population":0,
    "gn:timezone":"America/Santo_Domingo",
    "iso:country":"DO",
    "wof:name":"Estorga",
    "wof:placetype":"locality"
},
  "geometry": {"coordinates":[-69.60844,18.55103],"type":"Point"}
}