{
  "type": "Feature",
  "properties": {
    "gn:admin1_code":"27.0",
    "gn:admin2_code":"2703.0",
    "gn:admin3_code":"270302.0",
    "gn:admin4_code":"27030202.0",
    "gn:asciiname":"El Guabal",
    "gn:country_code":"DO",
    "gn:dem":50,
    "gn:feature_class":"P",
    "gn:feature_code":"PPL",
    "gn:name":"El Guabal",
    "gn:population":0,
    "gn:timezone":"America/Santo_Domingo",
    "iso:country":"DO",
    "wof:name":"El Guabal",
    "wof:placetype":"locality"
},
  "geometry": {"coordinates":[-71.13198,19.64006],"type":"Point"}
}