{
  "type": "Feature",
  "properties": {
    "gn:admin1_code":"20.0",
    "gn:admin2_code":"2001.0",
    "gn:admin3_code":"200101.0",
    "gn:admin4_code":"20010104.0",
    "gn:asciiname":"Los Platanos",
    "gn:country_code":"DO",
    "gn:dem":367,
    "gn:feature_class":"P",
    "gn:feature_code":"PPL",
    "gn:name":"Los Pl\u00e1tanos",
    "gn:population":0,
    "gn:timezone":"America/Santo_Domingo",
    "iso:country":"DO",
    "wof:name":"Los Platanos",
    "wof:placetype":"locality"
},
  "geometry": {"coordinates":[-69.38333,19.26667],"type":"Point"}
}