{
  "type": "Feature",
  "properties": {
    "gn:admin1_code":"10.0",
    "gn:admin2_code":"1102.0",
    "gn:admin3_code":"110201.0",
    "gn:admin4_code":"11020102.0",
    "gn:asciiname":"Cinco Palmas",
    "gn:cc2":"DO",
    "gn:country_code":"DO",
    "gn:dem":36,
    "gn:feature_class":"P",
    "gn:feature_code":"PPL",
    "gn:name":"Cinco Palmas",
    "gn:population":0,
    "gn:timezone":"America/Santo_Domingo",
    "iso:country":"DO",
    "name:und_x_variant":[
        "Cinco Palma",
        "Cinco Palmas"
    ],
    "wof:name":"Cinco Palmas",
    "wof:placetype":"locality"
},
  "geometry": {"coordinates":[-68.76666999999999,18.38333],"type":"Point"}
}