{
  "type": "Feature",
  "properties": {
    "gn:admin1_code":"32.0",
    "gn:admin2_code":"2905.0",
    "gn:admin3_code":"290501.0",
    "gn:admin4_code":"29050102.0",
    "gn:asciiname":"El Corozo Abajo",
    "gn:country_code":"DO",
    "gn:dem":150,
    "gn:feature_class":"P",
    "gn:feature_code":"PPL",
    "gn:name":"El Corozo Abajo",
    "gn:population":0,
    "gn:timezone":"America/Santo_Domingo",
    "iso:country":"DO",
    "wof:name":"El Corozo Abajo",
    "wof:placetype":"locality"
},
  "geometry": {"coordinates":[-70.04536,18.87297],"type":"Point"}
}