{
  "type": "Feature",
  "properties": {
    "gn:admin1_code":"32.0",
    "gn:admin2_code":"2905.0",
    "gn:admin3_code":"290501.0",
    "gn:admin4_code":"29050103.0",
    "gn:asciiname":"Cuancita",
    "gn:country_code":"DO",
    "gn:dem":249,
    "gn:feature_class":"P",
    "gn:feature_code":"PPL",
    "gn:name":"Cuancita",
    "gn:population":0,
    "gn:timezone":"America/Santo_Domingo",
    "iso:country":"DO",
    "wof:name":"Cuancita",
    "wof:placetype":"locality"
},
  "geometry": {"coordinates":[-70.11558000000001,18.82928],"type":"Point"}
}