{
  "type": "Feature",
  "properties": {
    "gn:admin1_code":"25.0",
    "gn:admin2_code":"2503.0",
    "gn:admin3_code":"250301.0",
    "gn:admin4_code":"25030105.0",
    "gn:asciiname":"La Cuchilla",
    "gn:country_code":"DO",
    "gn:dem":778,
    "gn:feature_class":"P",
    "gn:feature_code":"PPL",
    "gn:name":"La Cuchilla",
    "gn:population":0,
    "gn:timezone":"America/Santo_Domingo",
    "iso:country":"DO",
    "name:und_x_variant":[
        "Cuchilla",
        "La Cuchilla"
    ],
    "wof:name":"La Cuchilla",
    "wof:placetype":"locality"
},
  "geometry": {"coordinates":[-70.81187,19.24728],"type":"Point"}
}