{
  "type": "Feature",
  "properties": {
    "gn:admin1_code":"33.0",
    "gn:admin2_code":"2106.0",
    "gn:admin3_code":"210601.0",
    "gn:admin4_code":"21060103.0",
    "gn:asciiname":"Najayo al Medio",
    "gn:country_code":"DO",
    "gn:dem":80,
    "gn:feature_class":"P",
    "gn:feature_code":"PPL",
    "gn:name":"Najayo al Medio",
    "gn:population":0,
    "gn:timezone":"America/Santo_Domingo",
    "iso:country":"DO",
    "name:und_x_variant":[
        "Najayo en Medio",
        "Najayo al Medio"
    ],
    "wof:name":"Najayo al Medio",
    "wof:placetype":"locality"
},
  "geometry": {"coordinates":[-70.15013,18.34253],"type":"Point"}
}