{
  "type": "Feature",
  "properties": {
    "gn:admin1_code":"35.0",
    "gn:admin2_code":"1701.0",
    "gn:admin3_code":"170110.0",
    "gn:admin4_code":"17011002.0",
    "gn:asciiname":"Roblegar",
    "gn:country_code":"DO",
    "gn:dem":51,
    "gn:feature_class":"P",
    "gn:feature_code":"PPL",
    "gn:name":"Roblegar",
    "gn:population":0,
    "gn:timezone":"America/Santo_Domingo",
    "iso:country":"DO",
    "wof:name":"Roblegar",
    "wof:placetype":"locality"
},
  "geometry": {"coordinates":[-70.23654999999999,18.32333],"type":"Point"}
}