{
  "type": "Feature",
  "properties": {
    "gn:admin1_code":"25.0",
    "gn:admin2_code":"2505.0",
    "gn:admin3_code":"250501.0",
    "gn:admin4_code":"25050104.0",
    "gn:asciiname":"Mata Grande",
    "gn:country_code":"DO",
    "gn:dem":795,
    "gn:feature_class":"P",
    "gn:feature_code":"PPL",
    "gn:name":"Mata Grande",
    "gn:population":0,
    "gn:timezone":"America/Santo_Domingo",
    "iso:country":"DO",
    "name:und_x_variant":[
        "Meta Grande",
        "Mata Grande"
    ],
    "wof:name":"Mata Grande",
    "wof:placetype":"locality"
},
  "geometry": {"coordinates":[-70.96875,19.2073],"type":"Point"}
}