{
  "type": "Feature",
  "properties": {
    "gn:admin1_code":"32.0",
    "gn:admin2_code":"2904.0",
    "gn:admin3_code":"290401.0",
    "gn:admin4_code":"29040106.0",
    "gn:asciiname":"Pantoita",
    "gn:country_code":"DO",
    "gn:dem":98,
    "gn:feature_class":"P",
    "gn:feature_code":"PPL",
    "gn:name":"Panto\u00edta",
    "gn:population":0,
    "gn:timezone":"America/Santo_Domingo",
    "iso:country":"DO",
    "wof:name":"Pantoita",
    "wof:placetype":"locality"
},
  "geometry": {"coordinates":[-70.03414000000001,18.78718],"type":"Point"}
}