{
  "type": "Feature",
  "properties": {
    "gn:admin1_code":"32.0",
    "gn:admin2_code":"2905.0",
    "gn:admin3_code":"290501.0",
    "gn:admin4_code":"29050105.0",
    "gn:asciiname":"La Blanca",
    "gn:country_code":"DO",
    "gn:dem":159,
    "gn:feature_class":"P",
    "gn:feature_code":"PPL",
    "gn:name":"La Blanca",
    "gn:population":0,
    "gn:timezone":"America/Santo_Domingo",
    "iso:country":"DO",
    "name:ita_x_preferred":[
        "La Blanca"
    ],
    "name:por_x_preferred":[
        "La Blanca"
    ],
    "wof:name":"La Blanca",
    "wof:placetype":"locality"
},
  "geometry": {"coordinates":[-70.00588,18.82264],"type":"Point"}
}