{
  "type": "Feature",
  "properties": {
    "gn:admin1_code":"25.0",
    "gn:admin2_code":"2503.0",
    "gn:admin3_code":"250303.0",
    "gn:admin4_code":"25030304.0",
    "gn:asciiname":"Henequen",
    "gn:country_code":"DO",
    "gn:dem":533,
    "gn:feature_class":"P",
    "gn:feature_code":"PPL",
    "gn:name":"Henequ\u00e9n",
    "gn:population":0,
    "gn:timezone":"America/Santo_Domingo",
    "iso:country":"DO",
    "name:und_x_variant":[
        "El Henequ\u00e9n",
        "Henequ\u00e9n"
    ],
    "wof:name":"Henequen",
    "wof:placetype":"locality"
},
  "geometry": {"coordinates":[-70.7784,19.26835],"type":"Point"}
}