{
  "type": "Feature",
  "properties": {
    "gn:admin1_code":"19.0",
    "gn:admin2_code":"1902.0",
    "gn:admin3_code":"190201.0",
    "gn:admin4_code":"19020102.0",
    "gn:asciiname":"La Bajada",
    "gn:country_code":"DO",
    "gn:dem":307,
    "gn:feature_class":"P",
    "gn:feature_code":"PPL",
    "gn:name":"La Bajada",
    "gn:population":0,
    "gn:timezone":"America/Santo_Domingo",
    "iso:country":"DO",
    "wof:name":"La Bajada",
    "wof:placetype":"locality"
},
  "geometry": {"coordinates":[-70.31076,19.48838],"type":"Point"}
}