{
  "type": "Feature",
  "properties": {
    "gn:admin1_code":"1.0",
    "gn:admin2_code":"204.0",
    "gn:admin3_code":"20402.0",
    "gn:admin4_code":"2040204.0",
    "gn:asciiname":"Sabana de Las Canitas",
    "gn:cc2":"DO",
    "gn:country_code":"DO",
    "gn:dem":1404,
    "gn:feature_class":"P",
    "gn:feature_code":"PPL",
    "gn:name":"Sabana de Las Ca\u00f1itas",
    "gn:population":0,
    "gn:timezone":"America/Santo_Domingo",
    "iso:country":"DO",
    "name:und_x_variant":[
        "La Sabana de Las Ca\u00f1itas",
        "Las Ca\u00f1itas",
        "Sabana de Las Ca\u00f1itas"
    ],
    "wof:name":"Sabana de Las Canitas",
    "wof:placetype":"locality"
},
  "geometry": {"coordinates":[-70.90000000000001,18.86667000000001],"type":"Point"}
}