{
  "type": "Feature",
  "properties": {
    "gn:admin1_code":"24.0",
    "gn:admin2_code":"2302.0",
    "gn:admin3_code":"230201.0",
    "gn:admin4_code":"23020102.0",
    "gn:asciiname":"El Tintero",
    "gn:country_code":"DO",
    "gn:dem":43,
    "gn:feature_class":"P",
    "gn:feature_code":"PPL",
    "gn:name":"El Tintero",
    "gn:population":0,
    "gn:timezone":"America/Santo_Domingo",
    "iso:country":"DO",
    "name:und_x_variant":[
        "Tintero",
        "El Tintero"
    ],
    "wof:name":"El Tintero",
    "wof:placetype":"locality"
},
  "geometry": {"coordinates":[-69.49083,18.484],"type":"Point"}
}