{
  "type": "Feature",
  "properties": {
    "gn:admin1_code":"31.0",
    "gn:admin2_code":"2801.0",
    "gn:admin3_code":"280102.0",
    "gn:admin4_code":"28010203.0",
    "gn:asciiname":"La Vaca",
    "gn:country_code":"DO",
    "gn:dem":741,
    "gn:feature_class":"P",
    "gn:feature_code":"PPL",
    "gn:name":"La Vaca",
    "gn:population":0,
    "gn:timezone":"America/Santo_Domingo",
    "iso:country":"DO",
    "name:spa_x_preferred":[
        "Humedal La Vaca"
    ],
    "wof:name":"La Vaca",
    "wof:placetype":"locality"
},
  "geometry": {"coordinates":[-70.47915999999999,19.0303],"type":"Point"}
}