{
  "type": "Feature",
  "properties": {
    "gn:admin1_code":"10.0",
    "gn:admin2_code":"1102.0",
    "gn:admin3_code":"110201.0",
    "gn:admin4_code":"11020103.0",
    "gn:asciiname":"Canada de la Jina",
    "gn:country_code":"DO",
    "gn:dem":57,
    "gn:feature_class":"P",
    "gn:feature_code":"PPL",
    "gn:name":"Ca\u00f1ada de la Jina",
    "gn:population":0,
    "gn:timezone":"America/Santo_Domingo",
    "iso:country":"DO",
    "name:und_x_variant":[
        "La Gina",
        "Ca\u00f1ada la Jina",
        "Ca\u00f1ada",
        "Ca\u00f1ada de la Jina"
    ],
    "wof:name":"Canada de la Jina",
    "wof:placetype":"locality"
},
  "geometry": {"coordinates":[-68.83981999999999,18.46037],"type":"Point"}
}