{
  "type": "Feature",
  "properties": {
    "gn:admin1_code":"30.0",
    "gn:admin2_code":"1301.0",
    "gn:admin3_code":"130102.0",
    "gn:admin4_code":"13010208.0",
    "gn:asciiname":"La Destilera",
    "gn:country_code":"DO",
    "gn:dem":181,
    "gn:feature_class":"P",
    "gn:feature_code":"PPL",
    "gn:name":"La Destilera",
    "gn:population":0,
    "gn:timezone":"America/Santo_Domingo",
    "iso:country":"DO",
    "wof:name":"La Destilera",
    "wof:placetype":"locality"
},
  "geometry": {"coordinates":[-70.58161,19.3153],"type":"Point"}
}