{
  "type": "Feature",
  "properties": {
    "gn:admin1_code":"29.0",
    "gn:admin2_code":"3001.0",
    "gn:admin3_code":"300102.0",
    "gn:admin4_code":"30010202.0",
    "gn:asciiname":"Arroyo Higueero",
    "gn:country_code":"DO",
    "gn:dem":120,
    "gn:feature_class":"P",
    "gn:feature_code":"PPL",
    "gn:name":"Arroyo Hig\u00fcero",
    "gn:population":0,
    "gn:timezone":"America/Santo_Domingo",
    "iso:country":"DO",
    "wof:name":"Arroyo Higueero",
    "wof:placetype":"locality"
},
  "geometry": {"coordinates":[-69.33995,18.81574],"type":"Point"}
}