{
  "type": "Feature",
  "properties": {
    "gn:admin1_code":"37.0",
    "gn:admin2_code":"3203.0",
    "gn:admin3_code":"320301.0",
    "gn:admin4_code":"32030101.0",
    "gn:asciiname":"El Cachon",
    "gn:country_code":"DO",
    "gn:dem":29,
    "gn:feature_class":"P",
    "gn:feature_code":"PPL",
    "gn:name":"El Cach\u00f3n",
    "gn:population":0,
    "gn:timezone":"America/Santo_Domingo",
    "iso:country":"DO",
    "wof:name":"El Cachon",
    "wof:placetype":"locality"
},
  "geometry": {"coordinates":[-69.87619000000001,18.53607],"type":"Point"}
}