{
  "type": "Feature",
  "properties": {
    "gn:admin1_code":"8.0",
    "gn:admin2_code":"901.0",
    "gn:admin3_code":"90108.0",
    "gn:admin4_code":"9010803.0",
    "gn:asciiname":"Monte de la Jagua Arriba",
    "gn:country_code":"DO",
    "gn:dem":170,
    "gn:feature_class":"P",
    "gn:feature_code":"PPL",
    "gn:name":"Monte de la Jagua Arriba",
    "gn:population":0,
    "gn:timezone":"America/Santo_Domingo",
    "iso:country":"DO",
    "wof:name":"Monte de la Jagua Arriba",
    "wof:placetype":"locality"
},
  "geometry": {"coordinates":[-70.56115,19.39644],"type":"Point"}
}