{
  "type": "Feature",
  "properties": {
    "gn:admin1_code":"8.0",
    "gn:admin2_code":"903.0",
    "gn:admin3_code":"90303.0",
    "gn:admin4_code":"9030304.0",
    "gn:asciiname":"La Damajagua",
    "gn:country_code":"DO",
    "gn:dem":101,
    "gn:feature_class":"P",
    "gn:feature_code":"PPL",
    "gn:name":"La Damajagua",
    "gn:population":0,
    "gn:timezone":"America/Santo_Domingo",
    "iso:country":"DO",
    "wof:name":"La Damajagua",
    "wof:placetype":"locality"
},
  "geometry": {"coordinates":[-70.33710000000001,19.6368],"type":"Point"}
}