{
  "type": "Feature",
  "properties": {
    "gn:admin1_code":"25.0",
    "gn:admin2_code":"2503.0",
    "gn:admin3_code":"250301.0",
    "gn:admin4_code":"25030107.0",
    "gn:asciiname":"Gurabo",
    "gn:country_code":"DO",
    "gn:dem":390,
    "gn:feature_class":"P",
    "gn:feature_code":"PPL",
    "gn:name":"Gurabo",
    "gn:population":0,
    "gn:timezone":"America/Santo_Domingo",
    "iso:country":"DO",
    "name:ceb_x_preferred":[
        "Gurabo"
    ],
    "name:ita_x_preferred":[
        "Gurabo"
    ],
    "name:nld_x_preferred":[
        "Gurabo"
    ],
    "name:pol_x_preferred":[
        "Gurabo"
    ],
    "name:spa_x_preferred":[
        "Gurabo"
    ],
    "wof:name":"Gurabo",
    "wof:placetype":"locality"
},
  "geometry": {"coordinates":[-70.78793,19.32927],"type":"Point"}
}