{
  "type": "Feature",
  "properties": {
    "gn:admin1_code":"25.0",
    "gn:admin2_code":"2505.0",
    "gn:admin3_code":"250504.0",
    "gn:admin4_code":"25050405.0",
    "gn:asciiname":"Loma de los Rios",
    "gn:country_code":"DO",
    "gn:dem":1256,
    "gn:feature_class":"P",
    "gn:feature_code":"PPL",
    "gn:name":"Loma de los R\u00edos",
    "gn:population":0,
    "gn:timezone":"America/Santo_Domingo",
    "iso:country":"DO",
    "wof:name":"Loma de los Rios",
    "wof:placetype":"locality"
},
  "geometry": {"coordinates":[-70.89544000000002,19.14329],"type":"Point"}
}