{
  "type": "Feature",
  "properties": {
    "gn:admin1_code":"33.0",
    "gn:admin2_code":"2102.0",
    "gn:admin3_code":"210201.0",
    "gn:admin4_code":"21020102.0",
    "gn:asciiname":"Juan Baron",
    "gn:country_code":"DO",
    "gn:dem":37,
    "gn:feature_class":"P",
    "gn:feature_code":"PPL",
    "gn:name":"Juan Bar\u00f3n",
    "gn:population":0,
    "gn:timezone":"America/Santo_Domingo",
    "iso:country":"DO",
    "wof:name":"Juan Baron",
    "wof:placetype":"locality"
},
  "geometry": {"coordinates":[-70.17822,18.2522],"type":"Point"}
}