{
  "type": "Feature",
  "properties": {
    "gn:admin1_code":"25.0",
    "gn:admin2_code":"2501.0",
    "gn:admin3_code":"250101.0",
    "gn:admin4_code":"25010101.0",
    "gn:asciiname":"La Emboscada",
    "gn:cc2":"DO",
    "gn:country_code":"DO",
    "gn:dem":169,
    "gn:feature_class":"P",
    "gn:feature_code":"PPL",
    "gn:name":"La Emboscada",
    "gn:population":0,
    "gn:timezone":"America/Santo_Domingo",
    "iso:country":"DO",
    "name:und_x_variant":[
        "Rafel y Emboscada",
        "Emboscada Rafael y Hoyo de Lima",
        "Rafael Emboscada Hoya de Lima",
        "La Emboscada"
    ],
    "wof:name":"La Emboscada",
    "wof:placetype":"locality"
},
  "geometry": {"coordinates":[-70.73333000000002,19.46667],"type":"Point"}
}