{
  "type": "Feature",
  "properties": {
    "gn:admin1_code":"20.0",
    "gn:admin2_code":"2002.0",
    "gn:admin3_code":"200201.0",
    "gn:admin4_code":"20020105.0",
    "gn:asciiname":"Majagual",
    "gn:country_code":"DO",
    "gn:dem":28,
    "gn:feature_class":"P",
    "gn:feature_code":"PPL",
    "gn:name":"Majagual",
    "gn:population":0,
    "gn:timezone":"America/Santo_Domingo",
    "iso:country":"DO",
    "name:ceb_x_preferred":[
        "Majagual"
    ],
    "name:sco_x_preferred":[
        "Majagual"
    ],
    "name:swe_x_preferred":[
        "Majagual"
    ],
    "name:vie_x_preferred":[
        "Majagual"
    ],
    "wof:name":"Majagual",
    "wof:placetype":"locality"
},
  "geometry": {"coordinates":[-69.50588,19.2219],"type":"Point"}
}