{
  "type": "Feature",
  "properties": {
    "gn:admin1_code":"30.0",
    "gn:admin2_code":"1303.0",
    "gn:admin3_code":"130302.0",
    "gn:admin4_code":"13030204.0",
    "gn:asciiname":"Crucero",
    "gn:country_code":"DO",
    "gn:dem":600,
    "gn:feature_class":"P",
    "gn:feature_code":"PPL",
    "gn:name":"Crucero",
    "gn:population":0,
    "gn:timezone":"America/Santo_Domingo",
    "iso:country":"DO",
    "name:ceb_x_preferred":[
        "Crucero"
    ],
    "name:fas_x_preferred":[
        "\u06a9\u0631\u0648\u062b\u0631\u0648"
    ],
    "name:swe_x_preferred":[
        "Crucero"
    ],
    "wof:name":"Crucero",
    "wof:placetype":"locality"
},
  "geometry": {"coordinates":[-70.63668,19.18921],"type":"Point"}
}