{
  "type": "Feature",
  "properties": {
    "gn:admin1_code":"15.0",
    "gn:admin2_code":"1501.0",
    "gn:admin3_code":"150101.0",
    "gn:admin4_code":"15010103.0",
    "gn:asciiname":"Las Aguas",
    "gn:country_code":"DO",
    "gn:dem":13,
    "gn:feature_class":"P",
    "gn:feature_code":"PPL",
    "gn:name":"Las Aguas",
    "gn:population":0,
    "gn:timezone":"America/Santo_Domingo",
    "iso:country":"DO",
    "wof:name":"Las Aguas",
    "wof:placetype":"locality"
},
  "geometry": {"coordinates":[-71.59616,19.73586],"type":"Point"}
}