{
  "type": "Feature",
  "properties": {
    "gn:admin1_code":"9.0",
    "gn:admin2_code":"1001.0",
    "gn:admin3_code":"100101.0",
    "gn:admin4_code":"10010102.0",
    "gn:asciiname":"Hato Nuevo",
    "gn:country_code":"DO",
    "gn:dem":2,
    "gn:feature_class":"P",
    "gn:feature_code":"PPL",
    "gn:name":"Hato Nuevo",
    "gn:population":0,
    "gn:timezone":"America/Santo_Domingo",
    "iso:country":"DO",
    "wof:name":"Hato Nuevo",
    "wof:placetype":"locality"
},
  "geometry": {"coordinates":[-71.82194,18.49599],"type":"Point"}
}