{
  "type": "Feature",
  "properties": {
    "gn:admin1_code":"6.0",
    "gn:admin2_code":"601.0",
    "gn:admin3_code":"60103.0",
    "gn:admin4_code":"6010306.0",
    "gn:asciiname":"Mal Nombre",
    "gn:country_code":"DO",
    "gn:dem":56,
    "gn:feature_class":"P",
    "gn:feature_code":"PPL",
    "gn:name":"Mal Nombre",
    "gn:population":0,
    "gn:timezone":"America/Santo_Domingo",
    "iso:country":"DO",
    "wof:name":"Mal Nombre",
    "wof:placetype":"locality"
},
  "geometry": {"coordinates":[-70.30548,19.19094],"type":"Point"}
}