{
  "type": "Feature",
  "properties": {
    "gn:admin1_code":"10.0",
    "gn:admin2_code":"1101.0",
    "gn:admin3_code":"110103.0",
    "gn:admin4_code":"11010304.0",
    "gn:asciiname":"Hoyo del Isleno",
    "gn:country_code":"DO",
    "gn:dem":82,
    "gn:feature_class":"P",
    "gn:feature_code":"PPL",
    "gn:name":"Hoyo del Isle\u00f1o",
    "gn:population":0,
    "gn:timezone":"America/Santo_Domingo",
    "iso:country":"DO",
    "name:und_x_variant":[
        "Batey Los Isle\u00f1os",
        "El Hoyo del Isle\u00f1o",
        "Hoyo del Isle\u00f1o"
    ],
    "wof:name":"Hoyo del Isleno",
    "wof:placetype":"locality"
},
  "geometry": {"coordinates":[-68.61946,18.69184],"type":"Point"}
}