{
  "type": "Feature",
  "properties": {
    "gn:admin1_code":"33.0",
    "gn:admin2_code":"2103.0",
    "gn:admin3_code":"210301.0",
    "gn:admin4_code":"21030102.0",
    "gn:asciiname":"El Naranjal",
    "gn:country_code":"DO",
    "gn:dem":80,
    "gn:feature_class":"P",
    "gn:feature_code":"PPL",
    "gn:name":"El Naranjal",
    "gn:population":0,
    "gn:timezone":"America/Santo_Domingo",
    "iso:country":"DO",
    "wof:name":"El Naranjal",
    "wof:placetype":"locality"
},
  "geometry": {"coordinates":[-70.04655,18.4134],"type":"Point"}
}