{
  "type": "Feature",
  "properties": {
    "gn:admin1_code":"4.0",
    "gn:admin2_code":"502.0",
    "gn:admin3_code":"50202.0",
    "gn:admin4_code":"5020203.0",
    "gn:asciiname":"La Penita Abajo",
    "gn:country_code":"DO",
    "gn:dem":149,
    "gn:feature_class":"P",
    "gn:feature_code":"PPL",
    "gn:name":"La Pe\u00f1ita Abajo",
    "gn:population":0,
    "gn:timezone":"America/Santo_Domingo",
    "iso:country":"DO",
    "wof:name":"La Penita Abajo",
    "wof:placetype":"locality"
},
  "geometry": {"coordinates":[-71.66504999999999,19.45422],"type":"Point"}
}