{
  "type": "Feature",
  "properties": {
    "gn:admin1_code":"8.0",
    "gn:admin2_code":"903.0",
    "gn:admin3_code":"90302.0",
    "gn:admin4_code":"9030204.0",
    "gn:asciiname":"La Lomota",
    "gn:country_code":"DO",
    "gn:dem":127,
    "gn:feature_class":"P",
    "gn:feature_code":"PPL",
    "gn:name":"La Lomota",
    "gn:population":0,
    "gn:timezone":"America/Santo_Domingo",
    "iso:country":"DO",
    "wof:name":"La Lomota",
    "wof:placetype":"locality"
},
  "geometry": {"coordinates":[-70.28872,19.56294],"type":"Point"}
}