{
  "type": "Feature",
  "properties": {
    "gn:admin1_code":"35.0",
    "gn:admin2_code":"1702.0",
    "gn:admin3_code":"170201.0",
    "gn:admin4_code":"17020102.0",
    "gn:asciiname":"Sabana Jovero",
    "gn:cc2":"DO",
    "gn:country_code":"DO",
    "gn:dem":6,
    "gn:feature_class":"P",
    "gn:feature_code":"PPL",
    "gn:name":"Sabana Jovero",
    "gn:population":0,
    "gn:timezone":"America/Santo_Domingo",
    "iso:country":"DO",
    "name:und_x_variant":[
        "Sabana Jobero",
        "Sabana Jovero"
    ],
    "wof:name":"Sabana Jovero",
    "wof:placetype":"locality"
},
  "geometry": {"coordinates":[-70.23333000000001,18.23333],"type":"Point"}
}