{
  "type": "Feature",
  "properties": {
    "gn:admin1_code":"26.0",
    "gn:admin2_code":"2602.0",
    "gn:admin3_code":"260201.0",
    "gn:admin4_code":"26020105.0",
    "gn:asciiname":"Palma Larga",
    "gn:country_code":"DO",
    "gn:dem":416,
    "gn:feature_class":"P",
    "gn:feature_code":"PPL",
    "gn:name":"Palma Larga",
    "gn:population":0,
    "gn:timezone":"America/Santo_Domingo",
    "iso:country":"DO",
    "wof:name":"Palma Larga",
    "wof:placetype":"locality"
},
  "geometry": {"coordinates":[-71.45881999999997,19.36115],"type":"Point"}
}