{
  "type": "Feature",
  "properties": {
    "gn:admin1_code":"37.0",
    "gn:admin2_code":"3205.0",
    "gn:admin3_code":"320502.0",
    "gn:admin4_code":"32050204.0",
    "gn:asciiname":"Pantaleon",
    "gn:country_code":"DO",
    "gn:dem":23,
    "gn:feature_class":"P",
    "gn:feature_code":"PPL",
    "gn:name":"Pantale\u00f3n",
    "gn:population":0,
    "gn:timezone":"America/Santo_Domingo",
    "iso:country":"DO",
    "name:ben_x_preferred":[
        "\u09aa\u09be\u09a8\u09cd\u09a4\u09be\u09b2\u09bf\u0993\u09a8"
    ],
    "name:bul_x_preferred":[
        "\u041f\u0430\u043d\u0442\u0430\u043b\u0435\u043e\u043d"
    ],
    "name:deu_x_preferred":[
        "Pantaleon"
    ],
    "name:fra_x_preferred":[
        "Pantal\u00e9on"
    ],
    "name:ita_x_preferred":[
        "Pantaleone d'India"
    ],
    "name:pol_x_preferred":[
        "Pantaleon Baktryjski"
    ],
    "name:por_x_preferred":[
        "Pantale\u00e3o"
    ],
    "name:spa_x_preferred":[
        "Pantale\u00f3n"
    ],
    "name:ukr_x_preferred":[
        "\u041f\u0430\u043d\u0442\u0430\u043b\u0435\u043e\u043d"
    ],
    "name:vie_x_preferred":[
        "Pantaleontos"
    ],
    "name:zho_x_preferred":[
        "\u6f58\u9054\u96f7\u6602"
    ],
    "wof:name":"Pantaleon",
    "wof:placetype":"locality"
},
  "geometry": {"coordinates":[-69.61497,18.53958],"type":"Point"}
}