{
  "type": "Feature",
  "properties": {
    "gn:admin1_code":"37.0",
    "gn:admin2_code":"3205.0",
    "gn:admin3_code":"320502.0",
    "gn:admin4_code":"32050204.0",
    "gn:asciiname":"Pantaleon",
    "gn:country_code":"DO",
    "gn:dem":23,
    "gn:feature_class":"P",
    "gn:feature_code":"PPL",
    "gn:name":"Pantale\u00f3n",
    "gn:population":0,
    "gn:timezone":"America/Santo_Domingo",
    "iso:country":"DO",
    "wof:name":"Pantaleon",
    "wof:placetype":"locality"
},
  "geometry": {"coordinates":[-69.61497,18.53958],"type":"Point"}
}