{
  "type": "Feature",
  "properties": {
    "gn:admin1_code":"32.0",
    "gn:admin2_code":"2904.0",
    "gn:admin3_code":"290401.0",
    "gn:admin4_code":"29040106.0",
    "gn:asciiname":"Mayiga Arriba",
    "gn:country_code":"DO",
    "gn:dem":238,
    "gn:feature_class":"P",
    "gn:feature_code":"PPL",
    "gn:name":"M\u00e1yiga Arriba",
    "gn:population":0,
    "gn:timezone":"America/Santo_Domingo",
    "iso:country":"DO",
    "wof:name":"Mayiga Arriba",
    "wof:placetype":"locality"
},
  "geometry": {"coordinates":[-70.15055,18.75981],"type":"Point"}
}