{
  "type": "Feature",
  "properties": {
    "gn:admin1_code":"30.0",
    "gn:admin2_code":"1301.0",
    "gn:admin3_code":"130104.0",
    "gn:admin4_code":"13010404.0",
    "gn:asciiname":"El Capa",
    "gn:country_code":"DO",
    "gn:dem":430,
    "gn:feature_class":"P",
    "gn:feature_code":"PPL",
    "gn:name":"El Cap\u00e1",
    "gn:population":0,
    "gn:timezone":"America/Santo_Domingo",
    "iso:country":"DO",
    "wof:name":"El Capa",
    "wof:placetype":"locality"
},
  "geometry": {"coordinates":[-70.63913000000002,19.25262],"type":"Point"}
}