{
  "type": "Feature",
  "properties": {
    "gn:admin1_code":"37.0",
    "gn:asciiname":"Agua del Rey",
    "gn:country_code":"DO",
    "gn:dem":-9999,
    "gn:feature_class":"P",
    "gn:feature_code":"PPL",
    "gn:name":"Agua del Rey",
    "gn:population":0,
    "gn:timezone":"America/Santo_Domingo",
    "iso:country":"DO",
    "name:und_x_variant":[
        "Agua de Rey",
        "Agua del Rey"
    ],
    "wof:name":"Agua del Rey",
    "wof:placetype":"locality"
},
  "geometry": {"coordinates":[-69.58333,18.43333],"type":"Point"}
}