{
  "type": "Feature",
  "properties": {
    "gn:admin1_code":"36.0",
    "gn:admin2_code":"3101.0",
    "gn:admin3_code":"310102.0",
    "gn:admin4_code":"31010204.0",
    "gn:asciiname":"El Toro",
    "gn:country_code":"DO",
    "gn:dem":900,
    "gn:feature_class":"P",
    "gn:feature_code":"PPL",
    "gn:name":"El Toro",
    "gn:population":0,
    "gn:timezone":"America/Santo_Domingo",
    "iso:country":"DO",
    "name:ceb_x_preferred":[
        "El Toro"
    ],
    "name:deu_x_preferred":[
        "El Toro"
    ],
    "name:fra_x_preferred":[
        "El Toro"
    ],
    "name:ita_x_preferred":[
        "El Toro"
    ],
    "name:nld_x_preferred":[
        "El Toro"
    ],
    "name:pol_x_preferred":[
        "El Toro"
    ],
    "name:spa_x_preferred":[
        "El Toro"
    ],
    "name:srp_x_preferred":[
        "\u0415\u043b \u0422\u043e\u0440\u043e"
    ],
    "name:swe_x_preferred":[
        "El Toro"
    ],
    "wof:name":"El Toro",
    "wof:placetype":"locality"
},
  "geometry": {"coordinates":[-70.39685,18.60983],"type":"Point"}
}