{
  "type": "Feature",
  "properties": {
    "gn:admin1_code":"21.0",
    "gn:admin2_code":"2402.0",
    "gn:admin3_code":"240201.0",
    "gn:admin4_code":"24020102.0",
    "gn:asciiname":"Las Arenas",
    "gn:country_code":"DO",
    "gn:dem":66,
    "gn:feature_class":"P",
    "gn:feature_code":"PPL",
    "gn:name":"Las Arenas",
    "gn:population":0,
    "gn:timezone":"America/Santo_Domingo",
    "iso:country":"DO",
    "name:cat_x_preferred":[
        "Areeta"
    ],
    "name:eus_x_preferred":[
        "Areeta"
    ],
    "name:fra_x_preferred":[
        "Areeta"
    ],
    "name:glg_x_preferred":[
        "Areeta"
    ],
    "name:ita_x_preferred":[
        "Las Arenas"
    ],
    "name:spa_x_preferred":[
        "Las Arenas"
    ],
    "name:und_x_variant":[
        "Batey Las Arenas",
        "Las Arenas"
    ],
    "wof:name":"Las Arenas",
    "wof:placetype":"locality"
},
  "geometry": {"coordinates":[-69.9358,18.94391],"type":"Point"}
}