{
  "type": "Feature",
  "properties": {
    "gn:admin1_code":"6.0",
    "gn:admin2_code":"601.0",
    "gn:admin3_code":"60103.0",
    "gn:admin4_code":"6010304.0",
    "gn:asciiname":"La Nasa",
    "gn:country_code":"DO",
    "gn:dem":87,
    "gn:feature_class":"P",
    "gn:feature_code":"PPL",
    "gn:name":"La Nasa",
    "gn:population":0,
    "gn:timezone":"America/Santo_Domingo",
    "iso:country":"DO",
    "name:und_x_variant":[
        "La Naza",
        "La Nasa"
    ],
    "wof:name":"La Nasa",
    "wof:placetype":"locality"
},
  "geometry": {"coordinates":[-70.32455,19.28789],"type":"Point"}
}