{
  "type": "Feature",
  "properties": {
    "gn:admin1_code":"33.0",
    "gn:admin2_code":"2105.0",
    "gn:admin3_code":"210503.0",
    "gn:admin4_code":"21050305.0",
    "gn:asciiname":"Media Cara",
    "gn:country_code":"DO",
    "gn:dem":166,
    "gn:feature_class":"P",
    "gn:feature_code":"PPL",
    "gn:name":"Media Cara",
    "gn:population":0,
    "gn:timezone":"America/Santo_Domingo",
    "iso:country":"DO",
    "wof:name":"Media Cara",
    "wof:placetype":"locality"
},
  "geometry": {"coordinates":[-70.13387,18.51459],"type":"Point"}
}