{
  "type": "Feature",
  "properties": {
    "gn:admin1_code":"18.0",
    "gn:admin2_code":"1806.0",
    "gn:admin3_code":"180604.0",
    "gn:admin4_code":"18060404.0",
    "gn:asciiname":"Martin Alonzo",
    "gn:country_code":"DO",
    "gn:dem":42,
    "gn:feature_class":"P",
    "gn:feature_code":"PPL",
    "gn:name":"Mart\u00edn Alonzo",
    "gn:population":0,
    "gn:timezone":"America/Santo_Domingo",
    "iso:country":"DO",
    "name:und_x_variant":[
        "Mart\u00edn Alonso",
        "Mart\u00edn Alonzo"
    ],
    "wof:name":"Martin Alonzo",
    "wof:placetype":"locality"
},
  "geometry": {"coordinates":[-70.97439,19.82196],"type":"Point"}
}