{
  "type": "Feature",
  "properties": {
    "gn:admin1_code":"20.0",
    "gn:admin2_code":"2001.0",
    "gn:admin3_code":"200102.0",
    "gn:admin4_code":"20010202.0",
    "gn:asciiname":"El Cafe",
    "gn:country_code":"DO",
    "gn:dem":50,
    "gn:feature_class":"P",
    "gn:feature_code":"PPL",
    "gn:name":"El Caf\u00e9",
    "gn:population":0,
    "gn:timezone":"America/Santo_Domingo",
    "iso:country":"DO",
    "wof:name":"El Cafe",
    "wof:placetype":"locality"
},
  "geometry": {"coordinates":[-69.43333,19.28333],"type":"Point"}
}