{
  "type": "Feature",
  "properties": {
    "gn:admin1_code":"21.0",
    "gn:admin2_code":"2401.0",
    "gn:admin3_code":"240103.0",
    "gn:admin4_code":"24010304.0",
    "gn:asciiname":"El Mogote",
    "gn:country_code":"DO",
    "gn:dem":278,
    "gn:feature_class":"P",
    "gn:feature_code":"PPL",
    "gn:name":"El Mogote",
    "gn:population":0,
    "gn:timezone":"America/Santo_Domingo",
    "iso:country":"DO",
    "name:und_x_variant":[
        "Mogote",
        "El Mogote"
    ],
    "wof:name":"El Mogote",
    "wof:placetype":"locality"
},
  "geometry": {"coordinates":[-70.27698000000001,18.95665],"type":"Point"}
}