{
  "type": "Feature",
  "properties": {
    "gn:admin1_code":"36.0",
    "gn:admin2_code":"3103.0",
    "gn:admin3_code":"310301.0",
    "gn:admin4_code":"31030103.0",
    "gn:asciiname":"El Candongo",
    "gn:country_code":"DO",
    "gn:dem":926,
    "gn:feature_class":"P",
    "gn:feature_code":"PPL",
    "gn:name":"El Candongo",
    "gn:population":0,
    "gn:timezone":"America/Santo_Domingo",
    "iso:country":"DO",
    "wof:name":"El Candongo",
    "wof:placetype":"locality"
},
  "geometry": {"coordinates":[-70.39261999999999,18.65857],"type":"Point"}
}