{
  "type": "Feature",
  "properties": {
    "gn:admin1_code":"24.0",
    "gn:admin2_code":"2303.0",
    "gn:admin3_code":"230301.0",
    "gn:admin4_code":"23030103.0",
    "gn:asciiname":"Batey Atilano Numero Uno",
    "gn:country_code":"DO",
    "gn:dem":49,
    "gn:feature_class":"P",
    "gn:feature_code":"PPL",
    "gn:name":"Batey Atilano N\u00famero Uno",
    "gn:population":0,
    "gn:timezone":"America/Santo_Domingo",
    "iso:country":"DO",
    "name:und_x_variant":[
        "Atilano N\u00famero 1",
        "Batey Atilano N\u00famero Uno"
    ],
    "wof:name":"Batey Atilano Numero Uno",
    "wof:placetype":"locality"
},
  "geometry": {"coordinates":[-69.19691999999999,18.57771],"type":"Point"}
}