{
  "type": "Feature",
  "properties": {
    "gn:gn_country":"DO",
    "gn:gn_fcode":"PPL",
    "gn:gn_pop":4054,
    "gn:population":4054,
    "iso:country":"DO",
    "name:dut_x_preferred":[
        "Los Botados"
    ],
    "name:eng_x_preferred":[
        "Los Botados"
    ],
    "name:por_x_preferred":[
        "Los Botados"
    ],
    "name:swe_x_preferred":[
        "Los Botados"
    ],
    "name:unk_x_variant":[
        "El Centro"
    ],
    "qs_pg:aaroncc":"DO",
    "qs_pg:gn_country":"DO",
    "qs_pg:gn_fcode":"PPL",
    "qs_pg:gn_pop":4054,
    "qs_pg:name":"Los Botados",
    "qs_pg:photos_9r":0,
    "qs_pg:photos_sr":0,
    "qs_pg:pop_sr":4,
    "qs_pg:qs_pg_placetype":"locality",
    "wof:name":"Los Botados",
    "wof:placetype":"locality",
    "wof:population":4054
},
  "geometry": {"coordinates":[-69.99536000000001,18.73226],"type":"Point"}
}