{
  "type": "Feature",
  "properties": {
    "gn:admin1_code":"36.0",
    "gn:admin2_code":"3101.0",
    "gn:admin3_code":"310104.0",
    "gn:admin4_code":"31010402.0",
    "gn:asciiname":"El Bejucal",
    "gn:country_code":"DO",
    "gn:dem":840,
    "gn:feature_class":"P",
    "gn:feature_code":"PPL",
    "gn:name":"El Bejucal",
    "gn:population":0,
    "gn:timezone":"America/Santo_Domingo",
    "iso:country":"DO",
    "name:und_x_variant":[
        "Bejucol",
        "Bejucal",
        "El Bejucal"
    ],
    "wof:name":"El Bejucal",
    "wof:placetype":"locality"
},
  "geometry": {"coordinates":[-70.57346,18.59584],"type":"Point"}
}