{
  "type": "Feature",
  "properties": {
    "gn:admin1_code":"23.0",
    "gn:admin2_code":"2204.0",
    "gn:admin3_code":"220401.0",
    "gn:admin4_code":"22040102.0",
    "gn:asciiname":"Loma Verde",
    "gn:country_code":"DO",
    "gn:dem":490,
    "gn:feature_class":"P",
    "gn:feature_code":"PPL",
    "gn:name":"Loma Verde",
    "gn:population":0,
    "gn:timezone":"America/Santo_Domingo",
    "iso:country":"DO",
    "wof:name":"Loma Verde",
    "wof:placetype":"locality"
},
  "geometry": {"coordinates":[-71.21666999999999,18.86667000000001],"type":"Point"}
}