{
  "type": "Feature",
  "properties": {
    "gn:admin1_code":"26.0",
    "gn:admin2_code":"2603.0",
    "gn:admin3_code":"260301.0",
    "gn:admin4_code":"26030103.0",
    "gn:asciiname":"Los Dajaos",
    "gn:country_code":"DO",
    "gn:dem":616,
    "gn:feature_class":"P",
    "gn:feature_code":"PPL",
    "gn:name":"Los Dajaos",
    "gn:population":0,
    "gn:timezone":"America/Santo_Domingo",
    "iso:country":"DO",
    "wof:name":"Los Dajaos",
    "wof:placetype":"locality"
},
  "geometry": {"coordinates":[-71.26785,19.31615],"type":"Point"}
}