{
  "type": "Feature",
  "properties": {
    "gn:admin1_code":"6.0",
    "gn:asciiname":"Firme Las Taranas",
    "gn:country_code":"DO",
    "gn:dem":281,
    "gn:feature_class":"P",
    "gn:feature_code":"PPL",
    "gn:name":"Firme Las Taranas",
    "gn:population":0,
    "gn:timezone":"America/Santo_Domingo",
    "iso:country":"DO",
    "wof:name":"Firme Las Taranas",
    "wof:placetype":"locality"
},
  "geometry": {"coordinates":[-69.94677,19.25669],"type":"Point"}
}