{
  "type": "Feature",
  "properties": {
    "gn:admin1_code":"31.0",
    "gn:admin2_code":"2801.0",
    "gn:admin3_code":"280105.0",
    "gn:admin4_code":"28010503.0",
    "gn:asciiname":"Jayaco Abajo",
    "gn:country_code":"DO",
    "gn:dem":158,
    "gn:feature_class":"P",
    "gn:feature_code":"PPL",
    "gn:name":"Jayaco Abajo",
    "gn:population":0,
    "gn:timezone":"America/Santo_Domingo",
    "iso:country":"DO",
    "wof:name":"Jayaco Abajo",
    "wof:placetype":"locality"
},
  "geometry": {"coordinates":[-70.41874,19.00806],"type":"Point"}
}