{
  "type": "Feature",
  "properties": {
    "gn:admin1_code":"25.0",
    "gn:admin2_code":"2501.0",
    "gn:admin3_code":"250106.0",
    "gn:admin4_code":"25010606.0",
    "gn:asciiname":"Jacagua al Medio",
    "gn:country_code":"DO",
    "gn:dem":238,
    "gn:feature_class":"P",
    "gn:feature_code":"PPL",
    "gn:name":"Jacagua al Medio",
    "gn:population":0,
    "gn:timezone":"America/Santo_Domingo",
    "iso:country":"DO",
    "wof:name":"Jacagua al Medio",
    "wof:placetype":"locality"
},
  "geometry": {"coordinates":[-70.68333,19.51667],"type":"Point"}
}