{
  "type": "Feature",
  "properties": {
    "gn:country":"DO",
    "gn:fcode":"PPL",
    "gn:pop":1623,
    "iso:country":"DO",
    "name:ceb_x_preferred":[
        "Juancho"
    ],
    "name:eng_x_preferred":[
        "Juancho"
    ],
    "name:ita_x_preferred":[
        "Juancho"
    ],
    "name:nld_x_preferred":[
        "Juancho"
    ],
    "name:por_x_preferred":[
        "Juancho"
    ],
    "name:spa_x_preferred":[
        "Juancho"
    ],
    "name:swe_x_preferred":[
        "Juancho"
    ],
    "name:unk_x_variant":[
        "Juana"
    ],
    "qs:name":"Juancho",
    "qs:photos_9r":0,
    "qs:photos_sr":0,
    "qs:pop_sr":"3",
    "wd:wordcount":41,
    "wof:name":"Juancho",
    "wof:placetype":"locality",
    "wof:population":1623
},
  "geometry": {"coordinates":[-71.29311,17.85782],"type":"Point"}
}