{
  "type": "Feature",
  "properties": {
    "gn:admin1_code":"30.0",
    "gn:admin2_code":"1303.0",
    "gn:admin3_code":"130303.0",
    "gn:admin4_code":"13030304.0",
    "gn:asciiname":"Los Dajaos",
    "gn:country_code":"DO",
    "gn:dem":893,
    "gn:feature_class":"P",
    "gn:feature_code":"PPL",
    "gn:name":"Los Dajaos",
    "gn:population":0,
    "gn:timezone":"America/Santo_Domingo",
    "iso:country":"DO",
    "wof:name":"Los Dajaos",
    "wof:placetype":"locality"
},
  "geometry": {"coordinates":[-70.76006,19.07522],"type":"Point"}
}