{
  "type": "Feature",
  "properties": {
    "gn:admin1_code":"15.0",
    "gn:admin2_code":"1501.0",
    "gn:admin3_code":"150101.0",
    "gn:admin4_code":"15010102.0",
    "gn:asciiname":"La Canada",
    "gn:country_code":"DO",
    "gn:dem":22,
    "gn:feature_class":"P",
    "gn:feature_code":"PPL",
    "gn:name":"La Ca\u00f1ada",
    "gn:population":0,
    "gn:timezone":"America/Santo_Domingo",
    "iso:country":"DO",
    "wof:name":"La Canada",
    "wof:placetype":"locality"
},
  "geometry": {"coordinates":[-71.61628,19.82419],"type":"Point"}
}