{
  "type": "Feature",
  "properties": {
    "gn:admin1_code":"36.0",
    "gn:admin2_code":"3103.0",
    "gn:admin3_code":"310301.0",
    "gn:admin4_code":"31030104.0",
    "gn:asciiname":"El Cajon",
    "gn:country_code":"DO",
    "gn:dem":984,
    "gn:feature_class":"P",
    "gn:feature_code":"PPL",
    "gn:name":"El Caj\u00f3n",
    "gn:population":0,
    "gn:timezone":"America/Santo_Domingo",
    "iso:country":"DO",
    "wof:name":"El Cajon",
    "wof:placetype":"locality"
},
  "geometry": {"coordinates":[-70.53333000000001,18.73333],"type":"Point"}
}