{
  "type": "Feature",
  "properties": {
    "gn:admin1_code":"6.0",
    "gn:admin2_code":"601.0",
    "gn:admin3_code":"60101.0",
    "gn:admin4_code":"6010107.0",
    "gn:asciiname":"Cano Claro",
    "gn:country_code":"DO",
    "gn:dem":438,
    "gn:feature_class":"P",
    "gn:feature_code":"PPL",
    "gn:name":"Ca\u00f1o Claro",
    "gn:population":0,
    "gn:timezone":"America/Santo_Domingo",
    "iso:country":"DO",
    "wof:name":"Cano Claro",
    "wof:placetype":"locality"
},
  "geometry": {"coordinates":[-70.21292,19.46495],"type":"Point"}
}