{
  "type": "Feature",
  "properties": {
    "gn:admin1_code":"14.0",
    "gn:admin2_code":"1401.0",
    "gn:admin3_code":"140104.0",
    "gn:admin4_code":"14010402.0",
    "gn:asciiname":"Monte Llano",
    "gn:country_code":"DO",
    "gn:dem":142,
    "gn:feature_class":"P",
    "gn:feature_code":"PPL",
    "gn:name":"Monte Llano",
    "gn:population":0,
    "gn:timezone":"America/Santo_Domingo",
    "iso:country":"DO",
    "wof:name":"Monte Llano",
    "wof:placetype":"locality"
},
  "geometry": {"coordinates":[-70.06116999999999,19.38025],"type":"Point"}
}