{
  "type": "Feature",
  "properties": {
    "gn:admin1_code":"18.0",
    "gn:admin2_code":"1806.0",
    "gn:admin3_code":"180602.0",
    "gn:admin4_code":"18060202.0",
    "gn:asciiname":"La Ceibita",
    "gn:country_code":"DO",
    "gn:dem":85,
    "gn:feature_class":"P",
    "gn:feature_code":"PPL",
    "gn:name":"La Ceibita",
    "gn:population":0,
    "gn:timezone":"America/Santo_Domingo",
    "iso:country":"DO",
    "wof:name":"La Ceibita",
    "wof:placetype":"locality"
},
  "geometry": {"coordinates":[-71.05853,19.89112],"type":"Point"}
}