{
  "type": "Feature",
  "properties": {
    "gn:admin1_code":"8.0",
    "gn:admin2_code":"903.0",
    "gn:admin3_code":"90304.0",
    "gn:admin4_code":"9030401.0",
    "gn:asciiname":"La Yagua",
    "gn:country_code":"DO",
    "gn:dem":22,
    "gn:feature_class":"P",
    "gn:feature_code":"PPL",
    "gn:name":"La Yagua",
    "gn:population":0,
    "gn:timezone":"America/Santo_Domingo",
    "iso:country":"DO",
    "wof:name":"La Yagua",
    "wof:placetype":"locality"
},
  "geometry": {"coordinates":[-70.17740000000001,19.61401],"type":"Point"}
}