{
  "type": "Feature",
  "properties": {
    "gn:admin1_code":"30.0",
    "gn:admin2_code":"1303.0",
    "gn:admin3_code":"130303.0",
    "gn:admin4_code":"13030303.0",
    "gn:asciiname":"El Paso de la Perra",
    "gn:country_code":"DO",
    "gn:dem":954,
    "gn:feature_class":"P",
    "gn:feature_code":"PPL",
    "gn:name":"El Paso de la Perra",
    "gn:population":0,
    "gn:timezone":"America/Santo_Domingo",
    "iso:country":"DO",
    "name:und_x_variant":[
        "Paso de la Perra",
        "El Paso de la Perra"
    ],
    "wof:name":"El Paso de la Perra",
    "wof:placetype":"locality"
},
  "geometry": {"coordinates":[-70.82680999999999,19.07379],"type":"Point"}
}