{
  "type": "Feature",
  "properties": {
    "gn:admin1_code":"25.0",
    "gn:admin2_code":"2505.0",
    "gn:admin3_code":"250502.0",
    "gn:admin4_code":"25050203.0",
    "gn:asciiname":"Los Corralitos",
    "gn:country_code":"DO",
    "gn:dem":386,
    "gn:feature_class":"P",
    "gn:feature_code":"PPL",
    "gn:name":"Los Corralitos",
    "gn:population":0,
    "gn:timezone":"America/Santo_Domingo",
    "iso:country":"DO",
    "name:und_x_variant":[
        "Corralitos",
        "Los Corralitos"
    ],
    "wof:name":"Los Corralitos",
    "wof:placetype":"locality"
},
  "geometry": {"coordinates":[-71.04546999999999,19.399],"type":"Point"}
}