{
  "type": "Feature",
  "properties": {
    "gn:admin1_code":"29.0",
    "gn:admin2_code":"3001.0",
    "gn:admin3_code":"300102.0",
    "gn:admin4_code":"30010202.0",
    "gn:asciiname":"Villila",
    "gn:country_code":"DO",
    "gn:dem":205,
    "gn:feature_class":"P",
    "gn:feature_code":"PPL",
    "gn:name":"Villila",
    "gn:population":0,
    "gn:timezone":"America/Santo_Domingo",
    "iso:country":"DO",
    "wof:name":"Villila",
    "wof:placetype":"locality"
},
  "geometry": {"coordinates":[-69.37447,18.81612],"type":"Point"}
}