{
  "type": "Feature",
  "properties": {
    "gn:gn_country":"DO",
    "gn:gn_fcode":"PPLX",
    "gn:gn_pop":0,
    "gn:population":18756,
    "iso:country":"DO",
    "name:ceb_x_preferred":[
        "Ciudad Nueva"
    ],
    "name:eng_x_preferred":[
        "Ciudad Nueva"
    ],
    "name:nld_x_preferred":[
        "Ciudad Nueva"
    ],
    "name:spa_x_preferred":[
        "Ciudad Nueva"
    ],
    "name:swe_x_preferred":[
        "Ciudad Nueva"
    ],
    "name:unk_x_variant":[
        "Ciudad Nueva"
    ],
    "qs_pg:aaroncc":"DO",
    "qs_pg:gn_country":"DO",
    "qs_pg:gn_fcode":"PPLX",
    "qs_pg:gn_pop":0,
    "qs_pg:name":"Ciudad Nueva",
    "qs_pg:name_adm0":"Rep\u00fablica Dominicana",
    "qs_pg:name_adm1":"Distrito Nacional",
    "qs_pg:photos":196,
    "qs_pg:photos_1k":40,
    "qs_pg:photos_9k":1,
    "qs_pg:photos_9r":4,
    "qs_pg:photos_all":196,
    "qs_pg:photos_sr":4,
    "qs_pg:pop_sr":0,
    "qs_pg:qs_pg_placetype":"neighbourhood",
    "qs_pg:qs_pg_placetype_gp":"Suburb",
    "qs_pg:woe_adm0":23424800,
    "woe:adm0_id":23424800,
    "woe:name_adm0":"Rep\u00fablica Dominicana",
    "woe:name_adm1":"Distrito Nacional",
    "woe:placetype":"Suburb",
    "wof:name":"Ciudad Nueva",
    "wof:placetype":"neighbourhood",
    "wof:population":18756
},
  "geometry": {"coordinates":[-69.90000000000001,18.46667],"type":"Point"}
}