{
  "type": "Feature",
  "properties": {
    "gn:admin1_code":"25.0",
    "gn:admin2_code":"2505.0",
    "gn:admin3_code":"250502.0",
    "gn:admin4_code":"25050212.0",
    "gn:asciiname":"Los Melones",
    "gn:country_code":"DO",
    "gn:dem":446,
    "gn:feature_class":"P",
    "gn:feature_code":"PPL",
    "gn:name":"Los Melones",
    "gn:population":0,
    "gn:timezone":"America/Santo_Domingo",
    "iso:country":"DO",
    "wof:name":"Los Melones",
    "wof:placetype":"locality"
},
  "geometry": {"coordinates":[-71.05624,19.35433],"type":"Point"}
}