{
  "type": "Feature",
  "properties": {
    "gn:admin1_code":"18.0",
    "gn:admin2_code":"1804.0",
    "gn:admin3_code":"180401.0",
    "gn:admin4_code":"18040103.0",
    "gn:asciiname":"El Hoyazo",
    "gn:country_code":"DO",
    "gn:dem":236,
    "gn:feature_class":"P",
    "gn:feature_code":"PPL",
    "gn:name":"El Hoyazo",
    "gn:population":0,
    "gn:timezone":"America/Santo_Domingo",
    "iso:country":"DO",
    "name:und_x_variant":[
        "El Hoyaso",
        "El Hoyazo"
    ],
    "wof:name":"El Hoyazo",
    "wof:placetype":"locality"
},
  "geometry": {"coordinates":[-70.91963,19.74356],"type":"Point"}
}