{
  "type": "Feature",
  "properties": {
    "gn:admin1_code":"15.0",
    "gn:admin2_code":"1501.0",
    "gn:admin3_code":"150101.0",
    "gn:admin4_code":"15010101.0",
    "gn:asciiname":"La Barca",
    "gn:country_code":"DO",
    "gn:dem":24,
    "gn:feature_class":"P",
    "gn:feature_code":"PPL",
    "gn:name":"La Barca",
    "gn:population":0,
    "gn:timezone":"America/Santo_Domingo",
    "iso:country":"DO",
    "name:ceb_x_preferred":[
        "La Barca"
    ],
    "name:deu_x_preferred":[
        "La Barca"
    ],
    "name:ita_x_preferred":[
        "La barca"
    ],
    "name:spa_x_preferred":[
        "La Barca"
    ],
    "name:swe_x_preferred":[
        "La Barca"
    ],
    "wof:name":"La Barca",
    "wof:placetype":"locality"
},
  "geometry": {"coordinates":[-71.65000000000001,19.83333],"type":"Point"}
}