{
  "type": "Feature",
  "properties": {
    "gn:admin1_code":"28.0",
    "gn:admin2_code":"801.0",
    "gn:admin3_code":"80102.0",
    "gn:admin4_code":"8010203.0",
    "gn:asciiname":"El Grumo",
    "gn:country_code":"DO",
    "gn:dem":367,
    "gn:feature_class":"P",
    "gn:feature_code":"PPL",
    "gn:name":"El Grumo",
    "gn:population":0,
    "gn:timezone":"America/Santo_Domingo",
    "iso:country":"DO",
    "wof:name":"El Grumo",
    "wof:placetype":"locality"
},
  "geometry": {"coordinates":[-69.13283,18.86318],"type":"Point"}
}