{
  "type": "Feature",
  "properties": {
    "gn:admin1_code":"4.0",
    "gn:admin2_code":"504.0",
    "gn:admin3_code":"50401.0",
    "gn:admin4_code":"5040105.0",
    "gn:asciiname":"Las Rosas",
    "gn:country_code":"DO",
    "gn:dem":619,
    "gn:feature_class":"P",
    "gn:feature_code":"PPL",
    "gn:name":"Las Rosas",
    "gn:population":0,
    "gn:timezone":"America/Santo_Domingo",
    "iso:country":"DO",
    "wof:name":"Las Rosas",
    "wof:placetype":"locality"
},
  "geometry": {"coordinates":[-71.56928000000001,19.28733],"type":"Point"}
}