{
  "type": "Feature",
  "properties": {
    "gn:admin1_code":"8.0",
    "gn:asciiname":"La Cruz de Bonagua",
    "gn:country_code":"DO",
    "gn:dem":184,
    "gn:feature_class":"P",
    "gn:feature_code":"PPL",
    "gn:name":"La Cruz de Bonagua",
    "gn:population":0,
    "gn:timezone":"America/Santo_Domingo",
    "iso:country":"DO",
    "wof:name":"La Cruz de Bonagua",
    "wof:placetype":"locality"
},
  "geometry": {"coordinates":[-70.56641,19.35143],"type":"Point"}
}