{
  "type": "Feature",
  "properties": {
    "gn:admin1_code":"36.0",
    "gn:admin2_code":"3101.0",
    "gn:admin3_code":"310102.0",
    "gn:admin4_code":"31010203.0",
    "gn:asciiname":"Arenazo",
    "gn:country_code":"DO",
    "gn:dem":674,
    "gn:feature_class":"P",
    "gn:feature_code":"PPL",
    "gn:name":"Arenazo",
    "gn:population":0,
    "gn:timezone":"America/Santo_Domingo",
    "iso:country":"DO",
    "name:und_x_variant":[
        "Arenoso",
        "El Arenazo",
        "Arenazo"
    ],
    "wof:name":"Arenazo",
    "wof:placetype":"locality"
},
  "geometry": {"coordinates":[-70.45928000000001,18.58256],"type":"Point"}
}