{
  "type": "Feature",
  "properties": {
    "gn:admin1_code":"32.0",
    "gn:admin2_code":"2904.0",
    "gn:admin3_code":"290403.0",
    "gn:admin4_code":"29040303.0",
    "gn:asciiname":"Maimon",
    "gn:country_code":"DO",
    "gn:dem":157,
    "gn:feature_class":"P",
    "gn:feature_code":"PPL",
    "gn:name":"Maim\u00f3n",
    "gn:population":0,
    "gn:timezone":"America/Santo_Domingo",
    "iso:country":"DO",
    "wof:name":"Maimon",
    "wof:placetype":"locality"
},
  "geometry": {"coordinates":[-70.08583,18.71536],"type":"Point"}
}