{
  "type": "Feature",
  "properties": {
    "gn:admin1_code":"33.0",
    "gn:admin2_code":"2107.0",
    "gn:admin3_code":"210701.0",
    "gn:admin4_code":"21070104.0",
    "gn:asciiname":"Hato Viejo",
    "gn:country_code":"DO",
    "gn:dem":32,
    "gn:feature_class":"P",
    "gn:feature_code":"PPL",
    "gn:name":"Hato Viejo",
    "gn:population":0,
    "gn:timezone":"America/Santo_Domingo",
    "iso:country":"DO",
    "wof:name":"Hato Viejo",
    "wof:placetype":"locality"
},
  "geometry": {"coordinates":[-70.07643,18.35588],"type":"Point"}
}