{
  "type": "Feature",
  "properties": {
    "gn:admin1_code":"20.0",
    "gn:admin2_code":"2002.0",
    "gn:admin3_code":"200201.0",
    "gn:admin4_code":"20020104.0",
    "gn:asciiname":"Palmar Nuevo",
    "gn:country_code":"DO",
    "gn:dem":7,
    "gn:feature_class":"P",
    "gn:feature_code":"PPL",
    "gn:name":"Palmar Nuevo",
    "gn:population":0,
    "gn:timezone":"America/Santo_Domingo",
    "iso:country":"DO",
    "wof:name":"Palmar Nuevo",
    "wof:placetype":"locality"
},
  "geometry": {"coordinates":[-69.70565000000001,19.14894],"type":"Point"}
}