{
  "type": "Feature",
  "properties": {
    "gn:admin1_code":"15.0",
    "gn:admin2_code":"1501.0",
    "gn:admin3_code":"150101.0",
    "gn:admin4_code":"15010102.0",
    "gn:asciiname":"Los Cementos",
    "gn:country_code":"DO",
    "gn:dem":9,
    "gn:feature_class":"P",
    "gn:feature_code":"PPL",
    "gn:name":"Los Cementos",
    "gn:population":0,
    "gn:timezone":"America/Santo_Domingo",
    "iso:country":"DO",
    "wof:name":"Los Cementos",
    "wof:placetype":"locality"
},
  "geometry": {"coordinates":[-71.57444,19.77797],"type":"Point"}
}