{
  "type": "Feature",
  "properties": {
    "gn:admin1_code":"15.0",
    "gn:admin2_code":"1503.0",
    "gn:admin3_code":"150304.0",
    "gn:admin4_code":"15030404.0",
    "gn:asciiname":"Piloto",
    "gn:country_code":"DO",
    "gn:dem":59,
    "gn:feature_class":"P",
    "gn:feature_code":"PPL",
    "gn:name":"Piloto",
    "gn:population":0,
    "gn:timezone":"America/Santo_Domingo",
    "iso:country":"DO",
    "wof:name":"Piloto",
    "wof:placetype":"locality"
},
  "geometry": {"coordinates":[-71.20480000000001,19.60105],"type":"Point"}
}