{
  "type": "Feature",
  "properties": {
    "gn:admin1_code":"18.0",
    "gn:admin2_code":"1802.0",
    "gn:admin3_code":"180201.0",
    "gn:admin4_code":"18020103.0",
    "gn:asciiname":"Los Chicharrones",
    "gn:country_code":"DO",
    "gn:dem":960,
    "gn:feature_class":"P",
    "gn:feature_code":"PPL",
    "gn:name":"Los Chicharrones",
    "gn:population":0,
    "gn:timezone":"America/Santo_Domingo",
    "iso:country":"DO",
    "wof:name":"Los Chicharrones",
    "wof:placetype":"locality"
},
  "geometry": {"coordinates":[-70.75514,19.60424],"type":"Point"}
}