{
  "type": "Feature",
  "properties": {
    "gn:admin1_code":"24.0",
    "gn:admin2_code":"2305.0",
    "gn:admin3_code":"230501.0",
    "gn:admin4_code":"23050102.0",
    "gn:asciiname":"La Barca",
    "gn:country_code":"DO",
    "gn:dem":39,
    "gn:feature_class":"P",
    "gn:feature_code":"PPL",
    "gn:name":"La Barca",
    "gn:population":0,
    "gn:timezone":"America/Santo_Domingo",
    "iso:country":"DO",
    "name:ara_x_preferred":[
        "\u0644\u0627 \u0628\u0627\u0631\u0643\u0627"
    ],
    "name:ben_x_preferred":[
        "\u09b2\u09be \u09ac\u09be\u09b0\u09cd\u0995\u09be"
    ],
    "name:ceb_x_preferred":[
        "La Barca"
    ],
    "name:deu_x_preferred":[
        "La Barca"
    ],
    "name:ell_x_preferred":[
        "\u039b\u03b1 \u039c\u03c0\u03ac\u03c1\u03ba\u03b1"
    ],
    "name:fas_x_preferred":[
        "\u0644\u0627 \u0628\u0627\u0631\u0633\u0627"
    ],
    "name:heb_x_preferred":[
        "\u05dc\u05d4 \u05d1\u05e8\u05e7\u05d4"
    ],
    "name:hin_x_preferred":[
        "\u0932\u093e \u092c\u093e\u0930\u094d\u0915\u093e"
    ],
    "name:hun_x_preferred":[
        "La Barca"
    ],
    "name:ind_x_preferred":[
        "La Barca"
    ],
    "name:ita_x_preferred":[
        "La barca"
    ],
    "name:jpn_x_preferred":[
        "\u30e9\u30d0\u30eb\u30ab"
    ],
    "name:kor_x_preferred":[
        "\ub77c \ubc14\ub974\uce74"
    ],
    "name:pol_x_preferred":[
        "La Barca"
    ],
    "name:spa_x_preferred":[
        "La Barca"
    ],
    "name:swe_x_preferred":[
        "La Barca"
    ],
    "name:tur_x_preferred":[
        "La Barca"
    ],
    "name:ukr_x_preferred":[
        "\u041b\u0430-\u0411\u0430\u0440\u043a\u0430"
    ],
    "name:zho_cn_x_preferred":[
        "\u62c9\u5df4\u5c14\u5361"
    ],
    "name:zho_tw_x_preferred":[
        "\u62c9\u5df4\u5361"
    ],
    "wof:name":"La Barca",
    "wof:placetype":"locality"
},
  "geometry": {"coordinates":[-69.34159,18.50425],"type":"Point"}
}