{
  "type": "Feature",
  "properties": {
    "gn:admin1_code":"21.0",
    "gn:admin2_code":"2403.0",
    "gn:admin3_code":"240301.0",
    "gn:admin4_code":"24030102.0",
    "gn:asciiname":"Cojobal",
    "gn:country_code":"DO",
    "gn:dem":109,
    "gn:feature_class":"P",
    "gn:feature_code":"PPL",
    "gn:name":"Cojobal",
    "gn:population":0,
    "gn:timezone":"America/Santo_Domingo",
    "iso:country":"DO",
    "wof:name":"Cojobal",
    "wof:placetype":"locality"
},
  "geometry": {"coordinates":[-70.28230000000001,19.06341],"type":"Point"}
}