{
  "type": "Feature",
  "properties": {
    "gn:admin1_code":"18.0",
    "gn:admin2_code":"1801.0",
    "gn:admin3_code":"180102.0",
    "gn:admin4_code":"18010202.0",
    "gn:asciiname":"Los Martinez",
    "gn:country_code":"DO",
    "gn:dem":118,
    "gn:feature_class":"P",
    "gn:feature_code":"PPL",
    "gn:name":"Los Mart\u00ednez",
    "gn:population":0,
    "gn:timezone":"America/Santo_Domingo",
    "iso:country":"DO",
    "wof:name":"Los Martinez",
    "wof:placetype":"locality"
},
  "geometry": {"coordinates":[-70.55988000000001,19.62698],"type":"Point"}
}