{
  "type": "Feature",
  "properties": {
    "gn:admin1_code":"23.0",
    "gn:admin2_code":"2206.0",
    "gn:admin3_code":"220602.0",
    "gn:admin4_code":"22060202.0",
    "gn:asciiname":"Sabana Lino",
    "gn:country_code":"DO",
    "gn:dem":962,
    "gn:feature_class":"P",
    "gn:feature_code":"PPL",
    "gn:name":"Sabana Lino",
    "gn:population":0,
    "gn:timezone":"America/Santo_Domingo",
    "iso:country":"DO",
    "wof:name":"Sabana Lino",
    "wof:placetype":"locality"
},
  "geometry": {"coordinates":[-71.43333,18.71667],"type":"Point"}
}