{
  "type": "Feature",
  "properties": {
    "gn:country":"DO",
    "gn:fcode":"PPL",
    "gn:pop":5909,
    "iso:country":"DO",
    "name:cat_x_preferred":[
        "Rincon"
    ],
    "name:ceb_x_preferred":[
        "Rincon"
    ],
    "name:ita_x_preferred":[
        "Rincon"
    ],
    "name:jpn_x_preferred":[
        "\u30ea\u30f3\u30b3\u30f3"
    ],
    "name:nld_x_preferred":[
        "Rincon"
    ],
    "name:pol_x_preferred":[
        "Rincon"
    ],
    "name:por_x_preferred":[
        "Rincon"
    ],
    "name:rus_x_preferred":[
        "\u0420\u0438\u043d\u043a\u043e\u043d"
    ],
    "name:srp_x_preferred":[
        "\u0420\u0438\u043d\u043a\u043e\u043d"
    ],
    "name:swe_x_preferred":[
        "Rincon"
    ],
    "name:ukr_x_preferred":[
        "\u0420\u0456\u043d\u043a\u043e\u043d"
    ],
    "name:vol_x_preferred":[
        "Rincon"
    ],
    "qs:name":"Rinc\u00f3n",
    "qs:photos_9r":0,
    "qs:photos_sr":0,
    "qs:pop_sr":"5",
    "wd:wordcount":430,
    "wof:name":"Rinc\u00f3n",
    "wof:placetype":"locality",
    "wof:population":5909
},
  "geometry": {"coordinates":[-70.40631999999999,19.11938],"type":"Point"}
}