{
  "type": "Feature",
  "properties": {
    "gn:admin1_code":"2.0",
    "gn:admin2_code":"303.0",
    "gn:admin3_code":"30303.0",
    "gn:admin4_code":"3030301.0",
    "gn:asciiname":"La Caida",
    "gn:country_code":"DO",
    "gn:dem":40,
    "gn:feature_class":"P",
    "gn:feature_code":"PPL",
    "gn:name":"La Ca\u00edda",
    "gn:population":0,
    "gn:timezone":"America/Santo_Domingo",
    "iso:country":"DO",
    "wof:name":"La Caida",
    "wof:placetype":"locality"
},
  "geometry": {"coordinates":[-71.19179,18.41286],"type":"Point"}
}