{
  "type": "Feature",
  "properties": {
    "gn:admin1_code":"3.0",
    "gn:admin2_code":"411.0",
    "gn:admin3_code":"41101.0",
    "gn:admin4_code":"4110102.0",
    "gn:asciiname":"Puerto Alejandro",
    "gn:country_code":"DO",
    "gn:dem":9,
    "gn:feature_class":"P",
    "gn:feature_code":"PPL",
    "gn:name":"Puerto Alejandro",
    "gn:population":0,
    "gn:timezone":"America/Santo_Domingo",
    "iso:country":"DO",
    "wof:name":"Puerto Alejandro",
    "wof:placetype":"locality"
},
  "geometry": {"coordinates":[-71.03333000000001,18.31667],"type":"Point"}
}