{
  "type": "Feature",
  "properties": {
    "gn:admin1_code":"6.0",
    "gn:admin2_code":"605.0",
    "gn:admin3_code":"60501.0",
    "gn:admin4_code":"6050102.0",
    "gn:asciiname":"Ceiba de Los Pajaros",
    "gn:country_code":"DO",
    "gn:dem":22,
    "gn:feature_class":"P",
    "gn:feature_code":"PPL",
    "gn:name":"Ceiba de Los P\u00e1jaros",
    "gn:population":0,
    "gn:timezone":"America/Santo_Domingo",
    "iso:country":"DO",
    "name:und_x_variant":[
        "La Ceyba de Los Pajaros",
        "Ceiba de Los P\u00e1jaros"
    ],
    "wof:name":"Ceiba de Los Pajaros",
    "wof:placetype":"locality"
},
  "geometry": {"coordinates":[-69.9066,19.1494],"type":"Point"}
}