{
  "type": "Feature",
  "properties": {
    "gn:admin1_code":"26.0",
    "gn:admin2_code":"2601.0",
    "gn:admin3_code":"260101.0",
    "gn:admin4_code":"26010111.0",
    "gn:asciiname":"Los Patios",
    "gn:country_code":"DO",
    "gn:dem":1055,
    "gn:feature_class":"P",
    "gn:feature_code":"PPL",
    "gn:name":"Los Patios",
    "gn:population":0,
    "gn:timezone":"America/Santo_Domingo",
    "iso:country":"DO",
    "wof:name":"Los Patios",
    "wof:placetype":"locality"
},
  "geometry": {"coordinates":[-71.28216,19.19284],"type":"Point"}
}