{
  "type": "Feature",
  "properties": {
    "gn:admin1_code":"29.0",
    "gn:admin2_code":"3001.0",
    "gn:admin3_code":"300102.0",
    "gn:admin4_code":"30010203.0",
    "gn:asciiname":"El Retiro",
    "gn:country_code":"DO",
    "gn:dem":112,
    "gn:feature_class":"P",
    "gn:feature_code":"PPL",
    "gn:name":"El Retiro",
    "gn:population":0,
    "gn:timezone":"America/Santo_Domingo",
    "iso:country":"DO",
    "wof:name":"El Retiro",
    "wof:placetype":"locality"
},
  "geometry": {"coordinates":[-69.31718000000001,18.76163],"type":"Point"}
}