{
  "type": "Feature",
  "properties": {
    "gn:admin1_code":"1.0",
    "gn:admin2_code":"208.0",
    "gn:admin3_code":"20804.0",
    "gn:admin4_code":"2080402.0",
    "gn:asciiname":"Cuesta Blanca",
    "gn:country_code":"DO",
    "gn:dem":210,
    "gn:feature_class":"P",
    "gn:feature_code":"PPL",
    "gn:name":"Cuesta Blanca",
    "gn:population":0,
    "gn:timezone":"America/Santo_Domingo",
    "iso:country":"DO",
    "wof:name":"Cuesta Blanca",
    "wof:placetype":"locality"
},
  "geometry": {"coordinates":[-70.87186,18.52724],"type":"Point"}
}