{
  "type": "Feature",
  "properties": {
    "gn:admin1_code":"28.0",
    "gn:admin2_code":"801.0",
    "gn:admin3_code":"80101.0",
    "gn:admin4_code":"8010105.0",
    "gn:asciiname":"Paso Dos Bocas",
    "gn:cc2":"DO",
    "gn:country_code":"DO",
    "gn:dem":167,
    "gn:feature_class":"P",
    "gn:feature_code":"PPL",
    "gn:name":"Paso Dos Bocas",
    "gn:population":0,
    "gn:timezone":"America/Santo_Domingo",
    "iso:country":"DO",
    "name:und_x_variant":[
        "Las Dos Bocas",
        "Dos Bocas",
        "Paso Dos Bocas"
    ],
    "wof:name":"Paso Dos Bocas",
    "wof:placetype":"locality"
},
  "geometry": {"coordinates":[-68.98333000000001,18.83333],"type":"Point"}
}