{
  "type": "Feature",
  "properties": {
    "gn:admin1_code":"15.0",
    "gn:admin2_code":"1503.0",
    "gn:admin3_code":"150304.0",
    "gn:admin4_code":"15030403.0",
    "gn:asciiname":"Ranchadero",
    "gn:country_code":"DO",
    "gn:dem":42,
    "gn:feature_class":"P",
    "gn:feature_code":"PPL",
    "gn:name":"Ranchadero",
    "gn:population":0,
    "gn:timezone":"America/Santo_Domingo",
    "iso:country":"DO",
    "wof:name":"Ranchadero",
    "wof:placetype":"locality"
},
  "geometry": {"coordinates":[-71.37396,19.65349],"type":"Point"}
}