{
  "type": "Feature",
  "properties": {
    "gn:admin1_code":"33.0",
    "gn:admin2_code":"2104.0",
    "gn:admin3_code":"210401.0",
    "gn:admin4_code":"21040104.0",
    "gn:asciiname":"Mano Matuey Arriba",
    "gn:country_code":"DO",
    "gn:dem":677,
    "gn:feature_class":"P",
    "gn:feature_code":"PPL",
    "gn:name":"Mano Matuey Arriba",
    "gn:population":0,
    "gn:timezone":"America/Santo_Domingo",
    "iso:country":"DO",
    "wof:name":"Mano Matuey Arriba",
    "wof:placetype":"locality"
},
  "geometry": {"coordinates":[-70.25445999999999,18.4994],"type":"Point"}
}