{
  "type": "Feature",
  "properties": {
    "gn:admin1_code":"4.0",
    "gn:admin2_code":"501.0",
    "gn:admin3_code":"50101.0",
    "gn:admin4_code":"5010106.0",
    "gn:asciiname":"Las Brenas",
    "gn:country_code":"DO",
    "gn:dem":111,
    "gn:feature_class":"P",
    "gn:feature_code":"PPL",
    "gn:name":"Las Bre\u00f1as",
    "gn:population":0,
    "gn:timezone":"America/Santo_Domingo",
    "iso:country":"DO",
    "wof:name":"Las Brenas",
    "wof:placetype":"locality"
},
  "geometry": {"coordinates":[-71.56451,19.53739],"type":"Point"}
}