{
  "type": "Feature",
  "properties": {
    "gn:admin1_code":"37.0",
    "gn:admin2_code":"3204.0",
    "gn:admin3_code":"320401.0",
    "gn:admin4_code":"32040102.0",
    "gn:asciiname":"El Cruce",
    "gn:country_code":"DO",
    "gn:dem":32,
    "gn:feature_class":"P",
    "gn:feature_code":"PPL",
    "gn:name":"El Cruce",
    "gn:population":0,
    "gn:timezone":"America/Santo_Domingo",
    "iso:country":"DO",
    "name:und_x_variant":[
        "Cruce de Boca Chica",
        "Cruce Boca Chica",
        "El Cruce"
    ],
    "wof:name":"El Cruce",
    "wof:placetype":"locality"
},
  "geometry": {"coordinates":[-69.58958,18.48813],"type":"Point"}
}