{
  "type": "Feature",
  "properties": {
    "gn:admin1_code":"33.0",
    "gn:admin2_code":"2101.0",
    "gn:admin3_code":"210101.0",
    "gn:admin4_code":"21010104.0",
    "gn:asciiname":"Ingenio Nuevo",
    "gn:country_code":"DO",
    "gn:dem":92,
    "gn:feature_class":"P",
    "gn:feature_code":"PPL",
    "gn:name":"Ingenio Nuevo",
    "gn:population":0,
    "gn:timezone":"America/Santo_Domingo",
    "iso:country":"DO",
    "wof:name":"Ingenio Nuevo",
    "wof:placetype":"locality"
},
  "geometry": {"coordinates":[-70.13314,18.37173],"type":"Point"}
}