{
  "type": "Feature",
  "properties": {
    "gn:admin1_code":"32.0",
    "gn:admin2_code":"2901.0",
    "gn:admin3_code":"290103.0",
    "gn:admin4_code":"29010301.0",
    "gn:asciiname":"Chirino",
    "gn:country_code":"DO",
    "gn:dem":12,
    "gn:feature_class":"P",
    "gn:feature_code":"PPL",
    "gn:name":"Chirino",
    "gn:population":0,
    "gn:timezone":"America/Santo_Domingo",
    "iso:country":"DO",
    "name:und_x_variant":[
        "Batey Chirino",
        "Chirino"
    ],
    "wof:name":"Chirino",
    "wof:placetype":"locality"
},
  "geometry": {"coordinates":[-69.81562,18.67401],"type":"Point"}
}