{
  "type": "Feature",
  "properties": {
    "gn:admin1_code":"11.0",
    "gn:admin2_code":"702.0",
    "gn:admin3_code":"70201.0",
    "gn:admin4_code":"7020103.0",
    "gn:asciiname":"Los Pinos",
    "gn:country_code":"DO",
    "gn:dem":345,
    "gn:feature_class":"P",
    "gn:feature_code":"PPL",
    "gn:name":"Los Pinos",
    "gn:population":0,
    "gn:timezone":"America/Santo_Domingo",
    "iso:country":"DO",
    "wof:name":"Los Pinos",
    "wof:placetype":"locality"
},
  "geometry": {"coordinates":[-71.67666,19.06231],"type":"Point"}
}