{
  "type": "Feature",
  "properties": {
    "gn:admin1_code":"11.0",
    "gn:admin2_code":"702.0",
    "gn:admin3_code":"70201.0",
    "gn:admin4_code":"7020103.0",
    "gn:asciiname":"Los Pinos",
    "gn:country_code":"DO",
    "gn:dem":345,
    "gn:feature_class":"P",
    "gn:feature_code":"PPL",
    "gn:name":"Los Pinos",
    "gn:population":0,
    "gn:timezone":"America/Santo_Domingo",
    "iso:country":"DO",
    "name:fra_x_preferred":[
        "Los Pinos"
    ],
    "name:heb_x_preferred":[
        "\u05dc\u05d5\u05e1 \u05e4\u05d9\u05e0\u05d5\u05e1"
    ],
    "name:ita_x_preferred":[
        "Los Pinos"
    ],
    "name:msa_x_preferred":[
        "Los Pinos"
    ],
    "name:nld_x_preferred":[
        "Los Pinos"
    ],
    "name:nor_x_preferred":[
        "Los Pinos"
    ],
    "name:por_x_preferred":[
        "Los Pinos"
    ],
    "name:rus_x_preferred":[
        "\u041b\u043e\u0441 \u041f\u0438\u043d\u043e\u0441"
    ],
    "name:spa_x_preferred":[
        "Los Pinos"
    ],
    "name:swe_x_preferred":[
        "Los Pinos"
    ],
    "wof:name":"Los Pinos",
    "wof:placetype":"locality"
},
  "geometry": {"coordinates":[-71.67666,19.06231],"type":"Point"}
}