{
  "type": "Feature",
  "properties": {
    "gn:admin1_code":"1.0",
    "gn:admin2_code":"210.0",
    "gn:admin3_code":"21001.0",
    "gn:admin4_code":"2100106.0",
    "gn:asciiname":"Los Guayuyos",
    "gn:country_code":"DO",
    "gn:dem":1374,
    "gn:feature_class":"P",
    "gn:feature_code":"PPL",
    "gn:name":"Los Guayuyos",
    "gn:population":0,
    "gn:timezone":"America/Santo_Domingo",
    "iso:country":"DO",
    "name:und_x_variant":[
        "El Guayuyo",
        "Los Guayuyos"
    ],
    "wof:name":"Los Guayuyos",
    "wof:placetype":"locality"
},
  "geometry": {"coordinates":[-70.71091,18.58132],"type":"Point"}
}