{
  "type": "Feature",
  "properties": {
    "gn:admin1_code":"29.0",
    "gn:admin2_code":"3001.0",
    "gn:admin3_code":"300101.0",
    "gn:admin4_code":"30010102.0",
    "gn:asciiname":"Almirante",
    "gn:country_code":"DO",
    "gn:dem":108,
    "gn:feature_class":"P",
    "gn:feature_code":"PPL",
    "gn:name":"Almirante",
    "gn:population":0,
    "gn:timezone":"America/Santo_Domingo",
    "iso:country":"DO",
    "name:cat_x_preferred":[
        "Almirante"
    ],
    "name:deu_x_preferred":[
        "Almirante"
    ],
    "name:fra_x_preferred":[
        "Almirante"
    ],
    "name:glg_x_preferred":[
        "Almirante"
    ],
    "name:ita_x_preferred":[
        "Almirante"
    ],
    "name:por_x_preferred":[
        "Almirante"
    ],
    "wof:name":"Almirante",
    "wof:placetype":"locality"
},
  "geometry": {"coordinates":[-69.42017,18.78144],"type":"Point"}
}