{
  "type": "Feature",
  "properties": {
    "gn:country":"DO",
    "gn:fcode":"PPL",
    "gn:pop":1903,
    "iso:country":"DO",
    "name:dut_x_preferred":[
        "El Cach\u00f3n"
    ],
    "name:eng_x_preferred":[
        "El Cach\u00f3n"
    ],
    "name:spa_x_preferred":[
        "El Cach\u00f3n"
    ],
    "name:swe_x_preferred":[
        "Cach\u00f3n"
    ],
    "name:unk_x_variant":[
        "El Cach\u00f3n"
    ],
    "qs:name":"Cach\u00f3n",
    "qs:photos_9r":0,
    "qs:photos_sr":0,
    "qs:pop_sr":"3",
    "wd:wordcount":20,
    "wof:name":"Cach\u00f3n",
    "wof:placetype":"locality",
    "wof:population":1903
},
  "geometry": {"coordinates":[-71.18912,18.24833],"type":"Point"}
}