{
  "type": "Feature",
  "properties": {
    "gn:admin1_code":"24.0",
    "gn:admin2_code":"2303.0",
    "gn:admin3_code":"230301.0",
    "gn:admin4_code":"23030103.0",
    "gn:asciiname":"Javilla Gorda",
    "gn:cc2":"DO",
    "gn:country_code":"DO",
    "gn:dem":41,
    "gn:feature_class":"P",
    "gn:feature_code":"PPL",
    "gn:name":"Javilla Gorda",
    "gn:population":0,
    "gn:timezone":"America/Santo_Domingo",
    "iso:country":"DO",
    "name:und_x_variant":[
        "Jabilla Gorda N\u00famero Dos",
        "Javilla Gorda"
    ],
    "wof:name":"Javilla Gorda",
    "wof:placetype":"locality"
},
  "geometry": {"coordinates":[-69.18333,18.51667],"type":"Point"}
}