{
  "type": "Feature",
  "properties": {
    "gn:admin1_code":"4.0",
    "gn:admin2_code":"502.0",
    "gn:admin3_code":"50201.0",
    "gn:admin4_code":"5020105.0",
    "gn:asciiname":"Palo Colorado",
    "gn:country_code":"DO",
    "gn:dem":263,
    "gn:feature_class":"P",
    "gn:feature_code":"PPL",
    "gn:name":"Palo Colorado",
    "gn:population":0,
    "gn:timezone":"America/Santo_Domingo",
    "iso:country":"DO",
    "wof:name":"Palo Colorado",
    "wof:placetype":"locality"
},
  "geometry": {"coordinates":[-71.62769,19.4152],"type":"Point"}
}