{
  "type": "Feature",
  "properties": {
    "gn:admin1_code":"11.0",
    "gn:admin2_code":"701.0",
    "gn:admin3_code":"70101.0",
    "gn:admin4_code":"7010107.0",
    "gn:asciiname":"Las Patillas",
    "gn:cc2":"DO",
    "gn:country_code":"DO",
    "gn:dem":411,
    "gn:feature_class":"P",
    "gn:feature_code":"PPL",
    "gn:name":"Las Patillas",
    "gn:population":0,
    "gn:timezone":"America/Santo_Domingo",
    "iso:country":"DO",
    "name:und_x_variant":[
        "La Patilla",
        "Las Patillas"
    ],
    "wof:name":"Las Patillas",
    "wof:placetype":"locality"
},
  "geometry": {"coordinates":[-71.72055999999998,18.86889],"type":"Point"}
}