{
  "type": "Feature",
  "properties": {
    "gn:admin1_code":"34.0",
    "gn:admin2_code":"101.0",
    "gn:admin3_code":"10101.0",
    "gn:admin4_code":"1010101.0",
    "gn:asciiname":"Fundacion",
    "gn:country_code":"DO",
    "gn:dem":48,
    "gn:feature_class":"P",
    "gn:feature_code":"PPL",
    "gn:name":"Fundaci\u00f3n",
    "gn:population":0,
    "gn:timezone":"America/Santo_Domingo",
    "iso:country":"DO",
    "wof:name":"Fundacion",
    "wof:placetype":"locality"
},
  "geometry": {"coordinates":[-69.97184,18.52024],"type":"Point"}
}