{
  "type": "Feature",
  "properties": {
    "gn:admin1_code":"21.0",
    "gn:admin2_code":"2402.0",
    "gn:admin3_code":"240202.0",
    "gn:admin4_code":"24020203.0",
    "gn:asciiname":"El Cano",
    "gn:country_code":"DO",
    "gn:dem":80,
    "gn:feature_class":"P",
    "gn:feature_code":"PPL",
    "gn:name":"El Ca\u00f1o",
    "gn:population":0,
    "gn:timezone":"America/Santo_Domingo",
    "iso:country":"DO",
    "wof:name":"El Cano",
    "wof:placetype":"locality"
},
  "geometry": {"coordinates":[-70.00398,19.04785],"type":"Point"}
}