{
  "type": "Feature",
  "properties": {
    "gn:admin1_code":"30.0",
    "gn:admin2_code":"1301.0",
    "gn:admin3_code":"130104.0",
    "gn:admin4_code":"13010402.0",
    "gn:asciiname":"El Morro",
    "gn:country_code":"DO",
    "gn:dem":394,
    "gn:feature_class":"P",
    "gn:feature_code":"PPL",
    "gn:name":"El Morro",
    "gn:population":0,
    "gn:timezone":"America/Santo_Domingo",
    "iso:country":"DO",
    "name:ceb_x_preferred":[
        "El Morro"
    ],
    "name:deu_x_preferred":[
        "El Morro"
    ],
    "name:fra_x_preferred":[
        "El Morro"
    ],
    "name:spa_x_preferred":[
        "El Morro"
    ],
    "name:swe_x_preferred":[
        "El Morro"
    ],
    "wof:name":"El Morro",
    "wof:placetype":"locality"
},
  "geometry": {"coordinates":[-70.65101999999997,19.28612],"type":"Point"}
}