{
  "type": "Feature",
  "properties": {
    "gn:admin1_code":"18.0",
    "gn:admin2_code":"1804.0",
    "gn:admin3_code":"180401.0",
    "gn:admin4_code":"18040106.0",
    "gn:asciiname":"Saballo",
    "gn:country_code":"DO",
    "gn:dem":116,
    "gn:feature_class":"P",
    "gn:feature_code":"PPL",
    "gn:name":"Saballo",
    "gn:population":0,
    "gn:timezone":"America/Santo_Domingo",
    "iso:country":"DO",
    "name:und_x_variant":[
        "Seballo",
        "Saballo"
    ],
    "wof:name":"Saballo",
    "wof:placetype":"locality"
},
  "geometry": {"coordinates":[-70.85788000000002,19.76479],"type":"Point"}
}