{
  "type": "Feature",
  "properties": {
    "gn:admin1_code":"26.0",
    "gn:admin2_code":"2602.0",
    "gn:admin3_code":"260201.0",
    "gn:admin4_code":"26020103.0",
    "gn:asciiname":"Verbena",
    "gn:country_code":"DO",
    "gn:dem":503,
    "gn:feature_class":"P",
    "gn:feature_code":"PPL",
    "gn:name":"Verbena",
    "gn:population":0,
    "gn:timezone":"America/Santo_Domingo",
    "iso:country":"DO",
    "name:ara_x_preferred":[
        "\u0631\u0639\u064a \u0627\u0644\u062d\u0645\u0627\u0645"
    ],
    "name:aze_x_preferred":[
        "Mina\u00e7i\u00e7\u0259yi"
    ],
    "name:bel_x_preferred":[
        "\u0412\u0435\u0440\u0431\u0435\u043d\u0430"
    ],
    "name:bul_x_preferred":[
        "\u0412\u044a\u0440\u0431\u0438\u043d\u043a\u0430"
    ],
    "name:cat_x_preferred":[
        "Verbena"
    ],
    "name:ceb_x_preferred":[
        "Verbena"
    ],
    "name:dan_x_preferred":[
        "Jernurt"
    ],
    "name:deu_x_preferred":[
        "Verbenen"
    ],
    "name:epo_x_preferred":[
        "Verbeno"
    ],
    "name:fas_x_preferred":[
        "\u0634\u0627\u0647\u200c\u067e\u0633\u0646\u062f"
    ],
    "name:fin_x_preferred":[
        "Verbenat"
    ],
    "name:fra_x_preferred":[
        "Verbena"
    ],
    "name:gle_x_preferred":[
        "Beirbh\u00e9ine"
    ],
    "name:hrv_x_preferred":[
        "Spori\u0161"
    ],
    "name:hsb_x_preferred":[
        "Twjerd\u017aenka"
    ],
    "name:hun_x_preferred":[
        "Vasf\u0171"
    ],
    "name:hye_x_preferred":[
        "\u0531\u0572\u0561\u057e\u0576\u056b\u0573"
    ],
    "name:ido_x_preferred":[
        "Verbeno"
    ],
    "name:ita_x_preferred":[
        "Verbena"
    ],
    "name:jpn_x_preferred":[
        "\u30d0\u30fc\u30d9\u30ca"
    ],
    "name:kat_x_preferred":[
        "\u10ea\u10dd\u10ea\u10ee\u10d0\u10dc\u10d0"
    ],
    "name:kaz_x_preferred":[
        "\u041d\u0430\u0440\u049b\u0430\u0439\u0441\u0430\u0440"
    ],
    "name:kir_x_preferred":[
        "\u0412\u0435\u0440\u0431\u0435\u043d\u0430"
    ],
    "name:lat_x_preferred":[
        "Verbena"
    ],
    "name:lit_x_preferred":[
        "Verbena"
    ],
    "name:mal_x_preferred":[
        "\u0d35\u0d46\u0d7c\u0d2c\u0d28"
    ],
    "name:new_x_preferred":[
        "\u0917\u0932\u0901\u0907\u0901\u091a\u093e\u0938\u094d\u0935\u093e\u0902"
    ],
    "name:nld_x_preferred":[
        "Verbena"
    ],
    "name:pol_x_preferred":[
        "Werbena"
    ],
    "name:por_x_preferred":[
        "Verbena"
    ],
    "name:ron_x_preferred":[
        "Verbena"
    ],
    "name:rus_x_preferred":[
        "\u0412\u0435\u0440\u0431\u0435\u043d\u0430"
    ],
    "name:spa_x_preferred":[
        "Verbena"
    ],
    "name:srp_x_preferred":[
        "\u0412\u0435\u0440\u0431\u0435\u043d\u0430"
    ],
    "name:swe_x_preferred":[
        "Verbenasl\u00e4ktet"
    ],
    "name:ukr_x_preferred":[
        "\u0412\u0435\u0440\u0431\u0435\u043d\u0430"
    ],
    "name:und_x_variant":[
        "La Berbena",
        "Verbena"
    ],
    "name:uzb_x_preferred":[
        "Chamandagul"
    ],
    "name:war_x_preferred":[
        "Verbena"
    ],
    "name:zho_x_preferred":[
        "\u9a6c\u97ad\u8349\u5c5e"
    ],
    "wof:name":"Verbena",
    "wof:placetype":"locality"
},
  "geometry": {"coordinates":[-71.40886,19.32669],"type":"Point"}
}