{
  "type": "Feature",
  "properties": {
    "gn:admin1_code":"26.0",
    "gn:admin2_code":"2602.0",
    "gn:admin3_code":"260201.0",
    "gn:admin4_code":"26020103.0",
    "gn:asciiname":"Verbena",
    "gn:country_code":"DO",
    "gn:dem":503,
    "gn:feature_class":"P",
    "gn:feature_code":"PPL",
    "gn:name":"Verbena",
    "gn:population":0,
    "gn:timezone":"America/Santo_Domingo",
    "iso:country":"DO",
    "name:und_x_variant":[
        "La Berbena",
        "Verbena"
    ],
    "wof:name":"Verbena",
    "wof:placetype":"locality"
},
  "geometry": {"coordinates":[-71.40886,19.32669],"type":"Point"}
}