{
  "type": "Feature",
  "properties": {
    "gn:admin1_code":"36.0",
    "gn:admin2_code":"3102.0",
    "gn:admin3_code":"310201.0",
    "gn:admin4_code":"31020102.0",
    "gn:asciiname":"La Cienaga",
    "gn:country_code":"DO",
    "gn:dem":1106,
    "gn:feature_class":"P",
    "gn:feature_code":"PPL",
    "gn:name":"La Ci\u00e9naga",
    "gn:population":0,
    "gn:timezone":"America/Santo_Domingo",
    "iso:country":"DO",
    "wof:name":"La Cienaga",
    "wof:placetype":"locality"
},
  "geometry": {"coordinates":[-70.50881,18.62101],"type":"Point"}
}