{
  "type": "Feature",
  "properties": {
    "iso:country":"DO",
    "name:ceb_x_preferred":[
        "Villa Tapia"
    ],
    "name:eng_x_preferred":[
        "Villa Tapia"
    ],
    "name:ita_x_preferred":[
        "Villa Tapia"
    ],
    "name:nan_x_preferred":[
        "Villa Tapia"
    ],
    "name:nld_x_preferred":[
        "Villa Tapia"
    ],
    "name:por_x_preferred":[
        "Villa Tapia"
    ],
    "name:slv_x_preferred":[
        "Villa Tapia"
    ],
    "name:spa_x_preferred":[
        "Villa Tapia"
    ],
    "name:swe_x_preferred":[
        "Villa Tapia"
    ],
    "name:zho_min_nan_x_preferred":[
        "Villa Tapia"
    ],
    "name:zho_x_preferred":[
        "\u5854\u76ae\u4e9e\u93ae"
    ],
    "qs:gn_country":"DO",
    "qs:gn_fcode":"PPL",
    "qs:gn_pop":3113,
    "qs:name":"Villa Tapia",
    "qs:name_adm0":"Rep\u00fablica Dominicana",
    "qs:name_adm1":"Salcedo",
    "qs:photos":0,
    "qs:photos_1k":0,
    "qs:photos_9k":1,
    "qs:photos_9r":1,
    "qs:photos_all":7,
    "qs:photos_sr":0,
    "qs:placetype":"Town",
    "qs:pop_sr":"4",
    "qs:woe_adm0":23424800,
    "wd:wordcount":41,
    "wof:name":"Villa Tapia",
    "wof:placetype":"locality",
    "wof:population":3113
},
  "geometry": {"coordinates":[-70.42198999999999,19.30084],"type":"Point"}
}