{
  "type": "Feature",
  "properties": {
    "gn:admin1_code":"28.0",
    "gn:admin2_code":"802.0",
    "gn:admin3_code":"80201.0",
    "gn:admin4_code":"8020102.0",
    "gn:asciiname":"Monte Claro",
    "gn:country_code":"DO",
    "gn:dem":81,
    "gn:feature_class":"P",
    "gn:feature_code":"PPL",
    "gn:name":"Monte Claro",
    "gn:population":0,
    "gn:timezone":"America/Santo_Domingo",
    "iso:country":"DO",
    "wof:name":"Monte Claro",
    "wof:placetype":"locality"
},
  "geometry": {"coordinates":[-69.0976,18.96008],"type":"Point"}
}