{
  "type": "Feature",
  "properties": {
    "gn:admin1_code":"21.0",
    "gn:admin2_code":"2403.0",
    "gn:admin3_code":"240301.0",
    "gn:admin4_code":"24030102.0",
    "gn:asciiname":"Bacumi",
    "gn:country_code":"DO",
    "gn:dem":51,
    "gn:feature_class":"P",
    "gn:feature_code":"PPL",
    "gn:name":"Bacum\u00ed",
    "gn:population":0,
    "gn:timezone":"America/Santo_Domingo",
    "iso:country":"DO",
    "name:und_x_variant":[
        "Bacom\u00ed",
        "Bacum\u00ed"
    ],
    "wof:name":"Bacumi",
    "wof:placetype":"locality"
},
  "geometry": {"coordinates":[-70.25072,19.15],"type":"Point"}
}