{
  "type": "Feature",
  "properties": {
    "gn:admin1_code":"33.0",
    "gn:admin2_code":"2104.0",
    "gn:admin3_code":"210401.0",
    "gn:admin4_code":"21040104.0",
    "gn:asciiname":"Los Anones",
    "gn:country_code":"DO",
    "gn:dem":686,
    "gn:feature_class":"P",
    "gn:feature_code":"PPL",
    "gn:name":"Los Anones",
    "gn:population":0,
    "gn:timezone":"America/Santo_Domingo",
    "iso:country":"DO",
    "wof:name":"Los Anones",
    "wof:placetype":"locality"
},
  "geometry": {"coordinates":[-70.23362,18.46701],"type":"Point"}
}