{
  "type": "Feature",
  "properties": {
    "gn:admin1_code":"33.0",
    "gn:admin2_code":"2104.0",
    "gn:admin3_code":"210401.0",
    "gn:admin4_code":"21040105.0",
    "gn:asciiname":"Manantiales",
    "gn:country_code":"DO",
    "gn:dem":466,
    "gn:feature_class":"P",
    "gn:feature_code":"PPL",
    "gn:name":"Manantiales",
    "gn:population":0,
    "gn:timezone":"America/Santo_Domingo",
    "iso:country":"DO",
    "name:ceb_x_preferred":[
        "Manantiales"
    ],
    "name:deu_x_preferred":[
        "Manantiales"
    ],
    "name:spa_x_preferred":[
        "Manantiales"
    ],
    "name:swe_x_preferred":[
        "Manantiales"
    ],
    "wof:name":"Manantiales",
    "wof:placetype":"locality"
},
  "geometry": {"coordinates":[-70.29850999999999,18.51899],"type":"Point"}
}