{
  "type": "Feature",
  "properties": {
    "gn:admin1_code":"18.0",
    "gn:admin2_code":"1802.0",
    "gn:admin3_code":"180201.0",
    "gn:admin4_code":"18020106.0",
    "gn:asciiname":"Hervidor",
    "gn:country_code":"DO",
    "gn:dem":186,
    "gn:feature_class":"P",
    "gn:feature_code":"PPL",
    "gn:name":"Hervidor",
    "gn:population":0,
    "gn:timezone":"America/Santo_Domingo",
    "iso:country":"DO",
    "name:und_x_variant":[
        "Hervedor",
        "Hervidor"
    ],
    "wof:name":"Hervidor",
    "wof:placetype":"locality"
},
  "geometry": {"coordinates":[-70.79784000000002,19.69359],"type":"Point"}
}