{
  "type": "Feature",
  "properties": {
    "gn:admin1_code":"36.0",
    "gn:admin2_code":"3103.0",
    "gn:admin3_code":"310301.0",
    "gn:admin4_code":"31030104.0",
    "gn:asciiname":"La Cienaguita",
    "gn:country_code":"DO",
    "gn:dem":973,
    "gn:feature_class":"P",
    "gn:feature_code":"PPL",
    "gn:name":"La Cienaguita",
    "gn:population":0,
    "gn:timezone":"America/Santo_Domingo",
    "iso:country":"DO",
    "name:und_x_variant":[
        "La Cieneguita",
        "La Cienaguita"
    ],
    "wof:name":"La Cienaguita",
    "wof:placetype":"locality"
},
  "geometry": {"coordinates":[-70.48446,18.69477],"type":"Point"}
}