{
  "type": "Feature",
  "properties": {
    "gn:admin1_code":"35.0",
    "gn:admin2_code":"1701.0",
    "gn:admin3_code":"170101.0",
    "gn:admin4_code":"17010111.0",
    "gn:asciiname":"Rancho de Matos",
    "gn:country_code":"DO",
    "gn:dem":274,
    "gn:feature_class":"P",
    "gn:feature_code":"PPL",
    "gn:name":"Rancho de Matos",
    "gn:population":0,
    "gn:timezone":"America/Santo_Domingo",
    "iso:country":"DO",
    "wof:name":"Rancho de Matos",
    "wof:placetype":"locality"
},
  "geometry": {"coordinates":[-70.29154,18.45781],"type":"Point"}
}