{
  "type": "Feature",
  "properties": {
    "gn:admin1_code":"14.0",
    "gn:admin2_code":"1402.0",
    "gn:admin3_code":"140201.0",
    "gn:admin4_code":"14020102.0",
    "gn:asciiname":"Laguna Honda",
    "gn:country_code":"DO",
    "gn:dem":281,
    "gn:feature_class":"P",
    "gn:feature_code":"PPL",
    "gn:name":"Laguna Honda",
    "gn:population":0,
    "gn:timezone":"America/Santo_Domingo",
    "iso:country":"DO",
    "name:ceb_x_preferred":[
        "Laguna Honda"
    ],
    "name:swe_x_preferred":[
        "Laguna Honda"
    ],
    "wof:name":"Laguna Honda",
    "wof:placetype":"locality"
},
  "geometry": {"coordinates":[-69.93734000000001,19.6265],"type":"Point"}
}