{
  "type": "Feature",
  "properties": {
    "gn:admin1_code":"35.0",
    "gn:admin2_code":"1701.0",
    "gn:admin3_code":"170101.0",
    "gn:admin4_code":"17010108.0",
    "gn:asciiname":"La Jina",
    "gn:country_code":"DO",
    "gn:dem":138,
    "gn:feature_class":"P",
    "gn:feature_code":"PPL",
    "gn:name":"La Jina",
    "gn:population":0,
    "gn:timezone":"America/Santo_Domingo",
    "iso:country":"DO",
    "name:und_x_variant":[
        "La Gina",
        "La Jina"
    ],
    "wof:name":"La Jina",
    "wof:placetype":"locality"
},
  "geometry": {"coordinates":[-70.33282,18.34219],"type":"Point"}
}