{
  "type": "Feature",
  "properties": {
    "gn:admin1_code":"11.0",
    "gn:admin2_code":"706.0",
    "gn:admin3_code":"70601.0",
    "gn:admin4_code":"7060104.0",
    "gn:asciiname":"Sabana de La Loma",
    "gn:country_code":"DO",
    "gn:dem":663,
    "gn:feature_class":"P",
    "gn:feature_code":"PPL",
    "gn:name":"Sabana de La Loma",
    "gn:population":0,
    "gn:timezone":"America/Santo_Domingo",
    "iso:country":"DO",
    "wof:name":"Sabana de La Loma",
    "wof:placetype":"locality"
},
  "geometry": {"coordinates":[-71.58665000000001,18.74635],"type":"Point"}
}