{
  "type": "Feature",
  "properties": {
    "gn:admin1_code":"4.0",
    "gn:admin2_code":"505.0",
    "gn:admin3_code":"50501.0",
    "gn:admin4_code":"5050103.0",
    "gn:asciiname":"Marizan",
    "gn:country_code":"DO",
    "gn:dem":141,
    "gn:feature_class":"P",
    "gn:feature_code":"PPL",
    "gn:name":"Mariz\u00e1n",
    "gn:population":0,
    "gn:timezone":"America/Santo_Domingo",
    "iso:country":"DO",
    "wof:name":"Marizan",
    "wof:placetype":"locality"
},
  "geometry": {"coordinates":[-71.48997,19.48621],"type":"Point"}
}