{
  "type": "Feature",
  "properties": {
    "gn:admin1_code":"18.0",
    "gn:admin2_code":"1803.0",
    "gn:admin3_code":"180301.0",
    "gn:admin4_code":"18030102.0",
    "gn:asciiname":"Palma de los Hierros",
    "gn:country_code":"DO",
    "gn:dem":390,
    "gn:feature_class":"P",
    "gn:feature_code":"PPL",
    "gn:name":"Palma de los Hierros",
    "gn:population":0,
    "gn:timezone":"America/Santo_Domingo",
    "iso:country":"DO",
    "wof:name":"Palma de los Hierros",
    "wof:placetype":"locality"
},
  "geometry": {"coordinates":[-70.90064,19.67871],"type":"Point"}
}