{
  "type": "Feature",
  "properties": {
    "gn:admin1_code":"32.0",
    "gn:admin2_code":"2902.0",
    "gn:admin3_code":"290201.0",
    "gn:admin4_code":"29020101.0",
    "gn:asciiname":"Guayabo",
    "gn:country_code":"DO",
    "gn:dem":55,
    "gn:feature_class":"P",
    "gn:feature_code":"PPL",
    "gn:name":"Guayabo",
    "gn:population":0,
    "gn:timezone":"America/Santo_Domingo",
    "iso:country":"DO",
    "wof:name":"Guayabo",
    "wof:placetype":"locality"
},
  "geometry": {"coordinates":[-69.63069,18.75215],"type":"Point"}
}