{
  "type": "Feature",
  "properties": {
    "gn:admin1_code":"4.0",
    "gn:admin2_code":"501.0",
    "gn:admin3_code":"50101.0",
    "gn:admin4_code":"5010104.0",
    "gn:asciiname":"El Candelon",
    "gn:country_code":"DO",
    "gn:dem":90,
    "gn:feature_class":"P",
    "gn:feature_code":"PPL",
    "gn:name":"El Candel\u00f3n",
    "gn:population":0,
    "gn:timezone":"America/Santo_Domingo",
    "iso:country":"DO",
    "wof:name":"El Candelon",
    "wof:placetype":"locality"
},
  "geometry": {"coordinates":[-71.57069,19.56151],"type":"Point"}
}