{
  "type": "Feature",
  "properties": {
    "gn:admin1_code":"15.0",
    "gn:admin2_code":"1502.0",
    "gn:admin3_code":"150202.0",
    "gn:admin4_code":"15020203.0",
    "gn:asciiname":"Yaguarizo",
    "gn:country_code":"DO",
    "gn:dem":22,
    "gn:feature_class":"P",
    "gn:feature_code":"PPL",
    "gn:name":"Yaguarizo",
    "gn:population":0,
    "gn:timezone":"America/Santo_Domingo",
    "iso:country":"DO",
    "name:und_x_variant":[
        "Los Yag\u00fcarisos",
        "Yaguarizo"
    ],
    "wof:name":"Yaguarizo",
    "wof:placetype":"locality"
},
  "geometry": {"coordinates":[-71.52113,19.71235],"type":"Point"}
}