{
  "type": "Feature",
  "properties": {
    "gn:admin1_code":"31.0",
    "gn:admin2_code":"2801.0",
    "gn:admin3_code":"280106.0",
    "gn:admin4_code":"28010603.0",
    "gn:asciiname":"Blanco",
    "gn:country_code":"DO",
    "gn:dem":502,
    "gn:feature_class":"P",
    "gn:feature_code":"PPL",
    "gn:name":"Blanco",
    "gn:population":0,
    "gn:timezone":"America/Santo_Domingo",
    "iso:country":"DO",
    "name:cat_x_preferred":[
        "Blanco"
    ],
    "name:ceb_x_preferred":[
        "Blanco"
    ],
    "name:ces_x_preferred":[
        "Blanco"
    ],
    "name:deu_x_preferred":[
        "Blanco"
    ],
    "name:fin_x_preferred":[
        "Blanco"
    ],
    "name:fra_x_preferred":[
        "Blanco"
    ],
    "name:heb_x_preferred":[
        "\u05d1\u05dc\u05e0\u05e7\u05d5"
    ],
    "name:ita_x_preferred":[
        "Blanco"
    ],
    "name:nld_x_preferred":[
        "Blanco"
    ],
    "name:pol_x_preferred":[
        "Blanco"
    ],
    "name:slv_x_preferred":[
        "Blanco"
    ],
    "name:spa_x_preferred":[
        "Blanco"
    ],
    "name:swe_x_preferred":[
        "Blanco"
    ],
    "name:zho_x_preferred":[
        "\u5e03\u5170\u79d1"
    ],
    "wof:name":"Blanco",
    "wof:placetype":"locality"
},
  "geometry": {"coordinates":[-70.52449,18.88523],"type":"Point"}
}