{
  "type": "Feature",
  "properties": {
    "gn:admin1_code":"21.0",
    "gn:admin2_code":"2401.0",
    "gn:admin3_code":"240101.0",
    "gn:admin4_code":"24010105.0",
    "gn:asciiname":"Villa Rosa",
    "gn:country_code":"DO",
    "gn:dem":73,
    "gn:feature_class":"P",
    "gn:feature_code":"PPL",
    "gn:name":"Villa Rosa",
    "gn:population":0,
    "gn:timezone":"America/Santo_Domingo",
    "iso:country":"DO",
    "name:azb_x_preferred":[
        "\u0648\u06cc\u0644\u0627 \u0631\u0648\u0632\u0627"
    ],
    "name:ceb_x_preferred":[
        "Villa Rosa"
    ],
    "name:fas_x_preferred":[
        "\u0648\u06cc\u0644\u0627 \u0631\u0648\u0632\u0627"
    ],
    "name:ita_x_preferred":[
        "Villa Rosa"
    ],
    "name:srp_x_preferred":[
        "\u0412\u0438\u043b\u0430 \u0420\u043e\u0437\u0430"
    ],
    "name:und_x_variant":[
        "Villa Raza",
        "Villa Rosa"
    ],
    "wof:name":"Villa Rosa",
    "wof:placetype":"locality"
},
  "geometry": {"coordinates":[-70.10514000000001,19.02203],"type":"Point"}
}