{
  "type": "Feature",
  "properties": {
    "gn:admin1_code":"35.0",
    "gn:admin2_code":"1701.0",
    "gn:admin3_code":"170107.0",
    "gn:admin4_code":"17010702.0",
    "gn:asciiname":"Los Mayales",
    "gn:country_code":"DO",
    "gn:dem":129,
    "gn:feature_class":"P",
    "gn:feature_code":"PPL",
    "gn:name":"Los Mayales",
    "gn:population":0,
    "gn:timezone":"America/Santo_Domingo",
    "iso:country":"DO",
    "name:und_x_variant":[
        "Los Yayales",
        "Los Mayales"
    ],
    "wof:name":"Los Mayales",
    "wof:placetype":"locality"
},
  "geometry": {"coordinates":[-70.26911,18.30875],"type":"Point"}
}