{
  "type": "Feature",
  "properties": {
    "gn:admin1_code":"23.0",
    "gn:admin2_code":"2205.0",
    "gn:admin3_code":"220501.0",
    "gn:admin4_code":"22050103.0",
    "gn:asciiname":"El Alto",
    "gn:country_code":"DO",
    "gn:dem":577,
    "gn:feature_class":"P",
    "gn:feature_code":"PPL",
    "gn:name":"El Alto",
    "gn:population":0,
    "gn:timezone":"America/Santo_Domingo",
    "iso:country":"DO",
    "wof:name":"El Alto",
    "wof:placetype":"locality"
},
  "geometry": {"coordinates":[-71.46666999999999,18.98333],"type":"Point"}
}