{
  "type": "Feature",
  "properties": {
    "gn:admin1_code":"36.0",
    "gn:admin2_code":"3101.0",
    "gn:admin3_code":"310101.0",
    "gn:admin4_code":"31010102.0",
    "gn:asciiname":"Arenoso",
    "gn:country_code":"DO",
    "gn:dem":234,
    "gn:feature_class":"P",
    "gn:feature_code":"PPL",
    "gn:name":"Arenoso",
    "gn:population":0,
    "gn:timezone":"America/Santo_Domingo",
    "iso:country":"DO",
    "name:ceb_x_preferred":[
        "Arenoso"
    ],
    "name:ita_x_preferred":[
        "Arenoso"
    ],
    "name:por_x_preferred":[
        "Arenoso"
    ],
    "name:spa_x_preferred":[
        "Arenoso"
    ],
    "name:swe_x_preferred":[
        "Arenoso"
    ],
    "name:zho_x_preferred":[
        "\u963f\u96f7\u8afe\u7d22"
    ],
    "wof:name":"Arenoso",
    "wof:placetype":"locality"
},
  "geometry": {"coordinates":[-70.47719000000002,18.42677],"type":"Point"}
}