{
  "type": "Feature",
  "properties": {
    "gn:admin1_code":"36.0",
    "gn:admin2_code":"3101.0",
    "gn:admin3_code":"310102.0",
    "gn:admin4_code":"31010204.0",
    "gn:asciiname":"Los Capacitos",
    "gn:country_code":"DO",
    "gn:dem":1096,
    "gn:feature_class":"P",
    "gn:feature_code":"PPL",
    "gn:name":"Los Capacitos",
    "gn:population":0,
    "gn:timezone":"America/Santo_Domingo",
    "iso:country":"DO",
    "name:und_x_variant":[
        "El Capacito",
        "Los Capacitos"
    ],
    "wof:name":"Los Capacitos",
    "wof:placetype":"locality"
},
  "geometry": {"coordinates":[-70.38131,18.62667],"type":"Point"}
}