{
  "type": "Feature",
  "properties": {
    "gn:admin1_code":"32.0",
    "gn:admin2_code":"2902.0",
    "gn:admin3_code":"290201.0",
    "gn:admin4_code":"29020103.0",
    "gn:asciiname":"San Ramon",
    "gn:country_code":"DO",
    "gn:dem":63,
    "gn:feature_class":"P",
    "gn:feature_code":"PPL",
    "gn:name":"San Ram\u00f3n",
    "gn:population":0,
    "gn:timezone":"America/Santo_Domingo",
    "iso:country":"DO",
    "wof:name":"San Ramon",
    "wof:placetype":"locality"
},
  "geometry": {"coordinates":[-69.71720999999999,18.77329],"type":"Point"}
}