{
  "type": "Feature",
  "properties": {
    "gn:admin1_code":"32.0",
    "gn:admin2_code":"2902.0",
    "gn:admin3_code":"290201.0",
    "gn:admin4_code":"29020106.0",
    "gn:asciiname":"Trinidad",
    "gn:country_code":"DO",
    "gn:dem":169,
    "gn:feature_class":"P",
    "gn:feature_code":"PPL",
    "gn:name":"Trinidad",
    "gn:population":0,
    "gn:timezone":"America/Santo_Domingo",
    "iso:country":"DO",
    "wof:name":"Trinidad",
    "wof:placetype":"locality"
},
  "geometry": {"coordinates":[-69.50961,18.82934],"type":"Point"}
}