{
  "type": "Feature",
  "properties": {
    "gn:admin1_code":"37.0",
    "gn:admin2_code":"3205.0",
    "gn:admin3_code":"320501.0",
    "gn:admin4_code":"32050105.0",
    "gn:asciiname":"Maricarmen",
    "gn:country_code":"DO",
    "gn:dem":24,
    "gn:feature_class":"P",
    "gn:feature_code":"PPL",
    "gn:name":"Maricarmen",
    "gn:population":0,
    "gn:timezone":"America/Santo_Domingo",
    "iso:country":"DO",
    "wof:name":"Maricarmen",
    "wof:placetype":"locality"
},
  "geometry": {"coordinates":[-69.66667,18.61667000000001],"type":"Point"}
}