{
  "type": "Feature",
  "properties": {
    "gn:admin1_code":"35.0",
    "gn:admin2_code":"1701.0",
    "gn:admin3_code":"170103.0",
    "gn:admin4_code":"17010301.0",
    "gn:asciiname":"Fundacion de Sabana Buey",
    "gn:country_code":"DO",
    "gn:dem":124,
    "gn:feature_class":"P",
    "gn:feature_code":"PPL",
    "gn:name":"Fundaci\u00f3n de Sabana Buey",
    "gn:population":0,
    "gn:timezone":"America/Santo_Domingo",
    "iso:country":"DO",
    "name:und_x_variant":[
        "Fundaci\u00f3n",
        "Fundaci\u00f3n de Sabana Buey"
    ],
    "wof:name":"Fundacion de Sabana Buey",
    "wof:placetype":"locality"
},
  "geometry": {"coordinates":[-70.49601,18.28095],"type":"Point"}
}