{
  "type": "Feature",
  "properties": {
    "gn:admin1_code":"6.0",
    "gn:admin2_code":"601.0",
    "gn:admin3_code":"60102.0",
    "gn:admin4_code":"6010203.0",
    "gn:asciiname":"Demajagual",
    "gn:country_code":"DO",
    "gn:dem":211,
    "gn:feature_class":"P",
    "gn:feature_code":"PPL",
    "gn:name":"Demajagual",
    "gn:population":0,
    "gn:timezone":"America/Santo_Domingo",
    "iso:country":"DO",
    "name:und_x_variant":[
        "Majagual",
        "Demajagual"
    ],
    "wof:name":"Demajagual",
    "wof:placetype":"locality"
},
  "geometry": {"coordinates":[-70.11321,19.29463],"type":"Point"}
}