{
  "type": "Feature",
  "properties": {
    "gn:admin1_code":"6.0",
    "gn:admin2_code":"604.0",
    "gn:admin3_code":"60401.0",
    "gn:admin4_code":"6040103.0",
    "gn:asciiname":"Caobete",
    "gn:country_code":"DO",
    "gn:dem":42,
    "gn:feature_class":"P",
    "gn:feature_code":"PPL",
    "gn:name":"Caobete",
    "gn:population":0,
    "gn:timezone":"America/Santo_Domingo",
    "iso:country":"DO",
    "name:und_x_variant":[
        "Sabana Caobete",
        "Caobete"
    ],
    "wof:name":"Caobete",
    "wof:placetype":"locality"
},
  "geometry": {"coordinates":[-70.15098,19.18327],"type":"Point"}
}