{
  "type": "Feature",
  "properties": {
    "gn:admin1_code":"30.0",
    "gn:admin2_code":"1302.0",
    "gn:admin3_code":"130202.0",
    "gn:admin4_code":"13020205.0",
    "gn:asciiname":"La Angostura",
    "gn:country_code":"DO",
    "gn:dem":1067,
    "gn:feature_class":"P",
    "gn:feature_code":"PPL",
    "gn:name":"La Angostura",
    "gn:population":0,
    "gn:timezone":"America/Santo_Domingo",
    "iso:country":"DO",
    "name:und_x_variant":[
        "Angostura",
        "La Angostura"
    ],
    "wof:name":"La Angostura",
    "wof:placetype":"locality"
},
  "geometry": {"coordinates":[-70.56881,19.00218],"type":"Point"}
}