{
  "type": "Feature",
  "properties": {
    "gn:admin1_code":"29.0",
    "gn:admin2_code":"3001.0",
    "gn:admin3_code":"300101.0",
    "gn:admin4_code":"30010102.0",
    "gn:asciiname":"El Mamey",
    "gn:country_code":"DO",
    "gn:dem":109,
    "gn:feature_class":"P",
    "gn:feature_code":"PPL",
    "gn:name":"El Mamey",
    "gn:population":0,
    "gn:timezone":"America/Santo_Domingo",
    "iso:country":"DO",
    "wof:name":"El Mamey",
    "wof:placetype":"locality"
},
  "geometry": {"coordinates":[-69.40630999999999,18.77969],"type":"Point"}
}