{
  "type": "Feature",
  "properties": {
    "gn:admin1_code":"28.0",
    "gn:admin2_code":"801.0",
    "gn:admin3_code":"80104.0",
    "gn:admin4_code":"8010404.0",
    "gn:asciiname":"Batey Santa Teresa",
    "gn:country_code":"DO",
    "gn:dem":110,
    "gn:feature_class":"P",
    "gn:feature_code":"PPL",
    "gn:name":"Batey Santa Teresa",
    "gn:population":0,
    "gn:timezone":"America/Santo_Domingo",
    "iso:country":"DO",
    "wof:name":"Batey Santa Teresa",
    "wof:placetype":"locality"
},
  "geometry": {"coordinates":[-69.01666999999999,18.73333],"type":"Point"}
}