{
  "type": "Feature",
  "properties": {
    "gn:admin1_code":"23.0",
    "gn:admin2_code":"2201.0",
    "gn:admin3_code":"220110.0",
    "gn:admin4_code":"22011003.0",
    "gn:asciiname":"Media Cara",
    "gn:country_code":"DO",
    "gn:dem":532,
    "gn:feature_class":"P",
    "gn:feature_code":"PPL",
    "gn:name":"Media Cara",
    "gn:population":0,
    "gn:timezone":"America/Santo_Domingo",
    "iso:country":"DO",
    "wof:name":"Media Cara",
    "wof:placetype":"locality"
},
  "geometry": {"coordinates":[-71.40000000000001,18.83333],"type":"Point"}
}