{
  "type": "Feature",
  "properties": {
    "gn:admin1_code":"25.0",
    "gn:asciiname":"La Estancia",
    "gn:country_code":"DO",
    "gn:dem":328,
    "gn:feature_class":"P",
    "gn:feature_code":"PPL",
    "gn:name":"La Estancia",
    "gn:population":0,
    "gn:timezone":"America/Santo_Domingo",
    "iso:country":"DO",
    "name:ceb_x_preferred":[
        "La Estancia"
    ],
    "name:deu_x_preferred":[
        "La Estancia"
    ],
    "name:spa_x_preferred":[
        "La Estancia"
    ],
    "name:swe_x_preferred":[
        "La Estancia"
    ],
    "wof:name":"La Estancia",
    "wof:placetype":"locality"
},
  "geometry": {"coordinates":[-70.71666999999999,19.28333],"type":"Point"}
}