{
  "type": "Feature",
  "properties": {
    "gn:admin1_code":"6.0",
    "gn:admin2_code":"601.0",
    "gn:admin3_code":"60101.0",
    "gn:admin4_code":"6010104.0",
    "gn:asciiname":"Las Pajas",
    "gn:country_code":"DO",
    "gn:dem":164,
    "gn:feature_class":"P",
    "gn:feature_code":"PPL",
    "gn:name":"Las Pajas",
    "gn:population":0,
    "gn:timezone":"America/Santo_Domingo",
    "iso:country":"DO",
    "name:und_x_variant":[
        "La Paja",
        "Las Pajas"
    ],
    "wof:name":"Las Pajas",
    "wof:placetype":"locality"
},
  "geometry": {"coordinates":[-70.28584000000001,19.34475],"type":"Point"}
}