{
  "type": "Feature",
  "properties": {
    "gn:admin1_code":"30.0",
    "gn:admin2_code":"1303.0",
    "gn:admin3_code":"130301.0",
    "gn:admin4_code":"13030108.0",
    "gn:asciiname":"La Sabana",
    "gn:country_code":"DO",
    "gn:dem":1008,
    "gn:feature_class":"P",
    "gn:feature_code":"PPL",
    "gn:name":"La Sabana",
    "gn:population":0,
    "gn:timezone":"America/Santo_Domingo",
    "iso:country":"DO",
    "name:ceb_x_preferred":[
        "La S\u00e1bana"
    ],
    "name:spa_x_preferred":[
        "La Sabana"
    ],
    "name:urd_x_preferred":[
        "\u0644\u0627 \u0633\u0627\u0628\u0627\u0646\u0627"
    ],
    "wof:name":"La Sabana",
    "wof:placetype":"locality"
},
  "geometry": {"coordinates":[-70.62196999999998,19.05635],"type":"Point"}
}