{
  "type": "Feature",
  "properties": {
    "gn:admin1_code":"23.0",
    "gn:admin2_code":"2205.0",
    "gn:admin3_code":"220503.0",
    "gn:admin4_code":"22050305.0",
    "gn:asciiname":"Los Ranchitos",
    "gn:country_code":"DO",
    "gn:dem":515,
    "gn:feature_class":"P",
    "gn:feature_code":"PPL",
    "gn:name":"Los Ranchitos",
    "gn:population":0,
    "gn:timezone":"America/Santo_Domingo",
    "iso:country":"DO",
    "name:und_x_variant":[
        "Ranchito",
        "Los Ranchitos"
    ],
    "wof:name":"Los Ranchitos",
    "wof:placetype":"locality"
},
  "geometry": {"coordinates":[-71.50530000000001,19.00447],"type":"Point"}
}