{
  "type": "Feature",
  "properties": {
    "gn:admin1_code":"2.0",
    "gn:admin2_code":"305.0",
    "gn:admin3_code":"30502.0",
    "gn:admin4_code":"3050203.0",
    "gn:asciiname":"Dos Ranchos",
    "gn:country_code":"DO",
    "gn:dem":481,
    "gn:feature_class":"P",
    "gn:feature_code":"PPL",
    "gn:name":"Dos Ranchos",
    "gn:population":0,
    "gn:timezone":"America/Santo_Domingo",
    "iso:country":"DO",
    "wof:name":"Dos Ranchos",
    "wof:placetype":"locality"
},
  "geometry": {"coordinates":[-71.55,18.56667],"type":"Point"}
}