{
  "type": "Feature",
  "properties": {
    "gn:admin1_code":"30.0",
    "gn:admin2_code":"1304.0",
    "gn:admin3_code":"130401.0",
    "gn:admin4_code":"13040104.0",
    "gn:asciiname":"La Boca de Jima",
    "gn:cc2":"DO",
    "gn:country_code":"DO",
    "gn:dem":55,
    "gn:feature_class":"P",
    "gn:feature_code":"PPL",
    "gn:name":"La Boca de Jima",
    "gn:population":0,
    "gn:timezone":"America/Santo_Domingo",
    "iso:country":"DO",
    "name:und_x_variant":[
        "Boca de Jima",
        "La Boca de Jima"
    ],
    "wof:name":"La Boca de Jima",
    "wof:placetype":"locality"
},
  "geometry": {"coordinates":[-70.36667,19.16667],"type":"Point"}
}