{
  "type": "Feature",
  "properties": {
    "gn:admin1_code":"36.0",
    "gn:admin2_code":"3103.0",
    "gn:admin3_code":"310301.0",
    "gn:admin4_code":"31030102.0",
    "gn:asciiname":"La Vigia",
    "gn:country_code":"DO",
    "gn:dem":713,
    "gn:feature_class":"P",
    "gn:feature_code":"PPL",
    "gn:name":"La Vig\u00eda",
    "gn:population":0,
    "gn:timezone":"America/Santo_Domingo",
    "iso:country":"DO",
    "wof:name":"La Vigia",
    "wof:placetype":"locality"
},
  "geometry": {"coordinates":[-70.43411,18.73738],"type":"Point"}
}