{
  "type": "Feature",
  "properties": {
    "gn:admin1_code":"1.0",
    "gn:admin2_code":"205.0",
    "gn:admin3_code":"20501.0",
    "gn:admin4_code":"2050104.0",
    "gn:asciiname":"Puerta Vieja",
    "gn:country_code":"DO",
    "gn:dem":452,
    "gn:feature_class":"P",
    "gn:feature_code":"PPL",
    "gn:name":"Puerta Vieja",
    "gn:population":0,
    "gn:timezone":"America/Santo_Domingo",
    "iso:country":"DO",
    "name:und_x_variant":[
        "Puerto Viejo",
        "Puerta Vieja"
    ],
    "wof:name":"Puerta Vieja",
    "wof:placetype":"locality"
},
  "geometry": {"coordinates":[-70.77795,18.57518],"type":"Point"}
}