{
  "type": "Feature",
  "properties": {
    "gn:admin1_code":"12.0",
    "gn:admin2_code":"1202.0",
    "gn:admin3_code":"120201.0",
    "gn:admin4_code":"12020103.0",
    "gn:asciiname":"Culebra",
    "gn:country_code":"DO",
    "gn:dem":83,
    "gn:feature_class":"P",
    "gn:feature_code":"PPL",
    "gn:name":"Culebra",
    "gn:population":0,
    "gn:timezone":"America/Santo_Domingo",
    "iso:country":"DO",
    "name:ceb_x_preferred":[
        "Culebra"
    ],
    "name:fra_x_preferred":[
        "Culebra"
    ],
    "name:ita_x_preferred":[
        "Culebra"
    ],
    "name:pol_x_preferred":[
        "Culebra"
    ],
    "name:rus_x_preferred":[
        "\u041a\u0443\u043b\u0435\u0431\u0440\u0430"
    ],
    "name:spa_x_preferred":[
        "Culebra"
    ],
    "name:swe_x_preferred":[
        "Culebra"
    ],
    "wof:name":"Culebra",
    "wof:placetype":"locality"
},
  "geometry": {"coordinates":[-68.89624999999999,18.52181],"type":"Point"}
}