{
  "type": "Feature",
  "properties": {
    "gn:admin1_code":"18.0",
    "gn:admin2_code":"1803.0",
    "gn:admin3_code":"180301.0",
    "gn:admin4_code":"18030102.0",
    "gn:asciiname":"Fundacion",
    "gn:country_code":"DO",
    "gn:dem":229,
    "gn:feature_class":"P",
    "gn:feature_code":"PPL",
    "gn:name":"Fundaci\u00f3n",
    "gn:population":0,
    "gn:timezone":"America/Santo_Domingo",
    "iso:country":"DO",
    "wof:name":"Fundacion",
    "wof:placetype":"locality"
},
  "geometry": {"coordinates":[-70.89298000000002,19.70499],"type":"Point"}
}