{
  "type": "Feature",
  "properties": {
    "gn:admin1_code":"36.0",
    "gn:admin2_code":"3101.0",
    "gn:admin3_code":"310102.0",
    "gn:admin4_code":"31010203.0",
    "gn:asciiname":"La Boca de Cazuela",
    "gn:country_code":"DO",
    "gn:dem":649,
    "gn:feature_class":"P",
    "gn:feature_code":"PPL",
    "gn:name":"La Boca de Cazuela",
    "gn:population":0,
    "gn:timezone":"America/Santo_Domingo",
    "iso:country":"DO",
    "wof:name":"La Boca de Cazuela",
    "wof:placetype":"locality"
},
  "geometry": {"coordinates":[-70.41079999999999,18.59562],"type":"Point"}
}