{
  "type": "Feature",
  "properties": {
    "gn:admin1_code":"18.0",
    "gn:admin2_code":"1804.0",
    "gn:admin3_code":"180401.0",
    "gn:admin4_code":"18040103.0",
    "gn:asciiname":"El Ranchito de los Peralta",
    "gn:country_code":"DO",
    "gn:dem":90,
    "gn:feature_class":"P",
    "gn:feature_code":"PPL",
    "gn:name":"El Ranchito de los Peralta",
    "gn:population":0,
    "gn:timezone":"America/Santo_Domingo",
    "iso:country":"DO",
    "name:und_x_variant":[
        "Ranchito de los Peralta",
        "Rancho de los Peralta",
        "El Ranchito de los Peralta"
    ],
    "wof:name":"El Ranchito de los Peralta",
    "wof:placetype":"locality"
},
  "geometry": {"coordinates":[-70.93109,19.77069],"type":"Point"}
}