{
  "type": "Feature",
  "properties": {
    "gn:admin1_code":"10.0",
    "gn:admin2_code":"1101.0",
    "gn:admin3_code":"110104.0",
    "gn:admin4_code":"11010403.0",
    "gn:asciiname":"Bavaro",
    "gn:country_code":"DO",
    "gn:dem":11,
    "gn:feature_class":"P",
    "gn:feature_code":"PPL",
    "gn:name":"B\u00e1varo",
    "gn:population":0,
    "gn:timezone":"America/Santo_Domingo",
    "iso:country":"DO",
    "name:fra_x_preferred":[
        "Bavaro"
    ],
    "name:heb_x_preferred":[
        "\u05d1\u05d5\u05d5\u05d0\u05e8\u05d5"
    ],
    "name:ita_x_preferred":[
        "B\u00e1varo"
    ],
    "name:por_x_preferred":[
        "B\u00e1varo"
    ],
    "name:spa_x_preferred":[
        "B\u00e1varo"
    ],
    "wof:name":"Bavaro",
    "wof:placetype":"locality"
},
  "geometry": {"coordinates":[-68.434,18.69634],"type":"Point"}
}