{
  "type": "Feature",
  "properties": {
    "gn:admin1_code":"14.0",
    "gn:admin2_code":"1401.0",
    "gn:admin3_code":"140104.0",
    "gn:admin4_code":"14010405.0",
    "gn:asciiname":"Las Piezas",
    "gn:country_code":"DO",
    "gn:dem":124,
    "gn:feature_class":"P",
    "gn:feature_code":"PPL",
    "gn:name":"Las Piezas",
    "gn:population":0,
    "gn:timezone":"America/Santo_Domingo",
    "iso:country":"DO",
    "name:und_x_variant":[
        "La Pieza",
        "Las Piezas"
    ],
    "wof:name":"Las Piezas",
    "wof:placetype":"locality"
},
  "geometry": {"coordinates":[-69.93789,19.35212000000001],"type":"Point"}
}