{
  "type": "Feature",
  "properties": {
    "gn:admin1_code":"32.0",
    "gn:admin2_code":"2904.0",
    "gn:admin3_code":"290402.0",
    "gn:admin4_code":"29040203.0",
    "gn:asciiname":"Quita Sueno",
    "gn:country_code":"DO",
    "gn:dem":191,
    "gn:feature_class":"P",
    "gn:feature_code":"PPL",
    "gn:name":"Quita Sue\u00f1o",
    "gn:population":0,
    "gn:timezone":"America/Santo_Domingo",
    "iso:country":"DO",
    "wof:name":"Quita Sueno",
    "wof:placetype":"locality"
},
  "geometry": {"coordinates":[-70.01786,18.70053],"type":"Point"}
}