{
  "type": "Feature",
  "properties": {
    "gn:admin1_code":"36.0",
    "gn:admin2_code":"3103.0",
    "gn:admin3_code":"310301.0",
    "gn:admin4_code":"31030104.0",
    "gn:asciiname":"Junumucu",
    "gn:country_code":"DO",
    "gn:dem":1103,
    "gn:feature_class":"P",
    "gn:feature_code":"PPL",
    "gn:name":"Junumuc\u00fa",
    "gn:population":0,
    "gn:timezone":"America/Santo_Domingo",
    "iso:country":"DO",
    "wof:name":"Junumucu",
    "wof:placetype":"locality"
},
  "geometry": {"coordinates":[-70.51196999999998,18.75202],"type":"Point"}
}