{
  "type": "Feature",
  "properties": {
    "gn:admin1_code":"12.0",
    "gn:admin2_code":"1201.0",
    "gn:admin3_code":"120101.0",
    "gn:admin4_code":"12010102.0",
    "gn:asciiname":"Batey Santoni",
    "gn:country_code":"DO",
    "gn:dem":68,
    "gn:feature_class":"P",
    "gn:feature_code":"PPL",
    "gn:name":"Batey Santoni",
    "gn:population":0,
    "gn:timezone":"America/Santo_Domingo",
    "iso:country":"DO",
    "name:und_x_variant":[
        "Santos",
        "Batey Santos",
        "Santoni",
        "Batey Santoni"
    ],
    "wof:name":"Batey Santoni",
    "wof:placetype":"locality"
},
  "geometry": {"coordinates":[-68.91385,18.48837],"type":"Point"}
}