{
  "type": "Feature",
  "properties": {
    "gn:admin1_code":"23.0",
    "gn:admin2_code":"2203.0",
    "gn:admin3_code":"220301.0",
    "gn:admin4_code":"22030103.0",
    "gn:asciiname":"Guayabal",
    "gn:country_code":"DO",
    "gn:dem":855,
    "gn:feature_class":"P",
    "gn:feature_code":"PPL",
    "gn:name":"Guayabal",
    "gn:population":0,
    "gn:timezone":"America/Santo_Domingo",
    "iso:country":"DO",
    "name:ceb_x_preferred":[
        "Guayabal"
    ],
    "name:deu_x_preferred":[
        "Guayabal"
    ],
    "name:fra_x_preferred":[
        "Guayabal"
    ],
    "name:ita_x_preferred":[
        "Guayabal"
    ],
    "name:nld_x_preferred":[
        "Guayabal"
    ],
    "name:por_x_preferred":[
        "Guayabal"
    ],
    "name:sco_x_preferred":[
        "Guayabal"
    ],
    "name:spa_x_preferred":[
        "Guayabal"
    ],
    "name:swe_x_preferred":[
        "Guayabal"
    ],
    "wof:name":"Guayabal",
    "wof:placetype":"locality"
},
  "geometry": {"coordinates":[-71.51827,18.70375],"type":"Point"}
}