{
  "type": "Feature",
  "properties": {
    "gn:admin1_code":"30.0",
    "gn:admin2_code":"1304.0",
    "gn:admin3_code":"130402.0",
    "gn:admin4_code":"13040204.0",
    "gn:asciiname":"El Caliche",
    "gn:country_code":"DO",
    "gn:dem":98,
    "gn:feature_class":"P",
    "gn:feature_code":"PPL",
    "gn:name":"El Caliche",
    "gn:population":0,
    "gn:timezone":"America/Santo_Domingo",
    "iso:country":"DO",
    "wof:name":"El Caliche",
    "wof:placetype":"locality"
},
  "geometry": {"coordinates":[-70.4516,19.14912],"type":"Point"}
}