{
  "type": "Feature",
  "properties": {
    "gn:admin1_code":"15.0",
    "gn:admin2_code":"1506.0",
    "gn:admin3_code":"150601.0",
    "gn:admin4_code":"15060103.0",
    "gn:asciiname":"La Costa de Buen Hombre",
    "gn:country_code":"DO",
    "gn:dem":23,
    "gn:feature_class":"P",
    "gn:feature_code":"PPL",
    "gn:name":"La Costa de Buen Hombre",
    "gn:population":0,
    "gn:timezone":"America/Santo_Domingo",
    "iso:country":"DO",
    "wof:name":"La Costa de Buen Hombre",
    "wof:placetype":"locality"
},
  "geometry": {"coordinates":[-71.40555000000001,19.86093],"type":"Point"}
}