{
  "type": "Feature",
  "properties": {
    "gn:admin1_code":"28.0",
    "gn:admin2_code":"801.0",
    "gn:admin3_code":"80101.0",
    "gn:admin4_code":"8010107.0",
    "gn:asciiname":"Las Carreras",
    "gn:country_code":"DO",
    "gn:dem":114,
    "gn:feature_class":"P",
    "gn:feature_code":"PPL",
    "gn:name":"Las Carreras",
    "gn:population":0,
    "gn:timezone":"America/Santo_Domingo",
    "iso:country":"DO",
    "wof:name":"Las Carreras",
    "wof:placetype":"locality"
},
  "geometry": {"coordinates":[-69.17522,18.81388],"type":"Point"}
}