{
  "type": "Feature",
  "properties": {
    "gn:admin1_code":"32.0",
    "gn:admin2_code":"2904.0",
    "gn:admin3_code":"290403.0",
    "gn:admin4_code":"29040303.0",
    "gn:asciiname":"Los Ranchitos",
    "gn:country_code":"DO",
    "gn:dem":99,
    "gn:feature_class":"P",
    "gn:feature_code":"PPL",
    "gn:name":"Los Ranchitos",
    "gn:population":0,
    "gn:timezone":"America/Santo_Domingo",
    "iso:country":"DO",
    "wof:name":"Los Ranchitos",
    "wof:placetype":"locality"
},
  "geometry": {"coordinates":[-70.0628,18.72381],"type":"Point"}
}