{
  "type": "Feature",
  "properties": {
    "gn:admin1_code":"37.0",
    "gn:admin2_code":"3203.0",
    "gn:admin3_code":"320302.0",
    "gn:admin4_code":"32030202.0",
    "gn:asciiname":"Ferragu",
    "gn:country_code":"DO",
    "gn:dem":30,
    "gn:feature_class":"P",
    "gn:feature_code":"PPL",
    "gn:name":"Ferrag\u00fa",
    "gn:population":0,
    "gn:timezone":"America/Santo_Domingo",
    "iso:country":"DO",
    "name:und_x_variant":[
        "Ferreg\u00fas",
        "Ferrag\u00fa"
    ],
    "wof:name":"Ferragu",
    "wof:placetype":"locality"
},
  "geometry": {"coordinates":[-69.88195999999999,18.59107],"type":"Point"}
}