{
  "type": "Feature",
  "properties": {
    "gn:admin1_code":"27.0",
    "gn:admin2_code":"2702.0",
    "gn:admin3_code":"270204.0",
    "gn:admin4_code":"27020402.0",
    "gn:asciiname":"La Boca de Mao Abajo",
    "gn:country_code":"DO",
    "gn:dem":75,
    "gn:feature_class":"P",
    "gn:feature_code":"PPL",
    "gn:name":"La Boca de Mao Abajo",
    "gn:population":0,
    "gn:timezone":"America/Santo_Domingo",
    "iso:country":"DO",
    "name:und_x_variant":[
        "Boca de Mao",
        "La Boca de Mao Abajo"
    ],
    "wof:name":"La Boca de Mao Abajo",
    "wof:placetype":"locality"
},
  "geometry": {"coordinates":[-71.02616999999999,19.58386],"type":"Point"}
}