{
  "type": "Feature",
  "properties": {
    "gn:admin1_code":"36.0",
    "gn:asciiname":"Los Naranjales",
    "gn:country_code":"DO",
    "gn:dem":871,
    "gn:feature_class":"P",
    "gn:feature_code":"PPL",
    "gn:name":"Los Naranjales",
    "gn:population":0,
    "gn:timezone":"America/Santo_Domingo",
    "iso:country":"DO",
    "wof:name":"Los Naranjales",
    "wof:placetype":"locality"
},
  "geometry": {"coordinates":[-70.43602,18.45357000000001],"type":"Point"}
}