{
  "type": "Feature",
  "properties": {
    "gn:admin1_code":"30.0",
    "gn:admin2_code":"1302.0",
    "gn:admin3_code":"130201.0",
    "gn:admin4_code":"13020102.0",
    "gn:asciiname":"La Culata",
    "gn:country_code":"DO",
    "gn:dem":1427,
    "gn:feature_class":"P",
    "gn:feature_code":"PPL",
    "gn:name":"La Culata",
    "gn:population":0,
    "gn:timezone":"America/Santo_Domingo",
    "iso:country":"DO",
    "wof:name":"La Culata",
    "wof:placetype":"locality"
},
  "geometry": {"coordinates":[-70.76591999999999,18.94845],"type":"Point"}
}