{
  "type": "Feature",
  "properties": {
    "gn:admin1_code":"10.0",
    "gn:admin2_code":"1102.0",
    "gn:admin3_code":"110201.0",
    "gn:admin4_code":"11020104.0",
    "gn:asciiname":"La Pinita",
    "gn:country_code":"DO",
    "gn:dem":57,
    "gn:feature_class":"P",
    "gn:feature_code":"PPL",
    "gn:name":"La Pi\u00f1ita",
    "gn:population":0,
    "gn:timezone":"America/Santo_Domingo",
    "iso:country":"DO",
    "wof:name":"La Pinita",
    "wof:placetype":"locality"
},
  "geometry": {"coordinates":[-68.72063,18.49792],"type":"Point"}
}