{
  "type": "Feature",
  "properties": {
    "gn:admin1_code":"23.0",
    "gn:admin2_code":"2205.0",
    "gn:admin3_code":"220503.0",
    "gn:admin4_code":"22050304.0",
    "gn:asciiname":"Hoyo Prieto",
    "gn:country_code":"DO",
    "gn:dem":778,
    "gn:feature_class":"P",
    "gn:feature_code":"PPL",
    "gn:name":"Hoyo Prieto",
    "gn:population":0,
    "gn:timezone":"America/Santo_Domingo",
    "iso:country":"DO",
    "wof:name":"Hoyo Prieto",
    "wof:placetype":"locality"
},
  "geometry": {"coordinates":[-71.46666999999999,19.01667],"type":"Point"}
}