{
  "type": "Feature",
  "properties": {
    "gn:admin1_code":"28.0",
    "gn:admin2_code":"801.0",
    "gn:admin3_code":"80101.0",
    "gn:admin4_code":"8010103.0",
    "gn:asciiname":"La Guarapa",
    "gn:country_code":"DO",
    "gn:dem":36,
    "gn:feature_class":"P",
    "gn:feature_code":"PPL",
    "gn:name":"La Guarapa",
    "gn:population":0,
    "gn:timezone":"America/Santo_Domingo",
    "iso:country":"DO",
    "name:und_x_variant":[
        "Guarapa",
        "La Guarapa"
    ],
    "wof:name":"La Guarapa",
    "wof:placetype":"locality"
},
  "geometry": {"coordinates":[-69.10745,18.66091],"type":"Point"}
}