{
  "type": "Feature",
  "properties": {
    "gn:admin1_code":"14.0",
    "gn:admin2_code":"1401.0",
    "gn:admin3_code":"140102.0",
    "gn:admin4_code":"14010203.0",
    "gn:asciiname":"Cano Abajo",
    "gn:country_code":"DO",
    "gn:dem":3,
    "gn:feature_class":"P",
    "gn:feature_code":"PPL",
    "gn:name":"Ca\u00f1o Abajo",
    "gn:population":0,
    "gn:timezone":"America/Santo_Domingo",
    "iso:country":"DO",
    "name:und_x_variant":[
        "Ca\u00f1o Abaja",
        "Ca\u00f1o Abajo"
    ],
    "wof:name":"Cano Abajo",
    "wof:placetype":"locality"
},
  "geometry": {"coordinates":[-69.77988000000001,19.25016],"type":"Point"}
}