{
  "type": "Feature",
  "properties": {
    "gn:admin1_code":"23.0",
    "gn:admin2_code":"2201.0",
    "gn:admin3_code":"220103.0",
    "gn:admin4_code":"22010303.0",
    "gn:asciiname":"Sabana del Rodeo",
    "gn:country_code":"DO",
    "gn:dem":730,
    "gn:feature_class":"P",
    "gn:feature_code":"PPL",
    "gn:name":"Sabana del Rodeo",
    "gn:population":0,
    "gn:timezone":"America/Santo_Domingo",
    "iso:country":"DO",
    "wof:name":"Sabana del Rodeo",
    "wof:placetype":"locality"
},
  "geometry": {"coordinates":[-71.28364000000001,19.00797],"type":"Point"}
}