{
  "type": "Feature",
  "properties": {
    "iso:country":"DO",
    "name:ceb_x_preferred":[
        "San Jos\u00e9 de Las Matas"
    ],
    "name:chi_x_preferred":[
        "\u8056\u4f55\u585e\u5fb7\u62c9\u65af\u99ac\u5854\u65af"
    ],
    "name:dut_x_preferred":[
        "San Jos\u00e9 de las Matas"
    ],
    "name:eng_x_preferred":[
        "San Jos\u00e9 de las Matas"
    ],
    "name:fre_x_preferred":[
        "San Jos\u00e9 de las Matas"
    ],
    "name:ita_x_preferred":[
        "San Jos\u00e9 de las Matas"
    ],
    "name:jpn_x_preferred":[
        "\u30b5\u30f3\u30fb\u30db\u30bb\u30fb\u30c7\u30fb\u30e9\u30b9\u30fb\u30de\u30bf\u30b9"
    ],
    "name:nan_x_preferred":[
        "San Jos\u00e9 de las Matas"
    ],
    "name:por_x_preferred":[
        "San Jos\u00e9 de las Matas"
    ],
    "name:spa_x_preferred":[
        "San Jos\u00e9 de Las Matas"
    ],
    "name:swe_x_preferred":[
        "San Jos\u00e9 de Las Matas"
    ],
    "name:unk_x_variant":[
        "San Jos\u00e9 de los Matas"
    ],
    "name:zho_min_nan_x_preferred":[
        "San Jos\u00e9 de las Matas"
    ],
    "name:zho_x_preferred":[
        "\u8056\u4f55\u585e\u5fb7\u62c9\u65af\u99ac\u5854\u65af"
    ],
    "qs:gn_country":"DO",
    "qs:gn_fcode":"PPL",
    "qs:gn_pop":9853,
    "qs:name":"San Jos\u00e9 de Las Matas",
    "qs:name_adm0":"Rep\u00fablica Dominicana",
    "qs:name_adm1":"Santiago",
    "qs:photos":0,
    "qs:photos_1k":0,
    "qs:photos_9k":1,
    "qs:photos_9r":1,
    "qs:photos_all":1,
    "qs:photos_sr":0,
    "qs:placetype":"Town",
    "qs:pop_sr":"5",
    "qs:woe_adm0":23424800,
    "wd:wordcount":162,
    "wof:name":"San Jos\u00e9 de Las Matas",
    "wof:placetype":"locality",
    "wof:population":9853
},
  "geometry": {"coordinates":[-70.93819000000001,19.33915],"type":"Point"}
}