{
  "type": "Feature",
  "properties": {
    "gn:admin1_code":"28.0",
    "gn:admin2_code":"801.0",
    "gn:admin3_code":"80102.0",
    "gn:admin4_code":"8010203.0",
    "gn:asciiname":"Majagua",
    "gn:country_code":"DO",
    "gn:dem":189,
    "gn:feature_class":"P",
    "gn:feature_code":"PPL",
    "gn:name":"Majagua",
    "gn:population":0,
    "gn:timezone":"America/Santo_Domingo",
    "iso:country":"DO",
    "name:ceb_x_preferred":[
        "Majagua"
    ],
    "name:fra_x_preferred":[
        "Majagua"
    ],
    "name:pol_x_preferred":[
        "Majagua"
    ],
    "name:spa_x_preferred":[
        "Majagua"
    ],
    "name:swe_x_preferred":[
        "Majagua"
    ],
    "wof:name":"Majagua",
    "wof:placetype":"locality"
},
  "geometry": {"coordinates":[-69.13061,18.87744],"type":"Point"}
}