{
  "type": "Feature",
  "properties": {
    "gn:admin1_code":"6.0",
    "gn:admin2_code":"601.0",
    "gn:admin3_code":"60102.0",
    "gn:admin4_code":"6010210.0",
    "gn:asciiname":"Pozo del Jobo",
    "gn:country_code":"DO",
    "gn:dem":233,
    "gn:feature_class":"P",
    "gn:feature_code":"PPL",
    "gn:name":"Pozo del Jobo",
    "gn:population":0,
    "gn:timezone":"America/Santo_Domingo",
    "iso:country":"DO",
    "name:und_x_variant":[
        "El Pozo del Jobo",
        "Pozo del Jobo"
    ],
    "wof:name":"Pozo del Jobo",
    "wof:placetype":"locality"
},
  "geometry": {"coordinates":[-70.15111999999999,19.30219],"type":"Point"}
}