{
  "type": "Feature",
  "properties": {
    "gn:admin1_code":"21.0",
    "gn:admin2_code":"2401.0",
    "gn:admin3_code":"240101.0",
    "gn:admin4_code":"24010103.0",
    "gn:asciiname":"Sabana Verde",
    "gn:country_code":"DO",
    "gn:dem":123,
    "gn:feature_class":"P",
    "gn:feature_code":"PPL",
    "gn:name":"Sabana Verde",
    "gn:population":0,
    "gn:timezone":"America/Santo_Domingo",
    "iso:country":"DO",
    "wof:name":"Sabana Verde",
    "wof:placetype":"locality"
},
  "geometry": {"coordinates":[-70.2226,18.937],"type":"Point"}
}