{
  "type": "Feature",
  "properties": {
    "gn:admin1_code":"10.0",
    "gn:admin2_code":"1102.0",
    "gn:admin3_code":"110201.0",
    "gn:admin4_code":"11020102.0",
    "gn:asciiname":"El Cascajal",
    "gn:country_code":"DO",
    "gn:dem":55,
    "gn:feature_class":"P",
    "gn:feature_code":"PPL",
    "gn:name":"El Cascajal",
    "gn:population":0,
    "gn:timezone":"America/Santo_Domingo",
    "iso:country":"DO",
    "wof:name":"El Cascajal",
    "wof:placetype":"locality"
},
  "geometry": {"coordinates":[-68.65600999999999,18.43053],"type":"Point"}
}