{
  "type": "Feature",
  "properties": {
    "gn:admin1_code":"32.0",
    "gn:admin2_code":"2905.0",
    "gn:admin3_code":"290501.0",
    "gn:admin4_code":"29050103.0",
    "gn:asciiname":"Cuanza",
    "gn:country_code":"DO",
    "gn:dem":175,
    "gn:feature_class":"P",
    "gn:feature_code":"PPL",
    "gn:name":"Cuanza",
    "gn:population":0,
    "gn:timezone":"America/Santo_Domingo",
    "iso:country":"DO",
    "name:ceb_x_preferred":[
        "Cuanza"
    ],
    "name:ces_x_preferred":[
        "Kwanza"
    ],
    "name:deu_x_preferred":[
        "Kwanza"
    ],
    "name:eus_x_preferred":[
        "Kwanza"
    ],
    "name:fra_x_preferred":[
        "Kwanza"
    ],
    "name:heb_x_preferred":[
        "\u05e7\u05d5\u05d5\u05d0\u05e0\u05d6\u05d4"
    ],
    "name:hun_x_preferred":[
        "Kwanza"
    ],
    "name:ita_x_preferred":[
        "Kwanza"
    ],
    "name:jpn_x_preferred":[
        "\u30af\u30ef\u30f3\u30b6"
    ],
    "name:nld_x_preferred":[
        "Kwanza"
    ],
    "name:por_x_preferred":[
        "Cuanza"
    ],
    "name:rus_x_preferred":[
        "\u0440\u0435\u043a\u0430 \u041a\u0432\u0430\u043d\u0437\u0430"
    ],
    "name:rus_x_variant":[
        "\u041a\u0432\u0430\u043d\u0437\u0430"
    ],
    "name:swe_x_preferred":[
        "Cuanza"
    ],
    "name:tur_x_preferred":[
        "Cuanza"
    ],
    "name:ukr_x_preferred":[
        "\u041a\u0432\u0430\u043d\u0437\u0430"
    ],
    "name:und_x_variant":[
        "Cuance"
    ],
    "name:urd_x_preferred":[
        "\u06a9\u0648\u0627\u0646\u0632\u0627"
    ],
    "name:vie_x_preferred":[
        "S\u00f4ng Cuanza"
    ],
    "name:zho_cn_x_preferred":[
        "\u5e7f\u8428\u6cb3"
    ],
    "name:zho_tw_x_preferred":[
        "\u5ee3\u85a9\u6cb3"
    ],
    "wof:name":"Cuanza",
    "wof:placetype":"locality"
},
  "geometry": {"coordinates":[-70.13822,18.84461],"type":"Point"}
}