{
  "type": "Feature",
  "properties": {
    "gn:admin1_code":"14.0",
    "gn:asciiname":"La Pocilga",
    "gn:country_code":"DO",
    "gn:dem":109,
    "gn:feature_class":"P",
    "gn:feature_code":"PPL",
    "gn:name":"La Pocilga",
    "gn:population":0,
    "gn:timezone":"America/Santo_Domingo",
    "iso:country":"DO",
    "wof:name":"La Pocilga",
    "wof:placetype":"locality"
},
  "geometry": {"coordinates":[-70.08544000000001,19.406],"type":"Point"}
}