{
  "type": "Feature",
  "properties": {
    "gn:admin1_code":"21.0",
    "gn:admin2_code":"2402.0",
    "gn:admin3_code":"240201.0",
    "gn:admin4_code":"24020102.0",
    "gn:asciiname":"El Duey",
    "gn:cc2":"DO",
    "gn:country_code":"DO",
    "gn:dem":480,
    "gn:feature_class":"P",
    "gn:feature_code":"PPL",
    "gn:name":"El Duey",
    "gn:population":0,
    "gn:timezone":"America/Santo_Domingo",
    "iso:country":"DO",
    "name:und_x_variant":[
        "Duey",
        "El Duey"
    ],
    "wof:name":"El Duey",
    "wof:placetype":"locality"
},
  "geometry": {"coordinates":[-70.01666999999999,18.96667],"type":"Point"}
}