{
  "type": "Feature",
  "properties": {
    "gn:admin1_code":"19.0",
    "gn:admin2_code":"1902.0",
    "gn:admin3_code":"190201.0",
    "gn:admin4_code":"19020103.0",
    "gn:asciiname":"La Amapola",
    "gn:cc2":"DO",
    "gn:country_code":"DO",
    "gn:dem":428,
    "gn:feature_class":"P",
    "gn:feature_code":"PPL",
    "gn:name":"La Amapola",
    "gn:population":0,
    "gn:timezone":"America/Santo_Domingo",
    "iso:country":"DO",
    "name:und_x_variant":[
        "Amapola",
        "La Amapola"
    ],
    "wof:name":"La Amapola",
    "wof:placetype":"locality"
},
  "geometry": {"coordinates":[-70.31667,19.43333],"type":"Point"}
}