{
  "type": "Feature",
  "properties": {
    "gn:admin1_code":"11.0",
    "gn:asciiname":"La Pocilga de Luciano",
    "gn:country_code":"DO",
    "gn:dem":365,
    "gn:feature_class":"P",
    "gn:feature_code":"PPL",
    "gn:name":"La Pocilga de Luciano",
    "gn:population":0,
    "gn:timezone":"America/Santo_Domingo",
    "iso:country":"DO",
    "wof:name":"La Pocilga de Luciano",
    "wof:placetype":"locality"
},
  "geometry": {"coordinates":[-71.6177,18.96342000000001],"type":"Point"}
}