{
  "type": "Feature",
  "properties": {
    "iso:country":"DO",
    "name:spa_x_colloquial":[
        "Mosquiteria"
    ],
    "name:spa_x_preferred":[
        "Mosquiter\u00eda"
    ],
    "name:spa_x_variant":[
        "Masqueteria"
    ],
    "qs:gn_adm0_cc":"DO",
    "qs:gn_local":7874116,
    "qs:gn_nam_loc":"limoncillar",
    "qs:gn_namadm1":"34",
    "qs:local_max":5287,
    "qs:local_sum":19037,
    "qs:localhoods":30,
    "qs:name":"Mosquiter\u00eda",
    "qs:name_adm0":"Rep\u00fablica Dominicana",
    "qs:name_adm1":"Santo Domingo",
    "qs:name_local":"Santo Domingo",
    "qs:photo_max":72,
    "qs:photo_sum":220,
    "qs:placetype":"Suburb",
    "qs:quad_count":11,
    "qs:woe_adm0":23424800,
    "qs:woe_adm1":28358196,
    "qs:woe_adm2":0,
    "qs:woe_lau":0,
    "qs:woe_local":76456,
    "qs:woe_ver":"7.10.0",
    "wof:lang":[
        "spa"
    ],
    "wof:name":"Mosquiter\u00eda",
    "wof:placetype":"neighbourhood"
},
  "geometry": {"coordinates":[-69.840873,18.481966],"type":"Point"}
}