{
  "type": "Feature",
  "properties": {
    "gn:admin1_code":"18.0",
    "gn:admin2_code":"1807.0",
    "gn:admin3_code":"180702.0",
    "gn:admin4_code":"18070202.0",
    "gn:asciiname":"La Catalina",
    "gn:country_code":"DO",
    "gn:dem":44,
    "gn:feature_class":"P",
    "gn:feature_code":"PPL",
    "gn:name":"La Catalina",
    "gn:population":0,
    "gn:timezone":"America/Santo_Domingo",
    "iso:country":"DO",
    "wof:name":"La Catalina",
    "wof:placetype":"locality"
},
  "geometry": {"coordinates":[-70.42182,19.68281],"type":"Point"}
}