{
  "type": "Feature",
  "properties": {
    "gn:admin1_code":"32.0",
    "gn:admin2_code":"2903.0",
    "gn:admin3_code":"290301.0",
    "gn:admin4_code":"29030103.0",
    "gn:asciiname":"Batey Altagracia",
    "gn:country_code":"DO",
    "gn:dem":211,
    "gn:feature_class":"P",
    "gn:feature_code":"PPL",
    "gn:name":"Batey Altagracia",
    "gn:population":0,
    "gn:timezone":"America/Santo_Domingo",
    "iso:country":"DO",
    "name:und_x_variant":[
        "Altagracia",
        "Batey Altagracia"
    ],
    "wof:name":"Batey Altagracia",
    "wof:placetype":"locality"
},
  "geometry": {"coordinates":[-69.84873,19.01213],"type":"Point"}
}