{
  "type": "Feature",
  "properties": {
    "gn:admin1_code":"18.0",
    "gn:admin2_code":"1804.0",
    "gn:admin3_code":"180401.0",
    "gn:admin4_code":"18040104.0",
    "gn:asciiname":"Los Cafeces",
    "gn:country_code":"DO",
    "gn:dem":78,
    "gn:feature_class":"P",
    "gn:feature_code":"PPL",
    "gn:name":"Los Cafeces",
    "gn:population":0,
    "gn:timezone":"America/Santo_Domingo",
    "iso:country":"DO",
    "wof:name":"Los Cafeces",
    "wof:placetype":"locality"
},
  "geometry": {"coordinates":[-70.90369,19.80035],"type":"Point"}
}