{
  "type": "Feature",
  "properties": {
    "gn:admin1_code":"25.0",
    "gn:admin2_code":"2503.0",
    "gn:admin3_code":"250301.0",
    "gn:admin4_code":"25030106.0",
    "gn:asciiname":"Los Corozos Arriba",
    "gn:country_code":"DO",
    "gn:dem":568,
    "gn:feature_class":"P",
    "gn:feature_code":"PPL",
    "gn:name":"Los Corozos Arriba",
    "gn:population":0,
    "gn:timezone":"America/Santo_Domingo",
    "iso:country":"DO",
    "name:und_x_variant":[
        "Los Corozos",
        "Los Corozos Arriba"
    ],
    "wof:name":"Los Corozos Arriba",
    "wof:placetype":"locality"
},
  "geometry": {"coordinates":[-70.83969999999999,19.30017],"type":"Point"}
}