{
  "type": "Feature",
  "properties": {
    "gn:admin1_code":"25.0",
    "gn:admin2_code":"2505.0",
    "gn:admin3_code":"250504.0",
    "gn:admin4_code":"25050405.0",
    "gn:asciiname":"Las Lagunas",
    "gn:country_code":"DO",
    "gn:dem":1180,
    "gn:feature_class":"P",
    "gn:feature_code":"PPL",
    "gn:name":"Las Lagunas",
    "gn:population":0,
    "gn:timezone":"America/Santo_Domingo",
    "iso:country":"DO",
    "name:ceb_x_preferred":[
        "Las Lagunas"
    ],
    "name:spa_x_preferred":[
        "Las Lagunas"
    ],
    "name:srp_x_preferred":[
        "\u041b\u0430\u0441 \u041b\u0430\u0433\u0443\u043d\u0430\u0441"
    ],
    "name:swe_x_preferred":[
        "Las Lagunas"
    ],
    "wof:name":"Las Lagunas",
    "wof:placetype":"locality"
},
  "geometry": {"coordinates":[-70.91761,19.14935],"type":"Point"}
}