{
  "type": "Feature",
  "properties": {
    "gn:admin1_code":"37.0",
    "gn:admin2_code":"3206.0",
    "gn:admin3_code":"320601.0",
    "gn:admin4_code":"32060102.0",
    "gn:asciiname":"Caballona",
    "gn:country_code":"DO",
    "gn:dem":59,
    "gn:feature_class":"P",
    "gn:feature_code":"PPL",
    "gn:name":"Caballona",
    "gn:population":0,
    "gn:timezone":"America/Santo_Domingo",
    "iso:country":"DO",
    "wof:name":"Caballona",
    "wof:placetype":"locality"
},
  "geometry": {"coordinates":[-70.05306,18.502],"type":"Point"}
}