{
  "type": "Feature",
  "properties": {
    "gn:admin1_code":"10.0",
    "gn:admin2_code":"1101.0",
    "gn:admin3_code":"110101.0",
    "gn:admin4_code":"11010104.0",
    "gn:asciiname":"Hoyo Claro",
    "gn:country_code":"DO",
    "gn:dem":21,
    "gn:feature_class":"P",
    "gn:feature_code":"PPL",
    "gn:name":"Hoyo Claro",
    "gn:population":0,
    "gn:timezone":"America/Santo_Domingo",
    "iso:country":"DO",
    "name:und_x_variant":[
        "Laguna Hoyo Claro",
        "Hoyo Claro"
    ],
    "wof:name":"Hoyo Claro",
    "wof:placetype":"locality"
},
  "geometry": {"coordinates":[-68.46236,18.52731],"type":"Point"}
}