{
  "type": "Feature",
  "properties": {
    "gn:admin1_code":"33.0",
    "gn:admin2_code":"2106.0",
    "gn:admin3_code":"210601.0",
    "gn:admin4_code":"21060103.0",
    "gn:asciiname":"Cruce de La Jagua",
    "gn:country_code":"DO",
    "gn:dem":43,
    "gn:feature_class":"P",
    "gn:feature_code":"PPL",
    "gn:name":"Cruce de La Jagua",
    "gn:population":0,
    "gn:timezone":"America/Santo_Domingo",
    "iso:country":"DO",
    "wof:name":"Cruce de La Jagua",
    "wof:placetype":"locality"
},
  "geometry": {"coordinates":[-70.20725999999999,18.31066],"type":"Point"}
}