{
  "type": "Feature",
  "properties": {
    "gn:admin1_code":"33.0",
    "gn:admin2_code":"2106.0",
    "gn:admin3_code":"210601.0",
    "gn:admin4_code":"21060102.0",
    "gn:asciiname":"Cribiti",
    "gn:country_code":"DO",
    "gn:dem":54,
    "gn:feature_class":"P",
    "gn:feature_code":"PPL",
    "gn:name":"Cribit\u00ed",
    "gn:population":0,
    "gn:timezone":"America/Santo_Domingo",
    "iso:country":"DO",
    "wof:name":"Cribiti",
    "wof:placetype":"locality"
},
  "geometry": {"coordinates":[-70.23333000000001,18.33333],"type":"Point"}
}