{
  "type": "Feature",
  "properties": {
    "gn:admin1_code":"25.0",
    "gn:admin2_code":"2501.0",
    "gn:admin3_code":"250102.0",
    "gn:admin4_code":"25010202.0",
    "gn:asciiname":"Las Auyamas",
    "gn:country_code":"DO",
    "gn:dem":500,
    "gn:feature_class":"P",
    "gn:feature_code":"PPL",
    "gn:name":"Las Auyamas",
    "gn:population":0,
    "gn:timezone":"America/Santo_Domingo",
    "iso:country":"DO",
    "wof:name":"Las Auyamas",
    "wof:placetype":"locality"
},
  "geometry": {"coordinates":[-70.66667,19.58333],"type":"Point"}
}