{
  "type": "Feature",
  "properties": {
    "gn:admin1_code":"37.0",
    "gn:admin2_code":"3207.0",
    "gn:admin3_code":"320703.0",
    "gn:admin4_code":"32070304.0",
    "gn:asciiname":"Victorino",
    "gn:country_code":"DO",
    "gn:dem":89,
    "gn:feature_class":"P",
    "gn:feature_code":"PPL",
    "gn:name":"Victorino",
    "gn:population":0,
    "gn:timezone":"America/Santo_Domingo",
    "iso:country":"DO",
    "name:und_x_variant":[
        "Victoriano",
        "Victorino"
    ],
    "wof:name":"Victorino",
    "wof:placetype":"locality"
},
  "geometry": {"coordinates":[-70.09393,18.58916],"type":"Point"}
}