{
  "type": "Feature",
  "properties": {
    "gn:admin1_code":"20.0",
    "gn:admin2_code":"2002.0",
    "gn:admin3_code":"200201.0",
    "gn:admin4_code":"20020103.0",
    "gn:asciiname":"Punta Gorda",
    "gn:country_code":"DO",
    "gn:dem":43,
    "gn:feature_class":"P",
    "gn:feature_code":"PPL",
    "gn:name":"Punta Gorda",
    "gn:population":0,
    "gn:timezone":"America/Santo_Domingo",
    "iso:country":"DO",
    "name:ast_x_preferred":[
        "Punta Gorda"
    ],
    "name:ceb_x_preferred":[
        "Punta Gorda"
    ],
    "name:deu_x_preferred":[
        "Punta Gorda"
    ],
    "name:fra_x_preferred":[
        "Punta Gorda"
    ],
    "name:ita_x_preferred":[
        "Punta Gorda"
    ],
    "name:nds_x_preferred":[
        "Punta Gorda"
    ],
    "name:nld_x_preferred":[
        "Punta Gorda"
    ],
    "name:pol_x_preferred":[
        "Punta Gorda"
    ],
    "name:por_x_preferred":[
        "Punta Gorda"
    ],
    "name:rus_x_preferred":[
        "\u041f\u0443\u043d\u0442\u0430-\u0413\u043e\u0440\u0434\u0430"
    ],
    "name:sco_x_preferred":[
        "Punta Gorda"
    ],
    "name:spa_x_preferred":[
        "Punta Gorda"
    ],
    "name:srp_x_preferred":[
        "\u041f\u0443\u043d\u0442\u0430 \u0413\u043e\u0440\u0434\u0430"
    ],
    "name:swe_x_preferred":[
        "Punta Gorda"
    ],
    "wof:name":"Punta Gorda",
    "wof:placetype":"locality"
},
  "geometry": {"coordinates":[-69.58263000000001,19.22673],"type":"Point"}
}