{
  "type": "Feature",
  "properties": {
    "gn:admin1_code":"18.0",
    "gn:admin2_code":"1801.0",
    "gn:admin3_code":"180101.0",
    "gn:admin4_code":"18010105.0",
    "gn:asciiname":"El Capa Horadao",
    "gn:country_code":"DO",
    "gn:dem":295,
    "gn:feature_class":"P",
    "gn:feature_code":"PPL",
    "gn:name":"El Cap\u00e1 Horadao",
    "gn:population":0,
    "gn:timezone":"America/Santo_Domingo",
    "iso:country":"DO",
    "name:und_x_variant":[
        "El Capa de Horadad",
        "El Cap\u00e1",
        "El Cap\u00e1 Horadao"
    ],
    "wof:name":"El Capa Horadao",
    "wof:placetype":"locality"
},
  "geometry": {"coordinates":[-70.60120000000001,19.65172],"type":"Point"}
}