{
  "type": "Feature",
  "properties": {
    "gn:admin1_code":"36.0",
    "gn:admin2_code":"3101.0",
    "gn:admin3_code":"310102.0",
    "gn:admin4_code":"31010204.0",
    "gn:asciiname":"Trapiche",
    "gn:country_code":"DO",
    "gn:dem":645,
    "gn:feature_class":"P",
    "gn:feature_code":"PPL",
    "gn:name":"Trapiche",
    "gn:population":0,
    "gn:timezone":"America/Santo_Domingo",
    "iso:country":"DO",
    "name:cat_x_preferred":[
        "Trapig"
    ],
    "name:fra_x_preferred":[
        "Trapiche"
    ],
    "name:por_x_preferred":[
        "Trapiche"
    ],
    "name:spa_x_preferred":[
        "Trapiche"
    ],
    "wof:name":"Trapiche",
    "wof:placetype":"locality"
},
  "geometry": {"coordinates":[-70.38333,18.56667],"type":"Point"}
}