{
  "type": "Feature",
  "properties": {
    "gn:admin1_code":"34.0",
    "gn:asciiname":"La Guabina",
    "gn:country_code":"DO",
    "gn:dem":8,
    "gn:feature_class":"P",
    "gn:feature_code":"PPL",
    "gn:name":"La Guabina",
    "gn:population":0,
    "gn:timezone":"America/Santo_Domingo",
    "iso:country":"DO",
    "wof:name":"La Guabina",
    "wof:placetype":"locality"
},
  "geometry": {"coordinates":[-69.80056,18.61556],"type":"Point"}
}