{
  "type": "Feature",
  "properties": {
    "gn:admin1_code":"32.0",
    "gn:admin2_code":"2901.0",
    "gn:admin3_code":"290102.0",
    "gn:admin4_code":"29010202.0",
    "gn:asciiname":"Bermejo",
    "gn:country_code":"DO",
    "gn:dem":87,
    "gn:feature_class":"P",
    "gn:feature_code":"PPL",
    "gn:name":"Bermejo",
    "gn:population":0,
    "gn:timezone":"America/Santo_Domingo",
    "iso:country":"DO",
    "name:ara_x_preferred":[
        "\u0628\u0631\u0645\u064a\u062e\u0648"
    ],
    "name:cat_x_preferred":[
        "Bermejo"
    ],
    "name:ceb_x_preferred":[
        "Bermejo"
    ],
    "name:deu_x_preferred":[
        "Bermejo"
    ],
    "name:fas_x_preferred":[
        "\u0628\u0631\u0645\u062c\u0648"
    ],
    "name:fra_x_preferred":[
        "Bermejo"
    ],
    "name:heb_x_preferred":[
        "\u05d1\u05e8\u05de\u05d7\u05d5"
    ],
    "name:hin_x_preferred":[
        "\u092c\u0930\u094d\u092e\u0947\u091c\u094b"
    ],
    "name:hrv_x_preferred":[
        "Bermejo"
    ],
    "name:hun_x_preferred":[
        "Bermejo"
    ],
    "name:ind_x_preferred":[
        "Bermejo"
    ],
    "name:ita_x_preferred":[
        "Bermejo"
    ],
    "name:kor_x_preferred":[
        "\ubca0\ub974\uba54\ud638"
    ],
    "name:nld_x_preferred":[
        "Bermejo"
    ],
    "name:rus_x_preferred":[
        "\u0411\u0435\u0440\u043c\u0435\u0445\u043e"
    ],
    "name:slk_x_preferred":[
        "Bermejo"
    ],
    "name:spa_x_preferred":[
        "Bermejo"
    ],
    "name:swe_x_preferred":[
        "Bermejo"
    ],
    "name:und_x_variant":[
        "Batey Belmejo"
    ],
    "name:urd_x_preferred":[
        "\u0628\u0631\u0645\u06cc\u062c\u0648"
    ],
    "wof:name":"Bermejo",
    "wof:placetype":"locality"
},
  "geometry": {"coordinates":[-69.9436,18.83994],"type":"Point"}
}