{
  "type": "Feature",
  "properties": {
    "gn:admin1_code":"32.0",
    "gn:admin2_code":"2901.0",
    "gn:admin3_code":"290102.0",
    "gn:admin4_code":"29010202.0",
    "gn:asciiname":"Bermejo",
    "gn:country_code":"DO",
    "gn:dem":87,
    "gn:feature_class":"P",
    "gn:feature_code":"PPL",
    "gn:name":"Bermejo",
    "gn:population":0,
    "gn:timezone":"America/Santo_Domingo",
    "iso:country":"DO",
    "name:cat_x_preferred":[
        "Bermejo"
    ],
    "name:ceb_x_preferred":[
        "Bermejo"
    ],
    "name:deu_x_preferred":[
        "Bermejo"
    ],
    "name:fra_x_preferred":[
        "Bermejo"
    ],
    "name:hrv_x_preferred":[
        "Bermejo"
    ],
    "name:ita_x_preferred":[
        "Bermejo"
    ],
    "name:nld_x_preferred":[
        "Bermejo"
    ],
    "name:rus_x_preferred":[
        "\u0411\u0435\u0440\u043c\u0435\u0445\u043e"
    ],
    "name:slk_x_preferred":[
        "Bermejo"
    ],
    "name:spa_x_preferred":[
        "Bermejo"
    ],
    "name:swe_x_preferred":[
        "Bermejo"
    ],
    "name:und_x_variant":[
        "Batey Belmejo",
        "Bermejo"
    ],
    "wof:name":"Bermejo",
    "wof:placetype":"locality"
},
  "geometry": {"coordinates":[-69.9436,18.83994],"type":"Point"}
}