{
  "type": "Feature",
  "properties": {
    "gn:admin1_code":"15.0",
    "gn:admin2_code":"1503.0",
    "gn:admin3_code":"150301.0",
    "gn:admin4_code":"15030103.0",
    "gn:asciiname":"Sabana de Machete",
    "gn:country_code":"DO",
    "gn:dem":83,
    "gn:feature_class":"P",
    "gn:feature_code":"PPL",
    "gn:name":"Sabana de Machete",
    "gn:population":0,
    "gn:timezone":"America/Santo_Domingo",
    "iso:country":"DO",
    "wof:name":"Sabana de Machete",
    "wof:placetype":"locality"
},
  "geometry": {"coordinates":[-71.42963,19.58449],"type":"Point"}
}