{
  "type": "Feature",
  "properties": {
    "gn:admin1_code":"6.0",
    "gn:admin2_code":"601.0",
    "gn:admin3_code":"60104.0",
    "gn:admin4_code":"6010406.0",
    "gn:asciiname":"La Ceiba",
    "gn:cc2":"DO",
    "gn:country_code":"DO",
    "gn:dem":463,
    "gn:feature_class":"P",
    "gn:feature_code":"PPL",
    "gn:name":"La Ceiba",
    "gn:population":0,
    "gn:timezone":"America/Santo_Domingo",
    "iso:country":"DO",
    "name:und_x_variant":[
        "Ceiba",
        "La Selva",
        "La Ceiba"
    ],
    "wof:name":"La Ceiba",
    "wof:placetype":"locality"
},
  "geometry": {"coordinates":[-70.23333000000001,19.36667000000001],"type":"Point"}
}