{
  "type": "Feature",
  "properties": {
    "gn:admin1_code":"32.0",
    "gn:admin2_code":"2902.0",
    "gn:admin3_code":"290201.0",
    "gn:admin4_code":"29020102.0",
    "gn:asciiname":"La Ceja",
    "gn:country_code":"DO",
    "gn:dem":89,
    "gn:feature_class":"P",
    "gn:feature_code":"PPL",
    "gn:name":"La Ceja",
    "gn:population":0,
    "gn:timezone":"America/Santo_Domingo",
    "iso:country":"DO",
    "name:ceb_x_preferred":[
        "La Ceja"
    ],
    "name:swe_x_preferred":[
        "La Ceja"
    ],
    "wof:name":"La Ceja",
    "wof:placetype":"locality"
},
  "geometry": {"coordinates":[-69.6589,18.79792],"type":"Point"}
}