{
  "type": "Feature",
  "properties": {
    "gn:admin1_code":"10.0",
    "gn:admin2_code":"1101.0",
    "gn:admin3_code":"110101.0",
    "gn:admin4_code":"11010102.0",
    "gn:asciiname":"Bejucal",
    "gn:country_code":"DO",
    "gn:dem":133,
    "gn:feature_class":"P",
    "gn:feature_code":"PPL",
    "gn:name":"Bejucal",
    "gn:population":0,
    "gn:timezone":"America/Santo_Domingo",
    "iso:country":"DO",
    "name:und_x_variant":[
        "Bejucalito",
        "Bejucal"
    ],
    "wof:name":"Bejucal",
    "wof:placetype":"locality"
},
  "geometry": {"coordinates":[-68.88498,18.67267],"type":"Point"}
}