{
  "type": "Feature",
  "properties": {
    "gn:admin1_code":"10.0",
    "gn:admin2_code":"1101.0",
    "gn:admin3_code":"110101.0",
    "gn:admin4_code":"11010102.0",
    "gn:asciiname":"Bejucal",
    "gn:country_code":"DO",
    "gn:dem":133,
    "gn:feature_class":"P",
    "gn:feature_code":"PPL",
    "gn:name":"Bejucal",
    "gn:population":0,
    "gn:timezone":"America/Santo_Domingo",
    "iso:country":"DO",
    "name:ceb_x_preferred":[
        "Bejucal"
    ],
    "name:deu_x_preferred":[
        "Bejucal"
    ],
    "name:fra_x_preferred":[
        "Bejucal"
    ],
    "name:hat_x_preferred":[
        "Bejucal"
    ],
    "name:ita_x_preferred":[
        "Bejucal"
    ],
    "name:kat_x_preferred":[
        "\u10d1\u10d4\u10ee\u10e3\u10d9\u10d0\u10da\u10d8"
    ],
    "name:por_x_preferred":[
        "Bejucal"
    ],
    "name:rus_x_preferred":[
        "\u0411\u0435\u0445\u0443\u043a\u0430\u043b\u044c"
    ],
    "name:sco_x_preferred":[
        "Bejucal"
    ],
    "name:spa_x_preferred":[
        "Bejucal"
    ],
    "name:ukr_x_preferred":[
        "\u0411\u0435\u0445\u0443\u043a\u0430\u043b\u044c"
    ],
    "name:und_x_variant":[
        "Bejucalito",
        "Bejucal"
    ],
    "name:vie_x_preferred":[
        "Bejucal"
    ],
    "name:zho_x_preferred":[
        "\u8c9d\u80e1\u5361\u723e"
    ],
    "wof:name":"Bejucal",
    "wof:placetype":"locality"
},
  "geometry": {"coordinates":[-68.88498,18.67267],"type":"Point"}
}