{
  "type": "Feature",
  "properties": {
    "gn:admin1_code":"25.0",
    "gn:admin2_code":"2505.0",
    "gn:admin3_code":"250502.0",
    "gn:admin4_code":"25050203.0",
    "gn:asciiname":"Los Fogones",
    "gn:country_code":"DO",
    "gn:dem":433,
    "gn:feature_class":"P",
    "gn:feature_code":"PPL",
    "gn:name":"Los Fogones",
    "gn:population":0,
    "gn:timezone":"America/Santo_Domingo",
    "iso:country":"DO",
    "wof:name":"Los Fogones",
    "wof:placetype":"locality"
},
  "geometry": {"coordinates":[-71.05181999999998,19.39195],"type":"Point"}
}