{
  "type": "Feature",
  "properties": {
    "gn:admin1_code":"31.0",
    "gn:admin2_code":"2801.0",
    "gn:admin3_code":"280104.0",
    "gn:admin4_code":"28010403.0",
    "gn:asciiname":"Los Bleos",
    "gn:country_code":"DO",
    "gn:dem":217,
    "gn:feature_class":"P",
    "gn:feature_code":"PPL",
    "gn:name":"Los Bleos",
    "gn:population":0,
    "gn:timezone":"America/Santo_Domingo",
    "iso:country":"DO",
    "wof:name":"Los Bleos",
    "wof:placetype":"locality"
},
  "geometry": {"coordinates":[-70.44188,18.96673],"type":"Point"}
}