{
  "type": "Feature",
  "properties": {
    "gn:admin1_code":"6.0",
    "gn:admin2_code":"601.0",
    "gn:admin3_code":"60104.0",
    "gn:admin4_code":"6010403.0",
    "gn:asciiname":"Alto de Los Ortega",
    "gn:country_code":"DO",
    "gn:dem":244,
    "gn:feature_class":"P",
    "gn:feature_code":"PPL",
    "gn:name":"Alto de Los Ortega",
    "gn:population":0,
    "gn:timezone":"America/Santo_Domingo",
    "iso:country":"DO",
    "name:und_x_variant":[
        "Firme los Ortegas",
        "Alto de Los Ortega"
    ],
    "wof:name":"Alto de Los Ortega",
    "wof:placetype":"locality"
},
  "geometry": {"coordinates":[-70.21963000000001,19.35639],"type":"Point"}
}