{
  "type": "Feature",
  "properties": {
    "gn:admin1_code":"3.0",
    "gn:admin2_code":"408.0",
    "gn:admin3_code":"40801.0",
    "gn:admin4_code":"4080102.0",
    "gn:asciiname":"La Bomba",
    "gn:country_code":"DO",
    "gn:dem":18,
    "gn:feature_class":"P",
    "gn:feature_code":"PPL",
    "gn:name":"La Bomba",
    "gn:population":0,
    "gn:timezone":"America/Santo_Domingo",
    "iso:country":"DO",
    "name:ceb_x_preferred":[
        "La Bomba"
    ],
    "name:ita_x_preferred":[
        "La bomba"
    ],
    "name:spa_x_preferred":[
        "La bomba"
    ],
    "name:srp_x_preferred":[
        "\u041b\u0430 \u0411\u043e\u043c\u0431\u0430"
    ],
    "name:swe_x_preferred":[
        "La Bomba"
    ],
    "wof:name":"La Bomba",
    "wof:placetype":"locality"
},
  "geometry": {"coordinates":[-71.17225000000001,18.29895],"type":"Point"}
}