{
  "type": "Feature",
  "properties": {
    "gn:admin1_code":"23.0",
    "gn:admin2_code":"2201.0",
    "gn:admin3_code":"220104.0",
    "gn:admin4_code":"22010403.0",
    "gn:asciiname":"Sabana Piedra",
    "gn:country_code":"DO",
    "gn:dem":420,
    "gn:feature_class":"P",
    "gn:feature_code":"PPL",
    "gn:name":"Sabana Piedra",
    "gn:population":0,
    "gn:timezone":"America/Santo_Domingo",
    "iso:country":"DO",
    "wof:name":"Sabana Piedra",
    "wof:placetype":"locality"
},
  "geometry": {"coordinates":[-71.10923000000003,18.77448],"type":"Point"}
}