{
  "type": "Feature",
  "properties": {
    "gn:admin1_code":"25.0",
    "gn:admin2_code":"2505.0",
    "gn:admin3_code":"250502.0",
    "gn:admin4_code":"25050212.0",
    "gn:asciiname":"La Guarana",
    "gn:country_code":"DO",
    "gn:dem":613,
    "gn:feature_class":"P",
    "gn:feature_code":"PPL",
    "gn:name":"La Guarana",
    "gn:population":0,
    "gn:timezone":"America/Santo_Domingo",
    "iso:country":"DO",
    "name:und_x_variant":[
        "Las Guaranas",
        "La Guarana"
    ],
    "wof:name":"La Guarana",
    "wof:placetype":"locality"
},
  "geometry": {"coordinates":[-71.06049,19.34006],"type":"Point"}
}