{
  "type": "Feature",
  "properties": {
    "gn:admin1_code":"1.0",
    "gn:admin2_code":"204.0",
    "gn:admin3_code":"20401.0",
    "gn:admin4_code":"2040102.0",
    "gn:asciiname":"El Corte",
    "gn:country_code":"DO",
    "gn:dem":391,
    "gn:feature_class":"P",
    "gn:feature_code":"PPL",
    "gn:name":"El Corte",
    "gn:population":0,
    "gn:timezone":"America/Santo_Domingo",
    "iso:country":"DO",
    "wof:name":"El Corte",
    "wof:placetype":"locality"
},
  "geometry": {"coordinates":[-71.03333000000001,18.73333],"type":"Point"}
}