{
  "type": "Feature",
  "properties": {
    "gn:admin1_code":"25.0",
    "gn:admin2_code":"2501.0",
    "gn:admin3_code":"250106.0",
    "gn:admin4_code":"25010604.0",
    "gn:asciiname":"La Cienaga",
    "gn:country_code":"DO",
    "gn:dem":183,
    "gn:feature_class":"P",
    "gn:feature_code":"PPL",
    "gn:name":"La Ci\u00e9naga",
    "gn:population":0,
    "gn:timezone":"America/Santo_Domingo",
    "iso:country":"DO",
    "name:und_x_variant":[
        "Las Ci\u00e9negas",
        "La Ci\u00e9nega",
        "La Ci\u00e9naga"
    ],
    "wof:name":"La Cienaga",
    "wof:placetype":"locality"
},
  "geometry": {"coordinates":[-70.73054,19.51989],"type":"Point"}
}