{
  "type": "Feature",
  "properties": {
    "gn:admin1_code":"33.0",
    "gn:admin2_code":"2108.0",
    "gn:admin3_code":"210801.0",
    "gn:admin4_code":"21080104.0",
    "gn:asciiname":"Mahomita",
    "gn:country_code":"DO",
    "gn:dem":697,
    "gn:feature_class":"P",
    "gn:feature_code":"PPL",
    "gn:name":"Mahomita",
    "gn:population":0,
    "gn:timezone":"America/Santo_Domingo",
    "iso:country":"DO",
    "wof:name":"Mahomita",
    "wof:placetype":"locality"
},
  "geometry": {"coordinates":[-70.32755999999999,18.61084],"type":"Point"}
}