{
  "type": "Feature",
  "properties": {
    "gn:admin1_code":"18.0",
    "gn:admin2_code":"1807.0",
    "gn:admin3_code":"180701.0",
    "gn:admin4_code":"18070103.0",
    "gn:asciiname":"Boca de Cangrejos",
    "gn:country_code":"DO",
    "gn:dem":5,
    "gn:feature_class":"P",
    "gn:feature_code":"PPL",
    "gn:name":"Boca de Cangrejos",
    "gn:population":0,
    "gn:timezone":"America/Santo_Domingo",
    "iso:country":"DO",
    "name:und_x_variant":[
        "Boca de Cangrejo",
        "Boca de Cangrejos"
    ],
    "wof:name":"Boca de Cangrejos",
    "wof:placetype":"locality"
},
  "geometry": {"coordinates":[-70.58769000000002,19.75324],"type":"Point"}
}