{
  "type": "Feature",
  "properties": {
    "iso:country":"DO",
    "qs:gn_pop":0,
    "qs:name":"San Fernando de Monte Cristi",
    "qs:name_adm0":"Rep\u00fablica Dominicana",
    "qs:name_adm1":"Monte Cristri",
    "qs:photos":1182,
    "qs:photos_1k":240,
    "qs:photos_9k":5,
    "qs:photos_9r":7,
    "qs:photos_all":1182,
    "qs:photos_sr":11,
    "qs:placetype":"Town",
    "qs:pop_sr":"0",
    "qs:woe_adm0":23424800,
    "wof:name":"San Fernando de Monte Cristi",
    "wof:placetype":"locality"
},
  "geometry": {"coordinates":[-71.64939800000001,19.853672],"type":"Point"}
}