{
  "type": "Feature",
  "properties": {
    "gn:admin1_code":"18.0",
    "gn:admin2_code":"1801.0",
    "gn:admin3_code":"180103.0",
    "gn:admin4_code":"18010306.0",
    "gn:asciiname":"Los Canos",
    "gn:country_code":"DO",
    "gn:dem":30,
    "gn:feature_class":"P",
    "gn:feature_code":"PPL",
    "gn:name":"Los Ca\u00f1os",
    "gn:population":0,
    "gn:timezone":"America/Santo_Domingo",
    "iso:country":"DO",
    "name:und_x_variant":[
        "Las Ca\u00f1as",
        "Los Ca\u00f1os"
    ],
    "wof:name":"Los Canos",
    "wof:placetype":"locality"
},
  "geometry": {"coordinates":[-70.79389,19.8104],"type":"Point"}
}