{
  "type": "Feature",
  "properties": {
    "gn:admin1_code":"18.0",
    "gn:admin2_code":"1801.0",
    "gn:admin3_code":"180101.0",
    "gn:admin4_code":"18010105.0",
    "gn:asciiname":"Tubagua",
    "gn:country_code":"DO",
    "gn:dem":289,
    "gn:feature_class":"P",
    "gn:feature_code":"PPL",
    "gn:name":"Tubagua",
    "gn:population":0,
    "gn:timezone":"America/Santo_Domingo",
    "iso:country":"DO",
    "wof:name":"Tubagua",
    "wof:placetype":"locality"
},
  "geometry": {"coordinates":[-70.61667,19.66667],"type":"Point"}
}