{
  "type": "Feature",
  "properties": {
    "gn:admin1_code":"6.0",
    "gn:admin2_code":"601.0",
    "gn:admin3_code":"60102.0",
    "gn:admin4_code":"6010203.0",
    "gn:asciiname":"Majagual",
    "gn:country_code":"DO",
    "gn:dem":178,
    "gn:feature_class":"P",
    "gn:feature_code":"PPL",
    "gn:name":"Majagual",
    "gn:population":0,
    "gn:timezone":"America/Santo_Domingo",
    "iso:country":"DO",
    "name:ceb_x_preferred":[
        "Majagual"
    ],
    "name:sco_x_preferred":[
        "Majagual"
    ],
    "name:swe_x_preferred":[
        "Majagual"
    ],
    "name:vie_x_preferred":[
        "Majagual"
    ],
    "wof:name":"Majagual",
    "wof:placetype":"locality"
},
  "geometry": {"coordinates":[-70.11667,19.28333],"type":"Point"}
}