{
  "type": "Feature",
  "properties": {
    "gn:admin1_code":"32.0",
    "gn:admin2_code":"2904.0",
    "gn:admin3_code":"290401.0",
    "gn:admin4_code":"29040102.0",
    "gn:asciiname":"La Jina",
    "gn:country_code":"DO",
    "gn:dem":167,
    "gn:feature_class":"P",
    "gn:feature_code":"PPL",
    "gn:name":"La Jina",
    "gn:population":0,
    "gn:timezone":"America/Santo_Domingo",
    "iso:country":"DO",
    "name:und_x_variant":[
        "La Gina",
        "La Jina"
    ],
    "wof:name":"La Jina",
    "wof:placetype":"locality"
},
  "geometry": {"coordinates":[-70.12323000000001,18.81376],"type":"Point"}
}