{
  "type": "Feature",
  "properties": {
    "iso:country":"DO",
    "name:ast_x_preferred":[
        "Constanza"
    ],
    "name:ceb_x_preferred":[
        "Constanza"
    ],
    "name:deu_x_preferred":[
        "Constanza"
    ],
    "name:eng_x_preferred":[
        "Constanza"
    ],
    "name:fas_x_preferred":[
        "\u06a9\u0646\u0633\u062a\u0627\u0646\u0632\u0627"
    ],
    "name:fin_x_preferred":[
        "Constanza"
    ],
    "name:fra_x_preferred":[
        "Constanza"
    ],
    "name:ita_x_preferred":[
        "Constanza"
    ],
    "name:jpn_x_preferred":[
        "\u30b3\u30f3\u30b9\u30bf\u30f3\u30b5"
    ],
    "name:nan_x_preferred":[
        "Constanza"
    ],
    "name:nld_x_preferred":[
        "Constanza"
    ],
    "name:pol_x_preferred":[
        "Constanza"
    ],
    "name:por_x_preferred":[
        "Constanza"
    ],
    "name:rus_x_preferred":[
        "\u041a\u043e\u043d\u0441\u0442\u0430\u043d\u0446\u0438\u044f"
    ],
    "name:rus_x_variant":[
        "\u041a\u043e\u043d\u0441\u0442\u0430\u043d\u0441\u0430"
    ],
    "name:spa_x_preferred":[
        "Constanza"
    ],
    "name:swe_x_preferred":[
        "Constanza"
    ],
    "name:und_x_variant":[
        "Villa de Constanza"
    ],
    "name:vep_x_preferred":[
        "Konstans"
    ],
    "name:zho_min_nan_x_preferred":[
        "Constanza"
    ],
    "name:zho_x_preferred":[
        "\u5b54\u65af\u5766\u85a9"
    ],
    "qs:gn_country":"DO",
    "qs:gn_fcode":"PPL",
    "qs:gn_pop":29481,
    "qs:name":"Constanza",
    "qs:name_adm0":"Rep\u00fablica Dominicana",
    "qs:name_adm1":"La Vega",
    "qs:photos":247,
    "qs:photos_1k":50,
    "qs:photos_9k":1,
    "qs:photos_9r":4,
    "qs:photos_all":247,
    "qs:photos_sr":4,
    "qs:placetype":"Town",
    "qs:pop_sr":"7",
    "qs:woe_adm0":23424800,
    "wd:wordcount":699,
    "wof:name":"Constanza",
    "wof:placetype":"locality",
    "wof:population":29481
},
  "geometry": {"coordinates":[-70.74499,18.90919],"type":"Point"}
}