{
  "type": "Feature",
  "properties": {
    "gn:admin1_code":"36.0",
    "gn:admin2_code":"3101.0",
    "gn:admin3_code":"310105.0",
    "gn:admin4_code":"31010502.0",
    "gn:asciiname":"Tumbaca",
    "gn:country_code":"DO",
    "gn:dem":631,
    "gn:feature_class":"P",
    "gn:feature_code":"PPL",
    "gn:name":"Tumbaca",
    "gn:population":0,
    "gn:timezone":"America/Santo_Domingo",
    "iso:country":"DO",
    "wof:name":"Tumbaca",
    "wof:placetype":"locality"
},
  "geometry": {"coordinates":[-70.48333000000002,18.53333],"type":"Point"}
}