{
  "type": "Feature",
  "properties": {
    "gn:admin1_code":"36.0",
    "gn:admin2_code":"3101.0",
    "gn:admin3_code":"310104.0",
    "gn:admin4_code":"31010402.0",
    "gn:asciiname":"El Corbanal",
    "gn:country_code":"DO",
    "gn:dem":527,
    "gn:feature_class":"P",
    "gn:feature_code":"PPL",
    "gn:name":"El Corbanal",
    "gn:population":0,
    "gn:timezone":"America/Santo_Domingo",
    "iso:country":"DO",
    "wof:name":"El Corbanal",
    "wof:placetype":"locality"
},
  "geometry": {"coordinates":[-70.55374999999999,18.52416],"type":"Point"}
}