{
  "type": "Feature",
  "properties": {
    "gn:admin1_code":"37.0",
    "gn:admin2_code":"3205.0",
    "gn:admin3_code":"320501.0",
    "gn:admin4_code":"32050103.0",
    "gn:asciiname":"La Joya",
    "gn:country_code":"DO",
    "gn:dem":35,
    "gn:feature_class":"P",
    "gn:feature_code":"PPL",
    "gn:name":"La Joya",
    "gn:population":0,
    "gn:timezone":"America/Santo_Domingo",
    "iso:country":"DO",
    "name:ceb_x_preferred":[
        "La Joya"
    ],
    "name:deu_x_preferred":[
        "La Joya"
    ],
    "name:nld_x_preferred":[
        "La Joya"
    ],
    "name:que_x_preferred":[
        "La Joya"
    ],
    "name:spa_x_preferred":[
        "La Joya"
    ],
    "name:srp_x_preferred":[
        "\u041b\u0430 \u0425\u043e\u0458\u0430"
    ],
    "name:swe_x_preferred":[
        "La Joya"
    ],
    "wof:name":"La Joya",
    "wof:placetype":"locality"
},
  "geometry": {"coordinates":[-69.63908000000001,18.58731],"type":"Point"}
}