{
  "type": "Feature",
  "properties": {
    "gn:admin1_code":"1.0",
    "gn:admin2_code":"204.0",
    "gn:admin3_code":"20405.0",
    "gn:admin4_code":"2040504.0",
    "gn:asciiname":"Monte Frio",
    "gn:country_code":"DO",
    "gn:dem":1118,
    "gn:feature_class":"P",
    "gn:feature_code":"PPL",
    "gn:name":"Monte Fr\u00edo",
    "gn:population":0,
    "gn:timezone":"America/Santo_Domingo",
    "iso:country":"DO",
    "name:und_x_variant":[
        "Los Montes Frios",
        "Monte Fr\u00edo"
    ],
    "wof:name":"Monte Frio",
    "wof:placetype":"locality"
},
  "geometry": {"coordinates":[-70.96734000000002,18.86924],"type":"Point"}
}