{
  "type": "Feature",
  "properties": {
    "gn:admin1_code":"10.0",
    "gn:admin2_code":"1102.0",
    "gn:admin3_code":"110202.0",
    "gn:admin4_code":"11020202.0",
    "gn:asciiname":"El Atajadizo",
    "gn:country_code":"DO",
    "gn:dem":44,
    "gn:feature_class":"P",
    "gn:feature_code":"PPL",
    "gn:name":"El Atajadizo",
    "gn:population":0,
    "gn:timezone":"America/Santo_Domingo",
    "iso:country":"DO",
    "name:und_x_variant":[
        "Atajadizos",
        "El Atajadizo"
    ],
    "wof:name":"El Atajadizo",
    "wof:placetype":"locality"
},
  "geometry": {"coordinates":[-68.60674,18.39509],"type":"Point"}
}