{
  "type": "Feature",
  "properties": {
    "gn:admin1_code":"18.0",
    "gn:admin2_code":"1801.0",
    "gn:admin3_code":"180103.0",
    "gn:admin4_code":"18010307.0",
    "gn:asciiname":"Loma de Las Bestias",
    "gn:country_code":"DO",
    "gn:dem":231,
    "gn:feature_class":"P",
    "gn:feature_code":"PPL",
    "gn:name":"Loma de Las Bestias",
    "gn:population":0,
    "gn:timezone":"America/Santo_Domingo",
    "iso:country":"DO",
    "wof:name":"Loma de Las Bestias",
    "wof:placetype":"locality"
},
  "geometry": {"coordinates":[-70.76725,19.7938],"type":"Point"}
}