{
  "type": "Feature",
  "properties": {
    "gn:admin1_code":"21.0",
    "gn:admin2_code":"2404.0",
    "gn:admin3_code":"240401.0",
    "gn:admin4_code":"24040102.0",
    "gn:asciiname":"Vera de Yuna",
    "gn:country_code":"DO",
    "gn:dem":54,
    "gn:feature_class":"P",
    "gn:feature_code":"PPL",
    "gn:name":"Vera de Yuna",
    "gn:population":0,
    "gn:timezone":"America/Santo_Domingo",
    "iso:country":"DO",
    "name:und_x_variant":[
        "Vereda de Yuna",
        "Vera de Yuna"
    ],
    "wof:name":"Vera de Yuna",
    "wof:placetype":"locality"
},
  "geometry": {"coordinates":[-70.18833000000001,19.07599],"type":"Point"}
}