{
  "type": "Feature",
  "properties": {
    "gn:admin1_code":"18.0",
    "gn:admin2_code":"1801.0",
    "gn:admin3_code":"180103.0",
    "gn:admin4_code":"18010302.0",
    "gn:asciiname":"La Gata",
    "gn:country_code":"DO",
    "gn:dem":278,
    "gn:feature_class":"P",
    "gn:feature_code":"PPL",
    "gn:name":"La Gata",
    "gn:population":0,
    "gn:timezone":"America/Santo_Domingo",
    "iso:country":"DO",
    "wof:name":"La Gata",
    "wof:placetype":"locality"
},
  "geometry": {"coordinates":[-70.76091,19.78041],"type":"Point"}
}