{
  "type": "Feature",
  "properties": {
    "gn:admin1_code":"15.0",
    "gn:admin2_code":"1503.0",
    "gn:admin3_code":"150302.0",
    "gn:admin4_code":"15030204.0",
    "gn:asciiname":"Villa Lobos Abajo",
    "gn:country_code":"DO",
    "gn:dem":69,
    "gn:feature_class":"P",
    "gn:feature_code":"PPL",
    "gn:name":"Villa Lobos Abajo",
    "gn:population":0,
    "gn:timezone":"America/Santo_Domingo",
    "iso:country":"DO",
    "name:und_x_variant":[
        "Villa Lobo Abajo",
        "Villa Lobos Abajo"
    ],
    "wof:name":"Villa Lobos Abajo",
    "wof:placetype":"locality"
},
  "geometry": {"coordinates":[-71.29680999999999,19.69347],"type":"Point"}
}