{
  "type": "Feature",
  "properties": {
    "gn:admin1_code":"14.0",
    "gn:admin2_code":"1402.0",
    "gn:admin3_code":"140201.0",
    "gn:admin4_code":"14020102.0",
    "gn:asciiname":"La Cabirma",
    "gn:country_code":"DO",
    "gn:dem":274,
    "gn:feature_class":"P",
    "gn:feature_code":"PPL",
    "gn:name":"La Cabirma",
    "gn:population":0,
    "gn:timezone":"America/Santo_Domingo",
    "iso:country":"DO",
    "name:und_x_variant":[
        "Loma de Burro",
        "Cabirmas",
        "La Cabirma"
    ],
    "wof:name":"La Cabirma",
    "wof:placetype":"locality"
},
  "geometry": {"coordinates":[-69.97766999999999,19.60979],"type":"Point"}
}