{
  "type": "Feature",
  "properties": {
    "gn:admin1_code":"32.0",
    "gn:admin2_code":"2905.0",
    "gn:admin3_code":"290501.0",
    "gn:admin4_code":"29050105.0",
    "gn:asciiname":"Tierra Mala",
    "gn:country_code":"DO",
    "gn:dem":123,
    "gn:feature_class":"P",
    "gn:feature_code":"PPL",
    "gn:name":"Tierra Mala",
    "gn:population":0,
    "gn:timezone":"America/Santo_Domingo",
    "iso:country":"DO",
    "wof:name":"Tierra Mala",
    "wof:placetype":"locality"
},
  "geometry": {"coordinates":[-70.04039,18.81415],"type":"Point"}
}