{
  "type": "Feature",
  "properties": {
    "gn:admin1_code":"28.0",
    "gn:admin2_code":"801.0",
    "gn:admin3_code":"80103.0",
    "gn:admin4_code":"8010303.0",
    "gn:asciiname":"El Rancho",
    "gn:country_code":"DO",
    "gn:dem":145,
    "gn:feature_class":"P",
    "gn:feature_code":"PPL",
    "gn:name":"El Rancho",
    "gn:population":0,
    "gn:timezone":"America/Santo_Domingo",
    "iso:country":"DO",
    "name:ceb_x_preferred":[
        "El Rancho"
    ],
    "name:deu_x_preferred":[
        "El Rancho"
    ],
    "name:ita_x_preferred":[
        "El Rancho"
    ],
    "name:spa_x_preferred":[
        "El Rancho"
    ],
    "name:srp_x_preferred":[
        "\u0415\u043b \u0420\u0430\u043d\u0447\u043e"
    ],
    "name:swe_x_preferred":[
        "El Rancho"
    ],
    "name:ukr_x_preferred":[
        "\u0415\u043b\u044c-\u0420\u0430\u043d\u0447\u043e"
    ],
    "wof:name":"El Rancho",
    "wof:placetype":"locality"
},
  "geometry": {"coordinates":[-69.2154,18.84411],"type":"Point"}
}