{
  "type": "Feature",
  "properties": {
    "gn:admin1_code":"25.0",
    "gn:admin2_code":"2507.0",
    "gn:admin3_code":"250702.0",
    "gn:admin4_code":"25070202.0",
    "gn:asciiname":"El Pozo",
    "gn:country_code":"DO",
    "gn:dem":179,
    "gn:feature_class":"P",
    "gn:feature_code":"PPL",
    "gn:name":"El Pozo",
    "gn:population":0,
    "gn:timezone":"America/Santo_Domingo",
    "iso:country":"DO",
    "wof:name":"El Pozo",
    "wof:placetype":"locality"
},
  "geometry": {"coordinates":[-70.74621999999999,19.54434],"type":"Point"}
}