{
  "type": "Feature",
  "properties": {
    "gn:admin1_code":"6.0",
    "gn:admin2_code":"603.0",
    "gn:admin3_code":"60301.0",
    "gn:admin4_code":"6030107.0",
    "gn:asciiname":"Yanabo",
    "gn:country_code":"DO",
    "gn:dem":98,
    "gn:feature_class":"P",
    "gn:feature_code":"PPL",
    "gn:name":"Yanabo",
    "gn:population":0,
    "gn:timezone":"America/Santo_Domingo",
    "iso:country":"DO",
    "wof:name":"Yanabo",
    "wof:placetype":"locality"
},
  "geometry": {"coordinates":[-69.98333000000001,19.21667],"type":"Point"}
}