{
  "type": "Feature",
  "properties": {
    "gn:admin1_code":"2.0",
    "gn:admin2_code":"302.0",
    "gn:admin3_code":"30201.0",
    "gn:admin4_code":"3020104.0",
    "gn:asciiname":"La Plena",
    "gn:country_code":"DO",
    "gn:dem":512,
    "gn:feature_class":"P",
    "gn:feature_code":"PPL",
    "gn:name":"La Plena",
    "gn:population":0,
    "gn:timezone":"America/Santo_Domingo",
    "iso:country":"DO",
    "wof:name":"La Plena",
    "wof:placetype":"locality"
},
  "geometry": {"coordinates":[-71.33333,18.56667],"type":"Point"}
}