{
  "type": "Feature",
  "properties": {
    "gn:admin1_code":"4.0",
    "gn:admin2_code":"503.0",
    "gn:admin3_code":"50301.0",
    "gn:admin4_code":"5030102.0",
    "gn:asciiname":"Los Indios",
    "gn:country_code":"DO",
    "gn:dem":173,
    "gn:feature_class":"P",
    "gn:feature_code":"PPL",
    "gn:name":"Los Indios",
    "gn:population":0,
    "gn:timezone":"America/Santo_Domingo",
    "iso:country":"DO",
    "wof:name":"Los Indios",
    "wof:placetype":"locality"
},
  "geometry": {"coordinates":[-71.56005999999999,19.50307],"type":"Point"}
}