{
  "type": "Feature",
  "properties": {
    "gn:admin1_code":"28.0",
    "gn:admin2_code":"801.0",
    "gn:admin3_code":"80101.0",
    "gn:admin4_code":"8010106.0",
    "gn:asciiname":"Rincon Chavon",
    "gn:country_code":"DO",
    "gn:dem":120,
    "gn:feature_class":"P",
    "gn:feature_code":"PPL",
    "gn:name":"Rinc\u00f3n Chav\u00f3n",
    "gn:population":0,
    "gn:timezone":"America/Santo_Domingo",
    "iso:country":"DO",
    "name:und_x_variant":[
        "Rinc\u00f3n",
        "Rinc\u00f3n Chav\u00f3n"
    ],
    "wof:name":"Rincon Chavon",
    "wof:placetype":"locality"
},
  "geometry": {"coordinates":[-68.90316999999999,18.75624],"type":"Point"}
}