{
  "type": "Feature",
  "properties": {
    "gn:admin1_code":"18.0",
    "gn:admin2_code":"1802.0",
    "gn:admin3_code":"180202.0",
    "gn:admin4_code":"18020205.0",
    "gn:asciiname":"La Vereda",
    "gn:country_code":"DO",
    "gn:dem":390,
    "gn:feature_class":"P",
    "gn:feature_code":"PPL",
    "gn:name":"La Vereda",
    "gn:population":0,
    "gn:timezone":"America/Santo_Domingo",
    "iso:country":"DO",
    "wof:name":"La Vereda",
    "wof:placetype":"locality"
},
  "geometry": {"coordinates":[-70.73664000000002,19.62567],"type":"Point"}
}