{
  "type": "Feature",
  "properties": {
    "gn:admin1_code":"8.0",
    "gn:admin2_code":"901.0",
    "gn:admin3_code":"90103.0",
    "gn:admin4_code":"9010305.0",
    "gn:asciiname":"Hato Viejo",
    "gn:country_code":"DO",
    "gn:dem":473,
    "gn:feature_class":"P",
    "gn:feature_code":"PPL",
    "gn:name":"Hato Viejo",
    "gn:population":0,
    "gn:timezone":"America/Santo_Domingo",
    "iso:country":"DO",
    "wof:name":"Hato Viejo",
    "wof:placetype":"locality"
},
  "geometry": {"coordinates":[-70.55719999999999,19.47688],"type":"Point"}
}