{
  "type": "Feature",
  "properties": {
    "gn:admin1_code":"32.0",
    "gn:admin2_code":"2902.0",
    "gn:admin3_code":"290201.0",
    "gn:admin4_code":"29020106.0",
    "gn:asciiname":"Castellanos",
    "gn:country_code":"DO",
    "gn:dem":190,
    "gn:feature_class":"P",
    "gn:feature_code":"PPL",
    "gn:name":"Castellanos",
    "gn:population":0,
    "gn:timezone":"America/Santo_Domingo",
    "iso:country":"DO",
    "name:cat_x_preferred":[
        "Castellanos"
    ],
    "name:ceb_x_preferred":[
        "Castellanos"
    ],
    "name:deu_x_preferred":[
        "Castellanos"
    ],
    "name:fra_x_preferred":[
        "Castellanos"
    ],
    "name:ita_x_preferred":[
        "Castellanos"
    ],
    "name:nld_x_preferred":[
        "Castellanos"
    ],
    "name:rus_x_preferred":[
        "\u041a\u0430\u0441\u0442\u0435\u043b\u044c\u044f\u043d\u043e\u0441"
    ],
    "name:spa_x_preferred":[
        "Castellanos"
    ],
    "name:swe_x_preferred":[
        "Castellanos"
    ],
    "name:ukr_x_preferred":[
        "\u041a\u0430\u0441\u0442\u0435\u043b\u044c\u044f\u043d\u043e\u0441"
    ],
    "name:und_x_variant":[
        "Costella",
        "Castella",
        "Castellanos"
    ],
    "wof:name":"Castellanos",
    "wof:placetype":"locality"
},
  "geometry": {"coordinates":[-69.47748,18.82504],"type":"Point"}
}