{
  "type": "Feature",
  "properties": {
    "gn:admin1_code":"32.0",
    "gn:admin2_code":"2904.0",
    "gn:admin3_code":"290401.0",
    "gn:admin4_code":"29040105.0",
    "gn:asciiname":"El Mogote",
    "gn:country_code":"DO",
    "gn:dem":94,
    "gn:feature_class":"P",
    "gn:feature_code":"PPL",
    "gn:name":"El Mogote",
    "gn:population":0,
    "gn:timezone":"America/Santo_Domingo",
    "iso:country":"DO",
    "wof:name":"El Mogote",
    "wof:placetype":"locality"
},
  "geometry": {"coordinates":[-70.00979,18.79963],"type":"Point"}
}