{
  "type": "Feature",
  "properties": {
    "gn:admin1_code":"21.0",
    "gn:admin2_code":"2401.0",
    "gn:admin3_code":"240104.0",
    "gn:admin4_code":"24010402.0",
    "gn:asciiname":"Comedero Arriba",
    "gn:country_code":"DO",
    "gn:dem":120,
    "gn:feature_class":"P",
    "gn:feature_code":"PPL",
    "gn:name":"Comedero Arriba",
    "gn:population":0,
    "gn:timezone":"America/Santo_Domingo",
    "iso:country":"DO",
    "wof:name":"Comedero Arriba",
    "wof:placetype":"locality"
},
  "geometry": {"coordinates":[-70.30224,19.04506],"type":"Point"}
}