{
  "type": "Feature",
  "properties": {
    "gn:admin1_code":"18.0",
    "gn:admin2_code":"1802.0",
    "gn:admin3_code":"180201.0",
    "gn:admin4_code":"18020103.0",
    "gn:asciiname":"Escalera Abajo",
    "gn:country_code":"DO",
    "gn:dem":510,
    "gn:feature_class":"P",
    "gn:feature_code":"PPL",
    "gn:name":"Escalera Abajo",
    "gn:population":0,
    "gn:timezone":"America/Santo_Domingo",
    "iso:country":"DO",
    "wof:name":"Escalera Abajo",
    "wof:placetype":"locality"
},
  "geometry": {"coordinates":[-70.79808,19.63743],"type":"Point"}
}