{
  "type": "Feature",
  "properties": {
    "gn:admin1_code":"1.0",
    "gn:admin2_code":"203.0",
    "gn:admin3_code":"20301.0",
    "gn:admin4_code":"2030102.0",
    "gn:asciiname":"Viajama",
    "gn:country_code":"DO",
    "gn:dem":538,
    "gn:feature_class":"P",
    "gn:feature_code":"PPL",
    "gn:name":"Viajama",
    "gn:population":0,
    "gn:timezone":"America/Santo_Domingo",
    "iso:country":"DO",
    "wof:name":"Viajama",
    "wof:placetype":"locality"
},
  "geometry": {"coordinates":[-70.8805,18.64122],"type":"Point"}
}