{
  "type": "Feature",
  "properties": {
    "gn:admin1_code":"10.0",
    "gn:admin2_code":"1101.0",
    "gn:admin3_code":"110102.0",
    "gn:admin4_code":"11010202.0",
    "gn:asciiname":"La Tranquera",
    "gn:country_code":"DO",
    "gn:dem":21,
    "gn:feature_class":"P",
    "gn:feature_code":"PPL",
    "gn:name":"La Tranquera",
    "gn:population":0,
    "gn:timezone":"America/Santo_Domingo",
    "iso:country":"DO",
    "wof:name":"La Tranquera",
    "wof:placetype":"locality"
},
  "geometry": {"coordinates":[-68.72790000000001,18.91544],"type":"Point"}
}