{
  "type": "Feature",
  "properties": {
    "gn:admin1_code":"23.0",
    "gn:admin2_code":"2201.0",
    "gn:admin3_code":"220111.0",
    "gn:admin4_code":"22011103.0",
    "gn:asciiname":"Carrera del Pino",
    "gn:cc2":"DO",
    "gn:country_code":"DO",
    "gn:dem":818,
    "gn:feature_class":"P",
    "gn:feature_code":"PPL",
    "gn:name":"Carrera del Pino",
    "gn:population":0,
    "gn:timezone":"America/Santo_Domingo",
    "iso:country":"DO",
    "name:und_x_variant":[
        "Carrepino",
        "Carrera del Pino"
    ],
    "wof:name":"Carrera del Pino",
    "wof:placetype":"locality"
},
  "geometry": {"coordinates":[-71.08333,18.86667000000001],"type":"Point"}
}