{
  "type": "Feature",
  "properties": {
    "gn:admin1_code":"19.0",
    "gn:admin2_code":"1901.0",
    "gn:admin3_code":"190101.0",
    "gn:admin4_code":"19010102.0",
    "gn:asciiname":"Conuco",
    "gn:country_code":"DO",
    "gn:dem":148,
    "gn:feature_class":"P",
    "gn:feature_code":"PPL",
    "gn:name":"Conuco",
    "gn:population":0,
    "gn:timezone":"America/Santo_Domingo",
    "iso:country":"DO",
    "wof:name":"Conuco",
    "wof:placetype":"locality"
},
  "geometry": {"coordinates":[-70.36604,19.35399],"type":"Point"}
}