{
  "type": "Feature",
  "properties": {
    "gn:admin1_code":"1.0",
    "gn:admin2_code":"203.0",
    "gn:admin3_code":"20302.0",
    "gn:admin4_code":"2030203.0",
    "gn:asciiname":"Gerardo",
    "gn:country_code":"DO",
    "gn:dem":346,
    "gn:feature_class":"P",
    "gn:feature_code":"PPL",
    "gn:name":"Gerardo",
    "gn:population":0,
    "gn:timezone":"America/Santo_Domingo",
    "iso:country":"DO",
    "name:ita_x_preferred":[
        "Gerardo"
    ],
    "name:pol_x_preferred":[
        "Gerarda"
    ],
    "name:spa_x_preferred":[
        "Gerardo"
    ],
    "wof:name":"Gerardo",
    "wof:placetype":"locality"
},
  "geometry": {"coordinates":[-71.03333000000001,18.66667],"type":"Point"}
}