{
  "type": "Feature",
  "properties": {
    "gn:admin1_code":"21.0",
    "gn:admin2_code":"2402.0",
    "gn:admin3_code":"240201.0",
    "gn:admin4_code":"24020103.0",
    "gn:asciiname":"La Lagunita",
    "gn:country_code":"DO",
    "gn:dem":149,
    "gn:feature_class":"P",
    "gn:feature_code":"PPL",
    "gn:name":"La Lagunita",
    "gn:population":0,
    "gn:timezone":"America/Santo_Domingo",
    "iso:country":"DO",
    "wof:name":"La Lagunita",
    "wof:placetype":"locality"
},
  "geometry": {"coordinates":[-69.94334000000001,19.06551],"type":"Point"}
}