{
  "type": "Feature",
  "properties": {
    "gn:admin1_code":"20.0",
    "gn:admin2_code":"2003.0",
    "gn:admin3_code":"200301.0",
    "gn:admin4_code":"20030104.0",
    "gn:asciiname":"La Barbacoa",
    "gn:country_code":"DO",
    "gn:dem":22,
    "gn:feature_class":"P",
    "gn:feature_code":"PPL",
    "gn:name":"La Barbacoa",
    "gn:population":0,
    "gn:timezone":"America/Santo_Domingo",
    "iso:country":"DO",
    "name:und_x_variant":[
        "Barbacoa",
        "La Barbacoa"
    ],
    "wof:name":"La Barbacoa",
    "wof:placetype":"locality"
},
  "geometry": {"coordinates":[-69.47423000000001,19.31096],"type":"Point"}
}