{
  "type": "Feature",
  "properties": {
    "gn:admin1_code":"32.0",
    "gn:admin2_code":"2904.0",
    "gn:admin3_code":"290401.0",
    "gn:admin4_code":"29040102.0",
    "gn:asciiname":"Pepe Perez",
    "gn:country_code":"DO",
    "gn:dem":318,
    "gn:feature_class":"P",
    "gn:feature_code":"PPL",
    "gn:name":"Pepe P\u00e9rez",
    "gn:population":0,
    "gn:timezone":"America/Santo_Domingo",
    "iso:country":"DO",
    "wof:name":"Pepe Perez",
    "wof:placetype":"locality"
},
  "geometry": {"coordinates":[-70.22354,18.84204],"type":"Point"}
}