{
  "type": "Feature",
  "properties": {
    "gn:admin1_code":"26.0",
    "gn:admin2_code":"2601.0",
    "gn:admin3_code":"260101.0",
    "gn:admin4_code":"26010104.0",
    "gn:asciiname":"Minaya",
    "gn:country_code":"DO",
    "gn:dem":179,
    "gn:feature_class":"P",
    "gn:feature_code":"PPL",
    "gn:name":"Minaya",
    "gn:population":0,
    "gn:timezone":"America/Santo_Domingo",
    "iso:country":"DO",
    "wof:name":"Minaya",
    "wof:placetype":"locality"
},
  "geometry": {"coordinates":[-71.33110000000001,19.44029],"type":"Point"}
}