{
  "type": "Feature",
  "properties": {
    "gn:admin1_code":"26.0",
    "gn:admin2_code":"2601.0",
    "gn:admin3_code":"260101.0",
    "gn:admin4_code":"26010104.0",
    "gn:asciiname":"Minaya",
    "gn:country_code":"DO",
    "gn:dem":179,
    "gn:feature_class":"P",
    "gn:feature_code":"PPL",
    "gn:name":"Minaya",
    "gn:population":0,
    "gn:timezone":"America/Santo_Domingo",
    "iso:country":"DO",
    "name:ara_x_preferred":[
        "\u0645\u064a\u0646\u0627\u064a\u0627"
    ],
    "name:arg_x_preferred":[
        "Minaya"
    ],
    "name:ast_x_preferred":[
        "Minaya"
    ],
    "name:azb_x_preferred":[
        "\u0645\u06cc\u0646\u0627\u06cc\u0627"
    ],
    "name:cat_x_preferred":[
        "Minaya"
    ],
    "name:ceb_x_preferred":[
        "Minaya"
    ],
    "name:eus_x_preferred":[
        "Minaya"
    ],
    "name:fas_x_preferred":[
        "\u0645\u06cc\u0646\u0627\u06cc\u0627"
    ],
    "name:fra_x_preferred":[
        "Minaya"
    ],
    "name:hun_x_preferred":[
        "Minaya"
    ],
    "name:ina_x_preferred":[
        "Minaya"
    ],
    "name:ita_x_preferred":[
        "Minaya"
    ],
    "name:msa_x_preferred":[
        "Minaya"
    ],
    "name:nld_x_preferred":[
        "Minaya"
    ],
    "name:oci_x_preferred":[
        "Minaya"
    ],
    "name:pol_x_preferred":[
        "Minaya"
    ],
    "name:por_x_preferred":[
        "Minaya"
    ],
    "name:ron_x_preferred":[
        "Minaya"
    ],
    "name:rus_x_preferred":[
        "\u041c\u0438\u043d\u0430\u044f"
    ],
    "name:spa_x_preferred":[
        "Minaya"
    ],
    "name:sqi_x_preferred":[
        "Minaya"
    ],
    "name:swe_x_preferred":[
        "Minaya"
    ],
    "name:ukr_x_preferred":[
        "\u041c\u0456\u043d\u0430\u044f"
    ],
    "name:vie_x_preferred":[
        "Minaya"
    ],
    "name:war_x_preferred":[
        "Minaya"
    ],
    "name:zho_x_preferred":[
        "\u7c73\u5948\u963f"
    ],
    "wof:name":"Minaya",
    "wof:placetype":"locality"
},
  "geometry": {"coordinates":[-71.33110000000001,19.44029],"type":"Point"}
}