{
  "type": "Feature",
  "properties": {
    "gn:admin1_code":"37.0",
    "gn:admin2_code":"3204.0",
    "gn:admin3_code":"320401.0",
    "gn:admin4_code":"32040101.0",
    "gn:asciiname":"El Higo",
    "gn:country_code":"DO",
    "gn:dem":10,
    "gn:feature_class":"P",
    "gn:feature_code":"PPL",
    "gn:name":"El Higo",
    "gn:population":0,
    "gn:timezone":"America/Santo_Domingo",
    "iso:country":"DO",
    "name:ceb_x_preferred":[
        "El Higo"
    ],
    "name:swe_x_preferred":[
        "El Higo"
    ],
    "wof:name":"El Higo",
    "wof:placetype":"locality"
},
  "geometry": {"coordinates":[-69.63333,18.45],"type":"Point"}
}