{
  "type": "Feature",
  "properties": {
    "gn:admin1_code":"24.0",
    "gn:admin2_code":"2305.0",
    "gn:admin3_code":"230501.0",
    "gn:admin4_code":"23050104.0",
    "gn:asciiname":"Moruno del Guano",
    "gn:country_code":"DO",
    "gn:dem":42,
    "gn:feature_class":"P",
    "gn:feature_code":"PPL",
    "gn:name":"Moruno del Guano",
    "gn:population":0,
    "gn:timezone":"America/Santo_Domingo",
    "iso:country":"DO",
    "name:und_x_variant":[
        "Moruno de Guano",
        "Moruno del Guano"
    ],
    "wof:name":"Moruno del Guano",
    "wof:placetype":"locality"
},
  "geometry": {"coordinates":[-69.43953,18.51205],"type":"Point"}
}