{
  "type": "Feature",
  "properties": {
    "gn:admin1_code":"37.0",
    "gn:admin2_code":"3202.0",
    "gn:admin3_code":"320201.0",
    "gn:admin4_code":"32020101.0",
    "gn:asciiname":"El Palmar",
    "gn:country_code":"DO",
    "gn:dem":63,
    "gn:feature_class":"P",
    "gn:feature_code":"PPL",
    "gn:name":"El Palmar",
    "gn:population":0,
    "gn:timezone":"America/Santo_Domingo",
    "iso:country":"DO",
    "wof:name":"El Palmar",
    "wof:placetype":"locality"
},
  "geometry": {"coordinates":[-69.98506,18.45363],"type":"Point"}
}