{
  "type": "Feature",
  "properties": {
    "gn:admin1_code":"26.0",
    "gn:admin2_code":"2603.0",
    "gn:admin3_code":"260301.0",
    "gn:admin4_code":"26030105.0",
    "gn:asciiname":"Duran",
    "gn:country_code":"DO",
    "gn:dem":388,
    "gn:feature_class":"P",
    "gn:feature_code":"PPL",
    "gn:name":"Dur\u00e1n",
    "gn:population":0,
    "gn:timezone":"America/Santo_Domingo",
    "iso:country":"DO",
    "wof:name":"Duran",
    "wof:placetype":"locality"
},
  "geometry": {"coordinates":[-71.17569,19.40185],"type":"Point"}
}