{
  "type": "Feature",
  "properties": {
    "gn:admin1_code":"8.0",
    "gn:admin2_code":"903.0",
    "gn:admin3_code":"90301.0",
    "gn:admin4_code":"9030103.0",
    "gn:asciiname":"Saltadero",
    "gn:country_code":"DO",
    "gn:dem":160,
    "gn:feature_class":"P",
    "gn:feature_code":"PPL",
    "gn:name":"Saltadero",
    "gn:population":0,
    "gn:timezone":"America/Santo_Domingo",
    "iso:country":"DO",
    "wof:name":"Saltadero",
    "wof:placetype":"locality"
},
  "geometry": {"coordinates":[-70.30533,19.62004],"type":"Point"}
}