{
  "type": "Feature",
  "properties": {
    "gn:admin1_code":"32.0",
    "gn:admin2_code":"2901.0",
    "gn:admin3_code":"290104.0",
    "gn:admin4_code":"29010404.0",
    "gn:asciiname":"Cruce de Tone",
    "gn:country_code":"DO",
    "gn:dem":76,
    "gn:feature_class":"P",
    "gn:feature_code":"PPL",
    "gn:name":"Cruce de To\u00f1\u00e9",
    "gn:population":0,
    "gn:timezone":"America/Santo_Domingo",
    "iso:country":"DO",
    "wof:name":"Cruce de Tone",
    "wof:placetype":"locality"
},
  "geometry": {"coordinates":[-69.76401,18.8583],"type":"Point"}
}