{
  "type": "Feature",
  "properties": {
    "gn:admin1_code":"27.0",
    "gn:admin2_code":"2702.0",
    "gn:admin3_code":"270202.0",
    "gn:admin4_code":"27020206.0",
    "gn:asciiname":"El Chorro",
    "gn:country_code":"DO",
    "gn:dem":205,
    "gn:feature_class":"P",
    "gn:feature_code":"PPL",
    "gn:name":"El Chorro",
    "gn:population":0,
    "gn:timezone":"America/Santo_Domingo",
    "iso:country":"DO",
    "wof:name":"El Chorro",
    "wof:placetype":"locality"
},
  "geometry": {"coordinates":[-71.00581,19.67753],"type":"Point"}
}