{
  "type": "Feature",
  "properties": {
    "gn:admin1_code":"11.0",
    "gn:admin2_code":"701.0",
    "gn:admin3_code":"70101.0",
    "gn:admin4_code":"7010102.0",
    "gn:asciiname":"Los Rinconcitos",
    "gn:country_code":"DO",
    "gn:dem":267,
    "gn:feature_class":"P",
    "gn:feature_code":"PPL",
    "gn:name":"Los Rinconcitos",
    "gn:population":0,
    "gn:timezone":"America/Santo_Domingo",
    "iso:country":"DO",
    "name:und_x_variant":[
        "Rinconcito",
        "Los Rinconcitos"
    ],
    "wof:name":"Los Rinconcitos",
    "wof:placetype":"locality"
},
  "geometry": {"coordinates":[-71.77668,18.95732000000001],"type":"Point"}
}