{
  "type": "Feature",
  "properties": {
    "gn:admin1_code":"21.0",
    "gn:admin2_code":"2401.0",
    "gn:admin3_code":"240101.0",
    "gn:admin4_code":"24010104.0",
    "gn:asciiname":"El Higo",
    "gn:country_code":"DO",
    "gn:dem":163,
    "gn:feature_class":"P",
    "gn:feature_code":"PPL",
    "gn:name":"El Higo",
    "gn:population":0,
    "gn:timezone":"America/Santo_Domingo",
    "iso:country":"DO",
    "wof:name":"El Higo",
    "wof:placetype":"locality"
},
  "geometry": {"coordinates":[-70.14664999999999,18.88643],"type":"Point"}
}