{
  "type": "Feature",
  "properties": {
    "gn:admin1_code":"37.0",
    "gn:admin2_code":"3205.0",
    "gn:admin3_code":"320501.0",
    "gn:admin4_code":"32050104.0",
    "gn:asciiname":"La Infinita",
    "gn:country_code":"DO",
    "gn:dem":27,
    "gn:feature_class":"P",
    "gn:feature_code":"PPL",
    "gn:name":"La Infinita",
    "gn:population":0,
    "gn:timezone":"America/Santo_Domingo",
    "iso:country":"DO",
    "wof:name":"La Infinita",
    "wof:placetype":"locality"
},
  "geometry": {"coordinates":[-69.70796,18.58474],"type":"Point"}
}