{
  "type": "Feature",
  "properties": {
    "gn:admin1_code":"8.0",
    "gn:asciiname":"Los Amaceyes Arriba",
    "gn:country_code":"DO",
    "gn:dem":353,
    "gn:feature_class":"P",
    "gn:feature_code":"PPL",
    "gn:name":"Los Amaceyes Arriba",
    "gn:population":0,
    "gn:timezone":"America/Santo_Domingo",
    "iso:country":"DO",
    "name:und_x_variant":[
        "Amaceyes Arriba",
        "Los Amaceyes Arriba"
    ],
    "wof:name":"Los Amaceyes Arriba",
    "wof:placetype":"locality"
},
  "geometry": {"coordinates":[-70.56477,19.49249],"type":"Point"}
}