{
  "type": "Feature",
  "properties": {
    "gn:admin1_code":"2.0",
    "gn:admin2_code":"303.0",
    "gn:admin3_code":"30302.0",
    "gn:admin4_code":"3030202.0",
    "gn:asciiname":"El Jobo",
    "gn:country_code":"DO",
    "gn:dem":23,
    "gn:feature_class":"P",
    "gn:feature_code":"PPL",
    "gn:name":"El Jobo",
    "gn:population":0,
    "gn:timezone":"America/Santo_Domingo",
    "iso:country":"DO",
    "wof:name":"El Jobo",
    "wof:placetype":"locality"
},
  "geometry": {"coordinates":[-71.20737,18.35407],"type":"Point"}
}