{
  "type": "Feature",
  "properties": {
    "gn:admin1_code":"25.0",
    "gn:admin2_code":"2503.0",
    "gn:admin3_code":"250303.0",
    "gn:admin4_code":"25030302.0",
    "gn:asciiname":"El Jagual",
    "gn:country_code":"DO",
    "gn:dem":412,
    "gn:feature_class":"P",
    "gn:feature_code":"PPL",
    "gn:name":"El Jagual",
    "gn:population":0,
    "gn:timezone":"America/Santo_Domingo",
    "iso:country":"DO",
    "wof:name":"El Jagual",
    "wof:placetype":"locality"
},
  "geometry": {"coordinates":[-70.69116,19.2573],"type":"Point"}
}