{
  "type": "Feature",
  "properties": {
    "gn:admin1_code":"33.0",
    "gn:admin2_code":"2101.0",
    "gn:admin3_code":"210101.0",
    "gn:admin4_code":"21010102.0",
    "gn:asciiname":"Lalica",
    "gn:country_code":"DO",
    "gn:dem":138,
    "gn:feature_class":"P",
    "gn:feature_code":"PPL",
    "gn:name":"Lalica",
    "gn:population":0,
    "gn:timezone":"America/Santo_Domingo",
    "iso:country":"DO",
    "wof:name":"Lalica",
    "wof:placetype":"locality"
},
  "geometry": {"coordinates":[-70.14423000000001,18.48595],"type":"Point"}
}