{
  "type": "Feature",
  "properties": {
    "gn:admin1_code":"37.0",
    "gn:admin2_code":"3203.0",
    "gn:admin3_code":"320301.0",
    "gn:admin4_code":"32030105.0",
    "gn:asciiname":"Higueero",
    "gn:country_code":"DO",
    "gn:dem":31,
    "gn:feature_class":"P",
    "gn:feature_code":"PPL",
    "gn:name":"Hig\u00fcero",
    "gn:population":0,
    "gn:timezone":"America/Santo_Domingo",
    "iso:country":"DO",
    "wof:name":"Higueero",
    "wof:placetype":"locality"
},
  "geometry": {"coordinates":[-69.99649000000001,18.56875],"type":"Point"}
}