{
  "type": "Feature",
  "properties": {
    "gn:admin1_code":"20.0",
    "gn:admin2_code":"2001.0",
    "gn:admin3_code":"200104.0",
    "gn:admin4_code":"20010402.0",
    "gn:asciiname":"Quintana",
    "gn:country_code":"DO",
    "gn:dem":97,
    "gn:feature_class":"P",
    "gn:feature_code":"PPL",
    "gn:name":"Quintana",
    "gn:population":0,
    "gn:timezone":"America/Santo_Domingo",
    "iso:country":"DO",
    "wof:name":"Quintana",
    "wof:placetype":"locality"
},
  "geometry": {"coordinates":[-69.18711,19.26354],"type":"Point"}
}