{
  "type": "Feature",
  "properties": {
    "gn:admin1_code":"20.0",
    "gn:admin2_code":"2001.0",
    "gn:admin3_code":"200104.0",
    "gn:admin4_code":"20010402.0",
    "gn:asciiname":"Quintana",
    "gn:country_code":"DO",
    "gn:dem":97,
    "gn:feature_class":"P",
    "gn:feature_code":"PPL",
    "gn:name":"Quintana",
    "gn:population":0,
    "gn:timezone":"America/Santo_Domingo",
    "iso:country":"DO",
    "name:ast_x_preferred":[
        "Quintana"
    ],
    "name:cat_x_preferred":[
        "Quintana"
    ],
    "name:ceb_x_preferred":[
        "Quintana"
    ],
    "name:deu_x_preferred":[
        "Quintana"
    ],
    "name:eus_x_preferred":[
        "Quintana"
    ],
    "name:fra_x_preferred":[
        "Quintana"
    ],
    "name:glg_x_preferred":[
        "Quintana"
    ],
    "name:ita_x_preferred":[
        "Quintana"
    ],
    "name:nld_x_preferred":[
        "Quintana"
    ],
    "name:pol_x_preferred":[
        "Quintana"
    ],
    "name:por_x_preferred":[
        "Quintana"
    ],
    "name:rus_x_preferred":[
        "\u041a\u0438\u043d\u0442\u0430\u043d\u0430"
    ],
    "name:spa_x_preferred":[
        "Quintana"
    ],
    "name:swe_x_preferred":[
        "Quintana"
    ],
    "wof:name":"Quintana",
    "wof:placetype":"locality"
},
  "geometry": {"coordinates":[-69.18711,19.26354],"type":"Point"}
}