{
  "type": "Feature",
  "properties": {
    "gn:admin1_code":"30.0",
    "gn:admin2_code":"1301.0",
    "gn:admin3_code":"130102.0",
    "gn:admin4_code":"13010206.0",
    "gn:asciiname":"Los Fabres",
    "gn:country_code":"DO",
    "gn:dem":164,
    "gn:feature_class":"P",
    "gn:feature_code":"PPL",
    "gn:name":"Los Fabres",
    "gn:population":0,
    "gn:timezone":"America/Santo_Domingo",
    "iso:country":"DO",
    "wof:name":"Los Fabres",
    "wof:placetype":"locality"
},
  "geometry": {"coordinates":[-70.57826999999997,19.31149],"type":"Point"}
}