{
  "type": "Feature",
  "properties": {
    "gn:admin1_code":"30.0",
    "gn:admin2_code":"1301.0",
    "gn:admin3_code":"130101.0",
    "gn:admin4_code":"13010116.0",
    "gn:asciiname":"Sabaneta",
    "gn:country_code":"DO",
    "gn:dem":77,
    "gn:feature_class":"P",
    "gn:feature_code":"PPL",
    "gn:name":"Sabaneta",
    "gn:population":0,
    "gn:timezone":"America/Santo_Domingo",
    "iso:country":"DO",
    "wof:name":"Sabaneta",
    "wof:placetype":"locality"
},
  "geometry": {"coordinates":[-70.47083000000001,19.22045],"type":"Point"}
}