{
  "type": "Feature",
  "properties": {
    "gn:admin1_code":"12.0",
    "gn:admin2_code":"1202.0",
    "gn:admin3_code":"120201.0",
    "gn:admin4_code":"12020102.0",
    "gn:asciiname":"Batey Renguelito",
    "gn:country_code":"DO",
    "gn:dem":79,
    "gn:feature_class":"P",
    "gn:feature_code":"PPL",
    "gn:name":"Batey Renguelito",
    "gn:population":0,
    "gn:timezone":"America/Santo_Domingo",
    "iso:country":"DO",
    "wof:name":"Batey Renguelito",
    "wof:placetype":"locality"
},
  "geometry": {"coordinates":[-69.04743000000001,18.49482],"type":"Point"}
}