{
  "type": "Feature",
  "properties": {
    "gn:admin1_code":"23.0",
    "gn:admin2_code":"2201.0",
    "gn:admin3_code":"220105.0",
    "gn:admin4_code":"22010504.0",
    "gn:asciiname":"Los Charcos",
    "gn:country_code":"DO",
    "gn:dem":496,
    "gn:feature_class":"P",
    "gn:feature_code":"PPL",
    "gn:name":"Los Charcos",
    "gn:population":0,
    "gn:timezone":"America/Santo_Domingo",
    "iso:country":"DO",
    "wof:name":"Los Charcos",
    "wof:placetype":"locality"
},
  "geometry": {"coordinates":[-71.21905,18.65056],"type":"Point"}
}