{
  "type": "Feature",
  "properties": {
    "gn:admin1_code":"1.0",
    "gn:admin2_code":"201.0",
    "gn:admin3_code":"20106.0",
    "gn:admin4_code":"2010602.0",
    "gn:asciiname":"Barreras",
    "gn:country_code":"DO",
    "gn:dem":181,
    "gn:feature_class":"P",
    "gn:feature_code":"PPL",
    "gn:name":"Barreras",
    "gn:population":0,
    "gn:timezone":"America/Santo_Domingo",
    "iso:country":"DO",
    "name:und_x_variant":[
        "Barrero",
        "Barrera",
        "Barreras"
    ],
    "wof:name":"Barreras",
    "wof:placetype":"locality"
},
  "geometry": {"coordinates":[-70.90827,18.32646],"type":"Point"}
}