{
  "type": "Feature",
  "properties": {
    "gn:admin1_code":"10.0",
    "gn:admin2_code":"1101.0",
    "gn:admin3_code":"110101.0",
    "gn:admin4_code":"11010103.0",
    "gn:asciiname":"Las Yayas",
    "gn:country_code":"DO",
    "gn:dem":151,
    "gn:feature_class":"P",
    "gn:feature_code":"PPL",
    "gn:name":"Las Yayas",
    "gn:population":0,
    "gn:timezone":"America/Santo_Domingo",
    "iso:country":"DO",
    "wof:name":"Las Yayas",
    "wof:placetype":"locality"
},
  "geometry": {"coordinates":[-68.76316,18.65025],"type":"Point"}
}