{
  "type": "Feature",
  "properties": {
    "gn:admin1_code":"3.0",
    "gn:admin2_code":"409.0",
    "gn:admin3_code":"40901.0",
    "gn:admin4_code":"4090102.0",
    "gn:asciiname":"Lemba",
    "gn:country_code":"DO",
    "gn:dem":60,
    "gn:feature_class":"P",
    "gn:feature_code":"PPL",
    "gn:name":"Lemba",
    "gn:population":0,
    "gn:timezone":"America/Santo_Domingo",
    "iso:country":"DO",
    "wof:name":"Lemba",
    "wof:placetype":"locality"
},
  "geometry": {"coordinates":[-71.32509,18.25462000000001],"type":"Point"}
}