{
  "type": "Feature",
  "properties": {
    "gn:admin1_code":"1.0",
    "gn:admin2_code":"210.0",
    "gn:admin3_code":"21001.0",
    "gn:admin4_code":"2100102.0",
    "gn:asciiname":"El Coco",
    "gn:country_code":"DO",
    "gn:dem":533,
    "gn:feature_class":"P",
    "gn:feature_code":"PPL",
    "gn:name":"El Coco",
    "gn:population":0,
    "gn:timezone":"America/Santo_Domingo",
    "iso:country":"DO",
    "wof:name":"El Coco",
    "wof:placetype":"locality"
},
  "geometry": {"coordinates":[-70.57065,18.51893],"type":"Point"}
}