{
  "type": "Feature",
  "properties": {
    "gn:admin1_code":"30.0",
    "gn:admin2_code":"1302.0",
    "gn:admin3_code":"130202.0",
    "gn:admin4_code":"13020207.0",
    "gn:asciiname":"El Naranjo",
    "gn:country_code":"DO",
    "gn:dem":1306,
    "gn:feature_class":"P",
    "gn:feature_code":"PPL",
    "gn:name":"El Naranjo",
    "gn:population":0,
    "gn:timezone":"America/Santo_Domingo",
    "iso:country":"DO",
    "name:und_x_variant":[
        "Naranjo",
        "El Naranjo"
    ],
    "wof:name":"El Naranjo",
    "wof:placetype":"locality"
},
  "geometry": {"coordinates":[-70.62011,18.90909],"type":"Point"}
}