{
  "type": "Feature",
  "properties": {
    "gn:admin1_code":"14.0",
    "gn:admin2_code":"1401.0",
    "gn:admin3_code":"140104.0",
    "gn:admin4_code":"14010404.0",
    "gn:asciiname":"Los Pontones",
    "gn:country_code":"DO",
    "gn:dem":35,
    "gn:feature_class":"P",
    "gn:feature_code":"PPL",
    "gn:name":"Los Pontones",
    "gn:population":0,
    "gn:timezone":"America/Santo_Domingo",
    "iso:country":"DO",
    "wof:name":"Los Pontones",
    "wof:placetype":"locality"
},
  "geometry": {"coordinates":[-69.99686,19.42166],"type":"Point"}
}