{
  "type": "Feature",
  "properties": {
    "gn:admin1_code":"28.0",
    "gn:admin2_code":"801.0",
    "gn:admin3_code":"80101.0",
    "gn:admin4_code":"8010102.0",
    "gn:asciiname":"Capitan",
    "gn:country_code":"DO",
    "gn:dem":166,
    "gn:feature_class":"P",
    "gn:feature_code":"PPL",
    "gn:name":"Capit\u00e1n",
    "gn:population":0,
    "gn:timezone":"America/Santo_Domingo",
    "iso:country":"DO",
    "name:ceb_x_preferred":[
        "Capitan"
    ],
    "name:deu_x_preferred":[
        "Capitan"
    ],
    "name:fas_x_preferred":[
        "\u06a9\u0627\u067e\u06cc\u062a\u0627\u0646"
    ],
    "name:fra_x_preferred":[
        "Capitan"
    ],
    "name:nld_x_preferred":[
        "Capitan"
    ],
    "name:spa_x_preferred":[
        "Capit\u00e1n"
    ],
    "name:swe_x_preferred":[
        "Capitan"
    ],
    "wof:name":"Capitan",
    "wof:placetype":"locality"
},
  "geometry": {"coordinates":[-69.00813000000001,18.81638],"type":"Point"}
}