{
  "type": "Feature",
  "properties": {
    "gn:admin1_code":"28.0",
    "gn:admin2_code":"801.0",
    "gn:admin3_code":"80101.0",
    "gn:admin4_code":"8010108.0",
    "gn:asciiname":"Covadonga",
    "gn:country_code":"DO",
    "gn:dem":47,
    "gn:feature_class":"P",
    "gn:feature_code":"PPL",
    "gn:name":"Covadonga",
    "gn:population":0,
    "gn:timezone":"America/Santo_Domingo",
    "iso:country":"DO",
    "name:ara_x_preferred":[
        "\u0635\u062e\u0631\u0629 \u0628\u0644\u0627\u064a"
    ],
    "name:arz_x_preferred":[
        "\u0645\u063a\u0627\u0631\u0629 \u0628\u0644\u0627\u0649"
    ],
    "name:ast_x_preferred":[
        "Cuadonga"
    ],
    "name:bre_x_preferred":[
        "Cuadonga"
    ],
    "name:cat_x_preferred":[
        "Cuadonga"
    ],
    "name:dan_x_preferred":[
        "Covadonga"
    ],
    "name:deu_x_preferred":[
        "Covadonga"
    ],
    "name:eus_x_preferred":[
        "Covadonga"
    ],
    "name:fra_x_preferred":[
        "Covadonga"
    ],
    "name:glg_x_preferred":[
        "Covadonga"
    ],
    "name:heb_x_preferred":[
        "\u05e7\u05d5\u05d1\u05d0\u05d3\u05d5\u05e0\u05d2\u05d4"
    ],
    "name:hun_x_preferred":[
        "Covadonga"
    ],
    "name:hye_x_preferred":[
        "\u053f\u0578\u057e\u0561\u0564\u0578\u0576\u0563\u0561"
    ],
    "name:ita_x_preferred":[
        "Covadonga"
    ],
    "name:jpn_x_preferred":[
        "\u30b3\u30d0\u30c9\u30f3\u30ac"
    ],
    "name:nld_x_preferred":[
        "Covadonga"
    ],
    "name:pol_x_preferred":[
        "Covadonga"
    ],
    "name:por_x_preferred":[
        "Covadonga"
    ],
    "name:rus_x_preferred":[
        "\u041a\u043e\u0432\u0430\u0434\u043e\u043d\u0433\u0430"
    ],
    "name:spa_x_preferred":[
        "Covadonga"
    ],
    "name:ukr_x_preferred":[
        "\u041a\u043e\u0432\u0430\u0434\u043e\u043d\u0433\u0430"
    ],
    "name:und_x_variant":[
        "Cobadonga",
        "Covadonga"
    ],
    "wof:name":"Covadonga",
    "wof:placetype":"locality"
},
  "geometry": {"coordinates":[-69.17339,18.67277],"type":"Point"}
}