{
  "type": "Feature",
  "properties": {
    "gn:admin1_code":"28.0",
    "gn:admin2_code":"801.0",
    "gn:admin3_code":"80101.0",
    "gn:admin4_code":"8010108.0",
    "gn:asciiname":"Covadonga",
    "gn:country_code":"DO",
    "gn:dem":47,
    "gn:feature_class":"P",
    "gn:feature_code":"PPL",
    "gn:name":"Covadonga",
    "gn:population":0,
    "gn:timezone":"America/Santo_Domingo",
    "iso:country":"DO",
    "name:und_x_variant":[
        "Cobadonga",
        "Covadonga"
    ],
    "wof:name":"Covadonga",
    "wof:placetype":"locality"
},
  "geometry": {"coordinates":[-69.17339,18.67277],"type":"Point"}
}