{
  "type": "Feature",
  "properties": {
    "gn:admin1_code":"29.0",
    "gn:admin2_code":"3001.0",
    "gn:admin3_code":"300103.0",
    "gn:admin4_code":"30010303.0",
    "gn:asciiname":"Los Jobos",
    "gn:country_code":"DO",
    "gn:dem":72,
    "gn:feature_class":"P",
    "gn:feature_code":"PPL",
    "gn:name":"Los Jobos",
    "gn:population":0,
    "gn:timezone":"America/Santo_Domingo",
    "iso:country":"DO",
    "wof:name":"Los Jobos",
    "wof:placetype":"locality"
},
  "geometry": {"coordinates":[-69.3289,18.70749],"type":"Point"}
}