{
  "type": "Feature",
  "properties": {
    "gn:admin1_code":"32.0",
    "gn:admin2_code":"2901.0",
    "gn:admin3_code":"290101.0",
    "gn:admin4_code":"29010102.0",
    "gn:asciiname":"El Dean",
    "gn:country_code":"DO",
    "gn:dem":76,
    "gn:feature_class":"P",
    "gn:feature_code":"PPL",
    "gn:name":"El Dean",
    "gn:population":0,
    "gn:timezone":"America/Santo_Domingo",
    "iso:country":"DO",
    "name:und_x_variant":[
        "El De\u00e1n Arriba",
        "El Dean"
    ],
    "wof:name":"El Dean",
    "wof:placetype":"locality"
},
  "geometry": {"coordinates":[-69.89017,18.84352],"type":"Point"}
}