{
  "type": "Feature",
  "properties": {
    "gn:admin1_code":"10.0",
    "gn:admin2_code":"1101.0",
    "gn:admin3_code":"110101.0",
    "gn:admin4_code":"11010105.0",
    "gn:asciiname":"Damajagua",
    "gn:country_code":"DO",
    "gn:dem":251,
    "gn:feature_class":"P",
    "gn:feature_code":"PPL",
    "gn:name":"Damajagua",
    "gn:population":0,
    "gn:timezone":"America/Santo_Domingo",
    "iso:country":"DO",
    "name:und_x_variant":[
        "La Majagua",
        "Damajuana",
        "Damajagua"
    ],
    "wof:name":"Damajagua",
    "wof:placetype":"locality"
},
  "geometry": {"coordinates":[-68.69821,18.69832],"type":"Point"}
}