{
  "type": "Feature",
  "properties": {
    "gn:admin1_code":"30.0",
    "gn:admin2_code":"1302.0",
    "gn:admin3_code":"130202.0",
    "gn:admin4_code":"13020206.0",
    "gn:asciiname":"Los Sanchez",
    "gn:country_code":"DO",
    "gn:dem":1245,
    "gn:feature_class":"P",
    "gn:feature_code":"PPL",
    "gn:name":"Los S\u00e1nchez",
    "gn:population":0,
    "gn:timezone":"America/Santo_Domingo",
    "iso:country":"DO",
    "wof:name":"Los Sanchez",
    "wof:placetype":"locality"
},
  "geometry": {"coordinates":[-70.64861999999999,18.96075],"type":"Point"}
}