{
  "type": "Feature",
  "properties": {
    "gn:admin1_code":"27.0",
    "gn:admin2_code":"2703.0",
    "gn:admin3_code":"270303.0",
    "gn:admin4_code":"27030302.0",
    "gn:asciiname":"Pozo Prieto",
    "gn:country_code":"DO",
    "gn:dem":224,
    "gn:feature_class":"P",
    "gn:feature_code":"PPL",
    "gn:name":"Pozo Prieto",
    "gn:population":0,
    "gn:timezone":"America/Santo_Domingo",
    "iso:country":"DO",
    "wof:name":"Pozo Prieto",
    "wof:placetype":"locality"
},
  "geometry": {"coordinates":[-71.14400999999999,19.72307],"type":"Point"}
}