{
  "type": "Feature",
  "properties": {
    "gn:admin1_code":"30.0",
    "gn:admin2_code":"1301.0",
    "gn:admin3_code":"130101.0",
    "gn:admin4_code":"13010103.0",
    "gn:asciiname":"Barranca",
    "gn:country_code":"DO",
    "gn:dem":86,
    "gn:feature_class":"P",
    "gn:feature_code":"PPL",
    "gn:name":"Barranca",
    "gn:population":0,
    "gn:timezone":"America/Santo_Domingo",
    "iso:country":"DO",
    "name:bre_x_preferred":[
        "Barranca"
    ],
    "name:ceb_x_preferred":[
        "Barranca"
    ],
    "name:deu_x_preferred":[
        "Barranca"
    ],
    "name:fra_x_preferred":[
        "Barranca"
    ],
    "name:nld_x_preferred":[
        "Barranca"
    ],
    "name:por_x_preferred":[
        "Barranca"
    ],
    "name:rus_x_preferred":[
        "\u0411\u0430\u0440\u0440\u0430\u043d\u043a\u0430"
    ],
    "name:spa_x_preferred":[
        "Barranca"
    ],
    "name:swe_x_preferred":[
        "Barranca"
    ],
    "wof:name":"Barranca",
    "wof:placetype":"locality"
},
  "geometry": {"coordinates":[-70.45396,19.26449],"type":"Point"}
}