{
  "type": "Feature",
  "properties": {
    "gn:admin1_code":"21.0",
    "gn:admin2_code":"2401.0",
    "gn:admin3_code":"240101.0",
    "gn:admin4_code":"24010102.0",
    "gn:asciiname":"La Hondonada",
    "gn:country_code":"DO",
    "gn:dem":121,
    "gn:feature_class":"P",
    "gn:feature_code":"PPL",
    "gn:name":"La Hondonada",
    "gn:population":0,
    "gn:timezone":"America/Santo_Domingo",
    "iso:country":"DO",
    "name:urd_x_preferred":[
        "\u0644\u0627 \u06c1\u0648\u0646\u062f\u0648\u0646\u0627\u0688\u0627"
    ],
    "wof:name":"La Hondonada",
    "wof:placetype":"locality"
},
  "geometry": {"coordinates":[-70.05329,18.93997],"type":"Point"}
}