{
  "type": "Feature",
  "properties": {
    "gn:admin1_code":"10.0",
    "gn:admin2_code":"1102.0",
    "gn:admin3_code":"110201.0",
    "gn:admin4_code":"11020104.0",
    "gn:asciiname":"Batey Cuatrocientos y Doce",
    "gn:country_code":"DO",
    "gn:dem":61,
    "gn:feature_class":"P",
    "gn:feature_code":"PPL",
    "gn:name":"Batey Cuatrocientos y Doce",
    "gn:population":0,
    "gn:timezone":"America/Santo_Domingo",
    "iso:country":"DO",
    "name:und_x_variant":[
        "Batey 412",
        "Batey Cuatrocientos y Doce"
    ],
    "wof:name":"Batey Cuatrocientos y Doce",
    "wof:placetype":"locality"
},
  "geometry": {"coordinates":[-68.73026999999999,18.48895],"type":"Point"}
}