{
  "type": "Feature",
  "properties": {
    "gn:admin1_code":"2.0",
    "gn:admin2_code":"302.0",
    "gn:admin3_code":"30202.0",
    "gn:admin4_code":"3020202.0",
    "gn:asciiname":"La Playa",
    "gn:country_code":"DO",
    "gn:dem":5,
    "gn:feature_class":"P",
    "gn:feature_code":"PPL",
    "gn:name":"La Playa",
    "gn:population":0,
    "gn:timezone":"America/Santo_Domingo",
    "iso:country":"DO",
    "wof:name":"La Playa",
    "wof:placetype":"locality"
},
  "geometry": {"coordinates":[-71.34766999999999,18.47826],"type":"Point"}
}