{
  "type": "Feature",
  "properties": {
    "gn:admin1_code":"2.0",
    "gn:admin2_code":"303.0",
    "gn:admin3_code":"30304.0",
    "gn:admin4_code":"3030402.0",
    "gn:asciiname":"La Cabria",
    "gn:country_code":"DO",
    "gn:dem":27,
    "gn:feature_class":"P",
    "gn:feature_code":"PPL",
    "gn:name":"La Cabria",
    "gn:population":0,
    "gn:timezone":"America/Santo_Domingo",
    "iso:country":"DO",
    "wof:name":"La Cabria",
    "wof:placetype":"locality"
},
  "geometry": {"coordinates":[-71.21734000000002,18.41189],"type":"Point"}
}