{
  "type": "Feature",
  "properties": {
    "gn:admin1_code":"10.0",
    "gn:admin2_code":"1101.0",
    "gn:admin3_code":"110101.0",
    "gn:admin4_code":"11010104.0",
    "gn:asciiname":"Batey San German",
    "gn:country_code":"DO",
    "gn:dem":65,
    "gn:feature_class":"P",
    "gn:feature_code":"PPL",
    "gn:name":"Batey San Germ\u00e1n",
    "gn:population":0,
    "gn:timezone":"America/Santo_Domingo",
    "iso:country":"DO",
    "name:und_x_variant":[
        "San Germ\u00e1n",
        "Batey San Germ\u00e1n"
    ],
    "wof:name":"Batey San German",
    "wof:placetype":"locality"
},
  "geometry": {"coordinates":[-68.62875,18.57484],"type":"Point"}
}