{
  "type": "Feature",
  "properties": {
    "gn:admin1_code":"11.0",
    "gn:admin2_code":"704.0",
    "gn:admin3_code":"70401.0",
    "gn:admin4_code":"7040103.0",
    "gn:asciiname":"Martincito",
    "gn:country_code":"DO",
    "gn:dem":1062,
    "gn:feature_class":"P",
    "gn:feature_code":"PPL",
    "gn:name":"Martincito",
    "gn:population":0,
    "gn:timezone":"America/Santo_Domingo",
    "iso:country":"DO",
    "wof:name":"Martincito",
    "wof:placetype":"locality"
},
  "geometry": {"coordinates":[-71.71723,18.71003],"type":"Point"}
}