{
  "type": "Feature",
  "properties": {
    "gn:admin1_code":"18.0",
    "gn:admin2_code":"1805.0",
    "gn:admin3_code":"180502.0",
    "gn:admin4_code":"18050202.0",
    "gn:asciiname":"Las Alforjas",
    "gn:country_code":"DO",
    "gn:dem":617,
    "gn:feature_class":"P",
    "gn:feature_code":"PPL",
    "gn:name":"Las Alforjas",
    "gn:population":0,
    "gn:timezone":"America/Santo_Domingo",
    "iso:country":"DO",
    "wof:name":"Las Alforjas",
    "wof:placetype":"locality"
},
  "geometry": {"coordinates":[-70.97575000000001,19.70589],"type":"Point"}
}