{
  "type": "Feature",
  "properties": {
    "gn:admin1_code":"1.0",
    "gn:admin2_code":"210.0",
    "gn:admin3_code":"21001.0",
    "gn:admin4_code":"2100110.0",
    "gn:asciiname":"Los Llanos de los Naranjitos",
    "gn:country_code":"DO",
    "gn:dem":1078,
    "gn:feature_class":"P",
    "gn:feature_code":"PPL",
    "gn:name":"Los Llanos de los Naranjitos",
    "gn:population":0,
    "gn:timezone":"America/Santo_Domingo",
    "iso:country":"DO",
    "wof:name":"Los Llanos de los Naranjitos",
    "wof:placetype":"locality"
},
  "geometry": {"coordinates":[-70.66526999999998,18.53473],"type":"Point"}
}