{
  "type": "Feature",
  "properties": {
    "gn:admin1_code":"1.0",
    "gn:admin2_code":"210.0",
    "gn:admin3_code":"21001.0",
    "gn:admin4_code":"2100111.0",
    "gn:asciiname":"Los Quemados",
    "gn:country_code":"DO",
    "gn:dem":669,
    "gn:feature_class":"P",
    "gn:feature_code":"PPL",
    "gn:name":"Los Quemados",
    "gn:population":0,
    "gn:timezone":"America/Santo_Domingo",
    "iso:country":"DO",
    "wof:name":"Los Quemados",
    "wof:placetype":"locality"
},
  "geometry": {"coordinates":[-70.59423000000002,18.51291],"type":"Point"}
}