{
  "type": "Feature",
  "properties": {
    "gn:admin1_code":"25.0",
    "gn:asciiname":"Nava",
    "gn:cc2":"DO",
    "gn:country_code":"DO",
    "gn:dem":154,
    "gn:feature_class":"P",
    "gn:feature_code":"PPL",
    "gn:name":"Nava",
    "gn:population":0,
    "gn:timezone":"America/Santo_Domingo",
    "iso:country":"DO",
    "name:und_x_variant":[
        "Nova",
        "Navas",
        "Nava"
    ],
    "wof:name":"Nava",
    "wof:placetype":"locality"
},
  "geometry": {"coordinates":[-70.98333000000002,19.46667],"type":"Point"}
}