{
  "type": "Feature",
  "properties": {
    "gn:admin1_code":"35.0",
    "gn:admin2_code":"1701.0",
    "gn:admin3_code":"170101.0",
    "gn:admin4_code":"17010101.0",
    "gn:asciiname":"El Anil",
    "gn:cc2":"DO",
    "gn:country_code":"DO",
    "gn:dem":52,
    "gn:feature_class":"P",
    "gn:feature_code":"PPL",
    "gn:name":"El A\u00f1il",
    "gn:population":0,
    "gn:timezone":"America/Santo_Domingo",
    "iso:country":"DO",
    "name:und_x_variant":[
        "El A\u00f1i",
        "El A\u00f1il"
    ],
    "wof:name":"El Anil",
    "wof:placetype":"locality"
},
  "geometry": {"coordinates":[-70.33333,18.26667],"type":"Point"}
}