{
  "type": "Feature",
  "properties": {
    "gn:admin1_code":"10.0",
    "gn:admin2_code":"1102.0",
    "gn:admin3_code":"110201.0",
    "gn:admin4_code":"11020103.0",
    "gn:asciiname":"Marota",
    "gn:country_code":"DO",
    "gn:dem":56,
    "gn:feature_class":"P",
    "gn:feature_code":"PPL",
    "gn:name":"Marota",
    "gn:population":0,
    "gn:timezone":"America/Santo_Domingo",
    "iso:country":"DO",
    "wof:name":"Marota",
    "wof:placetype":"locality"
},
  "geometry": {"coordinates":[-68.78333000000001,18.41667],"type":"Point"}
}