{
  "type": "Feature",
  "properties": {
    "gn:admin1_code":"25.0",
    "gn:admin2_code":"2501.0",
    "gn:admin3_code":"250101.0",
    "gn:admin4_code":"25010101.0",
    "gn:asciiname":"Hoya del Caimito",
    "gn:country_code":"DO",
    "gn:dem":200,
    "gn:feature_class":"P",
    "gn:feature_code":"PPL",
    "gn:name":"Hoya del Caimito",
    "gn:population":0,
    "gn:timezone":"America/Santo_Domingo",
    "iso:country":"DO",
    "name:und_x_variant":[
        "Hoyo del Caimito",
        "Hoya del Caimito"
    ],
    "wof:name":"Hoya del Caimito",
    "wof:placetype":"locality"
},
  "geometry": {"coordinates":[-70.66965999999999,19.45287],"type":"Point"}
}