{
  "type": "Feature",
  "properties": {
    "gn:admin1_code":"25.0",
    "gn:admin2_code":"2508.0",
    "gn:admin3_code":"250802.0",
    "gn:admin4_code":"25080202.0",
    "gn:asciiname":"Los Ciruelos",
    "gn:country_code":"DO",
    "gn:dem":315,
    "gn:feature_class":"P",
    "gn:feature_code":"PPL",
    "gn:name":"Los Ciruelos",
    "gn:population":0,
    "gn:timezone":"America/Santo_Domingo",
    "iso:country":"DO",
    "name:und_x_variant":[
        "Ciruelos",
        "Los Ciruelos"
    ],
    "wof:name":"Los Ciruelos",
    "wof:placetype":"locality"
},
  "geometry": {"coordinates":[-70.67988000000003,19.37026],"type":"Point"}
}