{
  "type": "Feature",
  "properties": {
    "gn:admin1_code":"6.0",
    "gn:admin2_code":"604.0",
    "gn:admin3_code":"60401.0",
    "gn:admin4_code":"6040105.0",
    "gn:asciiname":"Alto del Caimito",
    "gn:country_code":"DO",
    "gn:dem":183,
    "gn:feature_class":"P",
    "gn:feature_code":"PPL",
    "gn:name":"Alto del Caimito",
    "gn:population":0,
    "gn:timezone":"America/Santo_Domingo",
    "iso:country":"DO",
    "wof:name":"Alto del Caimito",
    "wof:placetype":"locality"
},
  "geometry": {"coordinates":[-70.10663000000001,19.27644],"type":"Point"}
}