{
  "type": "Feature",
  "properties": {
    "gn:admin1_code":"18.0",
    "gn:admin2_code":"1808.0",
    "gn:admin3_code":"180804.0",
    "gn:admin4_code":"18080402.0",
    "gn:asciiname":"La Loma",
    "gn:country_code":"DO",
    "gn:dem":595,
    "gn:feature_class":"P",
    "gn:feature_code":"PPL",
    "gn:name":"La Loma",
    "gn:population":0,
    "gn:timezone":"America/Santo_Domingo",
    "iso:country":"DO",
    "wof:name":"La Loma",
    "wof:placetype":"locality"
},
  "geometry": {"coordinates":[-71.08722,19.74375],"type":"Point"}
}