{
  "type": "Feature",
  "properties": {
    "gn:admin1_code":"32.0",
    "gn:admin2_code":"2903.0",
    "gn:admin3_code":"290301.0",
    "gn:admin4_code":"29030104.0",
    "gn:asciiname":"Palmar Viejo",
    "gn:country_code":"DO",
    "gn:dem":206,
    "gn:feature_class":"P",
    "gn:feature_code":"PPL",
    "gn:name":"Palmar Viejo",
    "gn:population":0,
    "gn:timezone":"America/Santo_Domingo",
    "iso:country":"DO",
    "wof:name":"Palmar Viejo",
    "wof:placetype":"locality"
},
  "geometry": {"coordinates":[-69.89178000000001,19.03829],"type":"Point"}
}