{
  "type": "Feature",
  "properties": {
    "gn:admin1_code":"24.0",
    "gn:admin2_code":"2302.0",
    "gn:admin3_code":"230202.0",
    "gn:admin4_code":"23020202.0",
    "gn:asciiname":"Contreras",
    "gn:country_code":"DO",
    "gn:dem":41,
    "gn:feature_class":"P",
    "gn:feature_code":"PPL",
    "gn:name":"Contreras",
    "gn:population":0,
    "gn:timezone":"America/Santo_Domingo",
    "iso:country":"DO",
    "name:cat_x_preferred":[
        "Contreras"
    ],
    "name:ceb_x_preferred":[
        "Contreras"
    ],
    "name:deu_x_preferred":[
        "Contreras"
    ],
    "name:fra_x_preferred":[
        "Contreras"
    ],
    "name:glg_x_preferred":[
        "Contreras"
    ],
    "name:nld_x_preferred":[
        "Contreras"
    ],
    "name:rus_x_preferred":[
        "\u041a\u043e\u043d\u0442\u0440\u0435\u0440\u0430\u0441"
    ],
    "name:spa_x_preferred":[
        "Contreras"
    ],
    "name:swe_x_preferred":[
        "Contreras"
    ],
    "name:ukr_x_preferred":[
        "\u041a\u043e\u043d\u0442\u0440\u0435\u0440\u0430\u0441"
    ],
    "name:und_x_variant":[
        "Contrera"
    ],
    "wof:name":"Contreras",
    "wof:placetype":"locality"
},
  "geometry": {"coordinates":[-69.45451,18.70413],"type":"Point"}
}