{
  "type": "Feature",
  "properties": {
    "gn:admin1_code":"24.0",
    "gn:admin2_code":"2302.0",
    "gn:admin3_code":"230202.0",
    "gn:admin4_code":"23020202.0",
    "gn:asciiname":"Contreras",
    "gn:country_code":"DO",
    "gn:dem":41,
    "gn:feature_class":"P",
    "gn:feature_code":"PPL",
    "gn:name":"Contreras",
    "gn:population":0,
    "gn:timezone":"America/Santo_Domingo",
    "iso:country":"DO",
    "name:und_x_variant":[
        "Contrera",
        "Contreras"
    ],
    "wof:name":"Contreras",
    "wof:placetype":"locality"
},
  "geometry": {"coordinates":[-69.45451,18.70413],"type":"Point"}
}