{
  "type": "Feature",
  "properties": {
    "gn:admin1_code":"3.0",
    "gn:admin2_code":"408.0",
    "gn:admin3_code":"40802.0",
    "gn:admin4_code":"4080202.0",
    "gn:asciiname":"Batey Guayacan",
    "gn:country_code":"DO",
    "gn:dem":11,
    "gn:feature_class":"P",
    "gn:feature_code":"PPL",
    "gn:name":"Batey Guayac\u00e1n",
    "gn:population":0,
    "gn:timezone":"America/Santo_Domingo",
    "iso:country":"DO",
    "name:und_x_variant":[
        "Guayacanes",
        "El Guayac\u00e1n",
        "Batey Guayac\u00e1n"
    ],
    "wof:name":"Batey Guayacan",
    "wof:placetype":"locality"
},
  "geometry": {"coordinates":[-71.15675,18.27818],"type":"Point"}
}