{
  "type": "Feature",
  "properties": {
    "gn:admin1_code":"23.0",
    "gn:admin2_code":"2202.0",
    "gn:admin3_code":"220203.0",
    "gn:admin4_code":"22020305.0",
    "gn:asciiname":"La Guama",
    "gn:country_code":"DO",
    "gn:dem":966,
    "gn:feature_class":"P",
    "gn:feature_code":"PPL",
    "gn:name":"La Guama",
    "gn:population":0,
    "gn:timezone":"America/Santo_Domingo",
    "iso:country":"DO",
    "wof:name":"La Guama",
    "wof:placetype":"locality"
},
  "geometry": {"coordinates":[-71.03333000000001,18.86667000000001],"type":"Point"}
}