{
  "type": "Feature",
  "properties": {
    "gn:admin1_code":"14.0",
    "gn:admin2_code":"1403.0",
    "gn:admin3_code":"140301.0",
    "gn:admin4_code":"14030102.0",
    "gn:asciiname":"Cinta Negra",
    "gn:country_code":"DO",
    "gn:dem":54,
    "gn:feature_class":"P",
    "gn:feature_code":"PPL",
    "gn:name":"Cinta Negra",
    "gn:population":0,
    "gn:timezone":"America/Santo_Domingo",
    "iso:country":"DO",
    "wof:name":"Cinta Negra",
    "wof:placetype":"locality"
},
  "geometry": {"coordinates":[-69.96319,19.28116],"type":"Point"}
}