{
  "type": "Feature",
  "properties": {
    "gn:admin1_code":"32.0",
    "gn:admin2_code":"2903.0",
    "gn:admin3_code":"290302.0",
    "gn:admin4_code":"29030204.0",
    "gn:asciiname":"El Hoyo de Puta",
    "gn:country_code":"DO",
    "gn:dem":265,
    "gn:feature_class":"P",
    "gn:feature_code":"PPL",
    "gn:name":"El Hoyo de Puta",
    "gn:population":0,
    "gn:timezone":"America/Santo_Domingo",
    "iso:country":"DO",
    "wof:name":"El Hoyo de Puta",
    "wof:placetype":"locality"
},
  "geometry": {"coordinates":[-69.76666999999999,18.95],"type":"Point"}
}