{
  "type": "Feature",
  "properties": {
    "gn:admin1_code":"25.0",
    "gn:admin2_code":"2503.0",
    "gn:admin3_code":"250302.0",
    "gn:admin4_code":"25030202.0",
    "gn:asciiname":"Sabaneta",
    "gn:country_code":"DO",
    "gn:dem":1020,
    "gn:feature_class":"P",
    "gn:feature_code":"PPL",
    "gn:name":"Sabaneta",
    "gn:population":0,
    "gn:timezone":"America/Santo_Domingo",
    "iso:country":"DO",
    "name:bar_x_preferred":[
        "Sabaneta"
    ],
    "name:ceb_x_preferred":[
        "Sabaneta"
    ],
    "name:deu_x_preferred":[
        "Sabaneta"
    ],
    "name:fas_x_preferred":[
        "\u0633\u0627\u0628\u0627\u0646\u062a\u0627"
    ],
    "name:fra_x_preferred":[
        "Sabaneta"
    ],
    "name:heb_x_preferred":[
        "\u05e1\u05d1\u05e0\u05d8\u05d4"
    ],
    "name:hun_x_preferred":[
        "Sabaneta"
    ],
    "name:ita_x_preferred":[
        "Sabaneta"
    ],
    "name:nld_x_preferred":[
        "Sabaneta"
    ],
    "name:pol_x_preferred":[
        "Sabaneta"
    ],
    "name:por_x_preferred":[
        "Sabaneta"
    ],
    "name:rus_x_preferred":[
        "\u0421\u0430\u0431\u0430\u043d\u0435\u0442\u0430"
    ],
    "name:sco_x_preferred":[
        "Sabaneta"
    ],
    "name:spa_x_preferred":[
        "Sabaneta"
    ],
    "name:srp_x_preferred":[
        "\u0421\u0430\u0431\u0430\u043d\u0435\u0442\u0430"
    ],
    "name:swe_x_preferred":[
        "Sabaneta"
    ],
    "name:vie_x_preferred":[
        "Sabaneta"
    ],
    "name:zho_x_preferred":[
        "\u8428\u74e6\u5185\u5854"
    ],
    "wof:name":"Sabaneta",
    "wof:placetype":"locality"
},
  "geometry": {"coordinates":[-70.81332,19.17417],"type":"Point"}
}