{
  "type": "Feature",
  "properties": {
    "gn:admin1_code":"10.0",
    "gn:admin2_code":"1101.0",
    "gn:admin3_code":"110104.0",
    "gn:admin4_code":"11010403.0",
    "gn:asciiname":"Canada Honda",
    "gn:country_code":"DO",
    "gn:dem":41,
    "gn:feature_class":"P",
    "gn:feature_code":"PPL",
    "gn:name":"Ca\u00f1ada Honda",
    "gn:population":0,
    "gn:timezone":"America/Santo_Domingo",
    "iso:country":"DO",
    "wof:name":"Canada Honda",
    "wof:placetype":"locality"
},
  "geometry": {"coordinates":[-68.61124000000001,18.71895],"type":"Point"}
}