{
  "type": "Feature",
  "properties": {
    "gn:admin1_code":"33.0",
    "gn:admin2_code":"2104.0",
    "gn:admin3_code":"210401.0",
    "gn:admin4_code":"21040105.0",
    "gn:asciiname":"Valentin",
    "gn:country_code":"DO",
    "gn:dem":986,
    "gn:feature_class":"P",
    "gn:feature_code":"PPL",
    "gn:name":"Valent\u00edn",
    "gn:population":0,
    "gn:timezone":"America/Santo_Domingo",
    "iso:country":"DO",
    "wof:name":"Valentin",
    "wof:placetype":"locality"
},
  "geometry": {"coordinates":[-70.26876999999999,18.47578],"type":"Point"}
}