{
  "type": "Feature",
  "properties": {
    "gn:admin1_code":"33.0",
    "gn:admin2_code":"2104.0",
    "gn:admin3_code":"210401.0",
    "gn:admin4_code":"21040105.0",
    "gn:asciiname":"Valentin",
    "gn:country_code":"DO",
    "gn:dem":986,
    "gn:feature_class":"P",
    "gn:feature_code":"PPL",
    "gn:name":"Valent\u00edn",
    "gn:population":0,
    "gn:timezone":"America/Santo_Domingo",
    "iso:country":"DO",
    "name:bre_x_preferred":[
        "Valentin"
    ],
    "name:ces_x_preferred":[
        "Valent\u00fdn"
    ],
    "name:deu_x_preferred":[
        "Valentin"
    ],
    "name:est_x_preferred":[
        "Valentin"
    ],
    "name:fin_x_preferred":[
        "Valentin"
    ],
    "name:jpn_x_preferred":[
        "\u30f4\u30a1\u30ec\u30f3\u30c6\u30a3\u30f3"
    ],
    "name:nno_x_preferred":[
        "Valentin"
    ],
    "name:nor_x_preferred":[
        "Valentin"
    ],
    "name:ron_x_preferred":[
        "Valentin"
    ],
    "name:rus_x_preferred":[
        "\u0412\u0430\u043b\u0435\u043d\u0442\u0438\u043d"
    ],
    "name:slv_x_preferred":[
        "Valentin"
    ],
    "name:spa_x_preferred":[
        "Valent\u00edn"
    ],
    "name:swe_x_preferred":[
        "Valentin"
    ],
    "name:tha_x_preferred":[
        "\u0e27\u0e32\u0e40\u0e25\u0e19\u0e44\u0e17\u0e19\u0e4c"
    ],
    "name:ukr_x_preferred":[
        "\u0412\u0430\u043b\u0435\u043d\u0442\u0438\u043d"
    ],
    "wof:name":"Valentin",
    "wof:placetype":"locality"
},
  "geometry": {"coordinates":[-70.26876999999999,18.47578],"type":"Point"}
}