{
  "type": "Feature",
  "properties": {
    "gn:admin1_code":"20.0",
    "gn:admin2_code":"2001.0",
    "gn:admin3_code":"200101.0",
    "gn:admin4_code":"20010105.0",
    "gn:asciiname":"Loma La Cruz",
    "gn:country_code":"DO",
    "gn:dem":200,
    "gn:feature_class":"P",
    "gn:feature_code":"PPL",
    "gn:name":"Loma La Cruz",
    "gn:population":0,
    "gn:timezone":"America/Santo_Domingo",
    "iso:country":"DO",
    "wof:name":"Loma La Cruz",
    "wof:placetype":"locality"
},
  "geometry": {"coordinates":[-69.45784999999999,19.27275],"type":"Point"}
}