{
  "type": "Feature",
  "properties": {
    "gn:admin1_code":"24.0",
    "gn:admin2_code":"2303.0",
    "gn:admin3_code":"230301.0",
    "gn:admin4_code":"23030102.0",
    "gn:asciiname":"Buena Vista",
    "gn:country_code":"DO",
    "gn:dem":6,
    "gn:feature_class":"P",
    "gn:feature_code":"PPL",
    "gn:name":"Buena Vista",
    "gn:population":0,
    "gn:timezone":"America/Santo_Domingo",
    "iso:country":"DO",
    "name:und_x_variant":[
        "El Hig\u00fceral",
        "Buena Vista"
    ],
    "wof:name":"Buena Vista",
    "wof:placetype":"locality"
},
  "geometry": {"coordinates":[-69.14153,18.41487],"type":"Point"}
}