{
  "type": "Feature",
  "properties": {
    "gn:admin1_code":"36.0",
    "gn:admin2_code":"3101.0",
    "gn:admin3_code":"310103.0",
    "gn:admin4_code":"31010303.0",
    "gn:asciiname":"Los Macos",
    "gn:country_code":"DO",
    "gn:dem":593,
    "gn:feature_class":"P",
    "gn:feature_code":"PPL",
    "gn:name":"Los Macos",
    "gn:population":0,
    "gn:timezone":"America/Santo_Domingo",
    "iso:country":"DO",
    "wof:name":"Los Macos",
    "wof:placetype":"locality"
},
  "geometry": {"coordinates":[-70.45565000000001,18.63042],"type":"Point"}
}