{
  "type": "Feature",
  "properties": {
    "gn:admin1_code":"4.0",
    "gn:admin2_code":"502.0",
    "gn:admin3_code":"50202.0",
    "gn:admin4_code":"5020203.0",
    "gn:asciiname":"El Junco",
    "gn:country_code":"DO",
    "gn:dem":230,
    "gn:feature_class":"P",
    "gn:feature_code":"PPL",
    "gn:name":"El Junco",
    "gn:population":0,
    "gn:timezone":"America/Santo_Domingo",
    "iso:country":"DO",
    "wof:name":"El Junco",
    "wof:placetype":"locality"
},
  "geometry": {"coordinates":[-71.66265,19.4034],"type":"Point"}
}