{
  "type": "Feature",
  "properties": {
    "gn:admin1_code":"28.0",
    "gn:admin2_code":"801.0",
    "gn:admin3_code":"80101.0",
    "gn:admin4_code":"8010105.0",
    "gn:asciiname":"Limoncillar",
    "gn:country_code":"DO",
    "gn:dem":148,
    "gn:feature_class":"P",
    "gn:feature_code":"PPL",
    "gn:name":"Limoncillar",
    "gn:population":0,
    "gn:timezone":"America/Santo_Domingo",
    "iso:country":"DO",
    "wof:name":"Limoncillar",
    "wof:placetype":"locality"
},
  "geometry": {"coordinates":[-68.96174999999999,18.82694],"type":"Point"}
}