{
  "type": "Feature",
  "properties": {
    "gn:country":"DO",
    "gn:fcode":"PPL",
    "gn:population":5445,
    "iso:country":"DO",
    "name:bul_x_preferred":[
        "\u0415\u0441\u043f\u0435\u0440\u0430\u043b\u0432\u0438\u043b\u043e"
    ],
    "name:ceb_x_preferred":[
        "Esperalvillo"
    ],
    "name:deu_x_preferred":[
        "Peralvillo"
    ],
    "name:eng_x_preferred":[
        "Peralvillo"
    ],
    "name:ita_x_preferred":[
        "Esperalvillo"
    ],
    "name:jpn_x_preferred":[
        "\u30da\u30e9\u30eb\u30d3\u30ea\u30e7"
    ],
    "name:nan_x_preferred":[
        "Peralvillo"
    ],
    "name:nld_x_preferred":[
        "Peralvillo"
    ],
    "name:por_x_preferred":[
        "Peralvillo"
    ],
    "name:spa_x_preferred":[
        "Peralvillo"
    ],
    "name:swe_x_preferred":[
        "Esperalvillo"
    ],
    "name:und_x_variant":[
        "Peraldillo"
    ],
    "name:zho_x_preferred":[
        "\u4f69\u62c9\u723e\u7dad\u7565"
    ],
    "qs:name":"Esperalvillo",
    "qs:photos_9r":0,
    "qs:photos_sr":0,
    "qs:pop_sr":"5",
    "wd:wordcount":86,
    "wof:name":"Esperalvillo",
    "wof:placetype":"locality",
    "wof:population":5445
},
  "geometry": {"coordinates":[-70.03557000000001,18.81509],"type":"Point"}
}