{
  "type": "Feature",
  "properties": {
    "gn:admin1_code":"37.0",
    "gn:admin2_code":"3205.0",
    "gn:admin3_code":"320501.0",
    "gn:admin4_code":"32050105.0",
    "gn:asciiname":"Las Barias",
    "gn:country_code":"DO",
    "gn:dem":22,
    "gn:feature_class":"P",
    "gn:feature_code":"PPL",
    "gn:name":"Las Bar\u00edas",
    "gn:population":0,
    "gn:timezone":"America/Santo_Domingo",
    "iso:country":"DO",
    "wof:name":"Las Barias",
    "wof:placetype":"locality"
},
  "geometry": {"coordinates":[-69.64969000000001,18.60172],"type":"Point"}
}