{
  "type": "Feature",
  "properties": {
    "gn:admin1_code":"33.0",
    "gn:admin2_code":"2101.0",
    "gn:admin3_code":"210101.0",
    "gn:admin4_code":"21010104.0",
    "gn:asciiname":"Niza",
    "gn:country_code":"DO",
    "gn:dem":71,
    "gn:feature_class":"P",
    "gn:feature_code":"PPL",
    "gn:name":"Niza",
    "gn:population":0,
    "gn:timezone":"America/Santo_Domingo",
    "iso:country":"DO",
    "name:ceb_x_preferred":[
        "Niza"
    ],
    "name:swe_x_preferred":[
        "Niza"
    ],
    "wof:name":"Niza",
    "wof:placetype":"locality"
},
  "geometry": {"coordinates":[-70.11881,18.35666],"type":"Point"}
}