{
  "type": "Feature",
  "properties": {
    "gn:admin1_code":"21.0",
    "gn:admin2_code":"2402.0",
    "gn:admin3_code":"240201.0",
    "gn:admin4_code":"24020103.0",
    "gn:asciiname":"Yunita",
    "gn:country_code":"DO",
    "gn:dem":74,
    "gn:feature_class":"P",
    "gn:feature_code":"PPL",
    "gn:name":"Yunita",
    "gn:population":0,
    "gn:timezone":"America/Santo_Domingo",
    "iso:country":"DO",
    "wof:name":"Yunita",
    "wof:placetype":"locality"
},
  "geometry": {"coordinates":[-69.95996,19.07296],"type":"Point"}
}