{
  "type": "Feature",
  "properties": {
    "gn:admin1_code":"25.0",
    "gn:admin2_code":"2505.0",
    "gn:admin3_code":"250502.0",
    "gn:admin4_code":"25050211.0",
    "gn:asciiname":"Corbano",
    "gn:country_code":"DO",
    "gn:dem":320,
    "gn:feature_class":"P",
    "gn:feature_code":"PPL",
    "gn:name":"C\u00f3rbano",
    "gn:population":0,
    "gn:timezone":"America/Santo_Domingo",
    "iso:country":"DO",
    "name:und_x_variant":[
        "El Corbano",
        "C\u00f3rbano"
    ],
    "wof:name":"Corbano",
    "wof:placetype":"locality"
},
  "geometry": {"coordinates":[-71.09949,19.40085],"type":"Point"}
}