{
  "type": "Feature",
  "properties": {
    "gn:admin1_code":"25.0",
    "gn:admin2_code":"2501.0",
    "gn:admin3_code":"250101.0",
    "gn:admin4_code":"25010101.0",
    "gn:asciiname":"Bartola",
    "gn:country_code":"DO",
    "gn:dem":180,
    "gn:feature_class":"P",
    "gn:feature_code":"PPL",
    "gn:name":"Bartola",
    "gn:population":0,
    "gn:timezone":"America/Santo_Domingo",
    "iso:country":"DO",
    "wof:name":"Bartola",
    "wof:placetype":"locality"
},
  "geometry": {"coordinates":[-70.70954,19.47578],"type":"Point"}
}