{
  "type": "Feature",
  "properties": {
    "gn:admin1_code":"9.0",
    "gn:admin2_code":"1002.0",
    "gn:admin3_code":"100201.0",
    "gn:admin4_code":"10020101.0",
    "gn:asciiname":"San Jose",
    "gn:country_code":"DO",
    "gn:dem":4,
    "gn:feature_class":"P",
    "gn:feature_code":"PPL",
    "gn:name":"San Jos\u00e9",
    "gn:population":0,
    "gn:timezone":"America/Santo_Domingo",
    "iso:country":"DO",
    "wof:name":"San Jose",
    "wof:placetype":"locality"
},
  "geometry": {"coordinates":[-71.52965,18.379],"type":"Point"}
}