{
  "type": "Feature",
  "properties": {
    "gn:admin1_code":"23.0",
    "gn:admin2_code":"2204.0",
    "gn:admin3_code":"220401.0",
    "gn:admin4_code":"22040103.0",
    "gn:asciiname":"Los Canos",
    "gn:country_code":"DO",
    "gn:dem":467,
    "gn:feature_class":"P",
    "gn:feature_code":"PPL",
    "gn:name":"Los Ca\u00f1os",
    "gn:population":0,
    "gn:timezone":"America/Santo_Domingo",
    "iso:country":"DO",
    "wof:name":"Los Canos",
    "wof:placetype":"locality"
},
  "geometry": {"coordinates":[-71.23333000000002,18.86667000000001],"type":"Point"}
}