{
  "type": "Feature",
  "properties": {
    "gn:admin1_code":"25.0",
    "gn:admin2_code":"2505.0",
    "gn:admin3_code":"250501.0",
    "gn:admin4_code":"25050102.0",
    "gn:asciiname":"Los Palmaritos",
    "gn:country_code":"DO",
    "gn:dem":341,
    "gn:feature_class":"P",
    "gn:feature_code":"PPL",
    "gn:name":"Los Palmaritos",
    "gn:population":0,
    "gn:timezone":"America/Santo_Domingo",
    "iso:country":"DO",
    "name:und_x_variant":[
        "Palmarito",
        "Los Palmaritos"
    ],
    "wof:name":"Los Palmaritos",
    "wof:placetype":"locality"
},
  "geometry": {"coordinates":[-71.00534,19.40818],"type":"Point"}
}