{
  "type": "Feature",
  "properties": {
    "gn:admin1_code":"23.0",
    "gn:admin2_code":"2205.0",
    "gn:admin3_code":"220502.0",
    "gn:admin4_code":"22050204.0",
    "gn:asciiname":"Cabeza de Vaca",
    "gn:country_code":"DO",
    "gn:dem":446,
    "gn:feature_class":"P",
    "gn:feature_code":"PPL",
    "gn:name":"Cabeza de Vaca",
    "gn:population":0,
    "gn:timezone":"America/Santo_Domingo",
    "iso:country":"DO",
    "wof:name":"Cabeza de Vaca",
    "wof:placetype":"locality"
},
  "geometry": {"coordinates":[-71.55769000000002,18.98931],"type":"Point"}
}