{
  "type": "Feature",
  "properties": {
    "gn:admin1_code":"32.0",
    "gn:admin2_code":"2903.0",
    "gn:admin3_code":"290301.0",
    "gn:admin4_code":"29030102.0",
    "gn:asciiname":"Lovaton",
    "gn:country_code":"DO",
    "gn:dem":370,
    "gn:feature_class":"P",
    "gn:feature_code":"PPL",
    "gn:name":"Lovat\u00f3n",
    "gn:population":0,
    "gn:timezone":"America/Santo_Domingo",
    "iso:country":"DO",
    "wof:name":"Lovaton",
    "wof:placetype":"locality"
},
  "geometry": {"coordinates":[-69.83674999999999,18.87376],"type":"Point"}
}