{
  "type": "Feature",
  "properties": {
    "gn:admin1_code":"6.0",
    "gn:admin2_code":"604.0",
    "gn:admin3_code":"60401.0",
    "gn:admin4_code":"6040102.0",
    "gn:asciiname":"Guanabano",
    "gn:country_code":"DO",
    "gn:dem":95,
    "gn:feature_class":"P",
    "gn:feature_code":"PPL",
    "gn:name":"Guan\u00e1bano",
    "gn:population":0,
    "gn:timezone":"America/Santo_Domingo",
    "iso:country":"DO",
    "wof:name":"Guanabano",
    "wof:placetype":"locality"
},
  "geometry": {"coordinates":[-70.11749,19.25322],"type":"Point"}
}