{
  "type": "Feature",
  "properties": {
    "gn:admin1_code":"33.0",
    "gn:admin2_code":"2101.0",
    "gn:admin3_code":"210101.0",
    "gn:admin4_code":"21010108.0",
    "gn:asciiname":"La Fundacion",
    "gn:country_code":"DO",
    "gn:dem":132,
    "gn:feature_class":"P",
    "gn:feature_code":"PPL",
    "gn:name":"La Fundaci\u00f3n",
    "gn:population":0,
    "gn:timezone":"America/Santo_Domingo",
    "iso:country":"DO",
    "name:und_x_variant":[
        "Fundaci\u00f3n",
        "La Fundaci\u00f3n"
    ],
    "wof:name":"La Fundacion",
    "wof:placetype":"locality"
},
  "geometry": {"coordinates":[-70.15869000000001,18.41697000000001],"type":"Point"}
}