{
  "type": "Feature",
  "properties": {
    "gn:admin1_code":"21.0",
    "gn:admin2_code":"2401.0",
    "gn:admin3_code":"240101.0",
    "gn:admin4_code":"24010104.0",
    "gn:asciiname":"La Quebradita",
    "gn:country_code":"DO",
    "gn:dem":237,
    "gn:feature_class":"P",
    "gn:feature_code":"PPL",
    "gn:name":"La Quebradita",
    "gn:population":0,
    "gn:timezone":"America/Santo_Domingo",
    "iso:country":"DO",
    "name:und_x_variant":[
        "Quebradita",
        "La Quebradilla",
        "La Quebradita"
    ],
    "wof:name":"La Quebradita",
    "wof:placetype":"locality"
},
  "geometry": {"coordinates":[-70.20994,18.87933],"type":"Point"}
}