{
  "type": "Feature",
  "properties": {
    "gn:admin1_code":"30.0",
    "gn:admin2_code":"1303.0",
    "gn:admin3_code":"130301.0",
    "gn:admin4_code":"13030106.0",
    "gn:asciiname":"El Llano de Jumunuco",
    "gn:country_code":"DO",
    "gn:dem":815,
    "gn:feature_class":"P",
    "gn:feature_code":"PPL",
    "gn:name":"El Llano de Jumunuco",
    "gn:population":0,
    "gn:timezone":"America/Santo_Domingo",
    "iso:country":"DO",
    "name:und_x_variant":[
        "Llano de Jumunuco",
        "El Llano de Jumunuco"
    ],
    "wof:name":"El Llano de Jumunuco",
    "wof:placetype":"locality"
},
  "geometry": {"coordinates":[-70.73924,19.12509],"type":"Point"}
}