{
  "type": "Feature",
  "properties": {
    "gn:admin1_code":"26.0",
    "gn:admin2_code":"2603.0",
    "gn:admin3_code":"260301.0",
    "gn:admin4_code":"26030103.0",
    "gn:asciiname":"Gurabo",
    "gn:country_code":"DO",
    "gn:dem":327,
    "gn:feature_class":"P",
    "gn:feature_code":"PPL",
    "gn:name":"Gurabo",
    "gn:population":0,
    "gn:timezone":"America/Santo_Domingo",
    "iso:country":"DO",
    "name:ceb_x_preferred":[
        "Gurabo"
    ],
    "name:ita_x_preferred":[
        "Gurabo"
    ],
    "name:nld_x_preferred":[
        "Gurabo"
    ],
    "name:pol_x_preferred":[
        "Gurabo"
    ],
    "name:spa_x_preferred":[
        "Gurabo"
    ],
    "wof:name":"Gurabo",
    "wof:placetype":"locality"
},
  "geometry": {"coordinates":[-71.19403,19.41954],"type":"Point"}
}