{
  "type": "Feature",
  "properties": {
    "gn:admin1_code":"32.0",
    "gn:admin2_code":"2905.0",
    "gn:admin3_code":"290501.0",
    "gn:admin4_code":"29050104.0",
    "gn:asciiname":"La Jagueita",
    "gn:country_code":"DO",
    "gn:dem":224,
    "gn:feature_class":"P",
    "gn:feature_code":"PPL",
    "gn:name":"La Jag\u00fcita",
    "gn:population":0,
    "gn:timezone":"America/Santo_Domingo",
    "iso:country":"DO",
    "name:und_x_variant":[
        "Jag\u00fcita",
        "La Jag\u00fcita"
    ],
    "wof:name":"La Jagueita",
    "wof:placetype":"locality"
},
  "geometry": {"coordinates":[-70.05131,18.86082],"type":"Point"}
}