{
  "type": "Feature",
  "properties": {
    "gn:admin1_code":"6.0",
    "gn:admin2_code":"607.0",
    "gn:admin3_code":"60702.0",
    "gn:admin4_code":"6070202.0",
    "gn:asciiname":"Balsa",
    "gn:country_code":"DO",
    "gn:dem":27,
    "gn:feature_class":"P",
    "gn:feature_code":"PPL",
    "gn:name":"Balsa",
    "gn:population":0,
    "gn:timezone":"America/Santo_Domingo",
    "iso:country":"DO",
    "wof:name":"Balsa",
    "wof:placetype":"locality"
},
  "geometry": {"coordinates":[-70.01666999999999,19.15],"type":"Point"}
}