{
  "type": "Feature",
  "properties": {
    "gn:admin1_code":"24.0",
    "gn:admin2_code":"2306.0",
    "gn:admin3_code":"230601.0",
    "gn:admin4_code":"23060103.0",
    "gn:asciiname":"Batey Numero Dos",
    "gn:country_code":"DO",
    "gn:dem":26,
    "gn:feature_class":"P",
    "gn:feature_code":"PPL",
    "gn:name":"Batey N\u00famero Dos",
    "gn:population":0,
    "gn:timezone":"America/Santo_Domingo",
    "iso:country":"DO",
    "name:und_x_variant":[
        "Batey N\u00famero 2",
        "Batey 2",
        "Batey Dos",
        "Batey N\u00famero Dos"
    ],
    "wof:name":"Batey Numero Dos",
    "wof:placetype":"locality"
},
  "geometry": {"coordinates":[-69.35751999999999,18.48751],"type":"Point"}
}