{
  "type": "Feature",
  "properties": {
    "gn:admin1_code":"27.0",
    "gn:admin2_code":"2702.0",
    "gn:admin3_code":"270202.0",
    "gn:admin4_code":"27020205.0",
    "gn:asciiname":"El Llano",
    "gn:country_code":"DO",
    "gn:dem":706,
    "gn:feature_class":"P",
    "gn:feature_code":"PPL",
    "gn:name":"El Llano",
    "gn:population":0,
    "gn:timezone":"America/Santo_Domingo",
    "iso:country":"DO",
    "wof:name":"El Llano",
    "wof:placetype":"locality"
},
  "geometry": {"coordinates":[-70.95971999999998,19.67339],"type":"Point"}
}