{
  "type": "Feature",
  "properties": {
    "gn:admin1_code":"1.0",
    "gn:admin2_code":"201.0",
    "gn:admin3_code":"20108.0",
    "gn:admin4_code":"2010801.0",
    "gn:asciiname":"Clavellina",
    "gn:country_code":"DO",
    "gn:dem":41,
    "gn:feature_class":"P",
    "gn:feature_code":"PPL",
    "gn:name":"Clavellina",
    "gn:population":0,
    "gn:timezone":"America/Santo_Domingo",
    "iso:country":"DO",
    "name:und_x_variant":[
        "Las Clavellinas",
        "Clavellina"
    ],
    "wof:name":"Clavellina",
    "wof:placetype":"locality"
},
  "geometry": {"coordinates":[-70.74864000000002,18.43272],"type":"Point"}
}