{
  "type": "Feature",
  "properties": {
    "gn:admin1_code":"23.0",
    "gn:admin2_code":"2201.0",
    "gn:admin3_code":"220109.0",
    "gn:admin4_code":"22010905.0",
    "gn:asciiname":"Hato Nuevo",
    "gn:country_code":"DO",
    "gn:dem":567,
    "gn:feature_class":"P",
    "gn:feature_code":"PPL",
    "gn:name":"Hato Nuevo",
    "gn:population":0,
    "gn:timezone":"America/Santo_Domingo",
    "iso:country":"DO",
    "wof:name":"Hato Nuevo",
    "wof:placetype":"locality"
},
  "geometry": {"coordinates":[-71.27701,18.94541],"type":"Point"}
}