{
  "type": "Feature",
  "properties": {
    "gn:admin1_code":"25.0",
    "gn:admin2_code":"2501.0",
    "gn:admin3_code":"250106.0",
    "gn:admin4_code":"25010601.0",
    "gn:asciiname":"San Francisco Abajo",
    "gn:country_code":"DO",
    "gn:dem":225,
    "gn:feature_class":"P",
    "gn:feature_code":"PPL",
    "gn:name":"San Francisco Abajo",
    "gn:population":0,
    "gn:timezone":"America/Santo_Domingo",
    "iso:country":"DO",
    "wof:name":"San Francisco Abajo",
    "wof:placetype":"locality"
},
  "geometry": {"coordinates":[-70.70744000000001,19.52484],"type":"Point"}
}