{
  "type": "Feature",
  "properties": {
    "gn:admin1_code":"31.0",
    "gn:admin2_code":"2802.0",
    "gn:admin3_code":"280201.0",
    "gn:admin4_code":"28020102.0",
    "gn:asciiname":"La Travesia",
    "gn:country_code":"DO",
    "gn:dem":106,
    "gn:feature_class":"P",
    "gn:feature_code":"PPL",
    "gn:name":"La Traves\u00eda",
    "gn:population":0,
    "gn:timezone":"America/Santo_Domingo",
    "iso:country":"DO",
    "wof:name":"La Travesia",
    "wof:placetype":"locality"
},
  "geometry": {"coordinates":[-70.26338,18.91667],"type":"Point"}
}