{
  "type": "Feature",
  "properties": {
    "gn:admin1_code":"25.0",
    "gn:admin2_code":"2501.0",
    "gn:admin3_code":"250105.0",
    "gn:admin4_code":"25010502.0",
    "gn:asciiname":"Los Cerritos",
    "gn:country_code":"DO",
    "gn:dem":107,
    "gn:feature_class":"P",
    "gn:feature_code":"PPL",
    "gn:name":"Los Cerritos",
    "gn:population":0,
    "gn:timezone":"America/Santo_Domingo",
    "iso:country":"DO",
    "wof:name":"Los Cerritos",
    "wof:placetype":"locality"
},
  "geometry": {"coordinates":[-70.82118,19.5068],"type":"Point"}
}