{
  "type": "Feature",
  "properties": {
    "gn:admin1_code":"3.0",
    "gn:admin2_code":"405.0",
    "gn:admin3_code":"40501.0",
    "gn:admin4_code":"4050101.0",
    "gn:asciiname":"El Erizal",
    "gn:country_code":"DO",
    "gn:dem":41,
    "gn:feature_class":"P",
    "gn:feature_code":"PPL",
    "gn:name":"El Erizal",
    "gn:population":0,
    "gn:timezone":"America/Santo_Domingo",
    "iso:country":"DO",
    "name:und_x_variant":[
        "El Herisal",
        "El Erizal"
    ],
    "wof:name":"El Erizal",
    "wof:placetype":"locality"
},
  "geometry": {"coordinates":[-71.17797,18.39587],"type":"Point"}
}