{
  "type": "Feature",
  "properties": {
    "gn:admin1_code":"12.0",
    "gn:admin2_code":"1202.0",
    "gn:admin3_code":"120201.0",
    "gn:admin4_code":"12020102.0",
    "gn:asciiname":"Batey Numero Ochenta y Dos",
    "gn:country_code":"DO",
    "gn:dem":76,
    "gn:feature_class":"P",
    "gn:feature_code":"PPL",
    "gn:name":"Batey N\u00famero Ochenta y Dos",
    "gn:population":0,
    "gn:timezone":"America/Santo_Domingo",
    "iso:country":"DO",
    "name:und_x_variant":[
        "Batey N\u00famero 82",
        "Batey El-82",
        "Batey N\u00famero Ochenta y Dos"
    ],
    "wof:name":"Batey Numero Ochenta y Dos",
    "wof:placetype":"locality"
},
  "geometry": {"coordinates":[-69.01398,18.53818],"type":"Point"}
}