{
  "type": "Feature",
  "properties": {
    "gn:admin1_code":"29.0",
    "gn:admin2_code":"3002.0",
    "gn:admin3_code":"300201.0",
    "gn:admin4_code":"30020102.0",
    "gn:asciiname":"Pueblo Viejo",
    "gn:country_code":"DO",
    "gn:dem":87,
    "gn:feature_class":"P",
    "gn:feature_code":"PPL",
    "gn:name":"Pueblo Viejo",
    "gn:population":0,
    "gn:timezone":"America/Santo_Domingo",
    "iso:country":"DO",
    "name:ceb_x_preferred":[
        "Pueblo Viejo"
    ],
    "name:deu_x_preferred":[
        "Pueblo Viejo"
    ],
    "name:fra_x_preferred":[
        "Pueblo Viejo"
    ],
    "name:nds_x_preferred":[
        "Pueblo Viejo"
    ],
    "name:sco_x_preferred":[
        "Pueblo Viejo"
    ],
    "name:spa_x_preferred":[
        "Pueblo Viejo"
    ],
    "name:swe_x_preferred":[
        "Pueblo Viejo"
    ],
    "name:vie_x_preferred":[
        "Pueblo Viejo"
    ],
    "wof:name":"Pueblo Viejo",
    "wof:placetype":"locality"
},
  "geometry": {"coordinates":[-69.43089000000001,18.99669],"type":"Point"}
}