{
  "type": "Feature",
  "properties": {
    "gn:admin1_code":"32.0",
    "gn:admin2_code":"2903.0",
    "gn:admin3_code":"290301.0",
    "gn:admin4_code":"29030103.0",
    "gn:asciiname":"Juan Sanchez",
    "gn:country_code":"DO",
    "gn:dem":271,
    "gn:feature_class":"P",
    "gn:feature_code":"PPL",
    "gn:name":"Juan S\u00e1nchez",
    "gn:population":0,
    "gn:timezone":"America/Santo_Domingo",
    "iso:country":"DO",
    "name:und_x_variant":[
        "Batey Juan Sanchez",
        "Juan S\u00e1nchez"
    ],
    "wof:name":"Juan Sanchez",
    "wof:placetype":"locality"
},
  "geometry": {"coordinates":[-69.81815999999999,18.98874],"type":"Point"}
}