{
  "type": "Feature",
  "properties": {
    "gn:admin1_code":"12.0",
    "gn:admin2_code":"1202.0",
    "gn:admin3_code":"120201.0",
    "gn:admin4_code":"12020103.0",
    "gn:asciiname":"Batey Hoyo de Puerco",
    "gn:country_code":"DO",
    "gn:dem":88,
    "gn:feature_class":"P",
    "gn:feature_code":"PPL",
    "gn:name":"Batey Hoyo de Puerco",
    "gn:population":0,
    "gn:timezone":"America/Santo_Domingo",
    "iso:country":"DO",
    "wof:name":"Batey Hoyo de Puerco",
    "wof:placetype":"locality"
},
  "geometry": {"coordinates":[-68.93225,18.59569],"type":"Point"}
}