{
  "type": "Feature",
  "properties": {
    "gn:admin1_code":"14.0",
    "gn:admin2_code":"1401.0",
    "gn:admin3_code":"140101.0",
    "gn:admin4_code":"14010102.0",
    "gn:asciiname":"Cruce El Cano",
    "gn:country_code":"DO",
    "gn:dem":34,
    "gn:feature_class":"P",
    "gn:feature_code":"PPL",
    "gn:name":"Cruce El Ca\u00f1o",
    "gn:population":0,
    "gn:timezone":"America/Santo_Domingo",
    "iso:country":"DO",
    "name:und_x_variant":[
        "Cruce del Ca\u00f1o",
        "Cruce El Ca\u00f1o"
    ],
    "wof:name":"Cruce El Cano",
    "wof:placetype":"locality"
},
  "geometry": {"coordinates":[-69.87828,19.39567000000001],"type":"Point"}
}