{
  "type": "Feature",
  "properties": {
    "gn:admin1_code":"23.0",
    "gn:admin2_code":"2205.0",
    "gn:admin3_code":"220502.0",
    "gn:admin4_code":"22050202.0",
    "gn:asciiname":"El Almacigo",
    "gn:country_code":"DO",
    "gn:dem":450,
    "gn:feature_class":"P",
    "gn:feature_code":"PPL",
    "gn:name":"El Alm\u00e1cigo",
    "gn:population":0,
    "gn:timezone":"America/Santo_Domingo",
    "iso:country":"DO",
    "name:und_x_variant":[
        "Almacigo",
        "El Amacigo",
        "El Alm\u00e1cigo"
    ],
    "wof:name":"El Almacigo",
    "wof:placetype":"locality"
},
  "geometry": {"coordinates":[-71.59541999999998,18.86338],"type":"Point"}
}