{
  "type": "Feature",
  "properties": {
    "gn:admin1_code":"23.0",
    "gn:admin2_code":"2201.0",
    "gn:admin3_code":"220111.0",
    "gn:admin4_code":"22011104.0",
    "gn:asciiname":"Fondo Viejo",
    "gn:country_code":"DO",
    "gn:dem":434,
    "gn:feature_class":"P",
    "gn:feature_code":"PPL",
    "gn:name":"Fondo Viejo",
    "gn:population":0,
    "gn:timezone":"America/Santo_Domingo",
    "iso:country":"DO",
    "wof:name":"Fondo Viejo",
    "wof:placetype":"locality"
},
  "geometry": {"coordinates":[-71.12143,18.79542],"type":"Point"}
}