{
  "type": "Feature",
  "properties": {
    "gn:admin1_code":"10.0",
    "gn:admin2_code":"1101.0",
    "gn:admin3_code":"110102.0",
    "gn:admin4_code":"11010203.0",
    "gn:asciiname":"El Barrero",
    "gn:country_code":"DO",
    "gn:dem":102,
    "gn:feature_class":"P",
    "gn:feature_code":"PPL",
    "gn:name":"El Barrero",
    "gn:population":0,
    "gn:timezone":"America/Santo_Domingo",
    "iso:country":"DO",
    "name:ita_x_preferred":[
        "El Barrero"
    ],
    "name:spa_x_preferred":[
        "El Barrero"
    ],
    "name:zho_x_preferred":[
        "\u57c3\u5c14\u5df4\u96f7\u7f57"
    ],
    "wof:name":"El Barrero",
    "wof:placetype":"locality"
},
  "geometry": {"coordinates":[-68.77030999999999,18.89549],"type":"Point"}
}