{
  "type": "Feature",
  "properties": {
    "gn:admin1_code":"32.0",
    "gn:admin2_code":"2905.0",
    "gn:admin3_code":"290501.0",
    "gn:admin4_code":"29050105.0",
    "gn:asciiname":"Los Arroyos",
    "gn:country_code":"DO",
    "gn:dem":108,
    "gn:feature_class":"P",
    "gn:feature_code":"PPL",
    "gn:name":"Los Arroyos",
    "gn:population":0,
    "gn:timezone":"America/Santo_Domingo",
    "iso:country":"DO",
    "wof:name":"Los Arroyos",
    "wof:placetype":"locality"
},
  "geometry": {"coordinates":[-70.05033,18.82221],"type":"Point"}
}