{
  "type": "Feature",
  "properties": {
    "gn:admin1_code":"15.0",
    "gn:admin2_code":"1501.0",
    "gn:admin3_code":"150101.0",
    "gn:admin4_code":"15010103.0",
    "gn:asciiname":"Batey Higueero",
    "gn:country_code":"DO",
    "gn:dem":15,
    "gn:feature_class":"P",
    "gn:feature_code":"PPL",
    "gn:name":"Batey Hig\u00fcero",
    "gn:population":0,
    "gn:timezone":"America/Santo_Domingo",
    "iso:country":"DO",
    "name:und_x_variant":[
        "Batey Hig\u00fcero",
        "El Hig\u00fcero"
    ],
    "wof:name":"Batey Higueero",
    "wof:placetype":"locality"
},
  "geometry": {"coordinates":[-71.56475999999998,19.75089],"type":"Point"}
}