{
  "type": "Feature",
  "properties": {
    "gn:admin1_code":"21.0",
    "gn:admin2_code":"2402.0",
    "gn:admin3_code":"240201.0",
    "gn:admin4_code":"24020102.0",
    "gn:asciiname":"Cuesta Blanca",
    "gn:country_code":"DO",
    "gn:dem":202,
    "gn:feature_class":"P",
    "gn:feature_code":"PPL",
    "gn:name":"Cuesta Blanca",
    "gn:population":0,
    "gn:timezone":"America/Santo_Domingo",
    "iso:country":"DO",
    "wof:name":"Cuesta Blanca",
    "wof:placetype":"locality"
},
  "geometry": {"coordinates":[-69.95659000000001,18.94396],"type":"Point"}
}