{
  "type": "Feature",
  "properties": {
    "gn:admin1_code":"1.0",
    "gn:admin2_code":"208.0",
    "gn:admin3_code":"20804.0",
    "gn:admin4_code":"2080401.0",
    "gn:asciiname":"Arroyo Viejo",
    "gn:country_code":"DO",
    "gn:dem":240,
    "gn:feature_class":"P",
    "gn:feature_code":"PPL",
    "gn:name":"Arroyo Viejo",
    "gn:population":0,
    "gn:timezone":"America/Santo_Domingo",
    "iso:country":"DO",
    "name:ceb_x_preferred":[
        "Arroyo Viejo"
    ],
    "wof:name":"Arroyo Viejo",
    "wof:placetype":"locality"
},
  "geometry": {"coordinates":[-70.90347,18.54774],"type":"Point"}
}