{
  "type": "Feature",
  "properties": {
    "gn:admin1_code":"9.0",
    "gn:asciiname":"Agua Prieta",
    "gn:cc2":"DO",
    "gn:country_code":"DO",
    "gn:dem":1193,
    "gn:feature_class":"P",
    "gn:feature_code":"PPL",
    "gn:name":"Agua Prieta",
    "gn:population":0,
    "gn:timezone":"America/Santo_Domingo",
    "iso:country":"DO",
    "name:cat_x_preferred":[
        "Agua Prieta"
    ],
    "name:ces_x_preferred":[
        "Agua Prieta"
    ],
    "name:deu_x_preferred":[
        "Agua Prieta"
    ],
    "name:fra_x_preferred":[
        "Agua Prieta"
    ],
    "name:heb_x_preferred":[
        "\u05d0\u05d2\u05d5\u05d0\u05d4 \u05e4\u05e8\u05d9\u05d0\u05d8\u05d4"
    ],
    "name:ita_x_preferred":[
        "Agua Prieta"
    ],
    "name:nld_x_preferred":[
        "Agua Prieta"
    ],
    "name:pol_x_preferred":[
        "Agua Prieta"
    ],
    "name:ron_x_preferred":[
        "Agua Prieta"
    ],
    "name:rus_x_preferred":[
        "\u0410\u0433\u0443\u0430-\u041f\u0440\u0438\u0435\u0442\u0430"
    ],
    "name:spa_x_preferred":[
        "Agua Prieta"
    ],
    "name:srp_x_preferred":[
        "\u0410\u0433\u0432\u0430 \u041f\u0440\u0438\u0458\u0435\u0442\u0430"
    ],
    "name:und_x_variant":[
        "Ag\u00fcita Prieta"
    ],
    "wof:name":"Agua Prieta",
    "wof:placetype":"locality"
},
  "geometry": {"coordinates":[-71.58333,18.63333],"type":"Point"}
}