{
  "type": "Feature",
  "properties": {
    "gn:admin1_code":"9.0",
    "gn:asciiname":"Agua Prieta",
    "gn:cc2":"DO",
    "gn:country_code":"DO",
    "gn:dem":1193,
    "gn:feature_class":"P",
    "gn:feature_code":"PPL",
    "gn:name":"Agua Prieta",
    "gn:population":0,
    "gn:timezone":"America/Santo_Domingo",
    "iso:country":"DO",
    "name:und_x_variant":[
        "Ag\u00fcita Prieta",
        "Agua Prieta"
    ],
    "wof:name":"Agua Prieta",
    "wof:placetype":"locality"
},
  "geometry": {"coordinates":[-71.58333,18.63333],"type":"Point"}
}