{
  "type": "Feature",
  "properties": {
    "gn:country":"DO",
    "gn:fcode":"PPL",
    "gn:population":3887,
    "iso:country":"DO",
    "name:ceb_x_preferred":[
        "Villa Isabela"
    ],
    "name:eng_x_preferred":[
        "Villa Isabela"
    ],
    "name:ita_x_preferred":[
        "Villa Isabela"
    ],
    "name:jpn_x_preferred":[
        "\u30d3\u30fc\u30b8\u30e3\u30fb\u30a4\u30b5\u30d9\u30e9"
    ],
    "name:nan_x_preferred":[
        "Villa Isabela"
    ],
    "name:nld_x_preferred":[
        "Villa Isabela"
    ],
    "name:por_x_preferred":[
        "Villa Isabela"
    ],
    "name:spa_x_preferred":[
        "Villa Isabela"
    ],
    "name:swe_x_preferred":[
        "Villa Isabela"
    ],
    "name:und_x_variant":[
        "La Isabela"
    ],
    "name:zho_x_preferred":[
        "\u4f0a\u838e\u8c9d\u62c9\u93ae"
    ],
    "qs:name":"Villa Isabela",
    "qs:photos_9r":0,
    "qs:photos_sr":0,
    "qs:pop_sr":"4",
    "wd:wordcount":40,
    "wof:name":"Villa Isabela",
    "wof:placetype":"locality",
    "wof:population":3887
},
  "geometry": {"coordinates":[-71.05641,19.82288],"type":"Point"}
}