{
  "type": "Feature",
  "properties": {
    "gn:country":"DO",
    "gn:fcode":"PPL",
    "gn:pop":3887,
    "iso:country":"DO",
    "name:unk_x_variant":[
        "La Isabela"
    ],
    "qs:name":"Villa Isabela",
    "qs:photos_9r":0,
    "qs:photos_sr":0,
    "qs:pop_sr":"4",
    "wd:wordcount":40,
    "wof:name":"Villa Isabela",
    "wof:placetype":"locality",
    "wof:population":3887
},
  "geometry": {"coordinates":[-71.05641,19.82288],"type":"Point"}
}