{
  "type": "Feature",
  "properties": {
    "gn:admin1_code":"29.0",
    "gn:admin2_code":"3001.0",
    "gn:admin3_code":"300102.0",
    "gn:admin4_code":"30010203.0",
    "gn:asciiname":"La Represa",
    "gn:country_code":"DO",
    "gn:dem":85,
    "gn:feature_class":"P",
    "gn:feature_code":"PPL",
    "gn:name":"La Represa",
    "gn:population":0,
    "gn:timezone":"America/Santo_Domingo",
    "iso:country":"DO",
    "name:ita_x_preferred":[
        "La Represa"
    ],
    "name:spa_x_preferred":[
        "La Represa"
    ],
    "name:zho_x_preferred":[
        "\u62c9\u96f7\u666e\u96f7\u85a9"
    ],
    "wof:name":"La Represa",
    "wof:placetype":"locality"
},
  "geometry": {"coordinates":[-69.31855999999999,18.77148],"type":"Point"}
}