{
  "type": "Feature",
  "properties": {
    "gn:admin1_code":"9.0",
    "gn:admin2_code":"1003.0",
    "gn:admin3_code":"100301.0",
    "gn:admin4_code":"10030102.0",
    "gn:asciiname":"Angel Felix",
    "gn:cc2":"DO",
    "gn:country_code":"DO",
    "gn:dem":1112,
    "gn:feature_class":"P",
    "gn:feature_code":"PPL",
    "gn:name":"\u00c1ngel F\u00e9lix",
    "gn:population":0,
    "gn:timezone":"America/Santo_Domingo",
    "iso:country":"DO",
    "name:und_x_variant":[
        "Angel F\u00e9liz",
        "\u00c1ngel F\u00e9lix"
    ],
    "wof:name":"Angel Felix",
    "wof:placetype":"locality"
},
  "geometry": {"coordinates":[-71.77194,18.63694],"type":"Point"}
}