{
  "type": "Feature",
  "properties": {
    "gn:admin1_code":"32.0",
    "gn:admin2_code":"2904.0",
    "gn:admin3_code":"290401.0",
    "gn:admin4_code":"29040104.0",
    "gn:asciiname":"La Cuesta del Jobo",
    "gn:country_code":"DO",
    "gn:dem":47,
    "gn:feature_class":"P",
    "gn:feature_code":"PPL",
    "gn:name":"La Cuesta del Jobo",
    "gn:population":0,
    "gn:timezone":"America/Santo_Domingo",
    "iso:country":"DO",
    "wof:name":"La Cuesta del Jobo",
    "wof:placetype":"locality"
},
  "geometry": {"coordinates":[-69.99427,18.77645],"type":"Point"}
}