{
  "type": "Feature",
  "properties": {
    "gn:admin1_code":"6.0",
    "gn:admin2_code":"601.0",
    "gn:admin3_code":"60101.0",
    "gn:admin4_code":"6010101.0",
    "gn:asciiname":"Mata Larga",
    "gn:country_code":"DO",
    "gn:dem":111,
    "gn:feature_class":"P",
    "gn:feature_code":"PPL",
    "gn:name":"Mata Larga",
    "gn:population":0,
    "gn:timezone":"America/Santo_Domingo",
    "iso:country":"DO",
    "name:und_x_variant":[
        "Nata Larga",
        "Mata Larga"
    ],
    "wof:name":"Mata Larga",
    "wof:placetype":"locality"
},
  "geometry": {"coordinates":[-70.23743,19.28398],"type":"Point"}
}