{
  "type": "Feature",
  "properties": {
    "gn:admin1_code":"30.0",
    "gn:admin2_code":"1301.0",
    "gn:admin3_code":"130102.0",
    "gn:admin4_code":"13010205.0",
    "gn:asciiname":"Las Arenas",
    "gn:country_code":"DO",
    "gn:dem":141,
    "gn:feature_class":"P",
    "gn:feature_code":"PPL",
    "gn:name":"Las Arenas",
    "gn:population":0,
    "gn:timezone":"America/Santo_Domingo",
    "iso:country":"DO",
    "name:cat_x_preferred":[
        "Areeta"
    ],
    "name:eus_x_preferred":[
        "Areeta"
    ],
    "name:fra_x_preferred":[
        "Areeta"
    ],
    "name:glg_x_preferred":[
        "Areeta"
    ],
    "name:ita_x_preferred":[
        "Las Arenas"
    ],
    "name:spa_x_preferred":[
        "Las Arenas"
    ],
    "name:und_x_variant":[
        "La Arena"
    ],
    "wof:name":"Las Arenas",
    "wof:placetype":"locality"
},
  "geometry": {"coordinates":[-70.52213,19.32868],"type":"Point"}
}