{
  "type": "Feature",
  "properties": {
    "gn:admin1_code":"28.0",
    "gn:admin2_code":"801.0",
    "gn:admin3_code":"80101.0",
    "gn:admin4_code":"8010103.0",
    "gn:asciiname":"La Guanabana",
    "gn:country_code":"DO",
    "gn:dem":105,
    "gn:feature_class":"P",
    "gn:feature_code":"PPL",
    "gn:name":"La Guan\u00e1bana",
    "gn:population":0,
    "gn:timezone":"America/Santo_Domingo",
    "iso:country":"DO",
    "wof:name":"La Guanabana",
    "wof:placetype":"locality"
},
  "geometry": {"coordinates":[-69.03333000000001,18.65],"type":"Point"}
}