{
  "type": "Feature",
  "properties": {
    "gn:admin1_code":"14.0",
    "gn:admin2_code":"1401.0",
    "gn:admin3_code":"140102.0",
    "gn:admin4_code":"14010204.0",
    "gn:asciiname":"El Machete",
    "gn:country_code":"DO",
    "gn:dem":4,
    "gn:feature_class":"P",
    "gn:feature_code":"PPL",
    "gn:name":"El Machete",
    "gn:population":0,
    "gn:timezone":"America/Santo_Domingo",
    "iso:country":"DO",
    "wof:name":"El Machete",
    "wof:placetype":"locality"
},
  "geometry": {"coordinates":[-69.78333000000001,19.26667],"type":"Point"}
}