{
  "type": "Feature",
  "properties": {
    "gn:admin1_code":"30.0",
    "gn:admin2_code":"1302.0",
    "gn:admin3_code":"130203.0",
    "gn:admin4_code":"13020303.0",
    "gn:asciiname":"Cerro de Monte",
    "gn:country_code":"DO",
    "gn:dem":1235,
    "gn:feature_class":"P",
    "gn:feature_code":"PPL",
    "gn:name":"Cerro de Monte",
    "gn:population":0,
    "gn:timezone":"America/Santo_Domingo",
    "iso:country":"DO",
    "name:und_x_variant":[
        "Cerro de Montes",
        "Cerro de Monte"
    ],
    "wof:name":"Cerro de Monte",
    "wof:placetype":"locality"
},
  "geometry": {"coordinates":[-70.69741999999999,18.90164],"type":"Point"}
}