{
  "type": "Feature",
  "properties": {
    "gn:admin1_code":"1.0",
    "gn:admin2_code":"204.0",
    "gn:admin3_code":"20401.0",
    "gn:admin4_code":"2040102.0",
    "gn:asciiname":"Los Avaches",
    "gn:country_code":"DO",
    "gn:dem":480,
    "gn:feature_class":"P",
    "gn:feature_code":"PPL",
    "gn:name":"Los Avaches",
    "gn:population":0,
    "gn:timezone":"America/Santo_Domingo",
    "iso:country":"DO",
    "wof:name":"Los Avaches",
    "wof:placetype":"locality"
},
  "geometry": {"coordinates":[-70.95935,18.81268],"type":"Point"}
}