{
  "type": "Feature",
  "properties": {
    "gn:admin1_code":"24.0",
    "gn:asciiname":"Casui",
    "gn:country_code":"DO",
    "gn:dem":164,
    "gn:feature_class":"P",
    "gn:feature_code":"PPL",
    "gn:name":"Casu\u00ed",
    "gn:population":0,
    "gn:timezone":"America/Santo_Domingo",
    "iso:country":"DO",
    "wof:name":"Casui",
    "wof:placetype":"locality"
},
  "geometry": {"coordinates":[-69.45014999999999,18.80532],"type":"Point"}
}