{
  "type": "Feature",
  "properties": {
    "gn:admin1_code":"4.0",
    "gn:admin2_code":"501.0",
    "gn:admin3_code":"50101.0",
    "gn:admin4_code":"5010106.0",
    "gn:asciiname":"Tabique",
    "gn:country_code":"DO",
    "gn:dem":91,
    "gn:feature_class":"P",
    "gn:feature_code":"PPL",
    "gn:name":"Tabique",
    "gn:population":0,
    "gn:timezone":"America/Santo_Domingo",
    "iso:country":"DO",
    "name:und_x_variant":[
        "Taguique",
        "Tahuique",
        "Tabique"
    ],
    "wof:name":"Tabique",
    "wof:placetype":"locality"
},
  "geometry": {"coordinates":[-71.54055,19.54148],"type":"Point"}
}