{
  "type": "Feature",
  "properties": {
    "gn:admin1_code":"30.0",
    "gn:admin2_code":"1302.0",
    "gn:admin3_code":"130203.0",
    "gn:admin4_code":"13020305.0",
    "gn:asciiname":"Calderon",
    "gn:country_code":"DO",
    "gn:dem":1206,
    "gn:feature_class":"P",
    "gn:feature_code":"PPL",
    "gn:name":"Calder\u00f3n",
    "gn:population":0,
    "gn:timezone":"America/Santo_Domingo",
    "iso:country":"DO",
    "name:und_x_variant":[
        "Paraje Calder\u00f3n",
        "Calder\u00f3n"
    ],
    "wof:name":"Calderon",
    "wof:placetype":"locality"
},
  "geometry": {"coordinates":[-70.53628,18.76667],"type":"Point"}
}