{
  "type": "Feature",
  "properties": {
    "gn:admin1_code":"32.0",
    "gn:admin2_code":"2904.0",
    "gn:admin3_code":"290401.0",
    "gn:admin4_code":"29040105.0",
    "gn:asciiname":"Dajao",
    "gn:country_code":"DO",
    "gn:dem":88,
    "gn:feature_class":"P",
    "gn:feature_code":"PPL",
    "gn:name":"Dajao",
    "gn:population":0,
    "gn:timezone":"America/Santo_Domingo",
    "iso:country":"DO",
    "wof:name":"Dajao",
    "wof:placetype":"locality"
},
  "geometry": {"coordinates":[-70.02585000000001,18.79632],"type":"Point"}
}