{
  "type": "Feature",
  "properties": {
    "gn:admin1_code":"10.0",
    "gn:admin2_code":"1101.0",
    "gn:admin3_code":"110104.0",
    "gn:admin4_code":"11010402.0",
    "gn:asciiname":"Arena Gorda",
    "gn:country_code":"DO",
    "gn:dem":10,
    "gn:feature_class":"P",
    "gn:feature_code":"PPL",
    "gn:name":"Arena Gorda",
    "gn:population":0,
    "gn:timezone":"America/Santo_Domingo",
    "iso:country":"DO",
    "wof:name":"Arena Gorda",
    "wof:placetype":"locality"
},
  "geometry": {"coordinates":[-68.4718,18.73372],"type":"Point"}
}