{
  "type": "Feature",
  "properties": {
    "gn:admin1_code":"37.0",
    "gn:admin2_code":"3203.0",
    "gn:admin3_code":"320301.0",
    "gn:admin4_code":"32030106.0",
    "gn:asciiname":"Amor de Dios",
    "gn:country_code":"DO",
    "gn:dem":64,
    "gn:feature_class":"P",
    "gn:feature_code":"PPL",
    "gn:name":"Amor de Dios",
    "gn:population":0,
    "gn:timezone":"America/Santo_Domingo",
    "iso:country":"DO",
    "wof:name":"Amor de Dios",
    "wof:placetype":"locality"
},
  "geometry": {"coordinates":[-69.99554000000001,18.61357000000001],"type":"Point"}
}