{
  "type": "Feature",
  "properties": {
    "gn:admin1_code":"24.0",
    "gn:admin2_code":"2305.0",
    "gn:admin3_code":"230501.0",
    "gn:admin4_code":"23050107.0",
    "gn:asciiname":"Batey Luis Medina",
    "gn:country_code":"DO",
    "gn:dem":27,
    "gn:feature_class":"P",
    "gn:feature_code":"PPL",
    "gn:name":"Batey Luis Medina",
    "gn:population":0,
    "gn:timezone":"America/Santo_Domingo",
    "iso:country":"DO",
    "name:und_x_variant":[
        "Luis Medina",
        "Batey Medina",
        "Batey Luis Medina"
    ],
    "wof:name":"Batey Luis Medina",
    "wof:placetype":"locality"
},
  "geometry": {"coordinates":[-69.47763,18.56753],"type":"Point"}
}