{
  "type": "Feature",
  "properties": {
    "gn:admin1_code":"26.0",
    "gn:admin2_code":"2601.0",
    "gn:admin3_code":"260101.0",
    "gn:admin4_code":"26010102.0",
    "gn:asciiname":"Los Guaos",
    "gn:country_code":"DO",
    "gn:dem":245,
    "gn:feature_class":"P",
    "gn:feature_code":"PPL",
    "gn:name":"Los Guaos",
    "gn:population":0,
    "gn:timezone":"America/Santo_Domingo",
    "iso:country":"DO",
    "wof:name":"Los Guaos",
    "wof:placetype":"locality"
},
  "geometry": {"coordinates":[-71.38871999999998,19.40599],"type":"Point"}
}