{
  "type": "Feature",
  "properties": {
    "gn:admin1_code":"32.0",
    "gn:admin2_code":"2901.0",
    "gn:admin3_code":"290101.0",
    "gn:admin4_code":"29010105.0",
    "gn:asciiname":"Aguas Vivas",
    "gn:country_code":"DO",
    "gn:dem":57,
    "gn:feature_class":"P",
    "gn:feature_code":"PPL",
    "gn:name":"Aguas Vivas",
    "gn:population":0,
    "gn:timezone":"America/Santo_Domingo",
    "iso:country":"DO",
    "wof:name":"Aguas Vivas",
    "wof:placetype":"locality"
},
  "geometry": {"coordinates":[-69.73081999999999,18.78569],"type":"Point"}
}