{
  "type": "Feature",
  "properties": {
    "gn:admin1_code":"23.0",
    "gn:admin2_code":"2201.0",
    "gn:admin3_code":"220106.0",
    "gn:admin4_code":"22010602.0",
    "gn:asciiname":"El Ciruelo",
    "gn:country_code":"DO",
    "gn:dem":469,
    "gn:feature_class":"P",
    "gn:feature_code":"PPL",
    "gn:name":"El Ciruelo",
    "gn:population":0,
    "gn:timezone":"America/Santo_Domingo",
    "iso:country":"DO",
    "wof:name":"El Ciruelo",
    "wof:placetype":"locality"
},
  "geometry": {"coordinates":[-71.28333000000001,18.85],"type":"Point"}
}