{
  "type": "Feature",
  "properties": {
    "gn:admin1_code":"6.0",
    "gn:admin2_code":"604.0",
    "gn:admin3_code":"60401.0",
    "gn:admin4_code":"6040102.0",
    "gn:asciiname":"La Jagua",
    "gn:country_code":"DO",
    "gn:dem":109,
    "gn:feature_class":"P",
    "gn:feature_code":"PPL",
    "gn:name":"La Jagua",
    "gn:population":0,
    "gn:timezone":"America/Santo_Domingo",
    "iso:country":"DO",
    "name:und_x_variant":[
        "La Jugua",
        "La Jagua"
    ],
    "wof:name":"La Jagua",
    "wof:placetype":"locality"
},
  "geometry": {"coordinates":[-70.13685,19.26662],"type":"Point"}
}