{
  "type": "Feature",
  "properties": {
    "gn:admin1_code":"36.0",
    "gn:admin2_code":"3103.0",
    "gn:admin3_code":"310301.0",
    "gn:admin4_code":"31030101.0",
    "gn:asciiname":"Rancho Arriba",
    "gn:country_code":"DO",
    "gn:dem":699,
    "gn:feature_class":"P",
    "gn:feature_code":"PPL",
    "gn:name":"Rancho Arriba",
    "gn:population":0,
    "gn:timezone":"America/Santo_Domingo",
    "iso:country":"DO",
    "name:ceb_x_preferred":[
        "Rancho Arriba"
    ],
    "name:ita_x_preferred":[
        "Rancho Arriba"
    ],
    "name:por_x_preferred":[
        "Rancho Arriba"
    ],
    "name:spa_x_preferred":[
        "Rancho Arriba"
    ],
    "name:swe_x_preferred":[
        "Rancho Arriba"
    ],
    "name:zho_x_preferred":[
        "\u862d\u55ac\u963f\u91cc\u74e6"
    ],
    "wof:name":"Rancho Arriba",
    "wof:placetype":"locality"
},
  "geometry": {"coordinates":[-70.45464,18.70642],"type":"Point"}
}