{
  "type": "Feature",
  "properties": {
    "gn:admin1_code":"11.0",
    "gn:admin2_code":"702.0",
    "gn:admin3_code":"70202.0",
    "gn:admin4_code":"7020204.0",
    "gn:asciiname":"Manllalla",
    "gn:country_code":"DO",
    "gn:dem":224,
    "gn:feature_class":"P",
    "gn:feature_code":"PPL",
    "gn:name":"Manllalla",
    "gn:population":0,
    "gn:timezone":"America/Santo_Domingo",
    "iso:country":"DO",
    "wof:name":"Manllalla",
    "wof:placetype":"locality"
},
  "geometry": {"coordinates":[-71.80141,18.99649],"type":"Point"}
}