{
  "type": "Feature",
  "properties": {
    "gn:admin1_code":"25.0",
    "gn:admin2_code":"2501.0",
    "gn:admin3_code":"250101.0",
    "gn:admin4_code":"25010101.0",
    "gn:asciiname":"El Ejido",
    "gn:country_code":"DO",
    "gn:dem":180,
    "gn:feature_class":"P",
    "gn:feature_code":"PPL",
    "gn:name":"El Ejido",
    "gn:population":0,
    "gn:timezone":"America/Santo_Domingo",
    "iso:country":"DO",
    "name:und_x_variant":[
        "El Ingenio",
        "El Egido",
        "El Ejido"
    ],
    "wof:name":"El Ejido",
    "wof:placetype":"locality"
},
  "geometry": {"coordinates":[-70.69927,19.46433],"type":"Point"}
}