{
  "type": "Feature",
  "properties": {
    "gn:admin1_code":"25.0",
    "gn:admin2_code":"2501.0",
    "gn:admin3_code":"250101.0",
    "gn:admin4_code":"25010101.0",
    "gn:asciiname":"El Ejido",
    "gn:country_code":"DO",
    "gn:dem":180,
    "gn:feature_class":"P",
    "gn:feature_code":"PPL",
    "gn:name":"El Ejido",
    "gn:population":0,
    "gn:timezone":"America/Santo_Domingo",
    "iso:country":"DO",
    "name:ara_x_preferred":[
        "\u0625\u0644\u0625\u064a\u062c\u0627\u064a\u062f\u0648"
    ],
    "name:arg_x_preferred":[
        "El Ejido"
    ],
    "name:azb_x_preferred":[
        "\u0627\u0644 \u0627\u062e\u06cc\u062f\u0648"
    ],
    "name:bul_x_preferred":[
        "\u0415\u043b \u0415\u0445\u0438\u0434\u043e"
    ],
    "name:cat_x_preferred":[
        "El Ejido"
    ],
    "name:ceb_x_preferred":[
        "El Ejido"
    ],
    "name:deu_x_preferred":[
        "El Ejido"
    ],
    "name:ell_x_preferred":[
        "\u0395\u03c7\u03af\u03b4\u03bf"
    ],
    "name:eus_x_preferred":[
        "El Ejido"
    ],
    "name:fas_x_preferred":[
        "\u0627\u0644 \u0627\u062e\u06cc\u062f\u0648"
    ],
    "name:fin_x_preferred":[
        "El Ejido"
    ],
    "name:fra_x_preferred":[
        "El Ejido"
    ],
    "name:glg_x_preferred":[
        "El Ejido"
    ],
    "name:hat_x_preferred":[
        "El Ejido"
    ],
    "name:hun_x_preferred":[
        "El Ejido"
    ],
    "name:hye_x_preferred":[
        "\u0537\u056c-\u0537\u056d\u056b\u0564\u0578"
    ],
    "name:ina_x_preferred":[
        "El Ejido"
    ],
    "name:ita_x_preferred":[
        "El Ejido"
    ],
    "name:jpn_x_preferred":[
        "\u30a8\u30eb\u30fb\u30a8\u30d2\u30c9"
    ],
    "name:mkd_x_preferred":[
        "\u0415\u043b \u0415\u0445\u0438\u0434\u043e"
    ],
    "name:mlg_x_preferred":[
        "El Ejido"
    ],
    "name:msa_x_preferred":[
        "El Ejido"
    ],
    "name:nld_x_preferred":[
        "El Ejido"
    ],
    "name:nno_x_preferred":[
        "El Ejido"
    ],
    "name:oci_x_preferred":[
        "Ejido"
    ],
    "name:pol_x_preferred":[
        "El Ejido"
    ],
    "name:por_x_preferred":[
        "El Ejido"
    ],
    "name:ron_x_preferred":[
        "El Ejido"
    ],
    "name:rus_x_preferred":[
        "\u042d\u043b\u044c-\u042d\u0445\u0438\u0434\u043e"
    ],
    "name:spa_x_preferred":[
        "El Ejido"
    ],
    "name:srp_x_preferred":[
        "\u0415\u0445\u0438\u0434\u043e"
    ],
    "name:tur_x_preferred":[
        "El Ejido"
    ],
    "name:ukr_x_preferred":[
        "\u0415\u043b\u044c-\u0415\u0445\u0456\u0434\u043e"
    ],
    "name:und_x_variant":[
        "El Ingenio",
        "El Egido"
    ],
    "name:uzb_x_preferred":[
        "El Ejido"
    ],
    "name:vie_x_preferred":[
        "El Ejido"
    ],
    "name:war_x_preferred":[
        "El Ejido"
    ],
    "name:zho_x_preferred":[
        "\u57c3\u5c14\u57c3\u5e0c\u591a"
    ],
    "wof:name":"El Ejido",
    "wof:placetype":"locality"
},
  "geometry": {"coordinates":[-70.69927,19.46433],"type":"Point"}
}