{
  "type": "Feature",
  "properties": {
    "gn:admin1_code":"14.0",
    "gn:admin2_code":"1402.0",
    "gn:admin3_code":"140201.0",
    "gn:admin4_code":"14020102.0",
    "gn:asciiname":"Jobo Dulce",
    "gn:country_code":"DO",
    "gn:dem":342,
    "gn:feature_class":"P",
    "gn:feature_code":"PPL",
    "gn:name":"Jobo Dulce",
    "gn:population":0,
    "gn:timezone":"America/Santo_Domingo",
    "iso:country":"DO",
    "wof:name":"Jobo Dulce",
    "wof:placetype":"locality"
},
  "geometry": {"coordinates":[-70.00355999999999,19.61007],"type":"Point"}
}