{
  "type": "Feature",
  "properties": {
    "gn:admin1_code":"1.0",
    "gn:admin2_code":"208.0",
    "gn:admin3_code":"20804.0",
    "gn:admin4_code":"2080403.0",
    "gn:asciiname":"Arroyo Guayabo",
    "gn:country_code":"DO",
    "gn:dem":291,
    "gn:feature_class":"P",
    "gn:feature_code":"PPL",
    "gn:name":"Arroyo Guayabo",
    "gn:population":0,
    "gn:timezone":"America/Santo_Domingo",
    "iso:country":"DO",
    "wof:name":"Arroyo Guayabo",
    "wof:placetype":"locality"
},
  "geometry": {"coordinates":[-70.85814999999999,18.56114],"type":"Point"}
}