{
  "type": "Feature",
  "properties": {
    "gn:admin1_code":"33.0",
    "gn:admin2_code":"2108.0",
    "gn:admin3_code":"210801.0",
    "gn:admin4_code":"21080102.0",
    "gn:asciiname":"Los Jengibres",
    "gn:cc2":"DO",
    "gn:country_code":"DO",
    "gn:dem":1033,
    "gn:feature_class":"P",
    "gn:feature_code":"PPL",
    "gn:name":"Los Jengibres",
    "gn:population":0,
    "gn:timezone":"America/Santo_Domingo",
    "iso:country":"DO",
    "name:und_x_variant":[
        "Los Gencibres",
        "Los Jengibres"
    ],
    "wof:name":"Los Jengibres",
    "wof:placetype":"locality"
},
  "geometry": {"coordinates":[-70.34999999999999,18.55],"type":"Point"}
}