{
  "type": "Feature",
  "properties": {
    "gn:country":"DO",
    "gn:fcode":"PPL",
    "gn:pop":6625,
    "iso:country":"DO",
    "name:eng_x_preferred":[
        "Monci\u00f3n"
    ],
    "name:ita_x_preferred":[
        "Monci\u00f3n"
    ],
    "name:nan_x_preferred":[
        "Monci\u00f3n"
    ],
    "name:nld_x_preferred":[
        "Monci\u00f3n"
    ],
    "name:por_x_preferred":[
        "Monci\u00f3n"
    ],
    "name:spa_x_preferred":[
        "Monci\u00f3n"
    ],
    "name:swe_x_preferred":[
        "Monci\u00f3n"
    ],
    "name:unk_x_variant":[
        "Benito Monci\u00f3n"
    ],
    "name:zho_x_preferred":[
        "\u8499\u897f\u7fc1"
    ],
    "qs:name":"Monci\u00f3n",
    "qs:photos_9r":0,
    "qs:photos_sr":0,
    "qs:pop_sr":"5",
    "wd:wordcount":171,
    "wof:name":"Monci\u00f3n",
    "wof:placetype":"locality",
    "wof:population":6625
},
  "geometry": {"coordinates":[-71.15257,19.41084],"type":"Point"}
}