{
  "type": "Feature",
  "properties": {
    "gn:admin1_code":"30.0",
    "gn:admin2_code":"1303.0",
    "gn:admin3_code":"130302.0",
    "gn:admin4_code":"13030206.0",
    "gn:asciiname":"Piedra Blanca",
    "gn:country_code":"DO",
    "gn:dem":611,
    "gn:feature_class":"P",
    "gn:feature_code":"PPL",
    "gn:name":"Piedra Blanca",
    "gn:population":0,
    "gn:timezone":"America/Santo_Domingo",
    "iso:country":"DO",
    "name:ceb_x_preferred":[
        "Piedra Blanca"
    ],
    "name:fra_x_preferred":[
        "Piedra Blanca"
    ],
    "name:ita_x_preferred":[
        "Piedra Blanca"
    ],
    "name:por_x_preferred":[
        "Piedra Blanca"
    ],
    "name:spa_x_preferred":[
        "Piedra Blanca"
    ],
    "name:und_x_variant":[
        "Piedra Blanco"
    ],
    "name:zho_x_preferred":[
        "\u5f7c\u5fb7\u62c9\u5e03\u862d\u5361"
    ],
    "wof:name":"Piedra Blanca",
    "wof:placetype":"locality"
},
  "geometry": {"coordinates":[-70.64867,19.17439],"type":"Point"}
}