{
  "type": "Feature",
  "properties": {
    "gn:admin1_code":"32.0",
    "gn:admin2_code":"2903.0",
    "gn:admin3_code":"290301.0",
    "gn:admin4_code":"29030102.0",
    "gn:asciiname":"La Nue",
    "gn:country_code":"DO",
    "gn:dem":128,
    "gn:feature_class":"P",
    "gn:feature_code":"PPL",
    "gn:name":"La Nu\u00e9",
    "gn:population":0,
    "gn:timezone":"America/Santo_Domingo",
    "iso:country":"DO",
    "wof:name":"La Nue",
    "wof:placetype":"locality"
},
  "geometry": {"coordinates":[-69.85553,18.89697],"type":"Point"}
}