{
  "type": "Feature",
  "properties": {
    "gn:admin1_code":"25.0",
    "gn:asciiname":"Entrada de Mao",
    "gn:country_code":"DO",
    "gn:dem":172,
    "gn:feature_class":"P",
    "gn:feature_code":"PPL",
    "gn:name":"Entrada de Mao",
    "gn:population":0,
    "gn:timezone":"America/Santo_Domingo",
    "iso:country":"DO",
    "wof:name":"Entrada de Mao",
    "wof:placetype":"locality"
},
  "geometry": {"coordinates":[-71.03036999999998,19.4723],"type":"Point"}
}