{
  "type": "Feature",
  "properties": {
    "gn:admin1_code":"2.0",
    "gn:admin2_code":"303.0",
    "gn:admin3_code":"30301.0",
    "gn:admin4_code":"3030101.0",
    "gn:asciiname":"La Cuaba",
    "gn:country_code":"DO",
    "gn:dem":29,
    "gn:feature_class":"P",
    "gn:feature_code":"PPL",
    "gn:name":"La Cuaba",
    "gn:population":0,
    "gn:timezone":"America/Santo_Domingo",
    "iso:country":"DO",
    "wof:name":"La Cuaba",
    "wof:placetype":"locality"
},
  "geometry": {"coordinates":[-71.20822,18.39815],"type":"Point"}
}