{
  "type": "Feature",
  "properties": {
    "gn:admin1_code":"23.0",
    "gn:admin2_code":"2201.0",
    "gn:admin3_code":"220103.0",
    "gn:admin4_code":"22010304.0",
    "gn:asciiname":"El Chicharron",
    "gn:country_code":"DO",
    "gn:dem":803,
    "gn:feature_class":"P",
    "gn:feature_code":"PPL",
    "gn:name":"El Chicharr\u00f3n",
    "gn:population":0,
    "gn:timezone":"America/Santo_Domingo",
    "iso:country":"DO",
    "wof:name":"El Chicharron",
    "wof:placetype":"locality"
},
  "geometry": {"coordinates":[-71.3518,19.06857],"type":"Point"}
}