{
  "type": "Feature",
  "properties": {
    "gn:country":"DO",
    "gn:fcode":"PPL",
    "gn:population":11675,
    "iso:country":"DO",
    "name:ceb_x_preferred":[
        "Salsipuedes"
    ],
    "name:spa_x_preferred":[
        "Salsipuedes"
    ],
    "name:swe_x_preferred":[
        "Salsipuedes"
    ],
    "qs:name":"Salsipuedes",
    "qs:photos_9r":0,
    "qs:photos_sr":0,
    "qs:pop_sr":"6",
    "wof:name":"Salsipuedes",
    "wof:placetype":"locality",
    "wof:population":11675
},
  "geometry": {"coordinates":[-70.37985,19.40552],"type":"Point"}
}