{
  "type": "Feature",
  "properties": {
    "gn:admin1_code":"18.0",
    "gn:admin2_code":"1803.0",
    "gn:admin3_code":"180301.0",
    "gn:admin4_code":"18030103.0",
    "gn:asciiname":"Monte Gordo",
    "gn:country_code":"DO",
    "gn:dem":179,
    "gn:feature_class":"P",
    "gn:feature_code":"PPL",
    "gn:name":"Monte Gordo",
    "gn:population":0,
    "gn:timezone":"America/Santo_Domingo",
    "iso:country":"DO",
    "wof:name":"Monte Gordo",
    "wof:placetype":"locality"
},
  "geometry": {"coordinates":[-70.93295999999999,19.7377],"type":"Point"}
}