{
  "type": "Feature",
  "properties": {
    "gn:admin1_code":"3.0",
    "gn:admin2_code":"403.0",
    "gn:admin3_code":"40302.0",
    "gn:admin4_code":"4030202.0",
    "gn:asciiname":"Mencia",
    "gn:country_code":"DO",
    "gn:dem":15,
    "gn:feature_class":"P",
    "gn:feature_code":"PPL",
    "gn:name":"Menc\u00eda",
    "gn:population":0,
    "gn:timezone":"America/Santo_Domingo",
    "iso:country":"DO",
    "name:cat_x_preferred":[
        "Menc\u00eda"
    ],
    "name:deu_x_preferred":[
        "Mencia"
    ],
    "name:glg_x_preferred":[
        "Menc\u00eda"
    ],
    "name:ita_x_preferred":[
        "Menc\u00eda"
    ],
    "name:pol_x_preferred":[
        "Mencia"
    ],
    "name:spa_x_preferred":[
        "Menc\u00eda"
    ],
    "name:swe_x_preferred":[
        "Mencia"
    ],
    "name:vie_x_preferred":[
        "Nho Mencia"
    ],
    "wof:name":"Mencia",
    "wof:placetype":"locality"
},
  "geometry": {"coordinates":[-71.26645000000001,17.89256],"type":"Point"}
}