{
  "type": "Feature",
  "properties": {
    "gn:admin1_code":"23.0",
    "gn:admin2_code":"2201.0",
    "gn:admin3_code":"220101.0",
    "gn:admin4_code":"22010101.0",
    "gn:asciiname":"Santome",
    "gn:country_code":"DO",
    "gn:dem":426,
    "gn:feature_class":"P",
    "gn:feature_code":"PPL",
    "gn:name":"Santom\u00e9",
    "gn:population":0,
    "gn:timezone":"America/Santo_Domingo",
    "iso:country":"DO",
    "wof:name":"Santome",
    "wof:placetype":"locality"
},
  "geometry": {"coordinates":[-71.25,18.81667],"type":"Point"}
}