{
  "type": "Feature",
  "properties": {
    "gn:admin1_code":"25.0",
    "gn:admin2_code":"2503.0",
    "gn:admin3_code":"250301.0",
    "gn:admin4_code":"25030102.0",
    "gn:asciiname":"Cagueeyes",
    "gn:country_code":"DO",
    "gn:dem":612,
    "gn:feature_class":"P",
    "gn:feature_code":"PPL",
    "gn:name":"Cag\u00fceyes",
    "gn:population":0,
    "gn:timezone":"America/Santo_Domingo",
    "iso:country":"DO",
    "name:und_x_variant":[
        "Los Cag\u00fceyes",
        "Cag\u00fcelles",
        "Los Cag\u00fcelles",
        "Cag\u00fceyes"
    ],
    "wof:name":"Cagueeyes",
    "wof:placetype":"locality"
},
  "geometry": {"coordinates":[-70.83445999999998,19.28596],"type":"Point"}
}