{
  "type": "Feature",
  "properties": {
    "gn:admin1_code":"34.0",
    "gn:asciiname":"Vuelta Grande",
    "gn:cc2":"DO",
    "gn:country_code":"DO",
    "gn:dem":27,
    "gn:feature_class":"P",
    "gn:feature_code":"PPL",
    "gn:name":"Vuelta Grande",
    "gn:population":0,
    "gn:timezone":"America/Santo_Domingo",
    "iso:country":"DO",
    "name:und_x_variant":[
        "Vueta Grande",
        "Vuelta Grande"
    ],
    "wof:name":"Vuelta Grande",
    "wof:placetype":"locality"
},
  "geometry": {"coordinates":[-69.75,18.58333],"type":"Point"}
}