{
  "type": "Feature",
  "properties": {
    "gn:admin1_code":"11.0",
    "gn:admin2_code":"702.0",
    "gn:admin3_code":"70203.0",
    "gn:admin4_code":"7020304.0",
    "gn:asciiname":"Maguana",
    "gn:country_code":"DO",
    "gn:dem":438,
    "gn:feature_class":"P",
    "gn:feature_code":"PPL",
    "gn:name":"Maguana",
    "gn:population":0,
    "gn:timezone":"America/Santo_Domingo",
    "iso:country":"DO",
    "name:und_x_variant":[
        "Majuana",
        "Maguana"
    ],
    "wof:name":"Maguana",
    "wof:placetype":"locality"
},
  "geometry": {"coordinates":[-71.58929000000001,19.01845],"type":"Point"}
}