{
  "type": "Feature",
  "properties": {
    "gn:admin1_code":"30.0",
    "gn:admin2_code":"1301.0",
    "gn:admin3_code":"130104.0",
    "gn:admin4_code":"13010404.0",
    "gn:asciiname":"Loma Firme",
    "gn:country_code":"DO",
    "gn:dem":662,
    "gn:feature_class":"P",
    "gn:feature_code":"PPL",
    "gn:name":"Loma Firme",
    "gn:population":0,
    "gn:timezone":"America/Santo_Domingo",
    "iso:country":"DO",
    "wof:name":"Loma Firme",
    "wof:placetype":"locality"
},
  "geometry": {"coordinates":[-70.64335,19.23067],"type":"Point"}
}