{
  "type": "Feature",
  "properties": {
    "gn:admin1_code":"25.0",
    "gn:admin2_code":"2505.0",
    "gn:admin3_code":"250502.0",
    "gn:admin4_code":"25050212.0",
    "gn:asciiname":"Rincon Llano",
    "gn:country_code":"DO",
    "gn:dem":798,
    "gn:feature_class":"P",
    "gn:feature_code":"PPL",
    "gn:name":"Rinc\u00f3n Llano",
    "gn:population":0,
    "gn:timezone":"America/Santo_Domingo",
    "iso:country":"DO",
    "wof:name":"Rincon Llano",
    "wof:placetype":"locality"
},
  "geometry": {"coordinates":[-71.06667,19.31667],"type":"Point"}
}