{
  "type": "Feature",
  "properties": {
    "iso:country":"DO",
    "name:deu_x_preferred":[
        "Pedro Garc\u00eda"
    ],
    "name:hun_x_preferred":[
        "Pedro Garc\u00eda"
    ],
    "name:ita_x_preferred":[
        "Pedro Garc\u00eda"
    ],
    "name:spa_x_preferred":[
        "Pedro Garc\u00eda"
    ],
    "name:unk_x_variant":[
        "Padre Garc\u00eda"
    ],
    "qs:gn_country":"DO",
    "qs:gn_fcode":"PPL",
    "qs:gn_pop":1457,
    "qs:name":"Pedro Garc\u00eda",
    "qs:name_adm0":"Rep\u00fablica Dominicana",
    "qs:name_adm1":"Santiago",
    "qs:photos":0,
    "qs:photos_1k":0,
    "qs:photos_9k":0,
    "qs:photos_9r":0,
    "qs:photos_all":0,
    "qs:photos_sr":0,
    "qs:placetype":"Town",
    "qs:pop_sr":"3",
    "qs:woe_adm0":23424800,
    "wd:wordcount":89,
    "wof:name":"Pedro Garc\u00eda",
    "wof:placetype":"locality",
    "wof:population":1457
},
  "geometry": {"coordinates":[-70.65255999999999,19.59202],"type":"Point"}
}