{
  "type": "Feature",
  "properties": {
    "gn:admin1_code":"25.0",
    "gn:admin2_code":"2505.0",
    "gn:admin3_code":"250501.0",
    "gn:admin4_code":"25050106.0",
    "gn:asciiname":"Pedregal",
    "gn:country_code":"DO",
    "gn:dem":581,
    "gn:feature_class":"P",
    "gn:feature_code":"PPL",
    "gn:name":"Pedregal",
    "gn:population":0,
    "gn:timezone":"America/Santo_Domingo",
    "iso:country":"DO",
    "wof:name":"Pedregal",
    "wof:placetype":"locality"
},
  "geometry": {"coordinates":[-70.89944,19.32587],"type":"Point"}
}