{
  "type": "Feature",
  "properties": {
    "gn:admin1_code":"25.0",
    "gn:admin2_code":"2505.0",
    "gn:admin3_code":"250501.0",
    "gn:admin4_code":"25050106.0",
    "gn:asciiname":"Pedregal",
    "gn:country_code":"DO",
    "gn:dem":581,
    "gn:feature_class":"P",
    "gn:feature_code":"PPL",
    "gn:name":"Pedregal",
    "gn:population":0,
    "gn:timezone":"America/Santo_Domingo",
    "iso:country":"DO",
    "name:ceb_x_preferred":[
        "Pedregal"
    ],
    "name:fra_x_preferred":[
        "Pedregal"
    ],
    "name:ita_x_preferred":[
        "Pedregal"
    ],
    "name:pol_x_preferred":[
        "Pedregal"
    ],
    "name:por_x_preferred":[
        "Pedregal"
    ],
    "name:spa_x_preferred":[
        "Pedregal"
    ],
    "name:srp_x_preferred":[
        "\u041f\u0435\u0434\u0440\u0435\u0433\u0430\u043b"
    ],
    "name:swe_x_preferred":[
        "Pedregal"
    ],
    "wof:name":"Pedregal",
    "wof:placetype":"locality"
},
  "geometry": {"coordinates":[-70.89944,19.32587],"type":"Point"}
}