{
  "type": "Feature",
  "properties": {
    "gn:admin1_code":"28.0",
    "gn:admin2_code":"801.0",
    "gn:admin3_code":"80103.0",
    "gn:admin4_code":"8010303.0",
    "gn:asciiname":"Los Camarones",
    "gn:country_code":"DO",
    "gn:dem":240,
    "gn:feature_class":"P",
    "gn:feature_code":"PPL",
    "gn:name":"Los Camarones",
    "gn:population":0,
    "gn:timezone":"America/Santo_Domingo",
    "iso:country":"DO",
    "wof:name":"Los Camarones",
    "wof:placetype":"locality"
},
  "geometry": {"coordinates":[-69.24145,18.8808],"type":"Point"}
}