{
  "type": "Feature",
  "properties": {
    "gn:admin1_code":"18.0",
    "gn:admin2_code":"1808.0",
    "gn:admin3_code":"180803.0",
    "gn:admin4_code":"18080301.0",
    "gn:asciiname":"La Jaiba",
    "gn:country_code":"DO",
    "gn:dem":92,
    "gn:feature_class":"P",
    "gn:feature_code":"PPL",
    "gn:name":"La Jaiba",
    "gn:population":0,
    "gn:timezone":"America/Santo_Domingo",
    "iso:country":"DO",
    "name:ita_x_preferred":[
        "La Jaiba"
    ],
    "name:und_x_variant":[
        "Jaiba",
        "La Jaiba"
    ],
    "name:urd_x_preferred":[
        "\u0644\u0627 \u062c\u0627\u06cc\u0628\u0627"
    ],
    "wof:name":"La Jaiba",
    "wof:placetype":"locality"
},
  "geometry": {"coordinates":[-71.14655,19.7984],"type":"Point"}
}