{
  "type": "Feature",
  "properties": {
    "gn:admin1_code":"33.0",
    "gn:admin2_code":"2104.0",
    "gn:admin3_code":"210401.0",
    "gn:admin4_code":"21040105.0",
    "gn:asciiname":"Los Jibaros",
    "gn:country_code":"DO",
    "gn:dem":585,
    "gn:feature_class":"P",
    "gn:feature_code":"PPL",
    "gn:name":"Los J\u00edbaros",
    "gn:population":0,
    "gn:timezone":"America/Santo_Domingo",
    "iso:country":"DO",
    "wof:name":"Los Jibaros",
    "wof:placetype":"locality"
},
  "geometry": {"coordinates":[-70.29545,18.51168],"type":"Point"}
}