{
  "type": "Feature",
  "properties": {
    "gn:admin1_code":"23.0",
    "gn:admin2_code":"2201.0",
    "gn:admin3_code":"220110.0",
    "gn:admin4_code":"22011003.0",
    "gn:asciiname":"La Alcantarillas",
    "gn:country_code":"DO",
    "gn:dem":499,
    "gn:feature_class":"P",
    "gn:feature_code":"PPL",
    "gn:name":"La Alcantarillas",
    "gn:population":0,
    "gn:timezone":"America/Santo_Domingo",
    "iso:country":"DO",
    "wof:name":"La Alcantarillas",
    "wof:placetype":"locality"
},
  "geometry": {"coordinates":[-71.36639,18.8322],"type":"Point"}
}