{
  "type": "Feature",
  "properties": {
    "gn:admin1_code":"33.0",
    "gn:admin2_code":"2101.0",
    "gn:admin3_code":"210101.0",
    "gn:admin4_code":"21010105.0",
    "gn:asciiname":"Najayo Arriba",
    "gn:country_code":"DO",
    "gn:dem":169,
    "gn:feature_class":"P",
    "gn:feature_code":"PPL",
    "gn:name":"Najayo Arriba",
    "gn:population":0,
    "gn:timezone":"America/Santo_Domingo",
    "iso:country":"DO",
    "wof:name":"Najayo Arriba",
    "wof:placetype":"locality"
},
  "geometry": {"coordinates":[-70.18231999999999,18.38702],"type":"Point"}
}