{
  "type": "Feature",
  "properties": {
    "gn:admin1_code":"24.0",
    "gn:admin2_code":"2306.0",
    "gn:admin3_code":"230601.0",
    "gn:admin4_code":"23060101.0",
    "gn:asciiname":"La Habitacion",
    "gn:country_code":"DO",
    "gn:dem":13,
    "gn:feature_class":"P",
    "gn:feature_code":"PPL",
    "gn:name":"La Habitaci\u00f3n",
    "gn:population":0,
    "gn:timezone":"America/Santo_Domingo",
    "iso:country":"DO",
    "wof:name":"La Habitacion",
    "wof:placetype":"locality"
},
  "geometry": {"coordinates":[-69.45028000000001,18.43376],"type":"Point"}
}