{
  "type": "Feature",
  "properties": {
    "gn:admin1_code":"29.0",
    "gn:admin2_code":"3003.0",
    "gn:admin3_code":"300301.0",
    "gn:admin4_code":"30030103.0",
    "gn:asciiname":"Los Aniles",
    "gn:country_code":"DO",
    "gn:dem":34,
    "gn:feature_class":"P",
    "gn:feature_code":"PPL",
    "gn:name":"Los A\u00f1iles",
    "gn:population":0,
    "gn:timezone":"America/Santo_Domingo",
    "iso:country":"DO",
    "wof:name":"Los Aniles",
    "wof:placetype":"locality"
},
  "geometry": {"coordinates":[-69.38333,18.98333],"type":"Point"}
}