{
  "type": "Feature",
  "properties": {
    "gn:admin1_code":"36.0",
    "gn:admin2_code":"3101.0",
    "gn:admin3_code":"310102.0",
    "gn:admin4_code":"31010204.0",
    "gn:asciiname":"Arroyo de Pedro",
    "gn:country_code":"DO",
    "gn:dem":1083,
    "gn:feature_class":"P",
    "gn:feature_code":"PPL",
    "gn:name":"Arroyo de Pedro",
    "gn:population":0,
    "gn:timezone":"America/Santo_Domingo",
    "iso:country":"DO",
    "name:und_x_variant":[
        "Arroyo Pedro",
        "Arroyo de Pedro"
    ],
    "wof:name":"Arroyo de Pedro",
    "wof:placetype":"locality"
},
  "geometry": {"coordinates":[-70.38643,18.60333],"type":"Point"}
}