{
  "type": "Feature",
  "properties": {
    "gn:admin1_code":"28.0",
    "gn:admin2_code":"802.0",
    "gn:admin3_code":"80202.0",
    "gn:admin4_code":"8020203.0",
    "gn:asciiname":"El Amarradero",
    "gn:country_code":"DO",
    "gn:dem":57,
    "gn:feature_class":"P",
    "gn:feature_code":"PPL",
    "gn:name":"El Amarradero",
    "gn:population":0,
    "gn:timezone":"America/Santo_Domingo",
    "iso:country":"DO",
    "name:und_x_variant":[
        "Los Amarraderos",
        "El Amarradero"
    ],
    "wof:name":"El Amarradero",
    "wof:placetype":"locality"
},
  "geometry": {"coordinates":[-69.01078000000001,18.95171],"type":"Point"}
}