{
  "type": "Feature",
  "properties": {
    "gn:admin1_code":"4.0",
    "gn:admin2_code":"501.0",
    "gn:admin3_code":"50101.0",
    "gn:admin4_code":"5010104.0",
    "gn:asciiname":"Los Ciruelos",
    "gn:country_code":"DO",
    "gn:dem":94,
    "gn:feature_class":"P",
    "gn:feature_code":"PPL",
    "gn:name":"Los Ciruelos",
    "gn:population":0,
    "gn:timezone":"America/Santo_Domingo",
    "iso:country":"DO",
    "name:und_x_variant":[
        "Las Ciruelas",
        "Los Ciruelos"
    ],
    "wof:name":"Los Ciruelos",
    "wof:placetype":"locality"
},
  "geometry": {"coordinates":[-71.53024000000001,19.58991],"type":"Point"}
}