{
  "type": "Feature",
  "properties": {
    "gn:admin1_code":"24.0",
    "gn:admin2_code":"2304.0",
    "gn:admin3_code":"230401.0",
    "gn:admin4_code":"23040103.0",
    "gn:asciiname":"Don Juan",
    "gn:country_code":"DO",
    "gn:dem":45,
    "gn:feature_class":"P",
    "gn:feature_code":"PPL",
    "gn:name":"Don Juan",
    "gn:population":0,
    "gn:timezone":"America/Santo_Domingo",
    "iso:country":"DO",
    "name:und_x_variant":[
        "Batey Don Juan",
        "Don Juan"
    ],
    "wof:name":"Don Juan",
    "wof:placetype":"locality"
},
  "geometry": {"coordinates":[-69.30186999999999,18.53882],"type":"Point"}
}