{
  "type": "Feature",
  "properties": {
    "gn:admin1_code":"24.0",
    "gn:admin2_code":"2306.0",
    "gn:admin3_code":"230601.0",
    "gn:admin4_code":"23060102.0",
    "gn:asciiname":"Los Higueeros",
    "gn:country_code":"DO",
    "gn:dem":32,
    "gn:feature_class":"P",
    "gn:feature_code":"PPL",
    "gn:name":"Los Hig\u00fceros",
    "gn:population":0,
    "gn:timezone":"America/Santo_Domingo",
    "iso:country":"DO",
    "wof:name":"Los Higueeros",
    "wof:placetype":"locality"
},
  "geometry": {"coordinates":[-69.47639000000001,18.45317],"type":"Point"}
}