{
  "type": "Feature",
  "properties": {
    "gn:admin1_code":"36.0",
    "gn:admin2_code":"3101.0",
    "gn:admin3_code":"310102.0",
    "gn:admin4_code":"31010204.0",
    "gn:asciiname":"La Cuchilla de Pio",
    "gn:country_code":"DO",
    "gn:dem":780,
    "gn:feature_class":"P",
    "gn:feature_code":"PPL",
    "gn:name":"La Cuchilla de P\u00edo",
    "gn:population":0,
    "gn:timezone":"America/Santo_Domingo",
    "iso:country":"DO",
    "wof:name":"La Cuchilla de Pio",
    "wof:placetype":"locality"
},
  "geometry": {"coordinates":[-70.39191,18.55674],"type":"Point"}
}