{
  "type": "Feature",
  "properties": {
    "gn:admin1_code":"26.0",
    "gn:admin2_code":"2601.0",
    "gn:admin3_code":"260101.0",
    "gn:admin4_code":"26010110.0",
    "gn:asciiname":"Caimito",
    "gn:country_code":"DO",
    "gn:dem":168,
    "gn:feature_class":"P",
    "gn:feature_code":"PPL",
    "gn:name":"Caimito",
    "gn:population":0,
    "gn:timezone":"America/Santo_Domingo",
    "iso:country":"DO",
    "name:ceb_x_preferred":[
        "Caimito"
    ],
    "name:ita_x_preferred":[
        "Caimito"
    ],
    "name:nld_x_preferred":[
        "Caimito"
    ],
    "name:que_x_preferred":[
        "Caimito"
    ],
    "name:spa_x_preferred":[
        "Caimito"
    ],
    "name:swe_x_preferred":[
        "Caimito"
    ],
    "wof:name":"Caimito",
    "wof:placetype":"locality"
},
  "geometry": {"coordinates":[-71.28259,19.53211],"type":"Point"}
}