{
  "type": "Feature",
  "properties": {
    "gn:admin1_code":"31.0",
    "gn:admin2_code":"2801.0",
    "gn:admin3_code":"280105.0",
    "gn:admin4_code":"28010502.0",
    "gn:asciiname":"Jayaco Arriba",
    "gn:country_code":"DO",
    "gn:dem":168,
    "gn:feature_class":"P",
    "gn:feature_code":"PPL",
    "gn:name":"Jayaco Arriba",
    "gn:population":0,
    "gn:timezone":"America/Santo_Domingo",
    "iso:country":"DO",
    "name:und_x_variant":[
        "Jayaco",
        "Jayaco Arriba"
    ],
    "wof:name":"Jayaco Arriba",
    "wof:placetype":"locality"
},
  "geometry": {"coordinates":[-70.42270000000001,19.00141],"type":"Point"}
}