{
  "type": "Feature",
  "properties": {
    "gn:admin1_code":"4.0",
    "gn:admin2_code":"504.0",
    "gn:admin3_code":"50401.0",
    "gn:admin4_code":"5040103.0",
    "gn:asciiname":"Tierra Sucia",
    "gn:country_code":"DO",
    "gn:dem":616,
    "gn:feature_class":"P",
    "gn:feature_code":"PPL",
    "gn:name":"Tierra Sucia",
    "gn:population":0,
    "gn:timezone":"America/Santo_Domingo",
    "iso:country":"DO",
    "wof:name":"Tierra Sucia",
    "wof:placetype":"locality"
},
  "geometry": {"coordinates":[-71.69181999999998,19.33268],"type":"Point"}
}