{
  "type": "Feature",
  "properties": {
    "gn:admin1_code":"23.0",
    "gn:admin2_code":"2206.0",
    "gn:admin3_code":"220601.0",
    "gn:admin4_code":"22060102.0",
    "gn:asciiname":"Canada de Palma",
    "gn:country_code":"DO",
    "gn:dem":539,
    "gn:feature_class":"P",
    "gn:feature_code":"PPL",
    "gn:name":"Ca\u00f1ada de Palma",
    "gn:population":0,
    "gn:timezone":"America/Santo_Domingo",
    "iso:country":"DO",
    "wof:name":"Canada de Palma",
    "wof:placetype":"locality"
},
  "geometry": {"coordinates":[-71.24727,18.69485],"type":"Point"}
}