{
  "type": "Feature",
  "properties": {
    "gn:admin1_code":"14.0",
    "gn:admin2_code":"1404.0",
    "gn:admin3_code":"140401.0",
    "gn:admin4_code":"14040102.0",
    "gn:asciiname":"El Guano",
    "gn:country_code":"DO",
    "gn:dem":172,
    "gn:feature_class":"P",
    "gn:feature_code":"PPL",
    "gn:name":"El Guano",
    "gn:population":0,
    "gn:timezone":"America/Santo_Domingo",
    "iso:country":"DO",
    "wof:name":"El Guano",
    "wof:placetype":"locality"
},
  "geometry": {"coordinates":[-70.10727,19.54104],"type":"Point"}
}