{
  "type": "Feature",
  "properties": {
    "gn:admin1_code":"24.0",
    "gn:admin2_code":"2302.0",
    "gn:admin3_code":"230201.0",
    "gn:admin4_code":"23020104.0",
    "gn:asciiname":"El Jengibral",
    "gn:country_code":"DO",
    "gn:dem":21,
    "gn:feature_class":"P",
    "gn:feature_code":"PPL",
    "gn:name":"El Jengibral",
    "gn:population":0,
    "gn:timezone":"America/Santo_Domingo",
    "iso:country":"DO",
    "name:und_x_variant":[
        "Gengibral",
        "El Gengibral",
        "Jengibral",
        "El Jengibre",
        "El Jengibral"
    ],
    "wof:name":"El Jengibral",
    "wof:placetype":"locality"
},
  "geometry": {"coordinates":[-69.40858,18.6205],"type":"Point"}
}