{
  "type": "Feature",
  "properties": {
    "gn:admin1_code":"14.0",
    "gn:admin2_code":"1401.0",
    "gn:admin3_code":"140101.0",
    "gn:admin4_code":"14010101.0",
    "gn:asciiname":"San Jose de Villa",
    "gn:country_code":"DO",
    "gn:dem":11,
    "gn:feature_class":"P",
    "gn:feature_code":"PPL",
    "gn:name":"San Jos\u00e9 de Villa",
    "gn:population":0,
    "gn:timezone":"America/Santo_Domingo",
    "iso:country":"DO",
    "wof:name":"San Jose de Villa",
    "wof:placetype":"locality"
},
  "geometry": {"coordinates":[-69.84851,19.36675],"type":"Point"}
}