{
  "type": "Feature",
  "properties": {
    "gn:admin1_code":"37.0",
    "gn:admin2_code":"3205.0",
    "gn:admin3_code":"320501.0",
    "gn:admin4_code":"32050103.0",
    "gn:asciiname":"El Aji",
    "gn:country_code":"DO",
    "gn:dem":32,
    "gn:feature_class":"P",
    "gn:feature_code":"PPL",
    "gn:name":"El Aj\u00ed",
    "gn:population":0,
    "gn:timezone":"America/Santo_Domingo",
    "iso:country":"DO",
    "wof:name":"El Aji",
    "wof:placetype":"locality"
},
  "geometry": {"coordinates":[-69.65312,18.56043],"type":"Point"}
}