{
  "type": "Feature",
  "properties": {
    "gn:admin1_code":"24.0",
    "gn:admin2_code":"2305.0",
    "gn:admin3_code":"230501.0",
    "gn:admin4_code":"23050107.0",
    "gn:asciiname":"Barbadillo",
    "gn:country_code":"DO",
    "gn:dem":30,
    "gn:feature_class":"P",
    "gn:feature_code":"PPL",
    "gn:name":"Barbadillo",
    "gn:population":0,
    "gn:timezone":"America/Santo_Domingo",
    "iso:country":"DO",
    "wof:name":"Barbadillo",
    "wof:placetype":"locality"
},
  "geometry": {"coordinates":[-69.46725000000001,18.58564],"type":"Point"}
}