{
  "type": "Feature",
  "properties": {
    "gn:admin1_code":"24.0",
    "gn:admin2_code":"2305.0",
    "gn:admin3_code":"230501.0",
    "gn:admin4_code":"23050107.0",
    "gn:asciiname":"Barbadillo",
    "gn:country_code":"DO",
    "gn:dem":30,
    "gn:feature_class":"P",
    "gn:feature_code":"PPL",
    "gn:name":"Barbadillo",
    "gn:population":0,
    "gn:timezone":"America/Santo_Domingo",
    "iso:country":"DO",
    "name:arg_x_preferred":[
        "Barbadillo"
    ],
    "name:ast_x_preferred":[
        "Barbadillo"
    ],
    "name:cat_x_preferred":[
        "Barbadillo"
    ],
    "name:ceb_x_preferred":[
        "Barbadillo"
    ],
    "name:deu_x_preferred":[
        "Barbadillo"
    ],
    "name:eus_x_preferred":[
        "Barbadillo"
    ],
    "name:fra_x_preferred":[
        "Barbadillo"
    ],
    "name:haw_x_preferred":[
        "Barbadillo"
    ],
    "name:hun_x_preferred":[
        "Barbadillo"
    ],
    "name:ina_x_preferred":[
        "Barbadillo"
    ],
    "name:ita_x_preferred":[
        "Barbadillo"
    ],
    "name:kaz_x_preferred":[
        "\u0411\u0430\u0440\u0431\u0430\u0434\u0438\u043b\u044c\u043e"
    ],
    "name:msa_x_preferred":[
        "Barbadillo"
    ],
    "name:oci_x_preferred":[
        "Barbadillo"
    ],
    "name:pol_x_preferred":[
        "Barbadillo"
    ],
    "name:por_x_preferred":[
        "Barbadillo"
    ],
    "name:rus_x_preferred":[
        "\u0411\u0430\u0440\u0431\u0430\u0434\u0438\u043b\u044c\u043e"
    ],
    "name:spa_x_preferred":[
        "Barbadillo"
    ],
    "name:swe_x_preferred":[
        "Barbadillo"
    ],
    "name:ukr_x_preferred":[
        "\u0411\u0430\u0440\u0431\u0430\u0434\u0456\u043b\u044c\u0439\u043e"
    ],
    "name:vie_x_preferred":[
        "Barbadillo"
    ],
    "name:war_x_preferred":[
        "Barbadillo"
    ],
    "name:zho_x_preferred":[
        "\u5df4\u5c14\u74e6\u8fea\u7565"
    ],
    "wof:name":"Barbadillo",
    "wof:placetype":"locality"
},
  "geometry": {"coordinates":[-69.46725000000001,18.58564],"type":"Point"}
}