{
  "type": "Feature",
  "properties": {
    "gn:admin1_code":"29.0",
    "gn:admin2_code":"3001.0",
    "gn:admin3_code":"300103.0",
    "gn:admin4_code":"30010302.0",
    "gn:asciiname":"La Pena",
    "gn:country_code":"DO",
    "gn:dem":75,
    "gn:feature_class":"P",
    "gn:feature_code":"PPL",
    "gn:name":"La Pe\u00f1a",
    "gn:population":0,
    "gn:timezone":"America/Santo_Domingo",
    "iso:country":"DO",
    "wof:name":"La Pena",
    "wof:placetype":"locality"
},
  "geometry": {"coordinates":[-69.27065,18.72166],"type":"Point"}
}