{
  "type": "Feature",
  "properties": {
    "gn:admin1_code":"32.0",
    "gn:admin2_code":"2904.0",
    "gn:admin3_code":"290401.0",
    "gn:admin4_code":"29040106.0",
    "gn:asciiname":"Colorado",
    "gn:country_code":"DO",
    "gn:dem":284,
    "gn:feature_class":"P",
    "gn:feature_code":"PPL",
    "gn:name":"Colorado",
    "gn:population":0,
    "gn:timezone":"America/Santo_Domingo",
    "iso:country":"DO",
    "wof:name":"Colorado",
    "wof:placetype":"locality"
},
  "geometry": {"coordinates":[-70.14386999999999,18.74952],"type":"Point"}
}