{
  "type": "Feature",
  "properties": {
    "gn:admin1_code":"15.0",
    "gn:admin2_code":"1503.0",
    "gn:admin3_code":"150301.0",
    "gn:admin4_code":"15030103.0",
    "gn:asciiname":"Pozo Negro",
    "gn:country_code":"DO",
    "gn:dem":103,
    "gn:feature_class":"P",
    "gn:feature_code":"PPL",
    "gn:name":"Pozo Negro",
    "gn:population":0,
    "gn:timezone":"America/Santo_Domingo",
    "iso:country":"DO",
    "wof:name":"Pozo Negro",
    "wof:placetype":"locality"
},
  "geometry": {"coordinates":[-71.44441999999999,19.55197],"type":"Point"}
}