{
  "type": "Feature",
  "properties": {
    "gn:admin1_code":"33.0",
    "gn:admin2_code":"2101.0",
    "gn:admin3_code":"210101.0",
    "gn:admin4_code":"21010107.0",
    "gn:asciiname":"Higueereta",
    "gn:country_code":"DO",
    "gn:dem":93,
    "gn:feature_class":"P",
    "gn:feature_code":"PPL",
    "gn:name":"Hig\u00fcereta",
    "gn:population":0,
    "gn:timezone":"America/Santo_Domingo",
    "iso:country":"DO",
    "wof:name":"Higueereta",
    "wof:placetype":"locality"
},
  "geometry": {"coordinates":[-70.11542,18.44131],"type":"Point"}
}