{
  "type": "Feature",
  "properties": {
    "gn:admin1_code":"15.0",
    "gn:asciiname":"El Oregano",
    "gn:country_code":"DO",
    "gn:dem":139,
    "gn:feature_class":"P",
    "gn:feature_code":"PPL",
    "gn:name":"El Or\u00e9gano",
    "gn:population":0,
    "gn:timezone":"America/Santo_Domingo",
    "iso:country":"DO",
    "wof:name":"El Oregano",
    "wof:placetype":"locality"
},
  "geometry": {"coordinates":[-71.35765000000001,19.53838],"type":"Point"}
}