{
  "type": "Feature",
  "properties": {
    "gn:admin1_code":"25.0",
    "gn:admin2_code":"2501.0",
    "gn:admin3_code":"250104.0",
    "gn:admin4_code":"25010401.0",
    "gn:asciiname":"Arroyo Arriba",
    "gn:country_code":"DO",
    "gn:dem":271,
    "gn:feature_class":"P",
    "gn:feature_code":"PPL",
    "gn:name":"Arroyo Arriba",
    "gn:population":0,
    "gn:timezone":"America/Santo_Domingo",
    "iso:country":"DO",
    "wof:name":"Arroyo Arriba",
    "wof:placetype":"locality"
},
  "geometry": {"coordinates":[-70.70044,19.31883],"type":"Point"}
}