{
  "type": "Feature",
  "properties": {
    "gn:admin1_code":"36.0",
    "gn:admin2_code":"3102.0",
    "gn:admin3_code":"310201.0",
    "gn:admin4_code":"31020102.0",
    "gn:asciiname":"Los Naranjos",
    "gn:country_code":"DO",
    "gn:dem":1292,
    "gn:feature_class":"P",
    "gn:feature_code":"PPL",
    "gn:name":"Los Naranjos",
    "gn:population":0,
    "gn:timezone":"America/Santo_Domingo",
    "iso:country":"DO",
    "name:bre_x_preferred":[
        "Los Naranjos"
    ],
    "name:ceb_x_preferred":[
        "Los Naranjos"
    ],
    "name:deu_x_preferred":[
        "Los Naranjos"
    ],
    "name:spa_x_preferred":[
        "Los Naranjos"
    ],
    "name:swe_x_preferred":[
        "Los Naranjos"
    ],
    "wof:name":"Los Naranjos",
    "wof:placetype":"locality"
},
  "geometry": {"coordinates":[-70.55619,18.65226],"type":"Point"}
}