{
  "type": "Feature",
  "properties": {
    "gn:admin1_code":"23.0",
    "gn:admin2_code":"2201.0",
    "gn:admin3_code":"220107.0",
    "gn:admin4_code":"22010703.0",
    "gn:asciiname":"Los Bancos",
    "gn:country_code":"DO",
    "gn:dem":307,
    "gn:feature_class":"P",
    "gn:feature_code":"PPL",
    "gn:name":"Los Bancos",
    "gn:population":0,
    "gn:timezone":"America/Santo_Domingo",
    "iso:country":"DO",
    "wof:name":"Los Bancos",
    "wof:placetype":"locality"
},
  "geometry": {"coordinates":[-71.05919,18.685],"type":"Point"}
}