{
  "type": "Feature",
  "properties": {
    "gn:admin1_code":"30.0",
    "gn:admin2_code":"1301.0",
    "gn:admin3_code":"130102.0",
    "gn:admin4_code":"13010202.0",
    "gn:asciiname":"Arroyo Hondo Abajo",
    "gn:country_code":"DO",
    "gn:dem":166,
    "gn:feature_class":"P",
    "gn:feature_code":"PPL",
    "gn:name":"Arroyo Hondo Abajo",
    "gn:population":0,
    "gn:timezone":"America/Santo_Domingo",
    "iso:country":"DO",
    "name:und_x_variant":[
        "Arroyo Hondo",
        "Arroyo Hondo Abajo"
    ],
    "wof:name":"Arroyo Hondo Abajo",
    "wof:placetype":"locality"
},
  "geometry": {"coordinates":[-70.55885000000001,19.33678],"type":"Point"}
}