{
  "type": "Feature",
  "properties": {
    "gn:admin1_code":"25.0",
    "gn:admin2_code":"2505.0",
    "gn:admin3_code":"250501.0",
    "gn:admin4_code":"25050108.0",
    "gn:asciiname":"Los Llanos",
    "gn:country_code":"DO",
    "gn:dem":609,
    "gn:feature_class":"P",
    "gn:feature_code":"PPL",
    "gn:name":"Los Llanos",
    "gn:population":0,
    "gn:timezone":"America/Santo_Domingo",
    "iso:country":"DO",
    "wof:name":"Los Llanos",
    "wof:placetype":"locality"
},
  "geometry": {"coordinates":[-70.98623000000001,19.31538],"type":"Point"}
}