{
  "type": "Feature",
  "properties": {
    "gn:admin1_code":"24.0",
    "gn:admin2_code":"2304.0",
    "gn:admin3_code":"230401.0",
    "gn:admin4_code":"23040103.0",
    "gn:asciiname":"Consuelito",
    "gn:country_code":"DO",
    "gn:dem":48,
    "gn:feature_class":"P",
    "gn:feature_code":"PPL",
    "gn:name":"Consuelito",
    "gn:population":0,
    "gn:timezone":"America/Santo_Domingo",
    "iso:country":"DO",
    "name:und_x_variant":[
        "Batey Consuelito",
        "Consuelito"
    ],
    "wof:name":"Consuelito",
    "wof:placetype":"locality"
},
  "geometry": {"coordinates":[-69.2577,18.61237],"type":"Point"}
}