{
  "type": "Feature",
  "properties": {
    "gn:admin1_code":"29.0",
    "gn:admin2_code":"3001.0",
    "gn:admin3_code":"300101.0",
    "gn:admin4_code":"30010103.0",
    "gn:asciiname":"Arroyo Grande",
    "gn:country_code":"DO",
    "gn:dem":140,
    "gn:feature_class":"P",
    "gn:feature_code":"PPL",
    "gn:name":"Arroyo Grande",
    "gn:population":0,
    "gn:timezone":"America/Santo_Domingo",
    "iso:country":"DO",
    "wof:name":"Arroyo Grande",
    "wof:placetype":"locality"
},
  "geometry": {"coordinates":[-69.27155,18.79664],"type":"Point"}
}