{
  "type": "Feature",
  "properties": {
    "gn:admin1_code":"15.0",
    "gn:admin2_code":"1503.0",
    "gn:admin3_code":"150301.0",
    "gn:admin4_code":"15030103.0",
    "gn:asciiname":"El Pocito",
    "gn:country_code":"DO",
    "gn:dem":48,
    "gn:feature_class":"P",
    "gn:feature_code":"PPL",
    "gn:name":"El Pocito",
    "gn:population":0,
    "gn:timezone":"America/Santo_Domingo",
    "iso:country":"DO",
    "name:und_x_variant":[
        "Pocitos",
        "El Posito",
        "El Pocito"
    ],
    "wof:name":"El Pocito",
    "wof:placetype":"locality"
},
  "geometry": {"coordinates":[-71.422,19.66019],"type":"Point"}
}