{
  "type": "Feature",
  "properties": {
    "gn:admin1_code":"29.0",
    "gn:admin2_code":"3001.0",
    "gn:admin3_code":"300102.0",
    "gn:admin4_code":"30010202.0",
    "gn:asciiname":"Palmarejo",
    "gn:country_code":"DO",
    "gn:dem":185,
    "gn:feature_class":"P",
    "gn:feature_code":"PPL",
    "gn:name":"Palmarejo",
    "gn:population":0,
    "gn:timezone":"America/Santo_Domingo",
    "iso:country":"DO",
    "wof:name":"Palmarejo",
    "wof:placetype":"locality"
},
  "geometry": {"coordinates":[-69.40000000000001,18.81667],"type":"Point"}
}