{
  "type": "Feature",
  "properties": {
    "gn:admin1_code":"11.0",
    "gn:admin2_code":"702.0",
    "gn:admin3_code":"70201.0",
    "gn:admin4_code":"7020102.0",
    "gn:asciiname":"Las Canitas",
    "gn:country_code":"DO",
    "gn:dem":372,
    "gn:feature_class":"P",
    "gn:feature_code":"PPL",
    "gn:name":"Las Ca\u00f1itas",
    "gn:population":0,
    "gn:timezone":"America/Santo_Domingo",
    "iso:country":"DO",
    "wof:name":"Las Canitas",
    "wof:placetype":"locality"
},
  "geometry": {"coordinates":[-71.64860999999998,19.06141],"type":"Point"}
}