{
  "type": "Feature",
  "properties": {
    "gn:admin1_code":"21.0",
    "gn:admin2_code":"2401.0",
    "gn:admin3_code":"240103.0",
    "gn:admin4_code":"24010303.0",
    "gn:asciiname":"Los Palmaritos",
    "gn:country_code":"DO",
    "gn:dem":221,
    "gn:feature_class":"P",
    "gn:feature_code":"PPL",
    "gn:name":"Los Palmaritos",
    "gn:population":0,
    "gn:timezone":"America/Santo_Domingo",
    "iso:country":"DO",
    "wof:name":"Los Palmaritos",
    "wof:placetype":"locality"
},
  "geometry": {"coordinates":[-70.28443,19.01689],"type":"Point"}
}