{
  "type": "Feature",
  "properties": {
    "gn:admin1_code":"2.0",
    "gn:admin2_code":"302.0",
    "gn:admin3_code":"30202.0",
    "gn:admin4_code":"3020202.0",
    "gn:asciiname":"El Palmar de la Jurunela",
    "gn:country_code":"DO",
    "gn:dem":7,
    "gn:feature_class":"P",
    "gn:feature_code":"PPL",
    "gn:name":"El Palmar de la Jurunela",
    "gn:population":0,
    "gn:timezone":"America/Santo_Domingo",
    "iso:country":"DO",
    "wof:name":"El Palmar de la Jurunela",
    "wof:placetype":"locality"
},
  "geometry": {"coordinates":[-71.33431999999998,18.48561],"type":"Point"}
}