{
  "type": "Feature",
  "properties": {
    "gn:admin1_code":"25.0",
    "gn:admin2_code":"2501.0",
    "gn:admin3_code":"250106.0",
    "gn:admin4_code":"25010606.0",
    "gn:asciiname":"Jacagua Arriba",
    "gn:country_code":"DO",
    "gn:dem":255,
    "gn:feature_class":"P",
    "gn:feature_code":"PPL",
    "gn:name":"Jacagua Arriba",
    "gn:population":0,
    "gn:timezone":"America/Santo_Domingo",
    "iso:country":"DO",
    "wof:name":"Jacagua Arriba",
    "wof:placetype":"locality"
},
  "geometry": {"coordinates":[-70.67888000000001,19.51799],"type":"Point"}
}