{
  "type": "Feature",
  "properties": {
    "gn:admin1_code":"30.0",
    "gn:admin2_code":"1302.0",
    "gn:admin3_code":"130201.0",
    "gn:admin4_code":"13020101.0",
    "gn:asciiname":"El Arenoso",
    "gn:country_code":"DO",
    "gn:dem":1162,
    "gn:feature_class":"P",
    "gn:feature_code":"PPL",
    "gn:name":"El Arenoso",
    "gn:population":0,
    "gn:timezone":"America/Santo_Domingo",
    "iso:country":"DO",
    "wof:name":"El Arenoso",
    "wof:placetype":"locality"
},
  "geometry": {"coordinates":[-70.75308000000003,18.90858],"type":"Point"}
}