{
  "type": "Feature",
  "properties": {
    "gn:admin1_code":"8.0",
    "gn:admin2_code":"901.0",
    "gn:admin3_code":"90102.0",
    "gn:admin4_code":"9010204.0",
    "gn:asciiname":"La Llanada",
    "gn:country_code":"DO",
    "gn:dem":719,
    "gn:feature_class":"P",
    "gn:feature_code":"PPL",
    "gn:name":"La Llanada",
    "gn:population":0,
    "gn:timezone":"America/Santo_Domingo",
    "iso:country":"DO",
    "name:ceb_x_preferred":[
        "La Llanada"
    ],
    "name:fra_x_preferred":[
        "La Llanada"
    ],
    "name:ita_x_preferred":[
        "La Llanada"
    ],
    "name:kat_x_preferred":[
        "\u10da\u10d0-\u10da\u10d8\u10d0\u10dc\u10d0\u10d3\u10d0"
    ],
    "name:msa_x_preferred":[
        "La Llanada"
    ],
    "name:nld_x_preferred":[
        "La Llanada"
    ],
    "name:por_x_preferred":[
        "La Llanada"
    ],
    "name:spa_x_preferred":[
        "La Llanada"
    ],
    "name:swe_x_preferred":[
        "La Llanada"
    ],
    "name:tgl_x_preferred":[
        "La Llanada"
    ],
    "name:urd_x_preferred":[
        "\u0644\u0627 \u0644\u0627\u0646\u0627\u0688\u0627"
    ],
    "name:vie_x_preferred":[
        "La Llanada"
    ],
    "name:war_x_preferred":[
        "La Llanada"
    ],
    "name:zho_x_preferred":[
        "\u62c9\u5229\u4e9e\u7d0d\u9054"
    ],
    "wof:name":"La Llanada",
    "wof:placetype":"locality"
},
  "geometry": {"coordinates":[-70.47646999999998,19.50371],"type":"Point"}
}