{
  "type": "Feature",
  "properties": {
    "gn:admin1_code":"8.0",
    "gn:admin2_code":"901.0",
    "gn:admin3_code":"90102.0",
    "gn:admin4_code":"9010204.0",
    "gn:asciiname":"La Llanada",
    "gn:country_code":"DO",
    "gn:dem":719,
    "gn:feature_class":"P",
    "gn:feature_code":"PPL",
    "gn:name":"La Llanada",
    "gn:population":0,
    "gn:timezone":"America/Santo_Domingo",
    "iso:country":"DO",
    "wof:name":"La Llanada",
    "wof:placetype":"locality"
},
  "geometry": {"coordinates":[-70.47646999999998,19.50371],"type":"Point"}
}