{
  "type": "Feature",
  "properties": {
    "gn:admin1_code":"33.0",
    "gn:admin2_code":"2106.0",
    "gn:admin3_code":"210601.0",
    "gn:admin4_code":"21060104.0",
    "gn:asciiname":"El Maizal",
    "gn:country_code":"DO",
    "gn:dem":123,
    "gn:feature_class":"P",
    "gn:feature_code":"PPL",
    "gn:name":"El Maizal",
    "gn:population":0,
    "gn:timezone":"America/Santo_Domingo",
    "iso:country":"DO",
    "name:und_x_variant":[
        "Maizal",
        "El Maizal"
    ],
    "wof:name":"El Maizal",
    "wof:placetype":"locality"
},
  "geometry": {"coordinates":[-70.28404999999999,18.38595],"type":"Point"}
}