{
  "type": "Feature",
  "properties": {
    "gn:admin1_code":"28.0",
    "gn:admin2_code":"801.0",
    "gn:admin3_code":"80101.0",
    "gn:admin4_code":"8010103.0",
    "gn:asciiname":"Batey Copey",
    "gn:country_code":"DO",
    "gn:dem":86,
    "gn:feature_class":"P",
    "gn:feature_code":"PPL",
    "gn:name":"Batey Copey",
    "gn:population":0,
    "gn:timezone":"America/Santo_Domingo",
    "iso:country":"DO",
    "name:und_x_variant":[
        "Copey",
        "Batey Copey"
    ],
    "wof:name":"Batey Copey",
    "wof:placetype":"locality"
},
  "geometry": {"coordinates":[-69.03740999999999,18.58939],"type":"Point"}
}