{
  "type": "Feature",
  "properties": {
    "gn:admin1_code":"23.0",
    "gn:admin2_code":"2201.0",
    "gn:admin3_code":"220111.0",
    "gn:admin4_code":"22011106.0",
    "gn:asciiname":"La Canita",
    "gn:country_code":"DO",
    "gn:dem":550,
    "gn:feature_class":"P",
    "gn:feature_code":"PPL",
    "gn:name":"La Ca\u00f1ita",
    "gn:population":0,
    "gn:timezone":"America/Santo_Domingo",
    "iso:country":"DO",
    "wof:name":"La Canita",
    "wof:placetype":"locality"
},
  "geometry": {"coordinates":[-71.13333,18.85],"type":"Point"}
}