{
  "type": "Feature",
  "properties": {
    "gn:country":"DO",
    "gn:fcode":"PPL",
    "gn:pop":5135,
    "iso:country":"DO",
    "name:eng_x_preferred":[
        "Sabana Iglesia"
    ],
    "name:fra_x_preferred":[
        "Sabana Iglesia"
    ],
    "name:ita_x_preferred":[
        "Sabana Iglesia"
    ],
    "name:jpn_x_preferred":[
        "\u30b5\u30d0\u30ca\u30fb\u30a4\u30b0\u30ec\u30b7\u30a2"
    ],
    "name:nan_x_preferred":[
        "Sabana Iglesia"
    ],
    "name:nld_x_preferred":[
        "Sabana Iglesia"
    ],
    "name:por_x_preferred":[
        "Sabana Iglesia"
    ],
    "name:spa_x_preferred":[
        "Sabana Iglesia"
    ],
    "name:swe_x_preferred":[
        "Sabana Iglesia"
    ],
    "name:urd_x_preferred":[
        "\u0633\u0628\u0627\u0646\u06c1 \u0627\u06af\u0644\u0633\u06cc\u06c1"
    ],
    "name:zho_x_preferred":[
        "\u85a9\u74e6\u7d0d\u4f0a\u683c\u840a\u897f\u4e9e"
    ],
    "qs:name":"Sabana Iglesia",
    "qs:photos_9r":0,
    "qs:photos_sr":0,
    "qs:pop_sr":"5",
    "wd:wordcount":22,
    "wof:name":"Sabana Iglesia",
    "wof:placetype":"locality",
    "wof:population":5135
},
  "geometry": {"coordinates":[-70.75991999999999,19.32114],"type":"Point"}
}