{
  "type": "Feature",
  "properties": {
    "gn:admin1_code":"21.0",
    "gn:admin2_code":"2401.0",
    "gn:admin3_code":"240101.0",
    "gn:admin4_code":"24010103.0",
    "gn:asciiname":"Los Cacaos",
    "gn:country_code":"DO",
    "gn:dem":136,
    "gn:feature_class":"P",
    "gn:feature_code":"PPL",
    "gn:name":"Los Cacaos",
    "gn:population":0,
    "gn:timezone":"America/Santo_Domingo",
    "iso:country":"DO",
    "name:ita_x_preferred":[
        "Los Cacaos"
    ],
    "name:por_x_preferred":[
        "Los Cacaos"
    ],
    "name:spa_x_preferred":[
        "Los Cacaos"
    ],
    "name:zho_x_preferred":[
        "\u6d1b\u65af\u5361\u8003\u65af"
    ],
    "wof:name":"Los Cacaos",
    "wof:placetype":"locality"
},
  "geometry": {"coordinates":[-70.19225,18.93786],"type":"Point"}
}