{
  "type": "Feature",
  "properties": {
    "gn:admin1_code":"32.0",
    "gn:admin2_code":"2902.0",
    "gn:admin3_code":"290201.0",
    "gn:admin4_code":"29020103.0",
    "gn:asciiname":"Paso Los Anegadizos",
    "gn:country_code":"DO",
    "gn:dem":33,
    "gn:feature_class":"P",
    "gn:feature_code":"PPL",
    "gn:name":"Paso Los Anegadizos",
    "gn:population":0,
    "gn:timezone":"America/Santo_Domingo",
    "iso:country":"DO",
    "wof:name":"Paso Los Anegadizos",
    "wof:placetype":"locality"
},
  "geometry": {"coordinates":[-69.68673000000001,18.69179],"type":"Point"}
}