{
  "type": "Feature",
  "properties": {
    "gn:country":"DO",
    "gn:fcode":"PPLX",
    "gn:population":0,
    "iso:country":"DO",
    "name:spa_x_preferred":[
        "Los Mameyes"
    ],
    "qs:gn_adm0_cc":"DO",
    "qs:gn_fcode":"PPLX",
    "qs:gn_local":7874116,
    "qs:gn_nam_loc":"limoncillar",
    "qs:gn_namadm1":"37",
    "qs:gn_name":"Los Mameyes",
    "qs:local_max":5287,
    "qs:local_sum":19037,
    "qs:localhoods":30,
    "qs:name":"Los Mameyes",
    "qs:name_adm0":"Rep\u00fablica Dominicana",
    "qs:name_adm1":"Santo Domingo",
    "qs:name_local":"Santo Domingo",
    "qs:photo_max":81,
    "qs:photo_sum":197,
    "qs:placetype":"Suburb",
    "qs:quad_count":16,
    "qs:woe_adm0":23424800,
    "qs:woe_adm1":28358196,
    "qs:woe_adm2":0,
    "qs:woe_lau":0,
    "qs:woe_local":76456,
    "qs:woe_ver":"7.10.0",
    "qs_pg:aaroncc":"DO",
    "qs_pg:gn_country":"DO",
    "qs_pg:gn_fcode":"PPLX",
    "qs_pg:gn_pop":0,
    "qs_pg:name":"Los Mameyes",
    "qs_pg:name_adm0":"Rep\u00fablica Dominicana",
    "qs_pg:name_adm1":"Santo Domingo",
    "qs_pg:photos":202,
    "qs_pg:photos_1k":41,
    "qs_pg:photos_9k":1,
    "qs_pg:photos_9r":4,
    "qs_pg:photos_all":202,
    "qs_pg:photos_sr":4,
    "qs_pg:pop_sr":0,
    "qs_pg:qs_pg_placetype":"neighbourhood",
    "qs_pg:qs_pg_placetype_gp":"Suburb",
    "qs_pg:woe_adm0":23424800,
    "wof:lang":[
        "spa"
    ],
    "wof:name":"Los Mameyes",
    "wof:placetype":"neighbourhood"
},
  "geometry": {"coordinates":[-69.837571,18.470121],"type":"Point"}
}