{
  "type": "Feature",
  "properties": {
    "gn:admin1_code":"9.0",
    "gn:admin2_code":"1001.0",
    "gn:admin3_code":"100102.0",
    "gn:admin4_code":"10010202.0",
    "gn:asciiname":"Miguelito",
    "gn:country_code":"DO",
    "gn:dem":190,
    "gn:feature_class":"P",
    "gn:feature_code":"PPL",
    "gn:name":"Miguelito",
    "gn:population":0,
    "gn:timezone":"America/Santo_Domingo",
    "iso:country":"DO",
    "wof:name":"Miguelito",
    "wof:placetype":"locality"
},
  "geometry": {"coordinates":[-71.83333,18.46667],"type":"Point"}
}