{
  "type": "Feature",
  "properties": {
    "gn:admin1_code":"1.0",
    "gn:admin2_code":"204.0",
    "gn:admin3_code":"20402.0",
    "gn:admin4_code":"2040204.0",
    "gn:asciiname":"Los Cedros",
    "gn:country_code":"DO",
    "gn:dem":1353,
    "gn:feature_class":"P",
    "gn:feature_code":"PPL",
    "gn:name":"Los Cedros",
    "gn:population":0,
    "gn:timezone":"America/Santo_Domingo",
    "iso:country":"DO",
    "name:und_x_variant":[
        "El Cedro",
        "Los Cedros"
    ],
    "wof:name":"Los Cedros",
    "wof:placetype":"locality"
},
  "geometry": {"coordinates":[-70.88873000000002,18.86125],"type":"Point"}
}