{
  "type": "Feature",
  "properties": {
    "gn:admin1_code":"3.0",
    "gn:admin2_code":"405.0",
    "gn:admin3_code":"40504.0",
    "gn:admin4_code":"4050403.0",
    "gn:asciiname":"Salsipuedes",
    "gn:country_code":"DO",
    "gn:dem":25,
    "gn:feature_class":"P",
    "gn:feature_code":"PPL",
    "gn:name":"Salsipuedes",
    "gn:population":0,
    "gn:timezone":"America/Santo_Domingo",
    "iso:country":"DO",
    "wof:name":"Salsipuedes",
    "wof:placetype":"locality"
},
  "geometry": {"coordinates":[-71.1972,18.36198],"type":"Point"}
}