{
  "type": "Feature",
  "properties": {
    "gn:admin1_code":"32.0",
    "gn:admin2_code":"2905.0",
    "gn:admin3_code":"290501.0",
    "gn:admin4_code":"29050104.0",
    "gn:asciiname":"Los Morones",
    "gn:country_code":"DO",
    "gn:dem":117,
    "gn:feature_class":"P",
    "gn:feature_code":"PPL",
    "gn:name":"Los Morones",
    "gn:population":0,
    "gn:timezone":"America/Santo_Domingo",
    "iso:country":"DO",
    "wof:name":"Los Morones",
    "wof:placetype":"locality"
},
  "geometry": {"coordinates":[-70.015,18.84486],"type":"Point"}
}