{
  "type": "Feature",
  "properties": {
    "gn:admin1_code":"31.0",
    "gn:admin2_code":"2801.0",
    "gn:admin3_code":"280106.0",
    "gn:admin4_code":"28010603.0",
    "gn:asciiname":"El Higo",
    "gn:country_code":"DO",
    "gn:dem":821,
    "gn:feature_class":"P",
    "gn:feature_code":"PPL",
    "gn:name":"El Higo",
    "gn:population":0,
    "gn:timezone":"America/Santo_Domingo",
    "iso:country":"DO",
    "name:ceb_x_preferred":[
        "El Higo"
    ],
    "name:swe_x_preferred":[
        "El Higo"
    ],
    "wof:name":"El Higo",
    "wof:placetype":"locality"
},
  "geometry": {"coordinates":[-70.50035,18.844],"type":"Point"}
}