{
  "type": "Feature",
  "properties": {
    "gn:admin1_code":"24.0",
    "gn:asciiname":"El Vigia de Gautier",
    "gn:cc2":"DO",
    "gn:country_code":"DO",
    "gn:dem":32,
    "gn:feature_class":"P",
    "gn:feature_code":"PPL",
    "gn:name":"El Vig\u00eda de Gautier",
    "gn:population":0,
    "gn:timezone":"America/Santo_Domingo",
    "iso:country":"DO",
    "name:und_x_variant":[
        "El Vig\u00eda",
        "El Vig\u00eda de Gautier"
    ],
    "wof:name":"El Vigia de Gautier",
    "wof:placetype":"locality"
},
  "geometry": {"coordinates":[-69.56667,18.46667],"type":"Point"}
}