{
  "type": "Feature",
  "properties": {
    "gn:admin1_code":"6.0",
    "gn:admin2_code":"605.0",
    "gn:admin3_code":"60504.0",
    "gn:admin4_code":"6050403.0",
    "gn:asciiname":"Juana Rodriguez Arriba",
    "gn:country_code":"DO",
    "gn:dem":23,
    "gn:feature_class":"P",
    "gn:feature_code":"PPL",
    "gn:name":"Juana Rodr\u00edguez Arriba",
    "gn:population":0,
    "gn:timezone":"America/Santo_Domingo",
    "iso:country":"DO",
    "wof:name":"Juana Rodriguez Arriba",
    "wof:placetype":"locality"
},
  "geometry": {"coordinates":[-69.92192,19.14142],"type":"Point"}
}