{
  "type": "Feature",
  "properties": {
    "gn:admin1_code":"25.0",
    "gn:asciiname":"Altos de los Mates",
    "gn:country_code":"DO",
    "gn:dem":907,
    "gn:feature_class":"P",
    "gn:feature_code":"PPL",
    "gn:name":"Altos de los Mates",
    "gn:population":0,
    "gn:timezone":"America/Santo_Domingo",
    "iso:country":"DO",
    "name:und_x_variant":[
        "Alto de los Mates",
        "Altos de los Mates"
    ],
    "wof:name":"Altos de los Mates",
    "wof:placetype":"locality"
},
  "geometry": {"coordinates":[-70.76311,19.59977],"type":"Point"}
}