{
  "type": "Feature",
  "properties": {
    "gn:admin1_code":"28.0",
    "gn:admin2_code":"801.0",
    "gn:admin3_code":"80101.0",
    "gn:admin4_code":"8010104.0",
    "gn:asciiname":"Los Berracos",
    "gn:country_code":"DO",
    "gn:dem":185,
    "gn:feature_class":"P",
    "gn:feature_code":"PPL",
    "gn:name":"Los Berracos",
    "gn:population":0,
    "gn:timezone":"America/Santo_Domingo",
    "iso:country":"DO",
    "wof:name":"Los Berracos",
    "wof:placetype":"locality"
},
  "geometry": {"coordinates":[-69.10653000000001,18.82979],"type":"Point"}
}