{
  "type": "Feature",
  "properties": {
    "gn:admin1_code":"25.0",
    "gn:admin2_code":"2505.0",
    "gn:admin3_code":"250501.0",
    "gn:admin4_code":"25050102.0",
    "gn:asciiname":"Vera de Amina",
    "gn:country_code":"DO",
    "gn:dem":367,
    "gn:feature_class":"P",
    "gn:feature_code":"PPL",
    "gn:name":"Vera de Amina",
    "gn:population":0,
    "gn:timezone":"America/Santo_Domingo",
    "iso:country":"DO",
    "wof:name":"Vera de Amina",
    "wof:placetype":"locality"
},
  "geometry": {"coordinates":[-70.98983,19.35766],"type":"Point"}
}