{
  "type": "Feature",
  "properties": {
    "gn:admin1_code":"8.0",
    "gn:admin2_code":"904.0",
    "gn:admin3_code":"90401.0",
    "gn:admin4_code":"9040105.0",
    "gn:asciiname":"Arroyo Blanco",
    "gn:country_code":"DO",
    "gn:dem":338,
    "gn:feature_class":"P",
    "gn:feature_code":"PPL",
    "gn:name":"Arroyo Blanco",
    "gn:population":0,
    "gn:timezone":"America/Santo_Domingo",
    "iso:country":"DO",
    "wof:name":"Arroyo Blanco",
    "wof:placetype":"locality"
},
  "geometry": {"coordinates":[-70.46666999999999,19.56667],"type":"Point"}
}