{
  "type": "Feature",
  "properties": {
    "gn:admin1_code":"36.0",
    "gn:admin2_code":"3102.0",
    "gn:admin3_code":"310201.0",
    "gn:admin4_code":"31020102.0",
    "gn:asciiname":"El Canal",
    "gn:country_code":"DO",
    "gn:dem":681,
    "gn:feature_class":"P",
    "gn:feature_code":"PPL",
    "gn:name":"El Canal",
    "gn:population":0,
    "gn:timezone":"America/Santo_Domingo",
    "iso:country":"DO",
    "wof:name":"El Canal",
    "wof:placetype":"locality"
},
  "geometry": {"coordinates":[-70.52839,18.57471],"type":"Point"}
}