{
  "type": "Feature",
  "properties": {
    "gn:admin1_code":"25.0",
    "gn:admin2_code":"2505.0",
    "gn:admin3_code":"250503.0",
    "gn:admin4_code":"25050302.0",
    "gn:asciiname":"El Limpio",
    "gn:country_code":"DO",
    "gn:dem":433,
    "gn:feature_class":"P",
    "gn:feature_code":"PPL",
    "gn:name":"El Limpio",
    "gn:population":0,
    "gn:timezone":"America/Santo_Domingo",
    "iso:country":"DO",
    "wof:name":"El Limpio",
    "wof:placetype":"locality"
},
  "geometry": {"coordinates":[-70.90000000000001,19.43333],"type":"Point"}
}