{
  "type": "Feature",
  "properties": {
    "gn:admin1_code":"33.0",
    "gn:admin2_code":"2105.0",
    "gn:admin3_code":"210504.0",
    "gn:admin4_code":"21050401.0",
    "gn:asciiname":"La Cuchilla",
    "gn:country_code":"DO",
    "gn:dem":149,
    "gn:feature_class":"P",
    "gn:feature_code":"PPL",
    "gn:name":"La Cuchilla",
    "gn:population":0,
    "gn:timezone":"America/Santo_Domingo",
    "iso:country":"DO",
    "wof:name":"La Cuchilla",
    "wof:placetype":"locality"
},
  "geometry": {"coordinates":[-70.15661999999999,18.56495],"type":"Point"}
}