{
  "type": "Feature",
  "properties": {
    "gn:admin1_code":"21.0",
    "gn:admin2_code":"2401.0",
    "gn:admin3_code":"240105.0",
    "gn:admin4_code":"24010504.0",
    "gn:asciiname":"Las Cien Tareas",
    "gn:country_code":"DO",
    "gn:dem":100,
    "gn:feature_class":"P",
    "gn:feature_code":"PPL",
    "gn:name":"Las Cien Tareas",
    "gn:population":0,
    "gn:timezone":"America/Santo_Domingo",
    "iso:country":"DO",
    "wof:name":"Las Cien Tareas",
    "wof:placetype":"locality"
},
  "geometry": {"coordinates":[-70.04783,19.11019],"type":"Point"}
}