{
  "type": "Feature",
  "properties": {
    "gn:admin1_code":"2.0",
    "gn:admin2_code":"301.0",
    "gn:admin3_code":"30101.0",
    "gn:admin4_code":"3010109.0",
    "gn:asciiname":"La Mata de Naranja",
    "gn:country_code":"DO",
    "gn:dem":1625,
    "gn:feature_class":"P",
    "gn:feature_code":"PPL",
    "gn:name":"La Mata de Naranja",
    "gn:population":0,
    "gn:timezone":"America/Santo_Domingo",
    "iso:country":"DO",
    "name:und_x_variant":[
        "Mata de Naranja",
        "La Mata de Naranja"
    ],
    "wof:name":"La Mata de Naranja",
    "wof:placetype":"locality"
},
  "geometry": {"coordinates":[-71.4722,18.61918],"type":"Point"}
}