{
  "type": "Feature",
  "properties": {
    "gn:admin1_code":"28.0",
    "gn:admin2_code":"802.0",
    "gn:admin3_code":"80202.0",
    "gn:admin4_code":"8020203.0",
    "gn:asciiname":"Los Mosquitos",
    "gn:country_code":"DO",
    "gn:dem":46,
    "gn:feature_class":"P",
    "gn:feature_code":"PPL",
    "gn:name":"Los Mosquitos",
    "gn:population":0,
    "gn:timezone":"America/Santo_Domingo",
    "iso:country":"DO",
    "wof:name":"Los Mosquitos",
    "wof:placetype":"locality"
},
  "geometry": {"coordinates":[-68.94434,18.93795],"type":"Point"}
}