{
  "type": "Feature",
  "properties": {
    "gn:admin1_code":"18.0",
    "gn:admin2_code":"1807.0",
    "gn:admin3_code":"180701.0",
    "gn:admin4_code":"18070103.0",
    "gn:asciiname":"Sabaneta de Cangrejos",
    "gn:country_code":"DO",
    "gn:dem":14,
    "gn:feature_class":"P",
    "gn:feature_code":"PPL",
    "gn:name":"Sabaneta de Cangrejos",
    "gn:population":0,
    "gn:timezone":"America/Santo_Domingo",
    "iso:country":"DO",
    "name:und_x_variant":[
        "Sabana de Cangrejo",
        "Sabana de Cangrejos",
        "Sabaneta de Cangrejos"
    ],
    "wof:name":"Sabaneta de Cangrejos",
    "wof:placetype":"locality"
},
  "geometry": {"coordinates":[-70.58855,19.74752],"type":"Point"}
}