{
  "type": "Feature",
  "properties": {
    "gn:admin1_code":"35.0",
    "gn:admin2_code":"1701.0",
    "gn:admin3_code":"170101.0",
    "gn:admin4_code":"17010113.0",
    "gn:asciiname":"El Descansadero",
    "gn:country_code":"DO",
    "gn:dem":949,
    "gn:feature_class":"P",
    "gn:feature_code":"PPL",
    "gn:name":"El Descansadero",
    "gn:population":0,
    "gn:timezone":"America/Santo_Domingo",
    "iso:country":"DO",
    "wof:name":"El Descansadero",
    "wof:placetype":"locality"
},
  "geometry": {"coordinates":[-70.29369,18.43649],"type":"Point"}
}