{
  "type": "Feature",
  "properties": {
    "gn:admin1_code":"18.0",
    "gn:admin2_code":"1801.0",
    "gn:admin3_code":"180103.0",
    "gn:admin4_code":"18010306.0",
    "gn:asciiname":"Los Mates",
    "gn:country_code":"DO",
    "gn:dem":121,
    "gn:feature_class":"P",
    "gn:feature_code":"PPL",
    "gn:name":"Los Mates",
    "gn:population":0,
    "gn:timezone":"America/Santo_Domingo",
    "iso:country":"DO",
    "wof:name":"Los Mates",
    "wof:placetype":"locality"
},
  "geometry": {"coordinates":[-70.80370000000001,19.78726],"type":"Point"}
}