{
  "type": "Feature",
  "properties": {
    "gn:admin1_code":"18.0",
    "gn:admin2_code":"1802.0",
    "gn:admin3_code":"180202.0",
    "gn:admin4_code":"18020206.0",
    "gn:asciiname":"Pie de Jagua",
    "gn:country_code":"DO",
    "gn:dem":343,
    "gn:feature_class":"P",
    "gn:feature_code":"PPL",
    "gn:name":"P\u00ede de Jagua",
    "gn:population":0,
    "gn:timezone":"America/Santo_Domingo",
    "iso:country":"DO",
    "wof:name":"Pie de Jagua",
    "wof:placetype":"locality"
},
  "geometry": {"coordinates":[-70.73895,19.63957000000001],"type":"Point"}
}