{
  "type": "Feature",
  "properties": {
    "gn:admin1_code":"29.0",
    "gn:admin2_code":"3002.0",
    "gn:admin3_code":"300202.0",
    "gn:admin4_code":"30020202.0",
    "gn:asciiname":"Arroyo Rico",
    "gn:country_code":"DO",
    "gn:dem":102,
    "gn:feature_class":"P",
    "gn:feature_code":"PPL",
    "gn:name":"Arroyo Rico",
    "gn:population":0,
    "gn:timezone":"America/Santo_Domingo",
    "iso:country":"DO",
    "wof:name":"Arroyo Rico",
    "wof:placetype":"locality"
},
  "geometry": {"coordinates":[-69.20031,18.96427000000001],"type":"Point"}
}