{
  "type": "Feature",
  "properties": {
    "gn:admin1_code":"19.0",
    "gn:admin2_code":"1901.0",
    "gn:admin3_code":"190101.0",
    "gn:admin4_code":"19010103.0",
    "gn:asciiname":"Los Cacaos Salcedo",
    "gn:country_code":"DO",
    "gn:dem":406,
    "gn:feature_class":"P",
    "gn:feature_code":"PPL",
    "gn:name":"Los Cacaos Salcedo",
    "gn:population":0,
    "gn:timezone":"America/Santo_Domingo",
    "iso:country":"DO",
    "name:und_x_variant":[
        "Cacaos",
        "Los Cacaos",
        "Los Cacaos Salcedo"
    ],
    "wof:name":"Los Cacaos Salcedo",
    "wof:placetype":"locality"
},
  "geometry": {"coordinates":[-70.34806999999999,19.42591],"type":"Point"}
}