{
  "type": "Feature",
  "properties": {
    "gn:admin1_code":"14.0",
    "gn:admin2_code":"1401.0",
    "gn:admin3_code":"140104.0",
    "gn:admin4_code":"14010402.0",
    "gn:asciiname":"Cano Teloso",
    "gn:country_code":"DO",
    "gn:dem":63,
    "gn:feature_class":"P",
    "gn:feature_code":"PPL",
    "gn:name":"Ca\u00f1o Teloso",
    "gn:population":0,
    "gn:timezone":"America/Santo_Domingo",
    "iso:country":"DO",
    "wof:name":"Cano Teloso",
    "wof:placetype":"locality"
},
  "geometry": {"coordinates":[-69.96333,19.37352000000001],"type":"Point"}
}