{
  "type": "Feature",
  "properties": {
    "gn:admin1_code":"15.0",
    "gn:admin2_code":"1505.0",
    "gn:admin3_code":"150501.0",
    "gn:admin4_code":"15050103.0",
    "gn:asciiname":"Gozuela",
    "gn:country_code":"DO",
    "gn:dem":20,
    "gn:feature_class":"P",
    "gn:feature_code":"PPL",
    "gn:name":"Gozuela",
    "gn:population":0,
    "gn:timezone":"America/Santo_Domingo",
    "iso:country":"DO",
    "wof:name":"Gozuela",
    "wof:placetype":"locality"
},
  "geometry": {"coordinates":[-71.63328,19.66055],"type":"Point"}
}