{
  "type": "Feature",
  "properties": {
    "gn:admin1_code":"37.0",
    "gn:admin2_code":"3201.0",
    "gn:admin3_code":"320101.0",
    "gn:admin4_code":"32010101.0",
    "gn:asciiname":"Hainamosa",
    "gn:country_code":"DO",
    "gn:dem":27,
    "gn:feature_class":"P",
    "gn:feature_code":"PPL",
    "gn:name":"Hainamosa",
    "gn:population":0,
    "gn:timezone":"America/Santo_Domingo",
    "iso:country":"DO",
    "wof:name":"Hainamosa",
    "wof:placetype":"locality"
},
  "geometry": {"coordinates":[-69.83333,18.51667],"type":"Point"}
}