{
  "type": "Feature",
  "properties": {
    "gn:admin1_code":"10.0",
    "gn:admin2_code":"1101.0",
    "gn:admin3_code":"110102.0",
    "gn:admin4_code":"11010203.0",
    "gn:asciiname":"Las Dos Bocas",
    "gn:country_code":"DO",
    "gn:dem":73,
    "gn:feature_class":"P",
    "gn:feature_code":"PPL",
    "gn:name":"Las Dos Bocas",
    "gn:population":0,
    "gn:timezone":"America/Santo_Domingo",
    "iso:country":"DO",
    "wof:name":"Las Dos Bocas",
    "wof:placetype":"locality"
},
  "geometry": {"coordinates":[-68.75899,18.8587],"type":"Point"}
}