{
  "type": "Feature",
  "properties": {
    "gn:admin1_code":"27.0",
    "gn:admin2_code":"2701.0",
    "gn:admin3_code":"270103.0",
    "gn:admin4_code":"27010303.0",
    "gn:asciiname":"La Jagua",
    "gn:country_code":"DO",
    "gn:dem":81,
    "gn:feature_class":"P",
    "gn:feature_code":"PPL",
    "gn:name":"La Jagua",
    "gn:population":0,
    "gn:timezone":"America/Santo_Domingo",
    "iso:country":"DO",
    "name:und_x_variant":[
        "Pueblo La Yagua",
        "La Yagua",
        "La Jagua"
    ],
    "wof:name":"La Jagua",
    "wof:placetype":"locality"
},
  "geometry": {"coordinates":[-71.14846999999997,19.57884],"type":"Point"}
}