{
  "type": "Feature",
  "properties": {
    "gn:admin1_code":"2.0",
    "gn:admin2_code":"301.0",
    "gn:admin3_code":"30101.0",
    "gn:admin4_code":"3010106.0",
    "gn:asciiname":"El Botado",
    "gn:country_code":"DO",
    "gn:dem":464,
    "gn:feature_class":"P",
    "gn:feature_code":"PPL",
    "gn:name":"El Botado",
    "gn:population":0,
    "gn:timezone":"America/Santo_Domingo",
    "iso:country":"DO",
    "name:und_x_variant":[
        "El Botao",
        "El Botado"
    ],
    "wof:name":"El Botado",
    "wof:placetype":"locality"
},
  "geometry": {"coordinates":[-71.41269,18.56738],"type":"Point"}
}