{
  "type": "Feature",
  "properties": {
    "gn:admin1_code":"29.0",
    "gn:admin2_code":"3001.0",
    "gn:admin3_code":"300103.0",
    "gn:admin4_code":"30010302.0",
    "gn:asciiname":"Sabana Redo del Caimito",
    "gn:country_code":"DO",
    "gn:dem":81,
    "gn:feature_class":"P",
    "gn:feature_code":"PPL",
    "gn:name":"Sabana Redo del Caimito",
    "gn:population":0,
    "gn:timezone":"America/Santo_Domingo",
    "iso:country":"DO",
    "wof:name":"Sabana Redo del Caimito",
    "wof:placetype":"locality"
},
  "geometry": {"coordinates":[-69.27875999999999,18.72547],"type":"Point"}
}