{
  "type": "Feature",
  "properties": {
    "gn:admin1_code":"11.0",
    "gn:admin2_code":"702.0",
    "gn:admin3_code":"70203.0",
    "gn:admin4_code":"7020305.0",
    "gn:asciiname":"Brito",
    "gn:country_code":"DO",
    "gn:dem":501,
    "gn:feature_class":"P",
    "gn:feature_code":"PPL",
    "gn:name":"Brito",
    "gn:population":0,
    "gn:timezone":"America/Santo_Domingo",
    "iso:country":"DO",
    "name:bre_x_preferred":[
        "Brito"
    ],
    "name:ceb_x_preferred":[
        "Brito"
    ],
    "name:deu_x_preferred":[
        "Brito"
    ],
    "name:fin_x_preferred":[
        "Brito"
    ],
    "name:fra_x_preferred":[
        "Brito"
    ],
    "name:ita_x_preferred":[
        "Brito"
    ],
    "name:jpn_x_preferred":[
        "\u30d6\u30ea\u30c8\u30fc"
    ],
    "name:pol_x_preferred":[
        "Brito"
    ],
    "name:por_x_preferred":[
        "Brito"
    ],
    "name:und_x_variant":[
        "Los Britos"
    ],
    "wof:name":"Brito",
    "wof:placetype":"locality"
},
  "geometry": {"coordinates":[-71.56567,19.02879],"type":"Point"}
}