{
  "type": "Feature",
  "properties": {
    "gn:admin1_code":"24.0",
    "gn:admin2_code":"2304.0",
    "gn:admin3_code":"230401.0",
    "gn:admin4_code":"23040102.0",
    "gn:asciiname":"Trampa Legal",
    "gn:country_code":"DO",
    "gn:dem":53,
    "gn:feature_class":"P",
    "gn:feature_code":"PPL",
    "gn:name":"Trampa Legal",
    "gn:population":0,
    "gn:timezone":"America/Santo_Domingo",
    "iso:country":"DO",
    "name:und_x_variant":[
        "Batey Trampa",
        "Batey Trampa Legal",
        "Trampa Legal"
    ],
    "wof:name":"Trampa Legal",
    "wof:placetype":"locality"
},
  "geometry": {"coordinates":[-69.22516,18.58166],"type":"Point"}
}