{
  "type": "Feature",
  "properties": {
    "gn:admin1_code":"30.0",
    "gn:admin2_code":"1301.0",
    "gn:admin3_code":"130101.0",
    "gn:admin4_code":"13010112.0",
    "gn:asciiname":"La Quebrada",
    "gn:country_code":"DO",
    "gn:dem":68,
    "gn:feature_class":"P",
    "gn:feature_code":"PPL",
    "gn:name":"La Quebrada",
    "gn:population":0,
    "gn:timezone":"America/Santo_Domingo",
    "iso:country":"DO",
    "wof:name":"La Quebrada",
    "wof:placetype":"locality"
},
  "geometry": {"coordinates":[-70.35584,19.21224],"type":"Point"}
}