{
  "type": "Feature",
  "properties": {
    "gn:admin1_code":"32.0",
    "gn:admin2_code":"2901.0",
    "gn:admin3_code":"290104.0",
    "gn:admin4_code":"29010403.0",
    "gn:asciiname":"Cacique",
    "gn:country_code":"DO",
    "gn:dem":59,
    "gn:feature_class":"P",
    "gn:feature_code":"PPL",
    "gn:name":"Cacique",
    "gn:population":0,
    "gn:timezone":"America/Santo_Domingo",
    "iso:country":"DO",
    "name:aze_x_preferred":[
        "Kasike"
    ],
    "name:bel_x_preferred":[
        "\u041a\u0430\u0441\u0456\u043a"
    ],
    "name:bre_x_preferred":[
        "Cacique"
    ],
    "name:cat_x_preferred":[
        "Cacic"
    ],
    "name:ces_x_preferred":[
        "Kasik"
    ],
    "name:deu_x_preferred":[
        "Kazike"
    ],
    "name:epo_x_preferred":[
        "Kaciko"
    ],
    "name:eus_x_preferred":[
        "Kazike"
    ],
    "name:fra_x_preferred":[
        "Cacique"
    ],
    "name:glg_x_preferred":[
        "Cacique"
    ],
    "name:hrv_x_preferred":[
        "Cacique"
    ],
    "name:hun_x_preferred":[
        "Kacika"
    ],
    "name:ita_x_preferred":[
        "Cacicco"
    ],
    "name:jpn_x_preferred":[
        "\u30ab\u30b7\u30b1"
    ],
    "name:lit_x_preferred":[
        "Kasikas"
    ],
    "name:nld_x_preferred":[
        "Cacique"
    ],
    "name:nor_x_preferred":[
        "Cacique"
    ],
    "name:pol_x_preferred":[
        "Kacyk"
    ],
    "name:por_x_preferred":[
        "Cacique"
    ],
    "name:ron_x_preferred":[
        "Cacique"
    ],
    "name:rus_x_preferred":[
        "\u041a\u0430\u0441\u0438\u043a"
    ],
    "name:spa_x_preferred":[
        "Cacique"
    ],
    "name:swe_x_preferred":[
        "Cacique"
    ],
    "name:tha_x_preferred":[
        "\u0e01\u0e32\u0e0b\u0e35\u0e40\u0e01"
    ],
    "wof:name":"Cacique",
    "wof:placetype":"locality"
},
  "geometry": {"coordinates":[-69.85679,18.81596],"type":"Point"}
}