{
  "type": "Feature",
  "properties": {
    "gn:admin1_code":"32.0",
    "gn:admin2_code":"2901.0",
    "gn:admin3_code":"290104.0",
    "gn:admin4_code":"29010403.0",
    "gn:asciiname":"Cacique",
    "gn:country_code":"DO",
    "gn:dem":59,
    "gn:feature_class":"P",
    "gn:feature_code":"PPL",
    "gn:name":"Cacique",
    "gn:population":0,
    "gn:timezone":"America/Santo_Domingo",
    "iso:country":"DO",
    "wof:name":"Cacique",
    "wof:placetype":"locality"
},
  "geometry": {"coordinates":[-69.85679,18.81596],"type":"Point"}
}