{
  "type": "Feature",
  "properties": {
    "gn:admin1_code":"11.0",
    "gn:admin2_code":"705.0",
    "gn:admin3_code":"70502.0",
    "gn:admin4_code":"7050204.0",
    "gn:asciiname":"Los Corozos",
    "gn:country_code":"DO",
    "gn:dem":710,
    "gn:feature_class":"P",
    "gn:feature_code":"PPL",
    "gn:name":"Los Corozos",
    "gn:population":0,
    "gn:timezone":"America/Santo_Domingo",
    "iso:country":"DO",
    "wof:name":"Los Corozos",
    "wof:placetype":"locality"
},
  "geometry": {"coordinates":[-71.52731,19.1324],"type":"Point"}
}