{
  "type": "Feature",
  "properties": {
    "gn:admin1_code":"25.0",
    "gn:admin2_code":"2507.0",
    "gn:admin3_code":"250703.0",
    "gn:admin4_code":"25070304.0",
    "gn:asciiname":"La Pocilguita del Limon",
    "gn:country_code":"DO",
    "gn:dem":331,
    "gn:feature_class":"P",
    "gn:feature_code":"PPL",
    "gn:name":"La Pocilguita del Lim\u00f3n",
    "gn:population":0,
    "gn:timezone":"America/Santo_Domingo",
    "iso:country":"DO",
    "name:und_x_variant":[
        "La Pocilguita",
        "La Pocilguita del Lim\u00f3n"
    ],
    "wof:name":"La Pocilguita del Limon",
    "wof:placetype":"locality"
},
  "geometry": {"coordinates":[-70.82204,19.59842],"type":"Point"}
}