{
  "type": "Feature",
  "properties": {
    "gn:admin1_code":"11.0",
    "gn:admin2_code":"701.0",
    "gn:admin3_code":"70103.0",
    "gn:admin4_code":"7010303.0",
    "gn:asciiname":"Guayabo",
    "gn:country_code":"DO",
    "gn:dem":647,
    "gn:feature_class":"P",
    "gn:feature_code":"PPL",
    "gn:name":"Guayabo",
    "gn:population":0,
    "gn:timezone":"America/Santo_Domingo",
    "iso:country":"DO",
    "name:und_x_variant":[
        "El Guayabo",
        "Guayabo"
    ],
    "wof:name":"Guayabo",
    "wof:placetype":"locality"
},
  "geometry": {"coordinates":[-71.69426,18.83989],"type":"Point"}
}