{
  "type": "Feature",
  "properties": {
    "gn:admin1_code":"37.0",
    "gn:asciiname":"La Hondonada",
    "gn:country_code":"DO",
    "gn:dem":35,
    "gn:feature_class":"P",
    "gn:feature_code":"PPL",
    "gn:name":"La Hondonada",
    "gn:population":0,
    "gn:timezone":"America/Santo_Domingo",
    "iso:country":"DO",
    "name:und_x_variant":[
        "Hondonada",
        "La Hondonada"
    ],
    "name:urd_x_preferred":[
        "\u0644\u0627 \u06c1\u0648\u0646\u062f\u0648\u0646\u0627\u0688\u0627"
    ],
    "wof:name":"La Hondonada",
    "wof:placetype":"locality"
},
  "geometry": {"coordinates":[-69.97624999999999,18.54143],"type":"Point"}
}