{
  "type": "Feature",
  "properties": {
    "gn:admin1_code":"29.0",
    "gn:admin2_code":"3001.0",
    "gn:admin3_code":"300101.0",
    "gn:admin4_code":"30010102.0",
    "gn:asciiname":"Rincon Dulce",
    "gn:country_code":"DO",
    "gn:dem":42,
    "gn:feature_class":"P",
    "gn:feature_code":"PPL",
    "gn:name":"Rinc\u00f3n Dulce",
    "gn:population":0,
    "gn:timezone":"America/Santo_Domingo",
    "iso:country":"DO",
    "wof:name":"Rincon Dulce",
    "wof:placetype":"locality"
},
  "geometry": {"coordinates":[-69.40380999999999,18.71514],"type":"Point"}
}