{
  "type": "Feature",
  "properties": {
    "gn:admin1_code":"14.0",
    "gn:admin2_code":"1402.0",
    "gn:admin3_code":"140201.0",
    "gn:admin4_code":"14020104.0",
    "gn:asciiname":"El Diamante",
    "gn:country_code":"DO",
    "gn:dem":14,
    "gn:feature_class":"P",
    "gn:feature_code":"PPL",
    "gn:name":"El Diamante",
    "gn:population":0,
    "gn:timezone":"America/Santo_Domingo",
    "iso:country":"DO",
    "name:und_x_variant":[
        "Diamante",
        "La Diamante",
        "El Diamante"
    ],
    "wof:name":"El Diamante",
    "wof:placetype":"locality"
},
  "geometry": {"coordinates":[-69.89899,19.58211],"type":"Point"}
}