{
  "type": "Feature",
  "properties": {
    "gn:admin1_code":"10.0",
    "gn:admin2_code":"1101.0",
    "gn:admin3_code":"110102.0",
    "gn:admin4_code":"11010204.0",
    "gn:asciiname":"El Hierro",
    "gn:country_code":"DO",
    "gn:dem":100,
    "gn:feature_class":"P",
    "gn:feature_code":"PPL",
    "gn:name":"El Hierro",
    "gn:population":0,
    "gn:timezone":"America/Santo_Domingo",
    "iso:country":"DO",
    "name:afr_x_preferred":[
        "El Hierro"
    ],
    "name:arg_x_preferred":[
        "El Hierro"
    ],
    "name:ast_x_preferred":[
        "El Hierro"
    ],
    "name:aze_x_preferred":[
        "El-Hierro"
    ],
    "name:bel_x_preferred":[
        "\u042d\u043b\u044c-\u0415\u0440\u0430"
    ],
    "name:bul_x_preferred":[
        "\u0419\u0435\u0440\u043e"
    ],
    "name:cat_x_preferred":[
        "El Hierro"
    ],
    "name:ceb_x_preferred":[
        "El Hierro"
    ],
    "name:ces_x_preferred":[
        "El Hierro"
    ],
    "name:dan_x_preferred":[
        "El Hierro"
    ],
    "name:deu_x_preferred":[
        "El Hierro"
    ],
    "name:ell_x_preferred":[
        "\u0395\u03bb \u0399\u03ad\u03c1\u03c1\u03bf"
    ],
    "name:epo_x_preferred":[
        "El Hierro"
    ],
    "name:est_x_preferred":[
        "Hierro"
    ],
    "name:eus_x_preferred":[
        "Hierro"
    ],
    "name:fas_x_preferred":[
        "\u0627\u0644 \u0647\u06cc\u0631\u0648"
    ],
    "name:fin_x_preferred":[
        "El Hierro"
    ],
    "name:fra_x_preferred":[
        "El Hierro"
    ],
    "name:frr_x_preferred":[
        "El Hierro"
    ],
    "name:gla_x_preferred":[
        "El Hierro"
    ],
    "name:glg_x_preferred":[
        "El Hierro"
    ],
    "name:hun_x_preferred":[
        "El Hierro"
    ],
    "name:ind_x_preferred":[
        "El Hierro"
    ],
    "name:isl_x_preferred":[
        "El Hierro"
    ],
    "name:ita_x_preferred":[
        "El Hierro"
    ],
    "name:jpn_x_preferred":[
        "\u30a8\u30eb\u30fb\u30a4\u30a8\u30ed\u5cf6"
    ],
    "name:kor_x_preferred":[
        "\uc5d8\uc774\uc5d0\ub85c\uc12c"
    ],
    "name:lat_x_preferred":[
        "Insula Ferri"
    ],
    "name:lit_x_preferred":[
        "El Hieras"
    ],
    "name:ltz_x_preferred":[
        "El Hierro"
    ],
    "name:mrj_x_preferred":[
        "\u0418\u0435\u0440\u0440\u043e"
    ],
    "name:msa_x_preferred":[
        "El Hierro"
    ],
    "name:nld_x_preferred":[
        "Ferro"
    ],
    "name:nno_x_preferred":[
        "El Hierro"
    ],
    "name:nor_x_preferred":[
        "Hierro"
    ],
    "name:oci_x_preferred":[
        "El Hierro"
    ],
    "name:pol_x_preferred":[
        "El Hierro"
    ],
    "name:por_x_preferred":[
        "El Hierro"
    ],
    "name:ron_x_preferred":[
        "El Hierro"
    ],
    "name:rus_x_preferred":[
        "\u0418\u0435\u0440\u0440\u043e"
    ],
    "name:slk_x_preferred":[
        "El Hierro"
    ],
    "name:spa_x_preferred":[
        "El Hierro"
    ],
    "name:srp_x_preferred":[
        "\u0408\u0435\u0440\u043e"
    ],
    "name:swe_x_preferred":[
        "El Hierro"
    ],
    "name:tur_x_preferred":[
        "El Hierro"
    ],
    "name:ukr_x_preferred":[
        "\u0406\u0454\u0440\u0440\u043e"
    ],
    "name:vie_x_preferred":[
        "El Hierro"
    ],
    "name:war_x_preferred":[
        "El Hierro"
    ],
    "name:zho_x_preferred":[
        "\u8036\u7f57\u5c9b"
    ],
    "wof:name":"El Hierro",
    "wof:placetype":"locality"
},
  "geometry": {"coordinates":[-68.71714,18.7886],"type":"Point"}
}