{
  "type": "Feature",
  "properties": {
    "gn:admin1_code":"25.0",
    "gn:admin2_code":"2503.0",
    "gn:admin3_code":"250302.0",
    "gn:admin4_code":"25030204.0",
    "gn:asciiname":"La Culebra",
    "gn:country_code":"DO",
    "gn:dem":1094,
    "gn:feature_class":"P",
    "gn:feature_code":"PPL",
    "gn:name":"La Culebra",
    "gn:population":0,
    "gn:timezone":"America/Santo_Domingo",
    "iso:country":"DO",
    "wof:name":"La Culebra",
    "wof:placetype":"locality"
},
  "geometry": {"coordinates":[-70.82901,19.1994],"type":"Point"}
}