{
  "type": "Feature",
  "properties": {
    "gn:admin1_code":"32.0",
    "gn:admin2_code":"2901.0",
    "gn:admin3_code":"290101.0",
    "gn:admin4_code":"29010104.0",
    "gn:asciiname":"Batey La Luisa",
    "gn:country_code":"DO",
    "gn:dem":25,
    "gn:feature_class":"P",
    "gn:feature_code":"PPL",
    "gn:name":"Batey La Luisa",
    "gn:population":0,
    "gn:timezone":"America/Santo_Domingo",
    "iso:country":"DO",
    "wof:name":"Batey La Luisa",
    "wof:placetype":"locality"
},
  "geometry": {"coordinates":[-69.90535,18.71447],"type":"Point"}
}