{
  "type": "Feature",
  "properties": {
    "gn:admin1_code":"23.0",
    "gn:admin2_code":"2202.0",
    "gn:admin3_code":"220203.0",
    "gn:admin4_code":"22020303.0",
    "gn:asciiname":"Buena Vista",
    "gn:country_code":"DO",
    "gn:dem":598,
    "gn:feature_class":"P",
    "gn:feature_code":"PPL",
    "gn:name":"Buena Vista",
    "gn:population":0,
    "gn:timezone":"America/Santo_Domingo",
    "iso:country":"DO",
    "wof:name":"Buena Vista",
    "wof:placetype":"locality"
},
  "geometry": {"coordinates":[-71.06667,18.81667],"type":"Point"}
}