{
  "type": "Feature",
  "properties": {
    "gn:admin1_code":"15.0",
    "gn:admin2_code":"1505.0",
    "gn:admin3_code":"150501.0",
    "gn:admin4_code":"15050104.0",
    "gn:asciiname":"La Cabuya",
    "gn:country_code":"DO",
    "gn:dem":14,
    "gn:feature_class":"P",
    "gn:feature_code":"PPL",
    "gn:name":"La Cabuya",
    "gn:population":0,
    "gn:timezone":"America/Santo_Domingo",
    "iso:country":"DO",
    "wof:name":"La Cabuya",
    "wof:placetype":"locality"
},
  "geometry": {"coordinates":[-71.56229999999999,19.71168],"type":"Point"}
}