{
  "type": "Feature",
  "properties": {
    "gn:admin1_code":"28.0",
    "gn:admin2_code":"802.0",
    "gn:admin3_code":"80202.0",
    "gn:admin4_code":"8020203.0",
    "gn:asciiname":"El Hato",
    "gn:country_code":"DO",
    "gn:dem":35,
    "gn:feature_class":"P",
    "gn:feature_code":"PPL",
    "gn:name":"El Hato",
    "gn:population":0,
    "gn:timezone":"America/Santo_Domingo",
    "iso:country":"DO",
    "name:ita_x_preferred":[
        "El Hato"
    ],
    "name:spa_x_preferred":[
        "El Hato"
    ],
    "name:zho_x_preferred":[
        "\u57c3\u723e\u963f\u6258"
    ],
    "wof:name":"El Hato",
    "wof:placetype":"locality"
},
  "geometry": {"coordinates":[-68.99448000000001,18.94926],"type":"Point"}
}