{
  "type": "Feature",
  "properties": {
    "gn:admin1_code":"6.0",
    "gn:admin2_code":"601.0",
    "gn:admin3_code":"60101.0",
    "gn:admin4_code":"6010107.0",
    "gn:asciiname":"Atabalero Arriba",
    "gn:country_code":"DO",
    "gn:dem":494,
    "gn:feature_class":"P",
    "gn:feature_code":"PPL",
    "gn:name":"Atabalero Arriba",
    "gn:population":0,
    "gn:timezone":"America/Santo_Domingo",
    "iso:country":"DO",
    "name:und_x_variant":[
        "Atabalero",
        "Atabalero Arriba"
    ],
    "wof:name":"Atabalero Arriba",
    "wof:placetype":"locality"
},
  "geometry": {"coordinates":[-70.2984,19.404],"type":"Point"}
}