{
  "type": "Feature",
  "properties": {
    "gn:admin1_code":"27.0",
    "gn:admin2_code":"2702.0",
    "gn:admin3_code":"270201.0",
    "gn:admin4_code":"27020102.0",
    "gn:asciiname":"Cibao",
    "gn:country_code":"DO",
    "gn:dem":132,
    "gn:feature_class":"P",
    "gn:feature_code":"PPL",
    "gn:name":"Cibao",
    "gn:population":0,
    "gn:timezone":"America/Santo_Domingo",
    "iso:country":"DO",
    "name:fra_x_preferred":[
        "Cibao"
    ],
    "name:ita_x_preferred":[
        "Cibao"
    ],
    "name:nld_x_preferred":[
        "Cibao"
    ],
    "name:spa_x_preferred":[
        "Cibao"
    ],
    "name:ukr_x_preferred":[
        "\u0421\u0456\u0431\u0430\u043e"
    ],
    "name:war_x_preferred":[
        "Cibao"
    ],
    "wof:name":"Cibao",
    "wof:placetype":"locality"
},
  "geometry": {"coordinates":[-70.94503,19.59006],"type":"Point"}
}