{
  "type": "Feature",
  "properties": {
    "gn:admin1_code":"20.0",
    "gn:admin2_code":"2001.0",
    "gn:admin3_code":"200104.0",
    "gn:admin4_code":"20010402.0",
    "gn:asciiname":"Arroyo El Cabo",
    "gn:country_code":"DO",
    "gn:dem":36,
    "gn:feature_class":"P",
    "gn:feature_code":"PPL",
    "gn:name":"Arroyo El Cabo",
    "gn:population":0,
    "gn:timezone":"America/Santo_Domingo",
    "iso:country":"DO",
    "name:und_x_variant":[
        "El Cabo",
        "Arroyo del Cabo",
        "Arroyo El Cabo"
    ],
    "wof:name":"Arroyo El Cabo",
    "wof:placetype":"locality"
},
  "geometry": {"coordinates":[-69.20267,19.27129],"type":"Point"}
}