{
  "type": "Feature",
  "properties": {
    "gn:admin1_code":"8.0",
    "gn:admin2_code":"901.0",
    "gn:admin3_code":"90105.0",
    "gn:admin4_code":"9010502.0",
    "gn:asciiname":"Jayaba Al Medio",
    "gn:country_code":"DO",
    "gn:dem":221,
    "gn:feature_class":"P",
    "gn:feature_code":"PPL",
    "gn:name":"Jayaba Al Medio",
    "gn:population":0,
    "gn:timezone":"America/Santo_Domingo",
    "iso:country":"DO",
    "wof:name":"Jayaba Al Medio",
    "wof:placetype":"locality"
},
  "geometry": {"coordinates":[-70.47313,19.40646],"type":"Point"}
}