{
  "type": "Feature",
  "properties": {
    "gn:admin1_code":"10.0",
    "gn:admin2_code":"1101.0",
    "gn:admin3_code":"110101.0",
    "gn:admin4_code":"11010106.0",
    "gn:asciiname":"El Coya",
    "gn:country_code":"DO",
    "gn:dem":81,
    "gn:feature_class":"P",
    "gn:feature_code":"PPL",
    "gn:name":"El Coy\u00e1",
    "gn:population":0,
    "gn:timezone":"America/Santo_Domingo",
    "iso:country":"DO",
    "name:und_x_variant":[
        "Batey Cuy\u00e1",
        "El Cay\u00e1",
        "El Coy\u00e1"
    ],
    "wof:name":"El Coya",
    "wof:placetype":"locality"
},
  "geometry": {"coordinates":[-68.81681999999999,18.51728],"type":"Point"}
}