{
  "type": "Feature",
  "properties": {
    "gn:admin1_code":"4.0",
    "gn:admin2_code":"501.0",
    "gn:admin3_code":"50101.0",
    "gn:admin4_code":"5010105.0",
    "gn:asciiname":"Clavellina",
    "gn:country_code":"DO",
    "gn:dem":92,
    "gn:feature_class":"P",
    "gn:feature_code":"PPL",
    "gn:name":"Clavellina",
    "gn:population":0,
    "gn:timezone":"America/Santo_Domingo",
    "iso:country":"DO",
    "wof:name":"Clavellina",
    "wof:placetype":"locality"
},
  "geometry": {"coordinates":[-71.6344,19.56111],"type":"Point"}
}