{
  "type": "Feature",
  "properties": {
    "gn:admin1_code":"15.0",
    "gn:admin2_code":"1503.0",
    "gn:admin3_code":"150301.0",
    "gn:admin4_code":"15030103.0",
    "gn:asciiname":"Machete",
    "gn:country_code":"DO",
    "gn:dem":59,
    "gn:feature_class":"P",
    "gn:feature_code":"PPL",
    "gn:name":"Machete",
    "gn:population":0,
    "gn:timezone":"America/Santo_Domingo",
    "iso:country":"DO",
    "name:afr_x_preferred":[
        "Kapmes"
    ],
    "name:ara_x_preferred":[
        "\u0645\u0646\u062c\u0644 \u0645\u0627\u0634\u064a\u062a\u064a"
    ],
    "name:ast_x_preferred":[
        "Machete"
    ],
    "name:bul_x_preferred":[
        "\u041c\u0430\u0447\u0435\u0442\u0435"
    ],
    "name:cat_x_preferred":[
        "Matxet"
    ],
    "name:ces_x_preferred":[
        "Ma\u010deta"
    ],
    "name:dan_x_preferred":[
        "Machete"
    ],
    "name:deu_x_preferred":[
        "Machete"
    ],
    "name:epo_x_preferred":[
        "Ma\u0109eto"
    ],
    "name:est_x_preferred":[
        "Mat\u0161eete"
    ],
    "name:eus_x_preferred":[
        "Aihotz"
    ],
    "name:fas_x_preferred":[
        "\u0642\u062f\u0627\u0631\u0647"
    ],
    "name:fin_x_preferred":[
        "Viidakkoveitsi"
    ],
    "name:fra_x_preferred":[
        "Machette"
    ],
    "name:glg_x_preferred":[
        "Machete"
    ],
    "name:heb_x_preferred":[
        "\u05de\u05e6'\u05d8\u05d4"
    ],
    "name:hrv_x_preferred":[
        "Ma\u010deta"
    ],
    "name:hun_x_preferred":[
        "Machete"
    ],
    "name:hye_x_preferred":[
        "\u0544\u0561\u0579\u0565\u057f\u0565"
    ],
    "name:ita_x_preferred":[
        "Machete"
    ],
    "name:jpn_x_preferred":[
        "\u30de\u30c1\u30a7\u30c6"
    ],
    "name:kat_x_preferred":[
        "\u10db\u10d0\u10e9\u10d4\u10e2\u10d4"
    ],
    "name:kor_x_preferred":[
        "\ub9c8\uccb4\ud14c"
    ],
    "name:lav_x_preferred":[
        "Ma\u010dete"
    ],
    "name:lit_x_preferred":[
        "Ma\u010det\u0117"
    ],
    "name:nld_x_preferred":[
        "Kapmes"
    ],
    "name:nor_x_preferred":[
        "Machete"
    ],
    "name:pan_x_preferred":[
        "\u0a2e\u0a3e\u0a1b\u0a47\u0a24\u0a47"
    ],
    "name:pol_x_preferred":[
        "Maczeta"
    ],
    "name:por_x_preferred":[
        "Machete"
    ],
    "name:ron_x_preferred":[
        "Macet\u0103"
    ],
    "name:rus_x_preferred":[
        "\u041c\u0430\u0447\u0435\u0442\u0435"
    ],
    "name:sco_x_preferred":[
        "Machete"
    ],
    "name:slk_x_preferred":[
        "Ma\u010deta"
    ],
    "name:spa_x_preferred":[
        "Machete"
    ],
    "name:srp_x_preferred":[
        "\u041c\u0430\u0447\u0435\u0442\u0430"
    ],
    "name:swe_x_preferred":[
        "Machete"
    ],
    "name:ukr_x_preferred":[
        "\u041c\u0430\u0447\u0435\u0442\u0435"
    ],
    "name:uzb_x_preferred":[
        "Machete"
    ],
    "name:vie_x_preferred":[
        "M\u00e3 t\u1ea5u"
    ],
    "name:wln_x_preferred":[
        "Matchete"
    ],
    "name:xmf_x_preferred":[
        "\u10db\u10d0\u10e9\u10d4\u10e2\u10d4"
    ],
    "name:zho_x_preferred":[
        "\u958b\u5c71\u5200"
    ],
    "wof:name":"Machete",
    "wof:placetype":"locality"
},
  "geometry": {"coordinates":[-71.40397,19.57119],"type":"Point"}
}