{
  "type": "Feature",
  "properties": {
    "gn:admin1_code":"25.0",
    "gn:admin2_code":"2501.0",
    "gn:admin3_code":"250106.0",
    "gn:admin4_code":"25010611.0",
    "gn:asciiname":"El Alto del Jamo",
    "gn:country_code":"DO",
    "gn:dem":766,
    "gn:feature_class":"P",
    "gn:feature_code":"PPL",
    "gn:name":"El Alto del Jamo",
    "gn:population":0,
    "gn:timezone":"America/Santo_Domingo",
    "iso:country":"DO",
    "name:und_x_variant":[
        "El Alto",
        "El Alto del Jamo"
    ],
    "wof:name":"El Alto del Jamo",
    "wof:placetype":"locality"
},
  "geometry": {"coordinates":[-70.68705,19.55933],"type":"Point"}
}