{
  "type": "Feature",
  "properties": {
    "gn:admin1_code":"31.0",
    "gn:admin2_code":"2801.0",
    "gn:admin3_code":"280102.0",
    "gn:admin4_code":"28010202.0",
    "gn:asciiname":"Los Platanitos",
    "gn:country_code":"DO",
    "gn:dem":185,
    "gn:feature_class":"P",
    "gn:feature_code":"PPL",
    "gn:name":"Los Platanitos",
    "gn:population":0,
    "gn:timezone":"America/Santo_Domingo",
    "iso:country":"DO",
    "wof:name":"Los Platanitos",
    "wof:placetype":"locality"
},
  "geometry": {"coordinates":[-70.45664000000002,19.06501],"type":"Point"}
}