{
  "type": "Feature",
  "properties": {
    "gn:country":"DO",
    "gn:fcode":"PPL",
    "gn:pop":3038,
    "iso:country":"DO",
    "name:cat_x_preferred":[
        "Jaquimeyes"
    ],
    "name:chi_x_preferred":[
        "\u54c8\u57fa\u6885\u8036\u65af"
    ],
    "name:dut_x_preferred":[
        "Jaquimeyes"
    ],
    "name:eng_x_preferred":[
        "Jaquimeyes"
    ],
    "name:fre_x_preferred":[
        "Jaquimeyes"
    ],
    "name:ita_x_preferred":[
        "Jaquimeyes"
    ],
    "name:jpn_x_preferred":[
        "\u30cf\u30ad\u30e1\u30a4\u30a7\u30b9"
    ],
    "name:nan_x_preferred":[
        "Jaquimeyes"
    ],
    "name:por_x_preferred":[
        "Jaquimeyes"
    ],
    "name:swe_x_preferred":[
        "Jaquimeyes"
    ],
    "name:unk_x_variant":[
        "Los Jaquimelles"
    ],
    "name:urd_x_preferred":[
        "\u062c\u0642\u06cc\u0645\u06cc\u0633"
    ],
    "qs:name":"Jaquimeyes",
    "qs:photos_9r":0,
    "qs:photos_sr":0,
    "qs:pop_sr":"4",
    "wd:wordcount":19,
    "wof:name":"Jaquimeyes",
    "wof:placetype":"locality",
    "wof:population":3038
},
  "geometry": {"coordinates":[-71.16145,18.31173],"type":"Point"}
}