{
  "type": "Feature",
  "properties": {
    "gn:admin1_code":"6.0",
    "gn:admin2_code":"602.0",
    "gn:admin3_code":"60202.0",
    "gn:admin4_code":"6020204.0",
    "gn:asciiname":"Las Carreras",
    "gn:country_code":"DO",
    "gn:dem":7,
    "gn:feature_class":"P",
    "gn:feature_code":"PPL",
    "gn:name":"Las Carreras",
    "gn:population":0,
    "gn:timezone":"America/Santo_Domingo",
    "iso:country":"DO",
    "wof:name":"Las Carreras",
    "wof:placetype":"locality"
},
  "geometry": {"coordinates":[-69.78333000000001,19.16667],"type":"Point"}
}