{
  "type": "Feature",
  "properties": {
    "gn:admin1_code":"10.0",
    "gn:admin2_code":"1101.0",
    "gn:admin3_code":"110103.0",
    "gn:admin4_code":"11010303.0",
    "gn:asciiname":"La Curtiembre",
    "gn:country_code":"DO",
    "gn:dem":95,
    "gn:feature_class":"P",
    "gn:feature_code":"PPL",
    "gn:name":"La Curtiembre",
    "gn:population":0,
    "gn:timezone":"America/Santo_Domingo",
    "iso:country":"DO",
    "name:und_x_variant":[
        "La Cuitiembre",
        "La Cultiembre",
        "La Curtiembre"
    ],
    "wof:name":"La Curtiembre",
    "wof:placetype":"locality"
},
  "geometry": {"coordinates":[-68.67553000000001,18.75724],"type":"Point"}
}