{
  "type": "Feature",
  "properties": {
    "gn:admin1_code":"2.0",
    "gn:admin2_code":"301.0",
    "gn:admin3_code":"30101.0",
    "gn:admin4_code":"3010107.0",
    "gn:asciiname":"El Gajo",
    "gn:cc2":"DO",
    "gn:country_code":"DO",
    "gn:dem":1185,
    "gn:feature_class":"P",
    "gn:feature_code":"PPL",
    "gn:name":"El Gajo",
    "gn:population":0,
    "gn:timezone":"America/Santo_Domingo",
    "iso:country":"DO",
    "name:und_x_variant":[
        "El Gojo",
        "El Gajo"
    ],
    "wof:name":"El Gajo",
    "wof:placetype":"locality"
},
  "geometry": {"coordinates":[-71.36667,18.58333],"type":"Point"}
}