{
  "type": "Feature",
  "properties": {
    "gn:admin1_code":"30.0",
    "gn:admin2_code":"1301.0",
    "gn:admin3_code":"130101.0",
    "gn:admin4_code":"13010103.0",
    "gn:asciiname":"Jamo",
    "gn:country_code":"DO",
    "gn:dem":75,
    "gn:feature_class":"P",
    "gn:feature_code":"PPL",
    "gn:name":"Jamo",
    "gn:population":0,
    "gn:timezone":"America/Santo_Domingo",
    "iso:country":"DO",
    "name:und_x_variant":[
        "Bacu\u00ed",
        "Jamo"
    ],
    "wof:name":"Jamo",
    "wof:placetype":"locality"
},
  "geometry": {"coordinates":[-70.45213000000003,19.23294],"type":"Point"}
}