{
  "type": "Feature",
  "properties": {
    "gn:admin1_code":"25.0",
    "gn:admin2_code":"2508.0",
    "gn:admin3_code":"250802.0",
    "gn:admin4_code":"25080202.0",
    "gn:asciiname":"La Zanja",
    "gn:country_code":"DO",
    "gn:dem":279,
    "gn:feature_class":"P",
    "gn:feature_code":"PPL",
    "gn:name":"La Zanja",
    "gn:population":0,
    "gn:timezone":"America/Santo_Domingo",
    "iso:country":"DO",
    "wof:name":"La Zanja",
    "wof:placetype":"locality"
},
  "geometry": {"coordinates":[-70.66667,19.35],"type":"Point"}
}