{
  "type": "Feature",
  "properties": {
    "gn:admin1_code":"21.0",
    "gn:admin2_code":"2404.0",
    "gn:admin3_code":"240402.0",
    "gn:admin4_code":"24040203.0",
    "gn:asciiname":"Jobo Macho",
    "gn:country_code":"DO",
    "gn:dem":36,
    "gn:feature_class":"P",
    "gn:feature_code":"PPL",
    "gn:name":"Jobo Macho",
    "gn:population":0,
    "gn:timezone":"America/Santo_Domingo",
    "iso:country":"DO",
    "wof:name":"Jobo Macho",
    "wof:placetype":"locality"
},
  "geometry": {"coordinates":[-70.12578000000001,19.15337],"type":"Point"}
}