{
  "type": "Feature",
  "properties": {
    "gn:admin1_code":"28.0",
    "gn:admin2_code":"801.0",
    "gn:admin3_code":"80103.0",
    "gn:admin4_code":"8010303.0",
    "gn:asciiname":"Canada Mala",
    "gn:country_code":"DO",
    "gn:dem":94,
    "gn:feature_class":"P",
    "gn:feature_code":"PPL",
    "gn:name":"Ca\u00f1ada Mala",
    "gn:population":0,
    "gn:timezone":"America/Santo_Domingo",
    "iso:country":"DO",
    "wof:name":"Canada Mala",
    "wof:placetype":"locality"
},
  "geometry": {"coordinates":[-69.19449,18.81819],"type":"Point"}
}