{
  "type": "Feature",
  "properties": {
    "gn:admin1_code":"25.0",
    "gn:admin2_code":"2509.0",
    "gn:admin3_code":"250901.0",
    "gn:admin4_code":"25090102.0",
    "gn:asciiname":"La Caleta",
    "gn:country_code":"DO",
    "gn:dem":298,
    "gn:feature_class":"P",
    "gn:feature_code":"PPL",
    "gn:name":"La Caleta",
    "gn:population":0,
    "gn:timezone":"America/Santo_Domingo",
    "iso:country":"DO",
    "name:und_x_variant":[
        "La Galeta",
        "La Caleta"
    ],
    "wof:name":"La Caleta",
    "wof:placetype":"locality"
},
  "geometry": {"coordinates":[-70.73864,19.33314],"type":"Point"}
}