{
  "type": "Feature",
  "properties": {
    "gn:admin1_code":"25.0",
    "gn:admin2_code":"2506.0",
    "gn:admin3_code":"250601.0",
    "gn:admin4_code":"25060103.0",
    "gn:asciiname":"Guazumal Abajo",
    "gn:country_code":"DO",
    "gn:dem":245,
    "gn:feature_class":"P",
    "gn:feature_code":"PPL",
    "gn:name":"Guazumal Abajo",
    "gn:population":0,
    "gn:timezone":"America/Santo_Domingo",
    "iso:country":"DO",
    "wof:name":"Guazumal Abajo",
    "wof:placetype":"locality"
},
  "geometry": {"coordinates":[-70.62574000000002,19.47815],"type":"Point"}
}