{
  "type": "Feature",
  "properties": {
    "gn:admin1_code":"35.0",
    "gn:admin2_code":"1701.0",
    "gn:admin3_code":"170101.0",
    "gn:admin4_code":"17010113.0",
    "gn:asciiname":"La Bejuquera",
    "gn:country_code":"DO",
    "gn:dem":696,
    "gn:feature_class":"P",
    "gn:feature_code":"PPL",
    "gn:name":"La Bejuquera",
    "gn:population":0,
    "gn:timezone":"America/Santo_Domingo",
    "iso:country":"DO",
    "name:und_x_variant":[
        "Bejuquera",
        "La Bejuquera"
    ],
    "wof:name":"La Bejuquera",
    "wof:placetype":"locality"
},
  "geometry": {"coordinates":[-70.27297,18.44465],"type":"Point"}
}