{
  "type": "Feature",
  "properties": {
    "gn:admin1_code":"37.0",
    "gn:admin2_code":"3203.0",
    "gn:admin3_code":"320301.0",
    "gn:admin4_code":"32030105.0",
    "gn:asciiname":"La Jina",
    "gn:country_code":"DO",
    "gn:dem":39,
    "gn:feature_class":"P",
    "gn:feature_code":"PPL",
    "gn:name":"La Jina",
    "gn:population":0,
    "gn:timezone":"America/Santo_Domingo",
    "iso:country":"DO",
    "name:und_x_variant":[
        "La Gina",
        "La Ginita",
        "La Jina"
    ],
    "wof:name":"La Jina",
    "wof:placetype":"locality"
},
  "geometry": {"coordinates":[-69.97798,18.57244],"type":"Point"}
}