{
  "type": "Feature",
  "properties": {
    "gn:admin1_code":"25.0",
    "gn:admin2_code":"2509.0",
    "gn:admin3_code":"250901.0",
    "gn:admin4_code":"25090104.0",
    "gn:asciiname":"Canaveral",
    "gn:country_code":"DO",
    "gn:dem":265,
    "gn:feature_class":"P",
    "gn:feature_code":"PPL",
    "gn:name":"Ca\u00f1averal",
    "gn:population":0,
    "gn:timezone":"America/Santo_Domingo",
    "iso:country":"DO",
    "name:ceb_x_preferred":[
        "Ca\u00f1averal"
    ],
    "name:nld_x_preferred":[
        "Ca\u00f1averal"
    ],
    "name:por_x_preferred":[
        "Canaveral"
    ],
    "name:rus_x_preferred":[
        "\u041a\u0430\u043d\u044c\u044f\u0432\u0435\u0440\u0430\u043b\u044c"
    ],
    "name:spa_x_preferred":[
        "Ca\u00f1averal"
    ],
    "name:swe_x_preferred":[
        "Ca\u00f1averal"
    ],
    "wof:name":"Canaveral",
    "wof:placetype":"locality"
},
  "geometry": {"coordinates":[-70.71514000000001,19.30827],"type":"Point"}
}