{
  "type": "Feature",
  "properties": {
    "gn:admin1_code":"30.0",
    "gn:admin2_code":"1301.0",
    "gn:admin3_code":"130101.0",
    "gn:admin4_code":"13010101.0",
    "gn:asciiname":"Ponton",
    "gn:country_code":"DO",
    "gn:dem":87,
    "gn:feature_class":"P",
    "gn:feature_code":"PPL",
    "gn:name":"Pont\u00f3n",
    "gn:population":0,
    "gn:timezone":"America/Santo_Domingo",
    "iso:country":"DO",
    "name:deu_x_preferred":[
        "Ponton"
    ],
    "name:fra_x_preferred":[
        "Ponton"
    ],
    "name:heb_x_preferred":[
        "\u05e4\u05d5\u05e0\u05d8\u05d5\u05df"
    ],
    "name:pol_x_preferred":[
        "Ponton"
    ],
    "name:swe_x_preferred":[
        "Ponton"
    ],
    "wof:name":"Ponton",
    "wof:placetype":"locality"
},
  "geometry": {"coordinates":[-70.50591999999997,19.20406],"type":"Point"}
}