{
  "type": "Feature",
  "properties": {
    "gn:admin1_code":"30.0",
    "gn:admin2_code":"1301.0",
    "gn:admin3_code":"130101.0",
    "gn:admin4_code":"13010115.0",
    "gn:asciiname":"Aguas Altas",
    "gn:country_code":"DO",
    "gn:dem":263,
    "gn:feature_class":"P",
    "gn:feature_code":"PPL",
    "gn:name":"Aguas Altas",
    "gn:population":0,
    "gn:timezone":"America/Santo_Domingo",
    "iso:country":"DO",
    "wof:name":"Aguas Altas",
    "wof:placetype":"locality"
},
  "geometry": {"coordinates":[-70.51796,19.15546],"type":"Point"}
}