{
  "type": "Feature",
  "properties": {
    "gn:admin1_code":"35.0",
    "gn:admin2_code":"1701.0",
    "gn:admin3_code":"170101.0",
    "gn:admin4_code":"17010107.0",
    "gn:asciiname":"Honduras",
    "gn:country_code":"DO",
    "gn:dem":319,
    "gn:feature_class":"P",
    "gn:feature_code":"PPL",
    "gn:name":"Honduras",
    "gn:population":0,
    "gn:timezone":"America/Santo_Domingo",
    "iso:country":"DO",
    "wof:name":"Honduras",
    "wof:placetype":"locality"
},
  "geometry": {"coordinates":[-70.43768,18.38124],"type":"Point"}
}