{
  "type": "Feature",
  "properties": {
    "gn:admin1_code":"31.0",
    "gn:admin2_code":"2801.0",
    "gn:admin3_code":"280101.0",
    "gn:admin4_code":"28010103.0",
    "gn:asciiname":"Punta del Pino",
    "gn:country_code":"DO",
    "gn:dem":904,
    "gn:feature_class":"P",
    "gn:feature_code":"PPL",
    "gn:name":"Punta del Pino",
    "gn:population":0,
    "gn:timezone":"America/Santo_Domingo",
    "iso:country":"DO",
    "name:und_x_variant":[
        "Puerta del Pino",
        "Punta del Pino"
    ],
    "wof:name":"Punta del Pino",
    "wof:placetype":"locality"
},
  "geometry": {"coordinates":[-70.47569,18.98695],"type":"Point"}
}