{
  "type": "Feature",
  "properties": {
    "gn:admin1_code":"23.0",
    "gn:admin2_code":"2201.0",
    "gn:admin3_code":"220103.0",
    "gn:admin4_code":"22010304.0",
    "gn:asciiname":"Gajo de Bohio",
    "gn:country_code":"DO",
    "gn:dem":840,
    "gn:feature_class":"P",
    "gn:feature_code":"PPL",
    "gn:name":"Gajo de Boh\u00edo",
    "gn:population":0,
    "gn:timezone":"America/Santo_Domingo",
    "iso:country":"DO",
    "name:und_x_variant":[
        "Boca del Arroyo",
        "Gajo de Boechio",
        "Gajo del Boh\u00edo",
        "Gajo de Boh\u00edo"
    ],
    "wof:name":"Gajo de Bohio",
    "wof:placetype":"locality"
},
  "geometry": {"coordinates":[-71.36564,19.07678],"type":"Point"}
}