{
  "type": "Feature",
  "properties": {
    "gn:admin1_code":"28.0",
    "gn:admin2_code":"801.0",
    "gn:admin3_code":"80101.0",
    "gn:admin4_code":"8010106.0",
    "gn:asciiname":"Canada de La Vaca",
    "gn:country_code":"DO",
    "gn:dem":151,
    "gn:feature_class":"P",
    "gn:feature_code":"PPL",
    "gn:name":"Ca\u00f1ada de La Vaca",
    "gn:population":0,
    "gn:timezone":"America/Santo_Domingo",
    "iso:country":"DO",
    "name:und_x_variant":[
        "Ca\u00f1ada de Vaca",
        "Ca\u00f1ada de La Vaca"
    ],
    "wof:name":"Canada de La Vaca",
    "wof:placetype":"locality"
},
  "geometry": {"coordinates":[-68.95139,18.7408],"type":"Point"}
}