{
  "type": "Feature",
  "properties": {
    "gn:admin1_code":"18.0",
    "gn:admin2_code":"1802.0",
    "gn:admin3_code":"180201.0",
    "gn:admin4_code":"18020104.0",
    "gn:asciiname":"Guaranal",
    "gn:country_code":"DO",
    "gn:dem":391,
    "gn:feature_class":"P",
    "gn:feature_code":"PPL",
    "gn:name":"Guaranal",
    "gn:population":0,
    "gn:timezone":"America/Santo_Domingo",
    "iso:country":"DO",
    "wof:name":"Guaranal",
    "wof:placetype":"locality"
},
  "geometry": {"coordinates":[-70.86856,19.692],"type":"Point"}
}