{
  "type": "Feature",
  "properties": {
    "gn:admin1_code":"11.0",
    "gn:admin2_code":"702.0",
    "gn:admin3_code":"70203.0",
    "gn:admin4_code":"7020304.0",
    "gn:asciiname":"Charco Colorado",
    "gn:country_code":"DO",
    "gn:dem":506,
    "gn:feature_class":"P",
    "gn:feature_code":"PPL",
    "gn:name":"Charco Colorado",
    "gn:population":0,
    "gn:timezone":"America/Santo_Domingo",
    "iso:country":"DO",
    "name:und_x_variant":[
        "Charco Colorao",
        "Charco Colorado"
    ],
    "wof:name":"Charco Colorado",
    "wof:placetype":"locality"
},
  "geometry": {"coordinates":[-71.52254000000001,19.02022],"type":"Point"}
}