{
  "type": "Feature",
  "properties": {
    "gn:admin1_code":"11.0",
    "gn:admin2_code":"702.0",
    "gn:admin3_code":"70201.0",
    "gn:admin4_code":"7020102.0",
    "gn:asciiname":"Rincon Bellaco",
    "gn:country_code":"DO",
    "gn:dem":400,
    "gn:feature_class":"P",
    "gn:feature_code":"PPL",
    "gn:name":"Rinc\u00f3n Bellaco",
    "gn:population":0,
    "gn:timezone":"America/Santo_Domingo",
    "iso:country":"DO",
    "wof:name":"Rincon Bellaco",
    "wof:placetype":"locality"
},
  "geometry": {"coordinates":[-71.62084,19.0418],"type":"Point"}
}