{
  "type": "Feature",
  "properties": {
    "gn:admin1_code":"36.0",
    "gn:admin2_code":"3101.0",
    "gn:admin3_code":"310102.0",
    "gn:admin4_code":"31010203.0",
    "gn:asciiname":"Paso Hondo",
    "gn:country_code":"DO",
    "gn:dem":765,
    "gn:feature_class":"P",
    "gn:feature_code":"PPL",
    "gn:name":"Paso Hondo",
    "gn:population":0,
    "gn:timezone":"America/Santo_Domingo",
    "iso:country":"DO",
    "wof:name":"Paso Hondo",
    "wof:placetype":"locality"
},
  "geometry": {"coordinates":[-70.40999000000002,18.56732],"type":"Point"}
}