{
  "type": "Feature",
  "properties": {
    "gn:admin1_code":"29.0",
    "gn:admin2_code":"3001.0",
    "gn:admin3_code":"300103.0",
    "gn:admin4_code":"30010303.0",
    "gn:asciiname":"Batey Numero Seis",
    "gn:country_code":"DO",
    "gn:dem":22,
    "gn:feature_class":"P",
    "gn:feature_code":"PPL",
    "gn:name":"Batey N\u00famero Seis",
    "gn:population":0,
    "gn:timezone":"America/Santo_Domingo",
    "iso:country":"DO",
    "name:und_x_variant":[
        "Batey N\u00famero 6",
        "Batey N\u00famero Seis"
    ],
    "wof:name":"Batey Numero Seis",
    "wof:placetype":"locality"
},
  "geometry": {"coordinates":[-69.30682,18.59499],"type":"Point"}
}