{
  "type": "Feature",
  "properties": {
    "gn:admin1_code":"29.0",
    "gn:admin2_code":"3001.0",
    "gn:admin3_code":"300101.0",
    "gn:admin4_code":"30010102.0",
    "gn:asciiname":"Batey Altagracia",
    "gn:country_code":"DO",
    "gn:dem":46,
    "gn:feature_class":"P",
    "gn:feature_code":"PPL",
    "gn:name":"Batey Altagracia",
    "gn:population":0,
    "gn:timezone":"America/Santo_Domingo",
    "iso:country":"DO",
    "name:und_x_variant":[
        "Altagracia",
        "Batey Altagracia"
    ],
    "wof:name":"Batey Altagracia",
    "wof:placetype":"locality"
},
  "geometry": {"coordinates":[-69.38292,18.65624],"type":"Point"}
}