{
  "type": "Feature",
  "properties": {
    "gn:admin1_code":"25.0",
    "gn:admin2_code":"2505.0",
    "gn:admin3_code":"250502.0",
    "gn:admin4_code":"25050209.0",
    "gn:asciiname":"Pino Bonito",
    "gn:country_code":"DO",
    "gn:dem":476,
    "gn:feature_class":"P",
    "gn:feature_code":"PPL",
    "gn:name":"Pino Bonito",
    "gn:population":0,
    "gn:timezone":"America/Santo_Domingo",
    "iso:country":"DO",
    "wof:name":"Pino Bonito",
    "wof:placetype":"locality"
},
  "geometry": {"coordinates":[-71.19289000000001,19.36966],"type":"Point"}
}