{
  "type": "Feature",
  "properties": {
    "gn:admin1_code":"35.0",
    "gn:admin2_code":"1701.0",
    "gn:admin3_code":"170105.0",
    "gn:admin4_code":"17010504.0",
    "gn:asciiname":"Ojo de Agua",
    "gn:country_code":"DO",
    "gn:dem":85,
    "gn:feature_class":"P",
    "gn:feature_code":"PPL",
    "gn:name":"Ojo de Agua",
    "gn:population":0,
    "gn:timezone":"America/Santo_Domingo",
    "iso:country":"DO",
    "name:und_x_variant":[
        "El ojo de Agua",
        "Ojo de Agua"
    ],
    "wof:name":"Ojo de Agua",
    "wof:placetype":"locality"
},
  "geometry": {"coordinates":[-70.27024,18.27006],"type":"Point"}
}