{
  "type": "Feature",
  "properties": {
    "gn:admin1_code":"25.0",
    "gn:admin2_code":"2508.0",
    "gn:admin3_code":"250802.0",
    "gn:admin4_code":"25080202.0",
    "gn:asciiname":"Los Melados",
    "gn:cc2":"DO",
    "gn:country_code":"DO",
    "gn:dem":371,
    "gn:feature_class":"P",
    "gn:feature_code":"PPL",
    "gn:name":"Los Melados",
    "gn:population":0,
    "gn:timezone":"America/Santo_Domingo",
    "iso:country":"DO",
    "name:und_x_variant":[
        "Los Melaos",
        "Los Melados"
    ],
    "wof:name":"Los Melados",
    "wof:placetype":"locality"
},
  "geometry": {"coordinates":[-70.68333,19.35],"type":"Point"}
}