{
  "type": "Feature",
  "properties": {
    "gn:admin1_code":"15.0",
    "gn:admin2_code":"1501.0",
    "gn:admin3_code":"150101.0",
    "gn:admin4_code":"15010103.0",
    "gn:asciiname":"Carnero",
    "gn:country_code":"DO",
    "gn:dem":19,
    "gn:feature_class":"P",
    "gn:feature_code":"PPL",
    "gn:name":"Carnero",
    "gn:population":0,
    "gn:timezone":"America/Santo_Domingo",
    "iso:country":"DO",
    "name:und_x_variant":[
        "Carmona",
        "Carnero"
    ],
    "wof:name":"Carnero",
    "wof:placetype":"locality"
},
  "geometry": {"coordinates":[-71.54156,19.69208],"type":"Point"}
}