{
  "type": "Feature",
  "properties": {
    "gn:admin1_code":"25.0",
    "gn:admin2_code":"2501.0",
    "gn:admin3_code":"250105.0",
    "gn:admin4_code":"25010503.0",
    "gn:asciiname":"Sabana Grande",
    "gn:country_code":"DO",
    "gn:dem":159,
    "gn:feature_class":"P",
    "gn:feature_code":"PPL",
    "gn:name":"Sabana Grande",
    "gn:population":0,
    "gn:timezone":"America/Santo_Domingo",
    "iso:country":"DO",
    "wof:name":"Sabana Grande",
    "wof:placetype":"locality"
},
  "geometry": {"coordinates":[-70.80696999999998,19.47926],"type":"Point"}
}