{
  "type": "Feature",
  "properties": {
    "gn:admin1_code":"30.0",
    "gn:admin2_code":"1302.0",
    "gn:admin3_code":"130202.0",
    "gn:admin4_code":"13020205.0",
    "gn:asciiname":"El Arroyazo",
    "gn:country_code":"DO",
    "gn:dem":1038,
    "gn:feature_class":"P",
    "gn:feature_code":"PPL",
    "gn:name":"El Arroyazo",
    "gn:population":0,
    "gn:timezone":"America/Santo_Domingo",
    "iso:country":"DO",
    "name:und_x_variant":[
        "Arroyaso",
        "El Arroyazo"
    ],
    "wof:name":"El Arroyazo",
    "wof:placetype":"locality"
},
  "geometry": {"coordinates":[-70.55103000000003,19.0169],"type":"Point"}
}