{
  "type": "Feature",
  "properties": {
    "gn:admin1_code":"18.0",
    "gn:admin2_code":"1801.0",
    "gn:admin3_code":"180101.0",
    "gn:admin4_code":"18010101.0",
    "gn:asciiname":"San Marcos Abajo",
    "gn:country_code":"DO",
    "gn:dem":26,
    "gn:feature_class":"P",
    "gn:feature_code":"PPL",
    "gn:name":"San Marcos Abajo",
    "gn:population":0,
    "gn:timezone":"America/Santo_Domingo",
    "iso:country":"DO",
    "wof:name":"San Marcos Abajo",
    "wof:placetype":"locality"
},
  "geometry": {"coordinates":[-70.72568000000003,19.79123],"type":"Point"}
}