{
  "type": "Feature",
  "properties": {
    "gn:admin1_code":"20.0",
    "gn:admin2_code":"2002.0",
    "gn:admin3_code":"200201.0",
    "gn:admin4_code":"20020105.0",
    "gn:asciiname":"La Placeta",
    "gn:country_code":"DO",
    "gn:dem":263,
    "gn:feature_class":"P",
    "gn:feature_code":"PPL",
    "gn:name":"La Placeta",
    "gn:population":0,
    "gn:timezone":"America/Santo_Domingo",
    "iso:country":"DO",
    "wof:name":"La Placeta",
    "wof:placetype":"locality"
},
  "geometry": {"coordinates":[-69.49347,19.257],"type":"Point"}
}