{
  "type": "Feature",
  "properties": {
    "gn:admin1_code":"36.0",
    "gn:admin2_code":"3101.0",
    "gn:admin3_code":"310104.0",
    "gn:admin4_code":"31010402.0",
    "gn:asciiname":"Los Helechos",
    "gn:country_code":"DO",
    "gn:dem":706,
    "gn:feature_class":"P",
    "gn:feature_code":"PPL",
    "gn:name":"Los Helechos",
    "gn:population":0,
    "gn:timezone":"America/Santo_Domingo",
    "iso:country":"DO",
    "name:ceb_x_preferred":[
        "Los Helechos"
    ],
    "name:por_x_preferred":[
        "Los Helechos"
    ],
    "name:spa_x_preferred":[
        "Los Helechos"
    ],
    "name:swe_x_preferred":[
        "Los Helechos"
    ],
    "wof:name":"Los Helechos",
    "wof:placetype":"locality"
},
  "geometry": {"coordinates":[-70.54375,18.52488],"type":"Point"}
}