{
  "type": "Feature",
  "properties": {
    "gn:admin1_code":"3.0",
    "gn:admin2_code":"407.0",
    "gn:admin3_code":"40701.0",
    "gn:admin4_code":"4070102.0",
    "gn:asciiname":"Majagualito",
    "gn:country_code":"DO",
    "gn:dem":578,
    "gn:feature_class":"P",
    "gn:feature_code":"PPL",
    "gn:name":"Majagualito",
    "gn:population":0,
    "gn:timezone":"America/Santo_Domingo",
    "iso:country":"DO",
    "wof:name":"Majagualito",
    "wof:placetype":"locality"
},
  "geometry": {"coordinates":[-71.14530000000001,18.0432],"type":"Point"}
}