{
  "type": "Feature",
  "properties": {
    "gn:admin1_code":"10.0",
    "gn:admin2_code":"1101.0",
    "gn:admin3_code":"110101.0",
    "gn:admin4_code":"11010106.0",
    "gn:asciiname":"Hoyo Bonito",
    "gn:country_code":"DO",
    "gn:dem":80,
    "gn:feature_class":"P",
    "gn:feature_code":"PPL",
    "gn:name":"Hoyo Bonito",
    "gn:population":0,
    "gn:timezone":"America/Santo_Domingo",
    "iso:country":"DO",
    "wof:name":"Hoyo Bonito",
    "wof:placetype":"locality"
},
  "geometry": {"coordinates":[-68.7698,18.58003],"type":"Point"}
}