{
  "type": "Feature",
  "properties": {
    "gn:admin1_code":"32.0",
    "gn:admin2_code":"2903.0",
    "gn:admin3_code":"290302.0",
    "gn:admin4_code":"29030204.0",
    "gn:asciiname":"La Osua",
    "gn:country_code":"DO",
    "gn:dem":292,
    "gn:feature_class":"P",
    "gn:feature_code":"PPL",
    "gn:name":"La Os\u00faa",
    "gn:population":0,
    "gn:timezone":"America/Santo_Domingo",
    "iso:country":"DO",
    "name:und_x_variant":[
        "Las Hos\u00faas",
        "La Os\u00faa"
    ],
    "wof:name":"La Osua",
    "wof:placetype":"locality"
},
  "geometry": {"coordinates":[-69.70260999999999,18.9764],"type":"Point"}
}