{
  "type": "Feature",
  "properties": {
    "gn:admin1_code":"18.0",
    "gn:admin2_code":"1807.0",
    "gn:admin3_code":"180701.0",
    "gn:admin4_code":"18070103.0",
    "gn:asciiname":"Loma Blanca",
    "gn:country_code":"DO",
    "gn:dem":191,
    "gn:feature_class":"P",
    "gn:feature_code":"PPL",
    "gn:name":"Loma Blanca",
    "gn:population":0,
    "gn:timezone":"America/Santo_Domingo",
    "iso:country":"DO",
    "name:hye_x_preferred":[
        "\u053c\u0578\u0574\u0561 \u0532\u056c\u0561\u0576\u056f\u0561"
    ],
    "name:rus_x_preferred":[
        "\u041b\u043e\u043c\u0430-\u0411\u043b\u0430\u043d\u043a\u0430"
    ],
    "name:spa_x_preferred":[
        "Loma Blanca"
    ],
    "wof:name":"Loma Blanca",
    "wof:placetype":"locality"
},
  "geometry": {"coordinates":[-70.54545999999998,19.69825],"type":"Point"}
}