{
  "type": "Feature",
  "properties": {
    "gn:admin1_code":"30.0",
    "gn:admin2_code":"1301.0",
    "gn:admin3_code":"130101.0",
    "gn:admin4_code":"13010105.0",
    "gn:asciiname":"Carrera de Palma",
    "gn:country_code":"DO",
    "gn:dem":136,
    "gn:feature_class":"P",
    "gn:feature_code":"PPL",
    "gn:name":"Carrera de Palma",
    "gn:population":0,
    "gn:timezone":"America/Santo_Domingo",
    "iso:country":"DO",
    "name:und_x_variant":[
        "Carrera de la Palma",
        "Carrera de Palmas",
        "Carrera de Palma"
    ],
    "wof:name":"Carrera de Palma",
    "wof:placetype":"locality"
},
  "geometry": {"coordinates":[-70.53574999999999,19.28212000000001],"type":"Point"}
}