{
  "type": "Feature",
  "properties": {
    "iso:country":"DO",
    "name:und_x_variant":[
        "Soco"
    ],
    "qs:gn_country":"DO",
    "qs:gn_fcode":"PPL",
    "qs:gn_pop":0,
    "qs:name":"El Soco",
    "qs:name_adm0":"Rep\u00fablica Dominicana",
    "qs:name_adm1":"San Pedro de Marcoris",
    "qs:photos":280,
    "qs:photos_1k":57,
    "qs:photos_9k":1,
    "qs:photos_9r":4,
    "qs:photos_all":280,
    "qs:photos_sr":5,
    "qs:placetype":"Town",
    "qs:pop_sr":"3",
    "qs:woe_adm0":23424800,
    "wof:name":"El Soco",
    "wof:placetype":"locality"
},
  "geometry": {"coordinates":[-69.19156,18.45012],"type":"Point"}
}