{
  "type": "Feature",
  "properties": {
    "gn:admin1_code":"23.0",
    "gn:admin2_code":"2201.0",
    "gn:admin3_code":"220103.0",
    "gn:admin4_code":"22010305.0",
    "gn:asciiname":"Palo de Viento",
    "gn:country_code":"DO",
    "gn:dem":1486,
    "gn:feature_class":"P",
    "gn:feature_code":"PPL",
    "gn:name":"Palo de Viento",
    "gn:population":0,
    "gn:timezone":"America/Santo_Domingo",
    "iso:country":"DO",
    "wof:name":"Palo de Viento",
    "wof:placetype":"locality"
},
  "geometry": {"coordinates":[-71.30877,19.14605],"type":"Point"}
}