{
  "type": "Feature",
  "properties": {
    "gn:admin1_code":"31.0",
    "gn:admin2_code":"2801.0",
    "gn:admin3_code":"280104.0",
    "gn:admin4_code":"28010402.0",
    "gn:asciiname":"La Yerba",
    "gn:country_code":"DO",
    "gn:dem":572,
    "gn:feature_class":"P",
    "gn:feature_code":"PPL",
    "gn:name":"La Yerba",
    "gn:population":0,
    "gn:timezone":"America/Santo_Domingo",
    "iso:country":"DO",
    "wof:name":"La Yerba",
    "wof:placetype":"locality"
},
  "geometry": {"coordinates":[-70.46245999999999,18.91785],"type":"Point"}
}