{
  "type": "Feature",
  "properties": {
    "gn:admin1_code":"18.0",
    "gn:admin2_code":"1807.0",
    "gn:admin3_code":"180701.0",
    "gn:admin4_code":"18070103.0",
    "gn:asciiname":"El Guamo",
    "gn:country_code":"DO",
    "gn:dem":91,
    "gn:feature_class":"P",
    "gn:feature_code":"PPL",
    "gn:name":"El Guamo",
    "gn:population":0,
    "gn:timezone":"America/Santo_Domingo",
    "iso:country":"DO",
    "name:ceb_x_preferred":[
        "El Guamo"
    ],
    "name:fra_x_preferred":[
        "El Guamo"
    ],
    "name:ita_x_preferred":[
        "El Guamo"
    ],
    "name:kat_x_preferred":[
        "\u10d4\u10da-\u10d2\u10e3\u10d0\u10db\u10dd"
    ],
    "name:msa_x_preferred":[
        "El Guamo"
    ],
    "name:nld_x_preferred":[
        "El Guamo"
    ],
    "name:por_x_preferred":[
        "El Guamo"
    ],
    "name:rus_x_preferred":[
        "\u042d\u043b\u044c-\u0413\u0443\u0430\u043c\u043e"
    ],
    "name:spa_x_preferred":[
        "El Guamo"
    ],
    "name:swe_x_preferred":[
        "El Guamo"
    ],
    "name:tgl_x_preferred":[
        "El Guamo"
    ],
    "name:und_x_variant":[
        "El Guano"
    ],
    "name:vie_x_preferred":[
        "El Guamo"
    ],
    "name:war_x_preferred":[
        "El Guamo"
    ],
    "name:zho_x_preferred":[
        "\u57c3\u723e\u74dc\u83ab"
    ],
    "wof:name":"El Guamo",
    "wof:placetype":"locality"
},
  "geometry": {"coordinates":[-70.50303000000002,19.73242],"type":"Point"}
}