{
  "type": "Feature",
  "properties": {
    "gn:admin1_code":"18.0",
    "gn:admin2_code":"1807.0",
    "gn:admin3_code":"180701.0",
    "gn:admin4_code":"18070103.0",
    "gn:asciiname":"El Guamo",
    "gn:country_code":"DO",
    "gn:dem":91,
    "gn:feature_class":"P",
    "gn:feature_code":"PPL",
    "gn:name":"El Guamo",
    "gn:population":0,
    "gn:timezone":"America/Santo_Domingo",
    "iso:country":"DO",
    "name:und_x_variant":[
        "El Guano",
        "El Guamo"
    ],
    "wof:name":"El Guamo",
    "wof:placetype":"locality"
},
  "geometry": {"coordinates":[-70.50303000000002,19.73242],"type":"Point"}
}