{
  "type": "Feature",
  "properties": {
    "gn:admin1_code":"33.0",
    "gn:admin2_code":"2108.0",
    "gn:admin3_code":"210801.0",
    "gn:admin4_code":"21080103.0",
    "gn:asciiname":"Vallejo",
    "gn:country_code":"DO",
    "gn:dem":850,
    "gn:feature_class":"P",
    "gn:feature_code":"PPL",
    "gn:name":"Vallejo",
    "gn:population":0,
    "gn:timezone":"America/Santo_Domingo",
    "iso:country":"DO",
    "name:ceb_x_preferred":[
        "Vallejo"
    ],
    "name:deu_x_preferred":[
        "Vallejo"
    ],
    "name:fra_x_preferred":[
        "Vallejo"
    ],
    "name:jpn_x_preferred":[
        "\u30f4\u30a1\u30ec\u30fc\u30aa"
    ],
    "name:kor_x_preferred":[
        "\ubc14\uc608\ud638"
    ],
    "name:pol_x_preferred":[
        "Vallejo"
    ],
    "name:por_x_preferred":[
        "Vallejo"
    ],
    "name:rus_x_preferred":[
        "\u0412\u0430\u043b\u044c\u0435\u0445\u043e"
    ],
    "name:spa_x_preferred":[
        "Vallejo"
    ],
    "name:swe_x_preferred":[
        "Vallejo"
    ],
    "wof:name":"Vallejo",
    "wof:placetype":"locality"
},
  "geometry": {"coordinates":[-70.32568000000001,18.57409],"type":"Point"}
}