{
  "type": "Feature",
  "properties": {
    "gn:admin1_code":"33.0",
    "gn:admin2_code":"2108.0",
    "gn:admin3_code":"210801.0",
    "gn:admin4_code":"21080103.0",
    "gn:asciiname":"Vallejo",
    "gn:country_code":"DO",
    "gn:dem":850,
    "gn:feature_class":"P",
    "gn:feature_code":"PPL",
    "gn:name":"Vallejo",
    "gn:population":0,
    "gn:timezone":"America/Santo_Domingo",
    "iso:country":"DO",
    "wof:name":"Vallejo",
    "wof:placetype":"locality"
},
  "geometry": {"coordinates":[-70.32568000000001,18.57409],"type":"Point"}
}