{
  "type": "Feature",
  "properties": {
    "gn:admin1_code":"35.0",
    "gn:admin2_code":"1701.0",
    "gn:admin3_code":"170105.0",
    "gn:admin4_code":"17010503.0",
    "gn:asciiname":"Mata Gorda",
    "gn:country_code":"DO",
    "gn:dem":43,
    "gn:feature_class":"P",
    "gn:feature_code":"PPL",
    "gn:name":"Mata Gorda",
    "gn:population":0,
    "gn:timezone":"America/Santo_Domingo",
    "iso:country":"DO",
    "wof:name":"Mata Gorda",
    "wof:placetype":"locality"
},
  "geometry": {"coordinates":[-70.31423000000001,18.26554],"type":"Point"}
}