{
  "type": "Feature",
  "properties": {
    "gn:admin1_code":"31.0",
    "gn:admin2_code":"2803.0",
    "gn:admin3_code":"280301.0",
    "gn:admin4_code":"28030103.0",
    "gn:asciiname":"El Cinco",
    "gn:country_code":"DO",
    "gn:dem":145,
    "gn:feature_class":"P",
    "gn:feature_code":"PPL",
    "gn:name":"El Cinco",
    "gn:population":0,
    "gn:timezone":"America/Santo_Domingo",
    "iso:country":"DO",
    "wof:name":"El Cinco",
    "wof:placetype":"locality"
},
  "geometry": {"coordinates":[-70.30747,18.88179],"type":"Point"}
}