{
  "type": "Feature",
  "properties": {
    "gn:admin1_code":"30.0",
    "gn:admin2_code":"1302.0",
    "gn:admin3_code":"130202.0",
    "gn:admin4_code":"13020202.0",
    "gn:asciiname":"Cruz de Cuaba",
    "gn:country_code":"DO",
    "gn:dem":1519,
    "gn:feature_class":"P",
    "gn:feature_code":"PPL",
    "gn:name":"Cruz de Cuaba",
    "gn:population":0,
    "gn:timezone":"America/Santo_Domingo",
    "iso:country":"DO",
    "wof:name":"Cruz de Cuaba",
    "wof:placetype":"locality"
},
  "geometry": {"coordinates":[-70.71892,18.97685],"type":"Point"}
}