{
  "type": "Feature",
  "properties": {
    "gn:admin1_code":"31.0",
    "gn:admin2_code":"2801.0",
    "gn:admin3_code":"280103.0",
    "gn:admin4_code":"28010304.0",
    "gn:asciiname":"Jatico",
    "gn:country_code":"DO",
    "gn:dem":196,
    "gn:feature_class":"P",
    "gn:feature_code":"PPL",
    "gn:name":"J\u00e1tico",
    "gn:population":0,
    "gn:timezone":"America/Santo_Domingo",
    "iso:country":"DO",
    "wof:name":"Jatico",
    "wof:placetype":"locality"
},
  "geometry": {"coordinates":[-70.41167,18.90424],"type":"Point"}
}