{
  "type": "Feature",
  "properties": {
    "gn:admin1_code":"28.0",
    "gn:admin2_code":"801.0",
    "gn:admin3_code":"80101.0",
    "gn:admin4_code":"8010108.0",
    "gn:asciiname":"Las Guazumas",
    "gn:country_code":"DO",
    "gn:dem":83,
    "gn:feature_class":"P",
    "gn:feature_code":"PPL",
    "gn:name":"Las Gu\u00e1zumas",
    "gn:population":0,
    "gn:timezone":"America/Santo_Domingo",
    "iso:country":"DO",
    "name:und_x_variant":[
        "La Guaz\u00fama",
        "Las Gu\u00e1zumas"
    ],
    "wof:name":"Las Guazumas",
    "wof:placetype":"locality"
},
  "geometry": {"coordinates":[-69.19473000000001,18.68527000000001],"type":"Point"}
}