{
  "type": "Feature",
  "properties": {
    "gn:admin1_code":"26.0",
    "gn:admin2_code":"2602.0",
    "gn:admin3_code":"260201.0",
    "gn:admin4_code":"26020103.0",
    "gn:asciiname":"Los Cinco Puercos",
    "gn:country_code":"DO",
    "gn:dem":535,
    "gn:feature_class":"P",
    "gn:feature_code":"PPL",
    "gn:name":"Los Cinco Puercos",
    "gn:population":0,
    "gn:timezone":"America/Santo_Domingo",
    "iso:country":"DO",
    "wof:name":"Los Cinco Puercos",
    "wof:placetype":"locality"
},
  "geometry": {"coordinates":[-71.43315,19.30595],"type":"Point"}
}