{
  "type": "Feature",
  "properties": {
    "gn:admin1_code":"8.0",
    "gn:admin2_code":"901.0",
    "gn:admin3_code":"90107.0",
    "gn:admin4_code":"9010701.0",
    "gn:asciiname":"Higueerito Arriba",
    "gn:country_code":"DO",
    "gn:dem":232,
    "gn:feature_class":"P",
    "gn:feature_code":"PPL",
    "gn:name":"Hig\u00fcerito Arriba",
    "gn:population":0,
    "gn:timezone":"America/Santo_Domingo",
    "iso:country":"DO",
    "wof:name":"Higueerito Arriba",
    "wof:placetype":"locality"
},
  "geometry": {"coordinates":[-70.58413,19.36324],"type":"Point"}
}