{
  "type": "Feature",
  "properties": {
    "gn:admin1_code":"8.0",
    "gn:asciiname":"La Javilla",
    "gn:country_code":"DO",
    "gn:dem":164,
    "gn:feature_class":"P",
    "gn:feature_code":"PPL",
    "gn:name":"La Javilla",
    "gn:population":0,
    "gn:timezone":"America/Santo_Domingo",
    "iso:country":"DO",
    "name:und_x_variant":[
        "La Jabilla",
        "La Javilla"
    ],
    "wof:name":"La Javilla",
    "wof:placetype":"locality"
},
  "geometry": {"coordinates":[-70.58673,19.3878],"type":"Point"}
}