{
  "type": "Feature",
  "properties": {
    "gn:admin1_code":"28.0",
    "gn:admin2_code":"801.0",
    "gn:admin3_code":"80101.0",
    "gn:admin4_code":"8010105.0",
    "gn:asciiname":"Canada del Cacao Abajo",
    "gn:cc2":"DO",
    "gn:country_code":"DO",
    "gn:dem":139,
    "gn:feature_class":"P",
    "gn:feature_code":"PPL",
    "gn:name":"Ca\u00f1ada del Cacao Abajo",
    "gn:population":0,
    "gn:timezone":"America/Santo_Domingo",
    "iso:country":"DO",
    "name:und_x_variant":[
        "Ca\u00f1ada del Cacao",
        "Ca\u00f1ada del Cacao Abajo"
    ],
    "wof:name":"Canada del Cacao Abajo",
    "wof:placetype":"locality"
},
  "geometry": {"coordinates":[-68.96666999999999,18.81667],"type":"Point"}
}