{
  "type": "Feature",
  "properties": {
    "gn:admin1_code":"6.0",
    "gn:admin2_code":"607.0",
    "gn:admin3_code":"60701.0",
    "gn:admin4_code":"6070103.0",
    "gn:asciiname":"Cerrejon",
    "gn:country_code":"DO",
    "gn:dem":24,
    "gn:feature_class":"P",
    "gn:feature_code":"PPL",
    "gn:name":"Cerrej\u00f3n",
    "gn:population":0,
    "gn:timezone":"America/Santo_Domingo",
    "iso:country":"DO",
    "name:und_x_variant":[
        "Cerraj\u00f3n",
        "Cerrej\u00f3n"
    ],
    "wof:name":"Cerrejon",
    "wof:placetype":"locality"
},
  "geometry": {"coordinates":[-69.96455999999999,19.13514],"type":"Point"}
}