{
  "type": "Feature",
  "properties": {
    "gn:admin1_code":"25.0",
    "gn:admin2_code":"2503.0",
    "gn:admin3_code":"250301.0",
    "gn:admin4_code":"25030105.0",
    "gn:asciiname":"Jagua Abajo",
    "gn:country_code":"DO",
    "gn:dem":725,
    "gn:feature_class":"P",
    "gn:feature_code":"PPL",
    "gn:name":"Jagua Abajo",
    "gn:population":0,
    "gn:timezone":"America/Santo_Domingo",
    "iso:country":"DO",
    "wof:name":"Jagua Abajo",
    "wof:placetype":"locality"
},
  "geometry": {"coordinates":[-70.79518,19.25819],"type":"Point"}
}