{
  "type": "Feature",
  "properties": {
    "gn:admin1_code":"33.0",
    "gn:admin2_code":"2101.0",
    "gn:admin3_code":"210102.0",
    "gn:admin4_code":"21010202.0",
    "gn:asciiname":"Ingenge",
    "gn:country_code":"DO",
    "gn:dem":81,
    "gn:feature_class":"P",
    "gn:feature_code":"PPL",
    "gn:name":"Ingenge",
    "gn:population":0,
    "gn:timezone":"America/Santo_Domingo",
    "iso:country":"DO",
    "wof:name":"Ingenge",
    "wof:placetype":"locality"
},
  "geometry": {"coordinates":[-70.10089000000001,18.51881],"type":"Point"}
}