{
  "type": "Feature",
  "properties": {
    "gn:admin1_code":"6.0",
    "gn:admin2_code":"601.0",
    "gn:admin3_code":"60101.0",
    "gn:admin4_code":"6010107.0",
    "gn:asciiname":"La Malena",
    "gn:country_code":"DO",
    "gn:dem":338,
    "gn:feature_class":"P",
    "gn:feature_code":"PPL",
    "gn:name":"La Malena",
    "gn:population":0,
    "gn:timezone":"America/Santo_Domingo",
    "iso:country":"DO",
    "wof:name":"La Malena",
    "wof:placetype":"locality"
},
  "geometry": {"coordinates":[-70.27865,19.43274],"type":"Point"}
}