{
  "type": "Feature",
  "properties": {
    "gn:admin1_code":"32.0",
    "gn:admin2_code":"2904.0",
    "gn:admin3_code":"290402.0",
    "gn:admin4_code":"29040207.0",
    "gn:asciiname":"La Lomita",
    "gn:country_code":"DO",
    "gn:dem":124,
    "gn:feature_class":"P",
    "gn:feature_code":"PPL",
    "gn:name":"La Lomita",
    "gn:population":0,
    "gn:timezone":"America/Santo_Domingo",
    "iso:country":"DO",
    "wof:name":"La Lomita",
    "wof:placetype":"locality"
},
  "geometry": {"coordinates":[-69.97851,18.73988],"type":"Point"}
}