{
  "type": "Feature",
  "properties": {
    "gn:admin1_code":"24.0",
    "gn:admin2_code":"2303.0",
    "gn:admin3_code":"230301.0",
    "gn:admin4_code":"23030101.0",
    "gn:asciiname":"Amador",
    "gn:country_code":"DO",
    "gn:dem":33,
    "gn:feature_class":"P",
    "gn:feature_code":"PPL",
    "gn:name":"Amador",
    "gn:population":0,
    "gn:timezone":"America/Santo_Domingo",
    "iso:country":"DO",
    "name:deu_x_preferred":[
        "Amador"
    ],
    "name:fra_x_preferred":[
        "Amador"
    ],
    "name:ita_x_preferred":[
        "Amador"
    ],
    "name:jpn_x_preferred":[
        "\u30a2\u30de\u30c9\u30fc\u30eb"
    ],
    "name:nld_x_preferred":[
        "Amador"
    ],
    "name:pol_x_preferred":[
        "Amador"
    ],
    "name:por_x_preferred":[
        "Amador"
    ],
    "name:rus_x_preferred":[
        "\u0410\u043c\u0430\u0434\u043e\u0440"
    ],
    "name:sco_x_preferred":[
        "Amador"
    ],
    "name:spa_x_preferred":[
        "Amador"
    ],
    "name:srp_x_preferred":[
        "\u0410\u043c\u0430\u0434\u043e\u0440"
    ],
    "name:ukr_x_preferred":[
        "\u0410\u043c\u0430\u0434\u043e\u0440"
    ],
    "name:und_x_variant":[
        "Batey Amador"
    ],
    "wof:name":"Amador",
    "wof:placetype":"locality"
},
  "geometry": {"coordinates":[-69.1862,18.55047],"type":"Point"}
}