{
  "type": "Feature",
  "properties": {
    "gn:admin1_code":"19.0",
    "gn:asciiname":"La Caoba",
    "gn:country_code":"DO",
    "gn:dem":388,
    "gn:feature_class":"P",
    "gn:feature_code":"PPL",
    "gn:name":"La Caoba",
    "gn:population":0,
    "gn:timezone":"America/Santo_Domingo",
    "iso:country":"DO",
    "wof:name":"La Caoba",
    "wof:placetype":"locality"
},
  "geometry": {"coordinates":[-70.26666999999999,19.48333],"type":"Point"}
}