{
  "type": "Feature",
  "properties": {
    "gn:country":"DO",
    "gn:fcode":"PPL",
    "gn:population":3613,
    "iso:country":"DO",
    "name:ceb_x_preferred":[
        "R\u00edo Verde Arriba"
    ],
    "name:eng_x_preferred":[
        "R\u00edo Verde Arriba"
    ],
    "name:ita_x_preferred":[
        "R\u00edo Verde Arriba"
    ],
    "name:nld_x_preferred":[
        "R\u00edo Verde Arriba"
    ],
    "name:pol_x_preferred":[
        "R\u00edo Verde Arriba"
    ],
    "name:swe_x_preferred":[
        "R\u00edo Verde Arriba"
    ],
    "qs:name":"R\u00edo Verde Arriba",
    "qs:photos_9r":0,
    "qs:photos_sr":0,
    "qs:pop_sr":"4",
    "wd:wordcount":22,
    "wof:name":"R\u00edo Verde Arriba",
    "wof:placetype":"locality",
    "wof:population":3613
},
  "geometry": {"coordinates":[-70.56643,19.31583],"type":"Point"}
}