{
  "type": "Feature",
  "properties": {
    "gn:admin1_code":"24.0",
    "gn:admin2_code":"2306.0",
    "gn:admin3_code":"230601.0",
    "gn:admin4_code":"23060101.0",
    "gn:asciiname":"Barco Viejo",
    "gn:country_code":"DO",
    "gn:dem":5,
    "gn:feature_class":"P",
    "gn:feature_code":"PPL",
    "gn:name":"Barco Viejo",
    "gn:population":0,
    "gn:timezone":"America/Santo_Domingo",
    "iso:country":"DO",
    "wof:name":"Barco Viejo",
    "wof:placetype":"locality"
},
  "geometry": {"coordinates":[-69.45099,18.42371],"type":"Point"}
}