{
  "type": "Feature",
  "properties": {
    "gn:admin1_code":"33.0",
    "gn:admin2_code":"2101.0",
    "gn:admin3_code":"210101.0",
    "gn:admin4_code":"21010108.0",
    "gn:asciiname":"Cambita Sterling",
    "gn:country_code":"DO",
    "gn:dem":88,
    "gn:feature_class":"P",
    "gn:feature_code":"PPL",
    "gn:name":"Cambita Sterling",
    "gn:population":0,
    "gn:timezone":"America/Santo_Domingo",
    "iso:country":"DO",
    "name:und_x_variant":[
        "Cambita Esterlina",
        "Cambita Esterling",
        "Cambita Sterling"
    ],
    "wof:name":"Cambita Sterling",
    "wof:placetype":"locality"
},
  "geometry": {"coordinates":[-70.14958,18.42232000000001],"type":"Point"}
}