{
  "type": "Feature",
  "properties": {
    "gn:admin1_code":"12.0",
    "gn:admin2_code":"1202.0",
    "gn:admin3_code":"120201.0",
    "gn:admin4_code":"12020102.0",
    "gn:asciiname":"Higueeral",
    "gn:country_code":"DO",
    "gn:dem":86,
    "gn:feature_class":"P",
    "gn:feature_code":"PPL",
    "gn:name":"Hig\u00fceral",
    "gn:population":0,
    "gn:timezone":"America/Santo_Domingo",
    "iso:country":"DO",
    "wof:name":"Higueeral",
    "wof:placetype":"locality"
},
  "geometry": {"coordinates":[-69.01465,18.50053],"type":"Point"}
}