{
  "type": "Feature",
  "properties": {
    "gn:admin1_code":"36.0",
    "gn:admin2_code":"3103.0",
    "gn:admin3_code":"310301.0",
    "gn:admin4_code":"31030104.0",
    "gn:asciiname":"La Placeta de Yuna",
    "gn:country_code":"DO",
    "gn:dem":1294,
    "gn:feature_class":"P",
    "gn:feature_code":"PPL",
    "gn:name":"La Placeta de Yuna",
    "gn:population":0,
    "gn:timezone":"America/Santo_Domingo",
    "iso:country":"DO",
    "wof:name":"La Placeta de Yuna",
    "wof:placetype":"locality"
},
  "geometry": {"coordinates":[-70.4833,18.7667],"type":"Point"}
}