{
  "type": "Feature",
  "properties": {
    "gn:admin1_code":"33.0",
    "gn:admin2_code":"2105.0",
    "gn:admin3_code":"210501.0",
    "gn:admin4_code":"21050103.0",
    "gn:asciiname":"La Cienaga",
    "gn:country_code":"DO",
    "gn:dem":250,
    "gn:feature_class":"P",
    "gn:feature_code":"PPL",
    "gn:name":"La Ci\u00e9naga",
    "gn:population":0,
    "gn:timezone":"America/Santo_Domingo",
    "iso:country":"DO",
    "wof:name":"La Cienaga",
    "wof:placetype":"locality"
},
  "geometry": {"coordinates":[-70.22845,18.61524],"type":"Point"}
}