{
  "type": "Feature",
  "properties": {
    "gn:admin1_code":"6.0",
    "gn:admin2_code":"601.0",
    "gn:admin3_code":"60104.0",
    "gn:admin4_code":"6010405.0",
    "gn:asciiname":"La Jagueita",
    "gn:country_code":"DO",
    "gn:dem":411,
    "gn:feature_class":"P",
    "gn:feature_code":"PPL",
    "gn:name":"La Jag\u00fcita",
    "gn:population":0,
    "gn:timezone":"America/Santo_Domingo",
    "iso:country":"DO",
    "wof:name":"La Jagueita",
    "wof:placetype":"locality"
},
  "geometry": {"coordinates":[-70.20511999999999,19.37071],"type":"Point"}
}