{
  "type": "Feature",
  "properties": {
    "gn:admin1_code":"18.0",
    "gn:admin2_code":"1801.0",
    "gn:admin3_code":"180101.0",
    "gn:admin4_code":"18010102.0",
    "gn:asciiname":"El Naranjal",
    "gn:country_code":"DO",
    "gn:dem":105,
    "gn:feature_class":"P",
    "gn:feature_code":"PPL",
    "gn:name":"El Naranjal",
    "gn:population":0,
    "gn:timezone":"America/Santo_Domingo",
    "iso:country":"DO",
    "name:und_x_variant":[
        "Naranjal",
        "El Naranjal"
    ],
    "wof:name":"El Naranjal",
    "wof:placetype":"locality"
},
  "geometry": {"coordinates":[-70.69284,19.69881],"type":"Point"}
}