{
  "type": "Feature",
  "properties": {
    "gn:admin1_code":"28.0",
    "gn:admin2_code":"801.0",
    "gn:admin3_code":"80101.0",
    "gn:admin4_code":"8010108.0",
    "gn:asciiname":"Batey Haiti",
    "gn:country_code":"DO",
    "gn:dem":71,
    "gn:feature_class":"P",
    "gn:feature_code":"PPL",
    "gn:name":"Batey Hait\u00ed",
    "gn:population":0,
    "gn:timezone":"America/Santo_Domingo",
    "iso:country":"DO",
    "name:und_x_variant":[
        "Haiti",
        "Batey Hait\u00ed"
    ],
    "wof:name":"Batey Haiti",
    "wof:placetype":"locality"
},
  "geometry": {"coordinates":[-69.18354000000001,18.65409],"type":"Point"}
}