{
  "type": "Feature",
  "properties": {
    "gn:admin1_code":"32.0",
    "gn:admin2_code":"2902.0",
    "gn:admin3_code":"290201.0",
    "gn:admin4_code":"29020103.0",
    "gn:asciiname":"Carabela",
    "gn:country_code":"DO",
    "gn:dem":22,
    "gn:feature_class":"P",
    "gn:feature_code":"PPL",
    "gn:name":"Carabela",
    "gn:population":0,
    "gn:timezone":"America/Santo_Domingo",
    "iso:country":"DO",
    "name:und_x_variant":[
        "Carabelas",
        "Carabela"
    ],
    "wof:name":"Carabela",
    "wof:placetype":"locality"
},
  "geometry": {"coordinates":[-69.66604,18.67471],"type":"Point"}
}