{
  "type": "Feature",
  "properties": {
    "gn:admin1_code":"37.0",
    "gn:admin2_code":"3203.0",
    "gn:admin3_code":"320301.0",
    "gn:admin4_code":"32030103.0",
    "gn:asciiname":"Hoyo Oscuro",
    "gn:country_code":"DO",
    "gn:dem":85,
    "gn:feature_class":"P",
    "gn:feature_code":"PPL",
    "gn:name":"Hoyo Oscuro",
    "gn:population":0,
    "gn:timezone":"America/Santo_Domingo",
    "iso:country":"DO",
    "wof:name":"Hoyo Oscuro",
    "wof:placetype":"locality"
},
  "geometry": {"coordinates":[-69.98654999999999,18.63999],"type":"Point"}
}