{
  "type": "Feature",
  "properties": {
    "gn:admin1_code":"25.0",
    "gn:admin2_code":"2507.0",
    "gn:admin3_code":"250701.0",
    "gn:admin4_code":"25070102.0",
    "gn:asciiname":"Palmarejo",
    "gn:country_code":"DO",
    "gn:dem":161,
    "gn:feature_class":"P",
    "gn:feature_code":"PPL",
    "gn:name":"Palmarejo",
    "gn:population":0,
    "gn:timezone":"America/Santo_Domingo",
    "iso:country":"DO",
    "wof:name":"Palmarejo",
    "wof:placetype":"locality"
},
  "geometry": {"coordinates":[-70.80752,19.55113],"type":"Point"}
}