{
  "type": "Feature",
  "properties": {
    "gn:admin1_code":"4.0",
    "gn:admin2_code":"502.0",
    "gn:admin3_code":"50201.0",
    "gn:admin4_code":"5020104.0",
    "gn:asciiname":"Masquitos",
    "gn:country_code":"DO",
    "gn:dem":391,
    "gn:feature_class":"P",
    "gn:feature_code":"PPL",
    "gn:name":"Masquitos",
    "gn:population":0,
    "gn:timezone":"America/Santo_Domingo",
    "iso:country":"DO",
    "wof:name":"Masquitos",
    "wof:placetype":"locality"
},
  "geometry": {"coordinates":[-71.58893,19.37524],"type":"Point"}
}