{
  "type": "Feature",
  "properties": {
    "gn:admin1_code":"21.0",
    "gn:admin2_code":"2404.0",
    "gn:admin3_code":"240402.0",
    "gn:admin4_code":"24040204.0",
    "gn:asciiname":"Rincon de Camu",
    "gn:country_code":"DO",
    "gn:dem":37,
    "gn:feature_class":"P",
    "gn:feature_code":"PPL",
    "gn:name":"Rinc\u00f3n de Cam\u00fa",
    "gn:population":0,
    "gn:timezone":"America/Santo_Domingo",
    "iso:country":"DO",
    "wof:name":"Rincon de Camu",
    "wof:placetype":"locality"
},
  "geometry": {"coordinates":[-70.1481,19.14966],"type":"Point"}
}