{
  "type": "Feature",
  "properties": {
    "gn:admin1_code":"36.0",
    "gn:admin2_code":"3101.0",
    "gn:admin3_code":"310102.0",
    "gn:admin4_code":"31010202.0",
    "gn:asciiname":"Jigueey",
    "gn:country_code":"DO",
    "gn:dem":548,
    "gn:feature_class":"P",
    "gn:feature_code":"PPL",
    "gn:name":"Jig\u00fcey",
    "gn:population":0,
    "gn:timezone":"America/Santo_Domingo",
    "iso:country":"DO",
    "wof:name":"Jigueey",
    "wof:placetype":"locality"
},
  "geometry": {"coordinates":[-70.37649,18.53149],"type":"Point"}
}