{
  "type": "Feature",
  "properties": {
    "gn:admin1_code":"21.0",
    "gn:admin2_code":"2401.0",
    "gn:admin3_code":"240103.0",
    "gn:admin4_code":"24010301.0",
    "gn:asciiname":"Caballero",
    "gn:country_code":"DO",
    "gn:dem":116,
    "gn:feature_class":"P",
    "gn:feature_code":"PPL",
    "gn:name":"Caballero",
    "gn:population":0,
    "gn:timezone":"America/Santo_Domingo",
    "iso:country":"DO",
    "name:bul_x_preferred":[
        "\u041a\u0430\u0431\u0430\u043b\u0435\u0440\u043e"
    ],
    "name:ceb_x_preferred":[
        "Caballero"
    ],
    "name:deu_x_preferred":[
        "Caballero"
    ],
    "name:fra_x_preferred":[
        "Caballero"
    ],
    "name:glg_x_preferred":[
        "Caballero"
    ],
    "name:ita_x_preferred":[
        "Caballero"
    ],
    "name:jpn_x_preferred":[
        "\u30ad\u30e3\u30d0\u30ec\u30ed"
    ],
    "name:kor_x_preferred":[
        "\uce74\ubc14\uc608\ub85c"
    ],
    "name:nld_x_preferred":[
        "Caballero"
    ],
    "name:rus_x_preferred":[
        "\u041a\u0430\u0431\u0430\u043b\u044c\u0435\u0440\u043e"
    ],
    "name:spa_x_preferred":[
        "Abajo Caballero"
    ],
    "name:spa_x_variant":[
        "Caballero"
    ],
    "name:swe_x_preferred":[
        "Caballero"
    ],
    "name:ukr_x_preferred":[
        "\u041a\u0430\u0431\u0430\u043b\u044c\u0454\u0440\u043e"
    ],
    "wof:name":"Caballero",
    "wof:placetype":"locality"
},
  "geometry": {"coordinates":[-70.29765,18.99872],"type":"Point"}
}