{
  "type": "Feature",
  "properties": {
    "gn:admin1_code":"21.0",
    "gn:admin2_code":"2401.0",
    "gn:admin3_code":"240103.0",
    "gn:admin4_code":"24010301.0",
    "gn:asciiname":"Caballero",
    "gn:country_code":"DO",
    "gn:dem":116,
    "gn:feature_class":"P",
    "gn:feature_code":"PPL",
    "gn:name":"Caballero",
    "gn:population":0,
    "gn:timezone":"America/Santo_Domingo",
    "iso:country":"DO",
    "name:spa_x_preferred":[
        "Abajo Caballero"
    ],
    "wof:name":"Caballero",
    "wof:placetype":"locality"
},
  "geometry": {"coordinates":[-70.29765,18.99872],"type":"Point"}
}