{
  "type": "Feature",
  "properties": {
    "gn:admin1_code":"25.0",
    "gn:admin2_code":"2503.0",
    "gn:admin3_code":"250303.0",
    "gn:admin4_code":"25030306.0",
    "gn:asciiname":"La Guama",
    "gn:country_code":"DO",
    "gn:dem":718,
    "gn:feature_class":"P",
    "gn:feature_code":"PPL",
    "gn:name":"La Guama",
    "gn:population":0,
    "gn:timezone":"America/Santo_Domingo",
    "iso:country":"DO",
    "name:und_x_variant":[
        "Guama",
        "La Guama"
    ],
    "wof:name":"La Guama",
    "wof:placetype":"locality"
},
  "geometry": {"coordinates":[-70.70656,19.21977],"type":"Point"}
}