{
  "type": "Feature",
  "properties": {
    "gn:admin1_code":"6.0",
    "gn:admin2_code":"601.0",
    "gn:admin3_code":"60103.0",
    "gn:admin4_code":"6010307.0",
    "gn:asciiname":"Genimillo",
    "gn:country_code":"DO",
    "gn:dem":59,
    "gn:feature_class":"P",
    "gn:feature_code":"PPL",
    "gn:name":"Genimillo",
    "gn:population":0,
    "gn:timezone":"America/Santo_Domingo",
    "iso:country":"DO",
    "name:und_x_variant":[
        "Geminillo",
        "Genimillo"
    ],
    "wof:name":"Genimillo",
    "wof:placetype":"locality"
},
  "geometry": {"coordinates":[-70.29170000000001,19.22121],"type":"Point"}
}