{
  "type": "Feature",
  "properties": {
    "gn:admin1_code":"29.0",
    "gn:admin2_code":"3001.0",
    "gn:admin3_code":"300101.0",
    "gn:admin4_code":"30010102.0",
    "gn:asciiname":"Leguitimo",
    "gn:country_code":"DO",
    "gn:dem":79,
    "gn:feature_class":"P",
    "gn:feature_code":"PPL",
    "gn:name":"Legu\u00edtimo",
    "gn:population":0,
    "gn:timezone":"America/Santo_Domingo",
    "iso:country":"DO",
    "name:und_x_variant":[
        "Legu\u00edsimo",
        "Legu\u00edtimo"
    ],
    "wof:name":"Leguitimo",
    "wof:placetype":"locality"
},
  "geometry": {"coordinates":[-69.35911999999999,18.74026],"type":"Point"}
}