{
  "type": "Feature",
  "properties": {
    "gn:admin1_code":"23.0",
    "gn:admin2_code":"2205.0",
    "gn:admin3_code":"220503.0",
    "gn:admin4_code":"22050305.0",
    "gn:asciiname":"Baitoa",
    "gn:country_code":"DO",
    "gn:dem":498,
    "gn:feature_class":"P",
    "gn:feature_code":"PPL",
    "gn:name":"Baitoa",
    "gn:population":0,
    "gn:timezone":"America/Santo_Domingo",
    "iso:country":"DO",
    "name:ceb_x_preferred":[
        "Baitoa"
    ],
    "name:por_x_preferred":[
        "Baitoa"
    ],
    "name:swe_x_preferred":[
        "Baitoa"
    ],
    "name:und_x_variant":[
        "Baitoal"
    ],
    "name:zho_x_preferred":[
        "\u62dc\u6258\u963f"
    ],
    "wof:name":"Baitoa",
    "wof:placetype":"locality"
},
  "geometry": {"coordinates":[-71.50366,18.99938],"type":"Point"}
}