{
  "type": "Feature",
  "properties": {
    "gn:country":"DO",
    "gn:fcode":"PPL",
    "gn:pop":2526,
    "iso:country":"DO",
    "name:chi_x_preferred":[
        "\u5361\u8036\u5854\u8afe\u8d6b\u723e\u83ab\u68ee"
    ],
    "name:dut_x_preferred":[
        "Cayetano Germos\u00e9n"
    ],
    "name:eng_x_preferred":[
        "Cayetano Germos\u00e9n"
    ],
    "name:fre_x_preferred":[
        "Cayetano Germos\u00e9n"
    ],
    "name:ita_x_preferred":[
        "Cayetano Germos\u00e9n"
    ],
    "name:jpn_x_preferred":[
        "\u30ab\u30b8\u30a7\u30bf\u30ce\u30fb\u30d8\u30eb\u30e2\u30bb\u30f3"
    ],
    "name:nan_x_preferred":[
        "Cayetano Germosen"
    ],
    "name:por_x_preferred":[
        "Cayetano Germos\u00e9n"
    ],
    "name:slv_x_preferred":[
        "Cayetano Germos\u00e9n"
    ],
    "name:swe_x_preferred":[
        "Cayetano Germos\u00e9n"
    ],
    "name:unk_x_variant":[
        "Gayetano Germosen"
    ],
    "qs:name":"Cayetano Germos\u00e9n",
    "qs:photos_9r":0,
    "qs:photos_sr":0,
    "qs:pop_sr":"4",
    "wd:wordcount":47,
    "wof:name":"Cayetano Germos\u00e9n",
    "wof:placetype":"locality",
    "wof:population":2526
},
  "geometry": {"coordinates":[-70.48342,19.34413],"type":"Point"}
}