{
  "type": "Feature",
  "properties": {
    "gn:admin1_code":"18.0",
    "gn:admin2_code":"1809.0",
    "gn:admin3_code":"180901.0",
    "gn:admin4_code":"18090105.0",
    "gn:asciiname":"Los Muertos",
    "gn:cc2":"DO",
    "gn:country_code":"DO",
    "gn:dem":20,
    "gn:feature_class":"P",
    "gn:feature_code":"PPL",
    "gn:name":"Los Muertos",
    "gn:population":0,
    "gn:timezone":"America/Santo_Domingo",
    "iso:country":"DO",
    "name:und_x_variant":[
        "Cam\u00fa",
        "Los Muertos"
    ],
    "wof:name":"Los Muertos",
    "wof:placetype":"locality"
},
  "geometry": {"coordinates":[-70.59999999999999,19.71667],"type":"Point"}
}