{
  "type": "Feature",
  "properties": {
    "gn:admin1_code":"36.0",
    "gn:admin2_code":"3102.0",
    "gn:admin3_code":"310201.0",
    "gn:admin4_code":"31020102.0",
    "gn:asciiname":"Derrico Blanco",
    "gn:country_code":"DO",
    "gn:dem":844,
    "gn:feature_class":"P",
    "gn:feature_code":"PPL",
    "gn:name":"Derrico Blanco",
    "gn:population":0,
    "gn:timezone":"America/Santo_Domingo",
    "iso:country":"DO",
    "wof:name":"Derrico Blanco",
    "wof:placetype":"locality"
},
  "geometry": {"coordinates":[-70.54203000000003,18.61763],"type":"Point"}
}