{
  "type": "Feature",
  "properties": {
    "gn:admin1_code":"4.0",
    "gn:admin2_code":"502.0",
    "gn:admin3_code":"50203.0",
    "gn:admin4_code":"5020301.0",
    "gn:asciiname":"Santiago de La Cruz",
    "gn:country_code":"DO",
    "gn:dem":242,
    "gn:feature_class":"P",
    "gn:feature_code":"PPL",
    "gn:name":"Santiago de La Cruz",
    "gn:population":0,
    "gn:timezone":"America/Santo_Domingo",
    "iso:country":"DO",
    "wof:name":"Santiago de La Cruz",
    "wof:placetype":"locality"
},
  "geometry": {"coordinates":[-71.62764,19.48009],"type":"Point"}
}