{
  "type": "Feature",
  "properties": {
    "gn:admin1_code":"33.0",
    "gn:admin2_code":"2103.0",
    "gn:admin3_code":"210302.0",
    "gn:admin4_code":"21030202.0",
    "gn:asciiname":"Monte Adentro",
    "gn:country_code":"DO",
    "gn:dem":59,
    "gn:feature_class":"P",
    "gn:feature_code":"PPL",
    "gn:name":"Monte Adentro",
    "gn:population":0,
    "gn:timezone":"America/Santo_Domingo",
    "iso:country":"DO",
    "wof:name":"Monte Adentro",
    "wof:placetype":"locality"
},
  "geometry": {"coordinates":[-70.05,18.44399],"type":"Point"}
}