{
  "type": "Feature",
  "properties": {
    "gn:admin1_code":"18.0",
    "gn:admin2_code":"1802.0",
    "gn:admin3_code":"180202.0",
    "gn:admin4_code":"18020206.0",
    "gn:asciiname":"El Manguito",
    "gn:country_code":"DO",
    "gn:dem":332,
    "gn:feature_class":"P",
    "gn:feature_code":"PPL",
    "gn:name":"El Manguito",
    "gn:population":0,
    "gn:timezone":"America/Santo_Domingo",
    "iso:country":"DO",
    "wof:name":"El Manguito",
    "wof:placetype":"locality"
},
  "geometry": {"coordinates":[-70.74051999999998,19.65918],"type":"Point"}
}