{
  "type": "Feature",
  "properties": {
    "gn:admin1_code":"30.0",
    "gn:admin2_code":"1301.0",
    "gn:admin3_code":"130104.0",
    "gn:admin4_code":"13010405.0",
    "gn:asciiname":"Mocan",
    "gn:country_code":"DO",
    "gn:dem":309,
    "gn:feature_class":"P",
    "gn:feature_code":"PPL",
    "gn:name":"Moc\u00e1n",
    "gn:population":0,
    "gn:timezone":"America/Santo_Domingo",
    "iso:country":"DO",
    "wof:name":"Mocan",
    "wof:placetype":"locality"
},
  "geometry": {"coordinates":[-70.65061999999998,19.33071],"type":"Point"}
}