{
  "type": "Feature",
  "properties": {
    "gn:admin1_code":"28.0",
    "gn:admin2_code":"801.0",
    "gn:admin3_code":"80101.0",
    "gn:admin4_code":"8010102.0",
    "gn:asciiname":"Tio Pedro",
    "gn:country_code":"DO",
    "gn:dem":130,
    "gn:feature_class":"P",
    "gn:feature_code":"PPL",
    "gn:name":"T\u00edo Pedro",
    "gn:population":0,
    "gn:timezone":"America/Santo_Domingo",
    "iso:country":"DO",
    "wof:name":"Tio Pedro",
    "wof:placetype":"locality"
},
  "geometry": {"coordinates":[-69.01808,18.80494],"type":"Point"}
}