{
  "type": "Feature",
  "properties": {
    "gn:admin1_code":"6.0",
    "gn:admin2_code":"603.0",
    "gn:admin3_code":"60301.0",
    "gn:admin4_code":"6030106.0",
    "gn:asciiname":"Las Berenjenas",
    "gn:country_code":"DO",
    "gn:dem":248,
    "gn:feature_class":"P",
    "gn:feature_code":"PPL",
    "gn:name":"Las Berenjenas",
    "gn:population":0,
    "gn:timezone":"America/Santo_Domingo",
    "iso:country":"DO",
    "name:und_x_variant":[
        "La Berenjena",
        "Los Berenjenas",
        "Las Berenjenas"
    ],
    "wof:name":"Las Berenjenas",
    "wof:placetype":"locality"
},
  "geometry": {"coordinates":[-70.05556999999999,19.28092],"type":"Point"}
}