{
  "type": "Feature",
  "properties": {
    "gn:admin1_code":"8.0",
    "gn:asciiname":"La Culebra",
    "gn:country_code":"DO",
    "gn:dem":522,
    "gn:feature_class":"P",
    "gn:feature_code":"PPL",
    "gn:name":"La Culebra",
    "gn:population":0,
    "gn:timezone":"America/Santo_Domingo",
    "iso:country":"DO",
    "name:und_x_variant":[
        "Las Culebras",
        "La Culebra"
    ],
    "wof:name":"La Culebra",
    "wof:placetype":"locality"
},
  "geometry": {"coordinates":[-70.42187,19.45693],"type":"Point"}
}