{
  "type": "Feature",
  "properties": {
    "gn:admin1_code":"18.0",
    "gn:admin2_code":"1809.0",
    "gn:admin3_code":"180901.0",
    "gn:admin4_code":"18090102.0",
    "gn:asciiname":"Ojo de Agua",
    "gn:country_code":"DO",
    "gn:dem":215,
    "gn:feature_class":"P",
    "gn:feature_code":"PPL",
    "gn:name":"Ojo de Agua",
    "gn:population":0,
    "gn:timezone":"America/Santo_Domingo",
    "iso:country":"DO",
    "wof:name":"Ojo de Agua",
    "wof:placetype":"locality"
},
  "geometry": {"coordinates":[-70.55131,19.66514],"type":"Point"}
}