{
  "type": "Feature",
  "properties": {
    "gn:admin1_code":"1.0",
    "gn:admin2_code":"202.0",
    "gn:admin3_code":"20201.0",
    "gn:admin4_code":"2020103.0",
    "gn:asciiname":"Canada Cimarrona",
    "gn:country_code":"DO",
    "gn:dem":499,
    "gn:feature_class":"P",
    "gn:feature_code":"PPL",
    "gn:name":"Ca\u00f1ada Cimarrona",
    "gn:population":0,
    "gn:timezone":"America/Santo_Domingo",
    "iso:country":"DO",
    "wof:name":"Canada Cimarrona",
    "wof:placetype":"locality"
},
  "geometry": {"coordinates":[-70.56667,18.46667],"type":"Point"}
}