{
  "type": "Feature",
  "properties": {
    "gn:admin1_code":"20.0",
    "gn:admin2_code":"2001.0",
    "gn:admin3_code":"200104.0",
    "gn:admin4_code":"20010402.0",
    "gn:asciiname":"Manuel Chiquito",
    "gn:country_code":"DO",
    "gn:dem":42,
    "gn:feature_class":"P",
    "gn:feature_code":"PPL",
    "gn:name":"Manuel Chiquito",
    "gn:population":0,
    "gn:timezone":"America/Santo_Domingo",
    "iso:country":"DO",
    "name:und_x_variant":[
        "Chiquito",
        "Manuel Chiquito"
    ],
    "wof:name":"Manuel Chiquito",
    "wof:placetype":"locality"
},
  "geometry": {"coordinates":[-69.22161,19.23887],"type":"Point"}
}