{
  "type": "Feature",
  "properties": {
    "gn:admin1_code":"32.0",
    "gn:admin2_code":"2902.0",
    "gn:admin3_code":"290201.0",
    "gn:admin4_code":"29020104.0",
    "gn:asciiname":"Managueita",
    "gn:country_code":"DO",
    "gn:dem":111,
    "gn:feature_class":"P",
    "gn:feature_code":"PPL",
    "gn:name":"Manag\u00fcita",
    "gn:population":0,
    "gn:timezone":"America/Santo_Domingo",
    "iso:country":"DO",
    "wof:name":"Managueita",
    "wof:placetype":"locality"
},
  "geometry": {"coordinates":[-69.62671,18.80955],"type":"Point"}
}