{
  "type": "Feature",
  "properties": {
    "gn:admin1_code":"20.0",
    "gn:admin2_code":"2003.0",
    "gn:admin3_code":"200301.0",
    "gn:admin4_code":"20030102.0",
    "gn:asciiname":"El Naranjito",
    "gn:country_code":"DO",
    "gn:dem":380,
    "gn:feature_class":"P",
    "gn:feature_code":"PPL",
    "gn:name":"El Naranjito",
    "gn:population":0,
    "gn:timezone":"America/Santo_Domingo",
    "iso:country":"DO",
    "name:und_x_variant":[
        "Las Lomas",
        "Naranjito",
        "El Naranjito"
    ],
    "wof:name":"El Naranjito",
    "wof:placetype":"locality"
},
  "geometry": {"coordinates":[-69.55298000000001,19.26957],"type":"Point"}
}