{
  "type": "Feature",
  "properties": {
    "iso:country":"DO",
    "name:spa_x_preferred":[
        "Honduras"
    ],
    "name:unk_x_variant":[
        "Honduras"
    ],
    "qs:gn_adm0_cc":"DO",
    "qs:gn_fcode":"PPLX",
    "qs:gn_local":7874116,
    "qs:gn_nam_loc":"limoncillar",
    "qs:gn_namadm1":"34",
    "qs:gn_name":"Honduras",
    "qs:local_max":5287,
    "qs:local_sum":19037,
    "qs:localhoods":30,
    "qs:name":"Honduras",
    "qs:name_adm0":"Rep\u00fablica Dominicana",
    "qs:name_adm1":"Distrito Nacional",
    "qs:name_local":"Santo Domingo",
    "qs:photo_max":243,
    "qs:photo_sum":247,
    "qs:placetype":"Suburb",
    "qs:quad_count":4,
    "qs:woe_adm0":23424800,
    "qs:woe_adm1":2345176,
    "qs:woe_adm2":0,
    "qs:woe_lau":0,
    "qs:woe_local":76456,
    "qs:woe_ver":"7.10.0",
    "wof:lang":[
        "spa"
    ],
    "wof:name":"Honduras",
    "wof:placetype":"neighbourhood"
},
  "geometry": {"coordinates":[-69.929327,18.441802],"type":"Point"}
}