{
  "type": "Feature",
  "properties": {
    "gn:admin1_code":"25.0",
    "gn:admin2_code":"2503.0",
    "gn:admin3_code":"250302.0",
    "gn:admin4_code":"25030206.0",
    "gn:asciiname":"Cerro Prieto",
    "gn:country_code":"DO",
    "gn:dem":1347,
    "gn:feature_class":"P",
    "gn:feature_code":"PPL",
    "gn:name":"Cerro Prieto",
    "gn:population":0,
    "gn:timezone":"America/Santo_Domingo",
    "iso:country":"DO",
    "name:hun_x_preferred":[
        "Cerro Prieto"
    ],
    "name:hye_x_preferred":[
        "\u054d\u0565\u057c\u0578 \u054a\u0580\u056b\u0565\u057f\u0578"
    ],
    "name:ita_x_preferred":[
        "Cerro Prieto"
    ],
    "name:slk_x_preferred":[
        "Cerro Prieto"
    ],
    "name:spa_x_preferred":[
        "Cerro Prieto"
    ],
    "wof:name":"Cerro Prieto",
    "wof:placetype":"locality"
},
  "geometry": {"coordinates":[-70.81775,19.15407],"type":"Point"}
}