{
  "type": "Feature",
  "properties": {
    "gn:admin1_code":"3.0",
    "gn:admin2_code":"407.0",
    "gn:admin3_code":"40701.0",
    "gn:admin4_code":"4070102.0",
    "gn:asciiname":"Guayuyal",
    "gn:country_code":"DO",
    "gn:dem":653,
    "gn:feature_class":"P",
    "gn:feature_code":"PPL",
    "gn:name":"Guayuyal",
    "gn:population":0,
    "gn:timezone":"America/Santo_Domingo",
    "iso:country":"DO",
    "name:und_x_variant":[
        "Guayuyo",
        "Guayuyales",
        "Guayuyal"
    ],
    "wof:name":"Guayuyal",
    "wof:placetype":"locality"
},
  "geometry": {"coordinates":[-71.15058000000001,18.07127],"type":"Point"}
}