{
  "type": "Feature",
  "properties": {
    "gn:admin1_code":"6.0",
    "gn:admin2_code":"604.0",
    "gn:admin3_code":"60401.0",
    "gn:admin4_code":"6040104.0",
    "gn:asciiname":"Cuaba",
    "gn:cc2":"DO",
    "gn:country_code":"DO",
    "gn:dem":74,
    "gn:feature_class":"P",
    "gn:feature_code":"PPL",
    "gn:name":"Cuaba",
    "gn:population":0,
    "gn:timezone":"America/Santo_Domingo",
    "iso:country":"DO",
    "name:fra_x_preferred":[
        "Cuaba"
    ],
    "name:ita_x_preferred":[
        "Cuaba"
    ],
    "name:jpn_x_preferred":[
        "\u30af\u30a1\u30d0"
    ],
    "name:mkd_x_preferred":[
        "\u041a\u0443\u0430\u0431\u0430"
    ],
    "name:nor_x_preferred":[
        "Cuaba"
    ],
    "name:rus_x_preferred":[
        "Cuaba"
    ],
    "name:und_x_variant":[
        "Casa Viejo"
    ],
    "wof:name":"Cuaba",
    "wof:placetype":"locality"
},
  "geometry": {"coordinates":[-70.15000000000001,19.25],"type":"Point"}
}