{
  "type": "Feature",
  "properties": {
    "gn:admin1_code":"6.0",
    "gn:admin2_code":"604.0",
    "gn:admin3_code":"60401.0",
    "gn:admin4_code":"6040104.0",
    "gn:asciiname":"Cuaba",
    "gn:cc2":"DO",
    "gn:country_code":"DO",
    "gn:dem":74,
    "gn:feature_class":"P",
    "gn:feature_code":"PPL",
    "gn:name":"Cuaba",
    "gn:population":0,
    "gn:timezone":"America/Santo_Domingo",
    "iso:country":"DO",
    "name:und_x_variant":[
        "Casa Viejo",
        "Cuaba"
    ],
    "wof:name":"Cuaba",
    "wof:placetype":"locality"
},
  "geometry": {"coordinates":[-70.15000000000001,19.25],"type":"Point"}
}