{
  "type": "Feature",
  "properties": {
    "gn:admin1_code":"30.0",
    "gn:admin2_code":"1302.0",
    "gn:admin3_code":"130201.0",
    "gn:admin4_code":"13020101.0",
    "gn:asciiname":"Arroyo Arriba",
    "gn:country_code":"DO",
    "gn:dem":1208,
    "gn:feature_class":"P",
    "gn:feature_code":"PPL",
    "gn:name":"Arroyo Arriba",
    "gn:population":0,
    "gn:timezone":"America/Santo_Domingo",
    "iso:country":"DO",
    "wof:name":"Arroyo Arriba",
    "wof:placetype":"locality"
},
  "geometry": {"coordinates":[-70.74083,18.91984],"type":"Point"}
}