{
  "type": "Feature",
  "properties": {
    "gn:admin1_code":"30.0",
    "gn:admin2_code":"1301.0",
    "gn:admin3_code":"130101.0",
    "gn:admin4_code":"13010101.0",
    "gn:asciiname":"Ponton Abajo",
    "gn:country_code":"DO",
    "gn:dem":93,
    "gn:feature_class":"P",
    "gn:feature_code":"PPL",
    "gn:name":"Pont\u00f3n Abajo",
    "gn:population":0,
    "gn:timezone":"America/Santo_Domingo",
    "iso:country":"DO",
    "wof:name":"Ponton Abajo",
    "wof:placetype":"locality"
},
  "geometry": {"coordinates":[-70.51666999999998,19.21667],"type":"Point"}
}