{
  "type": "Feature",
  "properties": {
    "gn:admin1_code":"1.0",
    "gn:admin2_code":"201.0",
    "gn:admin3_code":"20107.0",
    "gn:admin4_code":"2010702.0",
    "gn:asciiname":"Monte Rio",
    "gn:country_code":"DO",
    "gn:dem":19,
    "gn:feature_class":"P",
    "gn:feature_code":"PPL",
    "gn:name":"Monte R\u00edo",
    "gn:population":0,
    "gn:timezone":"America/Santo_Domingo",
    "iso:country":"DO",
    "name:und_x_variant":[
        "Monte Fr\u00edo",
        "Monte R\u00edo"
    ],
    "wof:name":"Monte Rio",
    "wof:placetype":"locality"
},
  "geometry": {"coordinates":[-70.7097,18.42119],"type":"Point"}
}