{
  "type": "Feature",
  "properties": {
    "gn:admin1_code":"1.0",
    "gn:admin2_code":"210.0",
    "gn:admin3_code":"21001.0",
    "gn:admin4_code":"2100103.0",
    "gn:asciiname":"El Tiradero",
    "gn:country_code":"DO",
    "gn:dem":1133,
    "gn:feature_class":"P",
    "gn:feature_code":"PPL",
    "gn:name":"El Tiradero",
    "gn:population":0,
    "gn:timezone":"America/Santo_Domingo",
    "iso:country":"DO",
    "wof:name":"El Tiradero",
    "wof:placetype":"locality"
},
  "geometry": {"coordinates":[-70.68145,18.58692000000001],"type":"Point"}
}