{
  "type": "Feature",
  "properties": {
    "gn:admin1_code":"10.0",
    "gn:admin2_code":"1101.0",
    "gn:admin3_code":"110101.0",
    "gn:admin4_code":"11010106.0",
    "gn:asciiname":"El Capa",
    "gn:country_code":"DO",
    "gn:dem":72,
    "gn:feature_class":"P",
    "gn:feature_code":"PPL",
    "gn:name":"El Cap\u00e1",
    "gn:population":0,
    "gn:timezone":"America/Santo_Domingo",
    "iso:country":"DO",
    "wof:name":"El Capa",
    "wof:placetype":"locality"
},
  "geometry": {"coordinates":[-68.78865999999999,18.52952],"type":"Point"}
}