{
  "type": "Feature",
  "properties": {
    "gn:admin1_code":"21.0",
    "gn:admin2_code":"2402.0",
    "gn:admin3_code":"240202.0",
    "gn:admin4_code":"24020203.0",
    "gn:asciiname":"Sabana Grande",
    "gn:country_code":"DO",
    "gn:dem":70,
    "gn:feature_class":"P",
    "gn:feature_code":"PPL",
    "gn:name":"Sabana Grande",
    "gn:population":0,
    "gn:timezone":"America/Santo_Domingo",
    "iso:country":"DO",
    "name:ceb_x_preferred":[
        "Sabana Grande"
    ],
    "name:fra_x_preferred":[
        "Sabana Grande"
    ],
    "name:ita_x_preferred":[
        "Sabana Grande"
    ],
    "name:nld_x_preferred":[
        "Sabana Grande"
    ],
    "name:pol_x_preferred":[
        "Sabana Grande"
    ],
    "name:spa_x_preferred":[
        "Sabanagrande"
    ],
    "name:srp_x_preferred":[
        "\u0421\u0430\u0431\u0430\u043d\u0430 \u0413\u0440\u0430\u043d\u0434\u0435"
    ],
    "name:swe_x_preferred":[
        "Sabana Grande"
    ],
    "wof:name":"Sabana Grande",
    "wof:placetype":"locality"
},
  "geometry": {"coordinates":[-70.00904,19.05201],"type":"Point"}
}