{
  "type": "Feature",
  "properties": {
    "gn:admin1_code":"11.0",
    "gn:admin2_code":"705.0",
    "gn:admin3_code":"70501.0",
    "gn:admin4_code":"7050104.0",
    "gn:asciiname":"Guayajayuco",
    "gn:country_code":"DO",
    "gn:dem":409,
    "gn:feature_class":"P",
    "gn:feature_code":"PPL",
    "gn:name":"Guayajayuco",
    "gn:population":0,
    "gn:timezone":"America/Santo_Domingo",
    "iso:country":"DO",
    "wof:name":"Guayajayuco",
    "wof:placetype":"locality"
},
  "geometry": {"coordinates":[-71.61667,19.21667],"type":"Point"}
}