{
  "type": "Feature",
  "properties": {
    "gn:admin1_code":"33.0",
    "gn:admin2_code":"2106.0",
    "gn:admin3_code":"210601.0",
    "gn:admin4_code":"21060103.0",
    "gn:asciiname":"Boca de los Arroyos",
    "gn:country_code":"DO",
    "gn:dem":33,
    "gn:feature_class":"P",
    "gn:feature_code":"PPL",
    "gn:name":"Boca de los Arroyos",
    "gn:population":0,
    "gn:timezone":"America/Santo_Domingo",
    "iso:country":"DO",
    "name:und_x_variant":[
        "Boca del Arroyo",
        "Boca de los Arroyos"
    ],
    "wof:name":"Boca de los Arroyos",
    "wof:placetype":"locality"
},
  "geometry": {"coordinates":[-70.18666999999999,18.28482],"type":"Point"}
}