{
  "type": "Feature",
  "properties": {
    "gn:admin1_code":"12.0",
    "gn:admin2_code":"1202.0",
    "gn:admin3_code":"120201.0",
    "gn:admin4_code":"12020103.0",
    "gn:asciiname":"Aleton",
    "gn:country_code":"DO",
    "gn:dem":79,
    "gn:feature_class":"P",
    "gn:feature_code":"PPL",
    "gn:name":"Alet\u00f3n",
    "gn:population":0,
    "gn:timezone":"America/Santo_Domingo",
    "iso:country":"DO",
    "wof:name":"Aleton",
    "wof:placetype":"locality"
},
  "geometry": {"coordinates":[-68.95364000000001,18.53314],"type":"Point"}
}