{
  "type": "Feature",
  "properties": {
    "gn:admin1_code":"2.0",
    "gn:admin2_code":"303.0",
    "gn:admin3_code":"30301.0",
    "gn:admin4_code":"3030101.0",
    "gn:asciiname":"Rincon de Aji",
    "gn:country_code":"DO",
    "gn:dem":33,
    "gn:feature_class":"P",
    "gn:feature_code":"PPL",
    "gn:name":"Rinc\u00f3n de Aj\u00ed",
    "gn:population":0,
    "gn:timezone":"America/Santo_Domingo",
    "iso:country":"DO",
    "wof:name":"Rincon de Aji",
    "wof:placetype":"locality"
},
  "geometry": {"coordinates":[-71.20043000000003,18.40179],"type":"Point"}
}