{
  "type": "Feature",
  "properties": {
    "gn:admin1_code":"30.0",
    "gn:admin2_code":"1302.0",
    "gn:admin3_code":"130203.0",
    "gn:admin4_code":"13020303.0",
    "gn:asciiname":"La Sabina",
    "gn:country_code":"DO",
    "gn:dem":1198,
    "gn:feature_class":"P",
    "gn:feature_code":"PPL",
    "gn:name":"La Sabina",
    "gn:population":0,
    "gn:timezone":"America/Santo_Domingo",
    "iso:country":"DO",
    "wof:name":"La Sabina",
    "wof:placetype":"locality"
},
  "geometry": {"coordinates":[-70.70820999999999,18.89735],"type":"Point"}
}