{
  "type": "Feature",
  "properties": {
    "gn:admin1_code":"18.0",
    "gn:admin2_code":"1807.0",
    "gn:admin3_code":"180701.0",
    "gn:admin4_code":"18070103.0",
    "gn:asciiname":"Holguin",
    "gn:country_code":"DO",
    "gn:dem":80,
    "gn:feature_class":"P",
    "gn:feature_code":"PPL",
    "gn:name":"Holgu\u00edn",
    "gn:population":0,
    "gn:timezone":"America/Santo_Domingo",
    "iso:country":"DO",
    "name:und_x_variant":[
        "Olgu\u00edn",
        "Olqu\u00edn",
        "Holgu\u00edn"
    ],
    "wof:name":"Holguin",
    "wof:placetype":"locality"
},
  "geometry": {"coordinates":[-70.5688,19.73529],"type":"Point"}
}