{
  "type": "Feature",
  "properties": {
    "gn:admin1_code":"8.0",
    "gn:admin2_code":"901.0",
    "gn:admin3_code":"90103.0",
    "gn:admin4_code":"9010302.0",
    "gn:asciiname":"La Cidra",
    "gn:country_code":"DO",
    "gn:dem":391,
    "gn:feature_class":"P",
    "gn:feature_code":"PPL",
    "gn:name":"La Cidra",
    "gn:population":0,
    "gn:timezone":"America/Santo_Domingo",
    "iso:country":"DO",
    "name:und_x_variant":[
        "La Cidra de Cuero",
        "La Cidra"
    ],
    "wof:name":"La Cidra",
    "wof:placetype":"locality"
},
  "geometry": {"coordinates":[-70.50836,19.46256],"type":"Point"}
}