{
  "type": "Feature",
  "properties": {
    "gn:admin1_code":"25.0",
    "gn:admin2_code":"2505.0",
    "gn:admin3_code":"250501.0",
    "gn:admin4_code":"25050105.0",
    "gn:asciiname":"La Guazuma",
    "gn:country_code":"DO",
    "gn:dem":758,
    "gn:feature_class":"P",
    "gn:feature_code":"PPL",
    "gn:name":"La Gu\u00e1zuma",
    "gn:population":0,
    "gn:timezone":"America/Santo_Domingo",
    "iso:country":"DO",
    "name:und_x_variant":[
        "La Gu\u00e1zuma",
        "Gu\u00e1zuma"
    ],
    "wof:name":"La Guazuma",
    "wof:placetype":"locality"
},
  "geometry": {"coordinates":[-70.91889999999999,19.25815],"type":"Point"}
}