{
  "type": "Feature",
  "properties": {
    "gn:admin1_code":"30.0",
    "gn:admin2_code":"1301.0",
    "gn:admin3_code":"130102.0",
    "gn:admin4_code":"13010205.0",
    "gn:asciiname":"Los Coronados",
    "gn:country_code":"DO",
    "gn:dem":124,
    "gn:feature_class":"P",
    "gn:feature_code":"PPL",
    "gn:name":"Los Coronados",
    "gn:population":0,
    "gn:timezone":"America/Santo_Domingo",
    "iso:country":"DO",
    "wof:name":"Los Coronados",
    "wof:placetype":"locality"
},
  "geometry": {"coordinates":[-70.51052,19.31141],"type":"Point"}
}