{
  "type": "Feature",
  "properties": {
    "gn:admin1_code":"6.0",
    "gn:asciiname":"Arroyo El Naranjo",
    "gn:country_code":"DO",
    "gn:dem":176,
    "gn:feature_class":"P",
    "gn:feature_code":"PPL",
    "gn:name":"Arroyo El Naranjo",
    "gn:population":0,
    "gn:timezone":"America/Santo_Domingo",
    "iso:country":"DO",
    "wof:name":"Arroyo El Naranjo",
    "wof:placetype":"locality"
},
  "geometry": {"coordinates":[-69.92494000000001,19.0437],"type":"Point"}
}