{
  "type": "Feature",
  "properties": {
    "gn:admin1_code":"30.0",
    "gn:admin2_code":"1303.0",
    "gn:admin3_code":"130303.0",
    "gn:admin4_code":"13030301.0",
    "gn:asciiname":"Manabao",
    "gn:country_code":"DO",
    "gn:dem":877,
    "gn:feature_class":"P",
    "gn:feature_code":"PPL",
    "gn:name":"Manabao",
    "gn:population":0,
    "gn:timezone":"America/Santo_Domingo",
    "iso:country":"DO",
    "name:und_x_variant":[
        "Alanabao",
        "Manabao"
    ],
    "wof:name":"Manabao",
    "wof:placetype":"locality"
},
  "geometry": {"coordinates":[-70.79096,19.07061],"type":"Point"}
}