{
  "type": "Feature",
  "properties": {
    "gn:admin1_code":"23.0",
    "gn:admin2_code":"2201.0",
    "gn:admin3_code":"220101.0",
    "gn:admin4_code":"22010102.0",
    "gn:asciiname":"El Batey",
    "gn:country_code":"DO",
    "gn:dem":610,
    "gn:feature_class":"P",
    "gn:feature_code":"PPL",
    "gn:name":"El Batey",
    "gn:population":0,
    "gn:timezone":"America/Santo_Domingo",
    "iso:country":"DO",
    "wof:name":"El Batey",
    "wof:placetype":"locality"
},
  "geometry": {"coordinates":[-71.31667,18.76667],"type":"Point"}
}