{
  "type": "Feature",
  "properties": {
    "gn:admin1_code":"15.0",
    "gn:admin2_code":"1502.0",
    "gn:admin3_code":"150201.0",
    "gn:admin4_code":"15020103.0",
    "gn:asciiname":"Astoria",
    "gn:country_code":"DO",
    "gn:dem":29,
    "gn:feature_class":"P",
    "gn:feature_code":"PPL",
    "gn:name":"Astoria",
    "gn:population":0,
    "gn:timezone":"America/Santo_Domingo",
    "iso:country":"DO",
    "wof:name":"Astoria",
    "wof:placetype":"locality"
},
  "geometry": {"coordinates":[-71.48657,19.6877],"type":"Point"}
}