{
  "type": "Feature",
  "properties": {
    "gn:admin1_code":"21.0",
    "gn:admin2_code":"2404.0",
    "gn:admin3_code":"240404.0",
    "gn:admin4_code":"24040402.0",
    "gn:asciiname":"La Guamita",
    "gn:country_code":"DO",
    "gn:dem":79,
    "gn:feature_class":"P",
    "gn:feature_code":"PPL",
    "gn:name":"La Guamita",
    "gn:population":0,
    "gn:timezone":"America/Santo_Domingo",
    "iso:country":"DO",
    "wof:name":"La Guamita",
    "wof:placetype":"locality"
},
  "geometry": {"coordinates":[-70.23051,19.0694],"type":"Point"}
}