{
  "type": "Feature",
  "properties": {
    "gn:admin1_code":"6.0",
    "gn:asciiname":"Mata de Naranja",
    "gn:country_code":"DO",
    "gn:dem":1419,
    "gn:feature_class":"P",
    "gn:feature_code":"PPL",
    "gn:name":"Mata de Naranja",
    "gn:population":0,
    "gn:timezone":"America/Santo_Domingo",
    "iso:country":"DO",
    "wof:name":"Mata de Naranja",
    "wof:placetype":"locality"
},
  "geometry": {"coordinates":[-71.46666999999999,18.61667000000001],"type":"Point"}
}