{
  "type": "Feature",
  "properties": {
    "gn:admin1_code":"2.0",
    "gn:admin2_code":"305.0",
    "gn:admin3_code":"30502.0",
    "gn:admin4_code":"3050202.0",
    "gn:asciiname":"Los Amaceyes",
    "gn:country_code":"DO",
    "gn:dem":666,
    "gn:feature_class":"P",
    "gn:feature_code":"PPL",
    "gn:name":"Los Amaceyes",
    "gn:population":0,
    "gn:timezone":"America/Santo_Domingo",
    "iso:country":"DO",
    "wof:name":"Los Amaceyes",
    "wof:placetype":"locality"
},
  "geometry": {"coordinates":[-71.55339000000002,18.57802],"type":"Point"}
}