{
  "type": "Feature",
  "properties": {
    "gn:admin1_code":"30.0",
    "gn:admin2_code":"1304.0",
    "gn:admin3_code":"130401.0",
    "gn:admin4_code":"13040104.0",
    "gn:asciiname":"San Bartolo",
    "gn:country_code":"DO",
    "gn:dem":63,
    "gn:feature_class":"P",
    "gn:feature_code":"PPL",
    "gn:name":"San Bartolo",
    "gn:population":0,
    "gn:timezone":"America/Santo_Domingo",
    "iso:country":"DO",
    "name:ceb_x_preferred":[
        "San Bartolo"
    ],
    "name:deu_x_preferred":[
        "San Bartolo"
    ],
    "name:epo_x_preferred":[
        "San Bartolo"
    ],
    "name:fra_x_preferred":[
        "San Bartolo"
    ],
    "name:por_x_preferred":[
        "San Bartolo"
    ],
    "name:sco_x_preferred":[
        "San Bartolo"
    ],
    "name:spa_x_preferred":[
        "San Bartolo"
    ],
    "name:srp_x_preferred":[
        "San Bartolo"
    ],
    "name:swe_x_preferred":[
        "San Bartolo"
    ],
    "wof:name":"San Bartolo",
    "wof:placetype":"locality"
},
  "geometry": {"coordinates":[-70.37275,19.1551],"type":"Point"}
}