{
  "type": "Feature",
  "properties": {
    "gn:admin1_code":"35.0",
    "gn:admin2_code":"1701.0",
    "gn:admin3_code":"170109.0",
    "gn:admin4_code":"17010905.0",
    "gn:asciiname":"Buena Vista",
    "gn:country_code":"DO",
    "gn:dem":314,
    "gn:feature_class":"P",
    "gn:feature_code":"PPL",
    "gn:name":"Buena Vista",
    "gn:population":0,
    "gn:timezone":"America/Santo_Domingo",
    "iso:country":"DO",
    "wof:name":"Buena Vista",
    "wof:placetype":"locality"
},
  "geometry": {"coordinates":[-70.28869,18.33863],"type":"Point"}
}