{
  "type": "Feature",
  "properties": {
    "gn:admin1_code":"34.0",
    "gn:asciiname":"Palabe",
    "gn:country_code":"DO",
    "gn:dem":46,
    "gn:feature_class":"P",
    "gn:feature_code":"PPL",
    "gn:name":"Palabe",
    "gn:population":0,
    "gn:timezone":"America/Santo_Domingo",
    "iso:country":"DO",
    "name:und_x_variant":[
        "Palav\u00e9",
        "Palabe"
    ],
    "wof:name":"Palabe",
    "wof:placetype":"locality"
},
  "geometry": {"coordinates":[-70.05884,18.48339],"type":"Point"}
}