{
  "type": "Feature",
  "properties": {
    "gn:admin1_code":"21.0",
    "gn:admin2_code":"2401.0",
    "gn:admin3_code":"240101.0",
    "gn:admin4_code":"24010104.0",
    "gn:asciiname":"La Cerca",
    "gn:country_code":"DO",
    "gn:dem":115,
    "gn:feature_class":"P",
    "gn:feature_code":"PPL",
    "gn:name":"La Cerca",
    "gn:population":0,
    "gn:timezone":"America/Santo_Domingo",
    "iso:country":"DO",
    "wof:name":"La Cerca",
    "wof:placetype":"locality"
},
  "geometry": {"coordinates":[-70.16667,18.91667],"type":"Point"}
}