{
  "type": "Feature",
  "properties": {
    "gn:admin1_code":"14.0",
    "gn:admin2_code":"1401.0",
    "gn:admin3_code":"140104.0",
    "gn:admin4_code":"14010403.0",
    "gn:asciiname":"El Ramonal",
    "gn:country_code":"DO",
    "gn:dem":152,
    "gn:feature_class":"P",
    "gn:feature_code":"PPL",
    "gn:name":"El Ramonal",
    "gn:population":0,
    "gn:timezone":"America/Santo_Domingo",
    "iso:country":"DO",
    "name:und_x_variant":[
        "Los Ramones",
        "El Ramonal"
    ],
    "wof:name":"El Ramonal",
    "wof:placetype":"locality"
},
  "geometry": {"coordinates":[-70.00364,19.35077],"type":"Point"}
}