{
  "type": "Feature",
  "properties": {
    "gn:admin1_code":"9.0",
    "gn:admin2_code":"1002.0",
    "gn:admin3_code":"100201.0",
    "gn:admin4_code":"10020102.0",
    "gn:asciiname":"El Aguacate",
    "gn:country_code":"DO",
    "gn:dem":1082,
    "gn:feature_class":"P",
    "gn:feature_code":"PPL",
    "gn:name":"El Aguacate",
    "gn:population":0,
    "gn:timezone":"America/Santo_Domingo",
    "iso:country":"DO",
    "wof:name":"El Aguacate",
    "wof:placetype":"locality"
},
  "geometry": {"coordinates":[-71.69583,18.32929],"type":"Point"}
}