{
  "type": "Feature",
  "properties": {
    "gn:admin1_code":"18.0",
    "gn:admin2_code":"1803.0",
    "gn:admin3_code":"180301.0",
    "gn:admin4_code":"18030104.0",
    "gn:asciiname":"Los Hoyos",
    "gn:country_code":"DO",
    "gn:dem":568,
    "gn:feature_class":"P",
    "gn:feature_code":"PPL",
    "gn:name":"Los Hoyos",
    "gn:population":0,
    "gn:timezone":"America/Santo_Domingo",
    "iso:country":"DO",
    "wof:name":"Los Hoyos",
    "wof:placetype":"locality"
},
  "geometry": {"coordinates":[-70.93643,19.68927],"type":"Point"}
}