{
  "type": "Feature",
  "properties": {
    "gn:admin1_code":"24.0",
    "gn:admin2_code":"2302.0",
    "gn:admin3_code":"230203.0",
    "gn:admin4_code":"23020302.0",
    "gn:asciiname":"Plumita",
    "gn:country_code":"DO",
    "gn:dem":41,
    "gn:feature_class":"P",
    "gn:feature_code":"PPL",
    "gn:name":"Plumita",
    "gn:population":0,
    "gn:timezone":"America/Santo_Domingo",
    "iso:country":"DO",
    "name:und_x_variant":[
        "Batey La Plumita",
        "Plumita"
    ],
    "wof:name":"Plumita",
    "wof:placetype":"locality"
},
  "geometry": {"coordinates":[-69.57392,18.50996],"type":"Point"}
}