{
  "type": "Feature",
  "properties": {
    "gn:admin1_code":"30.0",
    "gn:admin2_code":"1303.0",
    "gn:admin3_code":"130301.0",
    "gn:admin4_code":"13030108.0",
    "gn:asciiname":"La Pita",
    "gn:country_code":"DO",
    "gn:dem":1172,
    "gn:feature_class":"P",
    "gn:feature_code":"PPL",
    "gn:name":"La Pita",
    "gn:population":0,
    "gn:timezone":"America/Santo_Domingo",
    "iso:country":"DO",
    "name:und_x_variant":[
        "Pita",
        "La Pinta",
        "La Pita"
    ],
    "wof:name":"La Pita",
    "wof:placetype":"locality"
},
  "geometry": {"coordinates":[-70.60695,19.01934],"type":"Point"}
}