{
  "type": "Feature",
  "properties": {
    "gn:admin1_code":"9.0",
    "gn:admin2_code":"1005.0",
    "gn:admin3_code":"100502.0",
    "gn:admin4_code":"10050202.0",
    "gn:asciiname":"El Bateycito",
    "gn:country_code":"DO",
    "gn:dem":20,
    "gn:feature_class":"P",
    "gn:feature_code":"PPL",
    "gn:name":"El Bateycito",
    "gn:population":0,
    "gn:timezone":"America/Santo_Domingo",
    "iso:country":"DO",
    "name:und_x_variant":[
        "El Bateicito",
        "El Bateycito"
    ],
    "wof:name":"El Bateycito",
    "wof:placetype":"locality"
},
  "geometry": {"coordinates":[-71.31667,18.2961],"type":"Point"}
}