{
  "type": "Feature",
  "properties": {
    "gn:admin1_code":"30.0",
    "gn:admin2_code":"1303.0",
    "gn:admin3_code":"130302.0",
    "gn:admin4_code":"13030202.0",
    "gn:asciiname":"Capacito",
    "gn:country_code":"DO",
    "gn:dem":561,
    "gn:feature_class":"P",
    "gn:feature_code":"PPL",
    "gn:name":"Capacito",
    "gn:population":0,
    "gn:timezone":"America/Santo_Domingo",
    "iso:country":"DO",
    "name:und_x_variant":[
        "Los Capacitos",
        "Capacito"
    ],
    "wof:name":"Capacito",
    "wof:placetype":"locality"
},
  "geometry": {"coordinates":[-70.59614999999999,19.14601],"type":"Point"}
}