{
  "type": "Feature",
  "properties": {
    "gn:admin1_code":"18.0",
    "gn:admin2_code":"1809.0",
    "gn:admin3_code":"180901.0",
    "gn:admin4_code":"18090107.0",
    "gn:asciiname":"Arroyo Blanco",
    "gn:country_code":"DO",
    "gn:dem":105,
    "gn:feature_class":"P",
    "gn:feature_code":"PPL",
    "gn:name":"Arroyo Blanco",
    "gn:population":0,
    "gn:timezone":"America/Santo_Domingo",
    "iso:country":"DO",
    "wof:name":"Arroyo Blanco",
    "wof:placetype":"locality"
},
  "geometry": {"coordinates":[-70.55964,19.71717],"type":"Point"}
}