{
  "type": "Feature",
  "properties": {
    "gn:admin1_code":"32.0",
    "gn:admin2_code":"2902.0",
    "gn:admin3_code":"290201.0",
    "gn:admin4_code":"29020102.0",
    "gn:asciiname":"El Manaclar",
    "gn:country_code":"DO",
    "gn:dem":181,
    "gn:feature_class":"P",
    "gn:feature_code":"PPL",
    "gn:name":"El Manaclar",
    "gn:population":0,
    "gn:timezone":"America/Santo_Domingo",
    "iso:country":"DO",
    "name:und_x_variant":[
        "Manacla",
        "El Manaclar"
    ],
    "wof:name":"El Manaclar",
    "wof:placetype":"locality"
},
  "geometry": {"coordinates":[-69.71944999999999,18.87826],"type":"Point"}
}