{
  "type": "Feature",
  "properties": {
    "gn:admin1_code":"24.0",
    "gn:admin2_code":"2302.0",
    "gn:admin3_code":"230201.0",
    "gn:admin4_code":"23020102.0",
    "gn:asciiname":"Dos Hermanos",
    "gn:country_code":"DO",
    "gn:dem":49,
    "gn:feature_class":"P",
    "gn:feature_code":"PPL",
    "gn:name":"Dos Hermanos",
    "gn:population":0,
    "gn:timezone":"America/Santo_Domingo",
    "iso:country":"DO",
    "name:und_x_variant":[
        "Dos Hermanas",
        "Dos Hermanos"
    ],
    "wof:name":"Dos Hermanos",
    "wof:placetype":"locality"
},
  "geometry": {"coordinates":[-69.49757,18.50182],"type":"Point"}
}