{
  "type": "Feature",
  "properties": {
    "gn:admin1_code":"37.0",
    "gn:admin2_code":"3201.0",
    "gn:admin3_code":"320102.0",
    "gn:admin4_code":"32010202.0",
    "gn:asciiname":"El Bonito",
    "gn:country_code":"DO",
    "gn:dem":16,
    "gn:feature_class":"P",
    "gn:feature_code":"PPL",
    "gn:name":"El Bonito",
    "gn:population":0,
    "gn:timezone":"America/Santo_Domingo",
    "iso:country":"DO",
    "name:und_x_variant":[
        "Bonito",
        "El Bonito"
    ],
    "wof:name":"El Bonito",
    "wof:placetype":"locality"
},
  "geometry": {"coordinates":[-69.77933,18.53521],"type":"Point"}
}