{
  "type": "Feature",
  "properties": {
    "gn:admin1_code":"6.0",
    "gn:admin2_code":"605.0",
    "gn:admin3_code":"60504.0",
    "gn:admin4_code":"6050404.0",
    "gn:asciiname":"Ceiba Gorda",
    "gn:country_code":"DO",
    "gn:dem":176,
    "gn:feature_class":"P",
    "gn:feature_code":"PPL",
    "gn:name":"Ceiba Gorda",
    "gn:population":0,
    "gn:timezone":"America/Santo_Domingo",
    "iso:country":"DO",
    "wof:name":"Ceiba Gorda",
    "wof:placetype":"locality"
},
  "geometry": {"coordinates":[-69.94704,19.21693],"type":"Point"}
}