{
  "type": "Feature",
  "properties": {
    "gn:admin1_code":"18.0",
    "gn:admin2_code":"1806.0",
    "gn:admin3_code":"180601.0",
    "gn:admin4_code":"18060105.0",
    "gn:asciiname":"Los Corozos",
    "gn:country_code":"DO",
    "gn:dem":92,
    "gn:feature_class":"P",
    "gn:feature_code":"PPL",
    "gn:name":"Los Corozos",
    "gn:population":0,
    "gn:timezone":"America/Santo_Domingo",
    "iso:country":"DO",
    "name:und_x_variant":[
        "El Corozo",
        "Los Corozos"
    ],
    "wof:name":"Los Corozos",
    "wof:placetype":"locality"
},
  "geometry": {"coordinates":[-70.89698,19.89147],"type":"Point"}
}