{
  "type": "Feature",
  "properties": {
    "gn:admin1_code":"24.0",
    "gn:admin2_code":"2301.0",
    "gn:admin3_code":"230101.0",
    "gn:admin4_code":"23010102.0",
    "gn:asciiname":"Los Palitos",
    "gn:country_code":"DO",
    "gn:dem":20,
    "gn:feature_class":"P",
    "gn:feature_code":"PPL",
    "gn:name":"Los Palitos",
    "gn:population":0,
    "gn:timezone":"America/Santo_Domingo",
    "iso:country":"DO",
    "wof:name":"Los Palitos",
    "wof:placetype":"locality"
},
  "geometry": {"coordinates":[-69.24024,18.46673],"type":"Point"}
}