{
  "type": "Feature",
  "properties": {
    "gn:admin1_code":"14.0",
    "gn:admin2_code":"1401.0",
    "gn:admin3_code":"140104.0",
    "gn:admin4_code":"14010403.0",
    "gn:asciiname":"Placer Bonito",
    "gn:country_code":"DO",
    "gn:dem":33,
    "gn:feature_class":"P",
    "gn:feature_code":"PPL",
    "gn:name":"Placer Bonito",
    "gn:population":0,
    "gn:timezone":"America/Santo_Domingo",
    "iso:country":"DO",
    "wof:name":"Placer Bonito",
    "wof:placetype":"locality"
},
  "geometry": {"coordinates":[-69.99542,19.39012],"type":"Point"}
}