{
  "type": "Feature",
  "properties": {
    "gn:admin1_code":"24.0",
    "gn:admin2_code":"2302.0",
    "gn:admin3_code":"230203.0",
    "gn:admin4_code":"23020302.0",
    "gn:asciiname":"La Mula",
    "gn:country_code":"DO",
    "gn:dem":35,
    "gn:feature_class":"P",
    "gn:feature_code":"PPL",
    "gn:name":"La Mula",
    "gn:population":0,
    "gn:timezone":"America/Santo_Domingo",
    "iso:country":"DO",
    "name:und_x_variant":[
        "Batey La Mula",
        "Cayacoa",
        "La Mula"
    ],
    "wof:name":"La Mula",
    "wof:placetype":"locality"
},
  "geometry": {"coordinates":[-69.5615,18.51175],"type":"Point"}
}