{
  "type": "Feature",
  "properties": {
    "gn:admin1_code":"14.0",
    "gn:admin2_code":"1404.0",
    "gn:admin3_code":"140401.0",
    "gn:admin4_code":"14040103.0",
    "gn:asciiname":"La Novilla",
    "gn:country_code":"DO",
    "gn:dem":224,
    "gn:feature_class":"P",
    "gn:feature_code":"PPL",
    "gn:name":"La Novilla",
    "gn:population":0,
    "gn:timezone":"America/Santo_Domingo",
    "iso:country":"DO",
    "wof:name":"La Novilla",
    "wof:placetype":"locality"
},
  "geometry": {"coordinates":[-70.03243000000001,19.64062],"type":"Point"}
}