{
  "type": "Feature",
  "properties": {
    "gn:admin1_code":"24.0",
    "gn:admin2_code":"2304.0",
    "gn:admin3_code":"230401.0",
    "gn:admin4_code":"23040103.0",
    "gn:asciiname":"Los Platanitos",
    "gn:country_code":"DO",
    "gn:dem":45,
    "gn:feature_class":"P",
    "gn:feature_code":"PPL",
    "gn:name":"Los Platanitos",
    "gn:population":0,
    "gn:timezone":"America/Santo_Domingo",
    "iso:country":"DO",
    "name:und_x_variant":[
        "Platanitos",
        "Platanito",
        "Los Platanitos"
    ],
    "wof:name":"Los Platanitos",
    "wof:placetype":"locality"
},
  "geometry": {"coordinates":[-69.27818000000001,18.57591],"type":"Point"}
}