{
  "type": "Feature",
  "properties": {
    "gn:admin1_code":"32.0",
    "gn:admin2_code":"2902.0",
    "gn:admin3_code":"290201.0",
    "gn:admin4_code":"29020102.0",
    "gn:asciiname":"La Cabezada",
    "gn:country_code":"DO",
    "gn:dem":178,
    "gn:feature_class":"P",
    "gn:feature_code":"PPL",
    "gn:name":"La Cabezada",
    "gn:population":0,
    "gn:timezone":"America/Santo_Domingo",
    "iso:country":"DO",
    "wof:name":"La Cabezada",
    "wof:placetype":"locality"
},
  "geometry": {"coordinates":[-69.70095000000001,18.87769],"type":"Point"}
}