{
  "type": "Feature",
  "properties": {
    "gn:admin1_code":"21.0",
    "gn:admin2_code":"2401.0",
    "gn:admin3_code":"240101.0",
    "gn:admin4_code":"24010107.0",
    "gn:asciiname":"Cojobal",
    "gn:country_code":"DO",
    "gn:dem":94,
    "gn:feature_class":"P",
    "gn:feature_code":"PPL",
    "gn:name":"Cojobal",
    "gn:population":0,
    "gn:timezone":"America/Santo_Domingo",
    "iso:country":"DO",
    "wof:name":"Cojobal",
    "wof:placetype":"locality"
},
  "geometry": {"coordinates":[-70.09999999999999,18.95],"type":"Point"}
}