{
  "type": "Feature",
  "properties": {
    "gn:admin1_code":"32.0",
    "gn:admin2_code":"2904.0",
    "gn:admin3_code":"290401.0",
    "gn:admin4_code":"29040101.0",
    "gn:asciiname":"Cercadillo",
    "gn:country_code":"DO",
    "gn:dem":75,
    "gn:feature_class":"P",
    "gn:feature_code":"PPL",
    "gn:name":"Cercadillo",
    "gn:population":0,
    "gn:timezone":"America/Santo_Domingo",
    "iso:country":"DO",
    "wof:name":"Cercadillo",
    "wof:placetype":"locality"
},
  "geometry": {"coordinates":[-70.01889,18.78436],"type":"Point"}
}